Workbook

Sheet Summary
B2: Glow Ventures — Client Requirements Tracker
B3: Every requirement from the client call and from the written follow-up that came after it, measured against the dashboard as it stands. Repeated asks are stated once.
B5: Overall complete | D5: Dashboard | F5: Research Centre
B6: =SUM(Checklist!$I$2:$I$68)/COUNTA(Checklist!$H$2:$H$68) -> 0.47761194 | D6: =SUMIF(Checklist!$B$2:$B$68,"Dashboard",Checklist!$I$2:$I$68)/COUNTIF(Checklist!$B$2:$B$68,"Dashboard") -> 0.64444444 | F6: =SUMIF(Checklist!$B$2:$B$68,"Research Centre",Checklist!$I$2:$I$68)/COUNTIF(Checklist!$B$2:$B$68,"Research Centre") -> 0.1875
B8: Done counts 100%, Partial 50%, Not started 0%. Every line item weighs the same. The tiles above are live formulas; as measured on 2 Sep 2026 they read 48% overall, 64% dashboard, 19% research centre. They read 29% / 37% / 19% on 1 Sep, before the push recorded in the last column of the Checklist tab.
B10: By status
B11: Status | C11: Items | D11: Share
B12: Done | C12: =COUNTIF(Checklist!$H$2:$H$68,$B12) -> 24 | D12: =C12/COUNTA(Checklist!$H$2:$H$68) -> 0.35820896
B13: Partial | C13: =COUNTIF(Checklist!$H$2:$H$68,$B13) -> 16 | D13: =C13/COUNTA(Checklist!$H$2:$H$68) -> 0.23880597
B14: Not started | C14: =COUNTIF(Checklist!$H$2:$H$68,$B14) -> 27 | D14: =C14/COUNTA(Checklist!$H$2:$H$68) -> 0.40298507
B15: Total | C15: =COUNTA(Checklist!$H$2:$H$68) -> 67
B18: By workstream
B19: Workstream | C19: Items | D19: Done | E19: Partial | F19: Not started | G19: % complete
B20: A. Structure & Polycab | C20: =COUNTIF(Checklist!$C$2:$C$68,$B20) -> 10 | D20: =COUNTIFS(Checklist!$C$2:$C$68,$B20,Checklist!$H$2:$H$68,"Done") -> 8 | E20: =COUNTIFS(Checklist!$C$2:$C$68,$B20,Checklist!$H$2:$H$68,"Partial") -> 1 | F20: =COUNTIFS(Checklist!$C$2:$C$68,$B20,Checklist!$H$2:$H$68,"Not started") -> 1 | G20: =IFERROR(SUMIF(Checklist!$C$2:$C$68,$B20,Checklist!$I$2:$I$68)/C20,"") -> 0.85
B21: B. Holdings table | C21: =COUNTIF(Checklist!$C$2:$C$68,$B21) -> 11 | D21: =COUNTIFS(Checklist!$C$2:$C$68,$B21,Checklist!$H$2:$H$68,"Done") -> 5 | E21: =COUNTIFS(Checklist!$C$2:$C$68,$B21,Checklist!$H$2:$H$68,"Partial") -> 4 | F21: =COUNTIFS(Checklist!$C$2:$C$68,$B21,Checklist!$H$2:$H$68,"Not started") -> 2 | G21: =IFERROR(SUMIF(Checklist!$C$2:$C$68,$B21,Checklist!$I$2:$I$68)/C21,"") -> 0.63636364
B22: C. Transactions | C22: =COUNTIF(Checklist!$C$2:$C$68,$B22) -> 4 | D22: =COUNTIFS(Checklist!$C$2:$C$68,$B22,Checklist!$H$2:$H$68,"Done") -> 3 | E22: =COUNTIFS(Checklist!$C$2:$C$68,$B22,Checklist!$H$2:$H$68,"Partial") -> 0 | F22: =COUNTIFS(Checklist!$C$2:$C$68,$B22,Checklist!$H$2:$H$68,"Not started") -> 1 | G22: =IFERROR(SUMIF(Checklist!$C$2:$C$68,$B22,Checklist!$I$2:$I$68)/C22,"") -> 0.75
B23: D. Overview (Morning CIO) | C23: =COUNTIF(Checklist!$C$2:$C$68,$B23) -> 9 | D23: =COUNTIFS(Checklist!$C$2:$C$68,$B23,Checklist!$H$2:$H$68,"Done") -> 5 | E23: =COUNTIFS(Checklist!$C$2:$C$68,$B23,Checklist!$H$2:$H$68,"Partial") -> 2 | F23: =COUNTIFS(Checklist!$C$2:$C$68,$B23,Checklist!$H$2:$H$68,"Not started") -> 2 | G23: =IFERROR(SUMIF(Checklist!$C$2:$C$68,$B23,Checklist!$I$2:$I$68)/C23,"") -> 0.66666667
B24: E. Baskets & family view | C24: =COUNTIF(Checklist!$C$2:$C$68,$B24) -> 3 | D24: =COUNTIFS(Checklist!$C$2:$C$68,$B24,Checklist!$H$2:$H$68,"Done") -> 0 | E24: =COUNTIFS(Checklist!$C$2:$C$68,$B24,Checklist!$H$2:$H$68,"Partial") -> 1 | F24: =COUNTIFS(Checklist!$C$2:$C$68,$B24,Checklist!$H$2:$H$68,"Not started") -> 2 | G24: =IFERROR(SUMIF(Checklist!$C$2:$C$68,$B24,Checklist!$I$2:$I$68)/C24,"") -> 0.16666667
B25: F. Data, pricing & look-through | C25: =COUNTIF(Checklist!$C$2:$C$68,$B25) -> 8 | D25: =COUNTIFS(Checklist!$C$2:$C$68,$B25,Checklist!$H$2:$H$68,"Done") -> 2 | E25: =COUNTIFS(Checklist!$C$2:$C$68,$B25,Checklist!$H$2:$H$68,"Partial") -> 4 | F25: =COUNTIFS(Checklist!$C$2:$C$68,$B25,Checklist!$H$2:$H$68,"Not started") -> 2 | G25: =IFERROR(SUMIF(Checklist!$C$2:$C$68,$B25,Checklist!$I$2:$I$68)/C25,"") -> 0.5
B26: G. Fund research | C26: =COUNTIF(Checklist!$C$2:$C$68,$B26) -> 10 | D26: =COUNTIFS(Checklist!$C$2:$C$68,$B26,Checklist!$H$2:$H$68,"Done") -> 1 | E26: =COUNTIFS(Checklist!$C$2:$C$68,$B26,Checklist!$H$2:$H$68,"Partial") -> 2 | F26: =COUNTIFS(Checklist!$C$2:$C$68,$B26,Checklist!$H$2:$H$68,"Not started") -> 7 | G26: =IFERROR(SUMIF(Checklist!$C$2:$C$68,$B26,Checklist!$I$2:$I$68)/C26,"") -> 0.2
B27: H. News & announcements | C27: =COUNTIF(Checklist!$C$2:$C$68,$B27) -> 6 | D27: =COUNTIFS(Checklist!$C$2:$C$68,$B27,Checklist!$H$2:$H$68,"Done") -> 0 | E27: =COUNTIFS(Checklist!$C$2:$C$68,$B27,Checklist!$H$2:$H$68,"Partial") -> 2 | F27: =COUNTIFS(Checklist!$C$2:$C$68,$B27,Checklist!$H$2:$H$68,"Not started") -> 4 | G27: =IFERROR(SUMIF(Checklist!$C$2:$C$68,$B27,Checklist!$I$2:$I$68)/C27,"") -> 0.16666667
B28: I. Process & access | C28: =COUNTIF(Checklist!$C$2:$C$68,$B28) -> 6 | D28: =COUNTIFS(Checklist!$C$2:$C$68,$B28,Checklist!$H$2:$H$68,"Done") -> 0 | E28: =COUNTIFS(Checklist!$C$2:$C$68,$B28,Checklist!$H$2:$H$68,"Partial") -> 0 | F28: =COUNTIFS(Checklist!$C$2:$C$68,$B28,Checklist!$H$2:$H$68,"Not started") -> 6 | G28: =IFERROR(SUMIF(Checklist!$C$2:$C$68,$B28,Checklist!$I$2:$I$68)/C28,"") -> 0
B29: All workstreams | C29: =SUM(C20:C28) -> 67 | D29: =SUM(D20:D28) -> 24 | E29: =SUM(E20:E28) -> 16 | F29: =SUM(F20:F28) -> 27 | G29: =SUM(Checklist!$I$2:$I$68)/C29 -> 0.47761194
B32: By round — where the ask came from
B33: Raised in | C33: Items | D33: Not started | E33: % complete
B34: Call | C34: =COUNTIF(Checklist!$F$2:$F$68,$B34) -> 54 | D34: =COUNTIFS(Checklist!$F$2:$F$68,$B34,Checklist!$H$2:$H$68,"Not started") -> 22 | E34: =IFERROR(SUMIF(Checklist!$F$2:$F$68,$B34,Checklist!$I$2:$I$68)/C34,"") -> 0.49074074
B35: Call + written | C35: =COUNTIF(Checklist!$F$2:$F$68,$B35) -> 2 | D35: =COUNTIFS(Checklist!$F$2:$F$68,$B35,Checklist!$H$2:$H$68,"Not started") -> 0 | E35: =IFERROR(SUMIF(Checklist!$F$2:$F$68,$B35,Checklist!$I$2:$I$68)/C35,"") -> 1
B36: Written feedback | C36: =COUNTIF(Checklist!$F$2:$F$68,$B36) -> 11 | D36: =COUNTIFS(Checklist!$F$2:$F$68,$B36,Checklist!$H$2:$H$68,"Not started") -> 5 | E36: =IFERROR(SUMIF(Checklist!$F$2:$F$68,$B36,Checklist!$I$2:$I$68)/C36,"") -> 0.31818182
B39: How to read this
B40: • Two products are in scope. Dashboard rows were checked against the code in techmuns/glowventures. Research Centre rows are a separate application not in that repository, so their status is what the client was shown live on the call.
B41: • The written follow-up added 11 requirements and sharpened 2 the client had already made on the call. Filter the “Raised in” column to see them: of the 11, 5 are still not started, 5 are part-built and 1 is complete — the four index levels carried on every screen. Both of the two it sharpened are now done. What the push did NOT touch on this list is the FIFO realised gain (B10), the Consolidated NAV rename (D9), the capital-invested gap (F8) and the two process items.
B42: • "Partial" means the plumbing is there and the screen is not, or the ask is met on one page and not the others. The "What is left to do" column says which.
B43: • Two of the open items are blocked on data rather than on build effort, and are worth raising with the client directly: fund look-through (F6, F7) now has the mutual-fund half from the AMCs' own monthly disclosures, but no Category II or III AIF is required to publish one, so ₹352 Cr of the book still has nothing to join; and the incomplete capital-invested figure (F8) needs a priced transaction history from the demats. The dated portfolio value series that blocked the Nifty comparison (D2) and the day / week / month returns (D7) has since been built — it covers 13 of 49 accounts, and widening it needs a monthly valuation statement from any of the other 36.
B44: • Change a Status cell on the Checklist tab and every percentage here recalculates — the roll-ups are formulas, not typed numbers.
B45: • What moved in the last 36 hours: 16 line items changed status — 12 to Done and 4 from Not started to Part-built — across the holdings table, the transactions view and the Morning CIO front page. The last column of the Checklist tab names the change and the commit behind each, so the ones that did NOT move are as visible as the ones that did.
B47: Sources: client call transcript, and the written follow-up (“Some more feedback to incorporate pls”, points 1–5). Dashboard status re-measured against techmuns/glowventures at commit 857b689, 2 September 2026 — 29 commits after the 1 September baseline (3b46e97) this sheet was first written against. Book as measured: current value of holdings 710.39 Cr ex-Polycab, 49 accounts, 371 positions, 6 holders and 2 trusts, unchanged over the push. Research Centre rows are a separate application and were not re-measured.

Sheet Checklist
A1: ID | B1: Scope | C1: Workstream | D1: Requirement | E1: What the client asked for | F1: Raised in | G1: Where it lives | H1: Status | I1: % done | J1: Current state of the dashboard | K1: What is left to do | L1: Status verified | M1: Moved in the 1–2 Sep push
A2: A1 | B2: Dashboard | C2: A. Structure & Polycab | D2: Remove Polycab from the consolidated NAV and from every calculation on the dashboard | E2: "Polycab must not be included in any data set information and any calculation in any other part of the dashboard" — consolidated NAV was reading 13,000 Cr | F2: Call | G2: scripts/build-book.mjs · whole app | H2: Done | I2: =IF(H2="Done",1,IF(H2="Partial",0.5,0)) -> 1 | J2: Ring-fenced at the book layer: the holding is spliced into BOOK_POLYCAB before any total, split, weight, sector or XIRR is struck. Consolidated NAV is 710.39 Cr ex-Polycab (was 13,061.63 Cr). `npm run check:pages` asserts the name appears nowhere in <main> on the other 26 routes. | K2: — | L2: Verified in repo | M2: —
A3: A2 | B3: Dashboard | C3: A. Structure & Polycab | D3: Give Polycab its own single page | E3: "Let it be as a single page" — keep it visible but out of the book | F3: Call | G3: /polycab | H3: Done | I3: =IF(H3="Done",1,IF(H3="Partial",0.5,0)) -> 1 | J3: Page live and first in the Daily nav group. Reads BOOK_POLYCAB directly rather than the portfolio context, so it cannot leak back into a total. /stock/<polycab> redirects here instead of rendering the holding as fully exited at 0. | K3: — | L3: Verified in repo | M3: —
A4: A3 | B4: Dashboard | C4: A. Structure & Polycab | D4: No include/exclude toggle — Polycab out entirely, retained in one place only | E4: "No no no toggle button… just keep it somewhere in the data or statements" | F4: Call | G4: /polycab · /audit | H4: Done | I4: =IF(H4="Done",1,IF(H4="Partial",0.5,0)) -> 1 | J4: No toggle anywhere. The statement stays in source/ and the full 38-row extraction stays in the audit archive, so provenance is intact without any dashboard figure moving. | K4: — | L4: Verified in repo | M4: —
A5: A4 | B5: Dashboard | C5: A. Structure & Polycab | D5: Polycab page to show the holding per demat, per holder, pledges, dividends and splits | E5: "How many Polycab shares are lying in which DMAT, how many belong to who, if there is a pledge created… what dividend has come in, is there a stock split" | F5: Call | G5: /polycab | H5: Done | I5: =IF(H5="Done",1,IF(H5="Partial",0.5,0)) -> 1 | J5: The page carries the holding per demat account and a per-holder rollup, each row with its share of the block, plus one card holding the three facts no document reports. Pledges, dividends and splits are READ FROM THE BOOK — corporate actions filtered on this holding's own securityKey, dividends summed off the position — so a drop that brings one in fills the row with no code change, and each row names the document that would carry it. An NSDL Statement of Holding has five columns and no pledge, lock-in or freeze column at all, so a nil pledge is never printed: check:pages asserts that row can never acquire a figure that parses as zero. Six invariants reconcile the rendered tables against BOOK_POLYCAB in both directions. | K5: Nothing on the build. Bharat's HDFC NSDL statement (51,08,911 further shares) is four JPEG pages with no text layer and no value column at all — re-measured 2 Sep, so OCR would not recover a figure either. It needs a text PDF from HDFC. | L5: Verified in repo · 2 Sep | M5: Yes · 1 Sep — the per-demat and per-holder tables, and the three absences named rather than drawn as empty boxes (6361b9d).
A6: A5 | B6: Dashboard | C6: A. Structure & Polycab | D6: Show every PMS / AIF as a single line item — never explode a manager's holdings into the main table | E6: "PMS should come as line items… I've been repeating this point again and again" · "we have to mirror that everywhere" | F6: Call | G6: /monitor · /cio · /family | H6: Done | I6: =IF(H6="Done",1,IF(H6="Partial",0.5,0)) -> 1 | J6: holdingBucket groups shares a manager chose into a 'PMS mandates' section (10 mandates standing for 281 holdings, 138.7 Cr); the rest groups by what it is. Applied on Portfolio Monitor, Morning CIO allocation, Family & Entities and the review deck. | K6: — | L6: Verified in repo | M6: —
A7: A6 | B7: Dashboard | C7: A. Structure & Polycab | D7: Drill down from a manager line into the holdings underneath it | E7: "When I click VEC it should expand and show me the holdings" | F7: Call | G7: /mandate/:accountId | H7: Done | I7: =IF(H7="Done",1,IF(H7="Partial",0.5,0)) -> 1 | J7: One page per mandate, keyed on the account, showing every share inside it with the manager, strategy and as-of, tying to that statement's own total. An AIF folio states plainly that its constituents are not reported to this book rather than drawing an empty table. | K7: — | L7: Verified in repo | M7: —
A8: A7 | B8: Dashboard | C8: A. Structure & Polycab | D8: Entity first, security second — club by entity, holdings only on drill-down | E8: "Entity goes first and then the security… only if I'm drilling down further" | F8: Call | G8: /monitor · /family | H8: Done | I8: =IF(H8="Done",1,IF(H8="Partial",0.5,0)) -> 1 | J8: By security / By entity toggle on the holdings table, expandable rows on both, and a per-member drill-down at /family?entity=<owner> that names, per row, whether the family or a manager chose the holding. | K8: — | L8: Verified in repo | M8: —
A9: A8 | B9: Dashboard | C9: A. Structure & Polycab | D9: Move the research tabs out of the dashboard's left nav into the Research Centre | E9: "Move all the research tab also from the left to the research centre. Nothing over here — over here we just want to see what our allocations are" | F9: Call | G9: src/components/Sidebar.tsx | H9: Not started | I9: =IF(H9="Done",1,IF(H9="Partial",0.5,0)) -> 0 | J9: The left nav still carries Knowledge & Memory, Compare Companies, Watchlist & Targets, Macro Research, Economy & Macro, Thesis & Triggers and Alerts alongside the portfolio pages. | K9: Decide what moves to the Research Centre, strip those entries and their routes, and leave the dashboard nav to allocation, holdings and performance. | L9: Verified in repo | M9: —
A10: A9 | B10: Dashboard | C10: A. Structure & Polycab | D10: Every summary tile and allocation row clicks through to its own holdings — never to Data Audit | E10: "We need drill down for all line items, these ones" — pointing at the Morning CIO allocation table (AIF, PMS mandates, Mutual Fund, Direct Equity, ETF) · repeated from the call: "when I click on direct equity it should just take me to direct equity… it is taking me to data audit" | F10: Call + written | G10: /cio · /monitor · /family | H10: Done | I10: =IF(H10="Done",1,IF(H10="Partial",0.5,0)) -> 1 | J10: Every KPI tile is one click target — the whole card, with the arithmetic popover still clickable inside it — and every allocation row, concentration figure and coverage line opens the holdings behind it at /holdings. One definition per set in src/lib/drilldown.ts, read both by the page that PRINTS a figure and by the page that LISTS the rows, so a tile and its drill-down cannot disagree. A row is the thing you would click into: 19 AIF statement lines render as 14 funds, 281 mandate-held shares as 10 mandates. The listed / private / no-cost sub-scopes became a toggle inside the tile's own page instead of competing links on the tile, and the old addresses still resolve. | K10: — | L10: Verified in repo · 2 Sep | M10: Yes · 2 Sep — the drill-down layer, then one row per thing you would click into, then one destination per tile (86c46d6, 9b517de, 857b689).
A11: A10 | B11: Dashboard | C11: A. Structure & Polycab | D11: Cleaner, more minimal dashboard — strip what the family does not read | E11: "It's not looking clean at all… too much happening. Remove the garbage which you don't want to see, make it minimal" | F11: Call | G11: whole app | H11: Partial | I11: =IF(H11="Done",1,IF(H11="Partial",0.5,0)) -> 0.5 | J11: Density rather than a design pass, and it is measured rather than asserted. The app defaults to the zoomed-out layout the family was reaching for with Ctrl-minus (--app-zoom, one custom property at >=1024px); the Portfolio Monitor went from four rows of chrome to two; the mandate rows lost their sub-line; and the holdings table went from 2 holdings visible at 1500x950 to 21. Morning CIO lost the Book performance card and three explanatory captions with not one figure lost — check:pages asserts both halves, because a page that dropped the card and the split together would pass a removal check while losing a measurement. The Review deck button, its 403-line module and pptxgenjs are deleted; the Holdings basis switch is gone and the basis is not. | K11: The rest is editorial rather than mechanical: decide what the family actually opens each morning and demote the rest behind the drill-downs that now exist. Morning CIO still carries method notes, coverage captions and absence panels written for an auditor. | L11: Verified in repo · 2 Sep | M11: Yes · 2 Sep — six separate passes: the zoom default, two density passes, the one-line headline, three chrome rows down to two, and the Book performance card removed (c6b8b2e, 0b51b73, af5aa5f, 298c4b6, a5574d8, 759d246).
A12: B1 | B12: Dashboard | C12: B. Holdings table | D12: Call it "all holdings", not "all companies" | E12: "In the portfolio monitor tab it should be all holdings, it's not all companies, because I'm buying multiple things" | F12: Call | G12: /monitor | H12: Done | I12: =IF(H12="Done",1,IF(H12="Partial",0.5,0)) -> 1 | J12: The security pick-list reads All holdings, its unit is holdings and its placeholder is Search holdings; the weight caption under the table says “the holdings you picked” to match. The first options it offers are an AIF folio, a Category-III strategy and two schemes, which is why the old label was a claim the list did not support. The shared MultiSelectFilter no longer hardcodes one caller's noun either, so the economic calendar's country filter stopped printing “No companies match” over a list of countries. | K12: — | L12: Verified in repo · 2 Sep | M12: Yes · 1 Sep (7312c08).
A13: B2 | B13: Dashboard | C13: B. Holdings table | D13: Move the Sector and Entity columns to the far right | E13: "The sector and entities column I had said can go to extreme right" | F13: Call | G13: /monitor | H13: Done | I13: =IF(H13="Done",1,IF(H13="Partial",0.5,0)) -> 1 | J13: The row reads Security, Qty, Avg cost, Invested, CMP, Day, Market value, Weight, Unrealised P&L, Realised P&L, Return, then Sector and Entities last — the money first and the two descriptor columns closing the table. Nothing about what any cell renders changed: every absent-cell reason, formula popover and basis note moved verbatim. The same order is applied to both drill-downs, the transactions tape and, at the family's request, the Excel export — whose cells are now keyed by column NAME rather than by literal index, which is what makes the next reorder one edit instead of fourteen and is covered by a new round-trip test. | K13: — | L13: Verified in repo · 2 Sep | M13: Yes · 1 Sep — the tab, then the export (7312c08, 7c155fa).
... A68: I6 | B68: Process | C68: I. Process & access | D68: Reconcile against the Motilal file the client sent, and adopt the data-set layouts in it | E68: "The Motilal file has been sent to you for reconciliation, and it also has some data sets the way we like to see" | F68: Written feedback | G68: scripts/ingest/* · /audit | H68: Not started | I68: =IF(H68="Done",1,IF(H68="Partial",0.5,0)) -> 0 | J68: Not received into source/. The pipeline already reads twelve Motilal Oswal demat documents from an earlier drop (102.16 Cr across seven accounts) and reconciles the book against the family's own consolidated review, so the machinery for a second reconciliation exists. | K68: Take the file in as a new delivery, run the control-run discipline (regenerate unchanged first, so every difference belongs to the new file), reconcile, and mirror its layouts where they are better than what is on screen. | L68: From the call (separate app) | M68: —
