Workbook
Name Index: #REF!
Name Index: '[1]Term Dump'!$B$3:$B$38
Name Index: '[1]Term Dump'!$B$3:$B$38
Name Index: '[2]Term Dump'!$B$3:$B$38
Name Index: '[3]Term Dump'!$B$3:$B$38
Name Index: '[4]Term Dump'!$B$3:$B$38
Name Index: #REF!
Name Index: #REF!
Name Index: #REF!
Name Transaction: #REF!
Name Transaction: '[1]Term Dump'!$C$3:$C$8
Name Transaction: '[1]Term Dump'!$C$3:$C$8
Name Transaction: '[2]Term Dump'!$C$3:$C$8
Name Transaction: '[3]Term Dump'!$C$3:$C$8
Name Transaction: '[4]Term Dump'!$C$3:$C$8
Name Transaction: #REF!
Name Transaction: #REF!
Name Transaction: #REF!

Sheet Portfolio Allocation
B1: from Live consol | D1: 3 | E1: 12.085 | F1: 41.5 | G1: 0.032 | H1: =IFERROR(G1/$G$5,0) -> 0.042299592 | J1: 9 | L1: =N1 -> 38.415 | N1: =(F1+J1)-E1 -> 38.415 | P1: 15 | Q1: 16 | S1: 18 | T1: 19
B2: Category | D2: Investment Date Range | E2: Investment at Cost | F2: Market Value | G2: Allocation (%) | H2: Allocation (% of Asset Class) | J2: Dividend / Interest | L2: Absolute Gain / (Loss) Including Redeemed Funds | N2: Absolute Gain / (Loss) Active Funds | P2: Absolute Returns (%) | S2: Annualized Returns (%)
C3: S | P3: Portfolio | Q3: Blended Index | S3: Portfolio | T3: Blended Index
B4: Equity | E4: =SUM(E7:E15) -> 810.70047 | F4: =SUM(F7:F15) -> 1024.9989 | G4: =SUM(G7:G15) -> 0.78843032 | H4: =SUM(H7:H15) -> 1 | J4: =SUM(J7:J14) -> 1.8432324 | L4: =SUM(L7:L15) -> 20734.548 | N4: =SUM(N7:N15) -> 216.14357 | P4: 0.26003127 | Q4: 0.049233916 | S4: 0.22988721 | T4: 0.051674172
B5: Equity (Excl NSE) | E5: =E4-E1 -> 798.61547 | F5: =F4-F1 -> 983.49886 | G5: =F5/F28 -> 0.75650847 | H5: =F5/F4 -> 0.95951215 | J5: 1.8432324 | L5: 20705.133 | N5: 186.72857 | P5: 0.1924727 | Q5: 0.041027379 | S5: 0.19345655 | T5: 0.048554507
B6: Equity (Excl NSE / External Direct Equity) | E6: =E5-E9 -> 648.20141 | F6: =F5-F9 -> 761.14021 | G6: =F6/F28 -> 0.58546994 | H6: =F6/F4 -> 0.74257664 | L6: =L5-L9 -> 13817.752 | N6: =N5-N9 -> 112.95665 | P6: =P29 -> 0.1458522 | Q6: =Q29 -> 0.035615199 | S6: =S29 -> 0.15754278 | T6: =T29 -> 0.042163882
B7: Direct Equity - MO | D7: Nov-22 - Dec-25 | E7: 17.731316 | F7: 21.640258 | G7: =F7/$F$28 -> 0.016645712 | H7: =F7/$F$4 -> 0.02111247 | J7: 0 | L7: 682.89959 | N7: 3.9089419 | P7: 0.26617787 | Q7: 0.055932598 | S7: 0.17558801 | T7: 0.038443562
B8: Direct Equity - Unlisted | D8: Dec-22 - Feb-25 | E8: 27.086596 | F8: 64.328516 | G8: =F8/$F$28 -> 0.04948157 | H8: =F8/$F$4 -> 0.062759597 | J8: 0 | L8: 3724.192 | N8: 37.24192 | P8: 1.3749206 | Q8: 0.29941829 | S8: 0.5395584 | T8: 0.15761568
B9: Direct Equity - Non MO | D9: Jul-23 - Jun-26 | E9: 150.41406 | F9: 222.35865 | G9: =F9/$F$28 -> 0.17103853 | H9: =F9/$F$4 -> 0.21693551 | J9: 1.8273252 | L9: 6887.3804 | N9: 73.771919 | P9: 0.43578585 | Q9: 0.069273635 | S9: 0.32026554 | T9: 0.072169986
B10: Multi Cap | D10: March 20 - Aug 25 | E10: 332.69671 | F10: 361.70793 | G10: =F10/$F$28 -> 0.27822617 | H10: =F10/$F$4 -> 0.35288618 | J10: 0 | L10: 2945.7612 | N10: 29.011228 | P10: 0.087685415 | Q10: 0.024078156 | S10: 0.093634906 | T10: 0.026127818
B11: Equity Hybrid | D11: May-22 - Jan-26 | E11: 96.675688 | F11: 105.98628 | G11: =F11/$F$28 -> 0.081524771 | H11: =F11/$F$4 -> 0.10340136 | J11: 0 | L11: 188.74821 | N11: 9.310592 | P11: 0.10094745 | Q11: 0.038213701 | S11: 0.016414568 | T11: 0.034314373
B12: Mid & Small Cap | D12: Sep-24 - Dec-25 | E12: 183.99973 | F12: 246.75783 | G12: =F12/$F$28 -> 0.18980641 | H12: =F12/$F$4 -> 0.24073962 | J12: 0.015907185 | L12: 6277.4015 | N12: 62.774015 | P12: 0.34116363 | Q12: 0.045401409 | S12: 0.4334171 | T12: 0.056590232
B13: Small Cap | D13: Oct-24 - Oct-24 | E13: 1 | F13: 1.1248249 | G13: =F13/$F$28 -> 0.00086521663 | H13: =F13/$F$4 -> 0.0010973914 | J13: 0 | L13: 12.48249 | N13: 0.1248249 | P13: 0.1248249 | Q13: 0.018808085 | S13: 0.072427824 | T13: 0.011138436
B14: SLBM | E14: 0 | F14: 0.24478595 | G14: =F14/$F$28 -> 0.00018828964 | H14: =F14/$F$4 -> 0.00023881583 | J14: 0 | L14: 24.478595 | N14: 0.24478595
B15: LKP Sec Portfolio | D15: Mar-25 - May-26 | E15: 1.0963805 | F15: 0.84977725 | G15: =F15/$F$28 -> 0.00065364966 | H15: =F15/$F$4 -> 0.0008290519 | J15: 0.00195 | L15: -8.7961095 | N15: -0.24465325 | P15: -0.072034374 | Q15: 0.069722837 | S15: -0.10054799 | T15: 0.09777804
B16: Debt | E16: =SUM(E17:E19) -> 43.954001 | F16: =SUM(F17:F19) -> 45.889164 | G16: =SUM(G17:G19) -> 0.035297998 | H16: 1 | J16: =SUM(J17:J19) -> 0.3592938 | L16: =SUM(L17:L19) -> 455.9288 | N16: =SUM(N17:N19) -> 2.2944563 | P16: 0.044904795 | Q16: 0.040250698 | S16: 0.081715778 | T16: 0.072796813
B17: High Yield Fund | D17: Oct-23 - Feb-26 | E17: 3.5 | F17: 3.768427 | G17: =F17/$F$28 -> 0.0028986784 | H17: =F17/$F$16 -> 0.082120193 | J17: 0.3592938 | L17: 76.934878 | N17: 0.62772078 | P17: 0.21981394 | Q17: 0.10395107 | S17: 0.14966583 | T17: 0.069996265
B18: PP Structures | D18: Sep-20 - Mar-24 | E18: 0.70001498 | F18: 1.0434584 | G18: =F18/$F$28 -> 0.00080262946 | H18: =F18/$F$16 -> 0.022738668 | J18: 0 | L18: 34.344347 | N18: 0.34344347 | P18: 0.49062302 | Q18: 0.24620557 | S18: 0.12367324 | T18: 0.067806676
B19: Arbitrage | D19: May-25 - May-26 | E19: 39.753986 | F19: 41.077278 | G19: =F19/$F$28 -> 0.031596691 | H19: =F19/$F$16 -> 0.89514114 | J19: 0 | L19: 344.64957 | N19: 1.3232921 | P19: 0.035409577 | Q19: 0.036478848 | S19: 0.07125822 | T19: 0.073410103
B20: Cash | E20: =E21 -> 5.1332383 | F20: =F21 -> 5.4365436 | G20: =G21 -> 0.0041817957 | H20: 1 | J20: =J21 -> 0 | L20: =L21 -> 34.79289 | N20: =N21 -> 0.30330523 | P20: 0.021945572 | Q20: 0.027548659 | S20: 0.042472556 | T20: 0.053490874
B21: Liquid | D21: Jul-19 - Jun-26 | E21: 5.1332383 | F21: 5.4365436 | G21: =F21/$F$28 -> 0.0041817957 | H21: =F21/$F$20 -> 1 | J21: 0 | L21: 34.79289 | N21: 0.30330523 | P21: 0.021945572 | Q21: 0.027548659 | S21: 0.042472556 | T21: 0.053490874
B22: Alternate | E22: =SUM(E23:E26) -> 216.22516 | F22: =SUM(F23:F26) -> 223.72546 | G22: =SUM(G23:G26) -> 0.17208988 | H22: =SUM(H23:H26) -> 1 | J22: =SUM(J23:J26) -> 0.4347699 | L22: =SUM(L23:L26) -> 505.32827 | N22: =SUM(N23:N26) -> 7.9350638 | P22: 0.055646167 | Q22: 0.03088796 | S22: 0.091461167 | T22: 0.050356653
B23: Silver | D23: Sept'25-Jan'26 | E23: 4.2561917 | F23: 6.5449619 | G23: =F23/$F$28 -> 0.0050343924 | H23: =F23/$F$22 -> 0.029254435 | J23: 0 | L23: 616.02738 | N23: 2.2887702 | P23: 0.74830014 | Q23: 0.82390612
B24: Gold | D24: Jan-26 - Jan-26 | E24: 53.585434 | F24: 48.307867 | G24: =F24/$F$28 -> 0.037158468 | H24: =F24/$F$22 -> 0.21592476 | J24: 0 | L24: -527.7567 | N24: -5.277567 | P24: -0.098488836 | Q24: -0.091201257
B25: PE Funds | D25: Apr-21 - Mar-26 | E25: 22.224236 | F25: 32.713327 | G25: =F25/$F$28 -> 0.025163129 | H25: =F25/$F$22 -> 0.14622085 | J25: 0.4347699 | L25: 417.05758 | N25: 10.923861 | P25: 0.14384676 | Q25: 0.031363764 | S25: 0.13349357 | T25: 0.030562511
B26: Private Equity | D26: Nov 12 - Sept 24 | E26: 136.1593 | F26: 136.1593 | G26: =F26/$F$28 -> 0.1047339 | H26: =F26/$F$22 -> 0.60859995 | J26: 0 | L26: 0 | N26: 0
B28: Total | E28: =E22+E20+E16+E4 -> 1076.0129 | F28: =F22+F20+F16+F4 -> 1300.05 | G28: =G4+G16+G20+G22 -> 1 | J28: =J4+J16+J20+J22 -> 2.6372961 | L28: =L4+L16+L20+L22 -> 21730.598 | N28: =N4+N16+N20+N22 -> 226.6764 | P28: 0.21815232 | Q28: 0.046464029 | S28: 0.21178462 | T28: 0.0528
B29: Total Excl. External Direct Equity / NSE | E29: 925.59881 | F29: 1077.6914 | G29: =G4+G16+G20+G22-G9 -> 0.82896147 | J29: 0.8 | L29: 14843.217 | N29: 152.90448 | P29: 0.1458522 | Q29: 0.035615199 | S29: 0.15754278 | T29: 0.042163882
B30: Note: For investments less than one year, absolute returns have been shown. Private equity is shown at cost.

Sheet Promoter Holding
B7: Product | C7: Quantity | D7: Market Value in lacs
A8: 542652 | B8: Polycab India Ltd. | C8: =SUM(C11:C16) -> 23729601 | D8: =(C8*E8)/10^5 -> 0
B9: Total | C9: =SUM(C8:C8) -> 23729601 | D9: =SUM(D8:D8) -> 0
B11: Ajay JS: Individual | C11: 13901229 | D11: =(C11*$E$8)/10^5 -> 0 | E11: Source: ICIC Demat
B12: Category : Others | C12: 1300100 | D12: =(C12*$E$8)/10^5 -> 0 | E12: Source: Investor release (March 25)
B13: Category : Others | C13: 1100100 | D13: =(C13*$E$8)/10^5 -> 0 | E13: Source: Investor release (March 25)
B14: Category : Others | C14: 2150100 | D14: =(C14*$E$8)/10^5 -> 0 | E14: Source: Investor release (March 25)
B15: Aarti Ajay JS | C15: =62500-7000 -> 55500 | E15: Source: ICICI Demat as on 29th August 2025
B16: Bahart JS | C16: 5222572 | D16: =(C16*$E$8)/10^5 -> 0 | E16: Source: Investor release (March 25)

Sheet Live Equity Performance
B1: From Equity Live file | E1: Check | F1: =F4-'Portfolio Allocation'!F4 -> 0
B2: Category | D2: Investment Date Range | E2: Investment at Cost | F2: Market Value | G2: Allocation (%) | H2: Allocation (% of Asset Class) | J2: Dividend / Interest | L2: Absolute Gain / (Loss) Including Redeemed Funds | N2: Absolute Gain / (Loss) Active Funds | P2: Absolute Returns (%) | S2: Annualized Returns (%)
P3: Portfolio | Q3: Blended Index | S3: Portfolio | T3: Blended Index
B4: Equity | E4: =SUM(E7:E15) -> 810.70047 | F4: =SUM(F7:F15) -> 1024.9989 | G4: =IFERROR(F4/$F$16,0) -> 1 | H4: =SUM(H7:H15) -> 1 | J4: =SUM(J7:J15) -> 1.8451824 | L4: =SUM(L7:L15) -> 20734.548 | N4: =SUM(N7:N15) -> 216.14357 | P4: =VLOOKUP($B4,'Portfolio Allocation'!$B$2:$T$29,15,0) -> 0.26003127 | Q4: =VLOOKUP($B4,'Portfolio Allocation'!$B$2:$T$29,16,0) -> 0.049233916 | S4: =VLOOKUP($B4,'Portfolio Allocation'!$B$2:$T$29,18,0) -> 0.22988721 | T4: =VLOOKUP($B4,'Portfolio Allocation'!$B$2:$T$29,19,0) -> 0.051674172
B5: Equity (Excl NSE) | E5: ='Portfolio Allocation'!E5 -> 798.61547 | F5: ='Portfolio Allocation'!F5 -> 983.49886 | J5: ='Portfolio Allocation'!J5 -> 1.8432324 | L5: =L4-L8 -> 17010.356 | N5: =N4-N8 -> 178.90165 | P5: =VLOOKUP($B5,'Portfolio Allocation'!$B$2:$T$29,15,0) -> 0.1924727 | Q5: =VLOOKUP($B5,'Portfolio Allocation'!$B$2:$T$29,16,0) -> 0.041027379 | S5: =VLOOKUP($B5,'Portfolio Allocation'!$B$2:$T$29,18,0) -> 0.19345655 | T5: =VLOOKUP($B5,'Portfolio Allocation'!$B$2:$T$29,19,0) -> 0.048554507
B6: Equity (Excl NSE / External Direct Equity) | E6: =E5-E9 -> 648.20141 | F6: =F5-F9 -> 761.14021 | L6: =L5-L9 -> 10122.975 | N6: =N5-N9 -> 105.12973 | P6: =VLOOKUP($B6,'Portfolio Allocation'!$B$2:$T$29,15,0) -> 0.1458522 | Q6: =VLOOKUP($B6,'Portfolio Allocation'!$B$2:$T$29,16,0) -> 0.035615199 | S6: =VLOOKUP($B6,'Portfolio Allocation'!$B$2:$T$29,18,0) -> 0.15754278 | T6: =VLOOKUP($B6,'Portfolio Allocation'!$B$2:$T$29,19,0) -> 0.042163882
A7: * | B7: Direct Equity - MO | D7: ='Portfolio Allocation'!D7 -> Nov-22 - Dec-25 | E7: =VLOOKUP($B7,'Portfolio Allocation'!$B$2:$T$29,4,0) -> 17.731316 | F7: =VLOOKUP($B7,'Portfolio Allocation'!$B$2:$T$29,5,0) -> 21.640258 | G7: =IFERROR(F7/$F$16,0) -> 0.02111247 | H7: =IFERROR(G7/$G$4,0) -> 0.02111247 | J7: =VLOOKUP($B7,'Portfolio Allocation'!$B$2:$T$29,9,0) -> 0 | L7: ='Portfolio Allocation'!L7 -> 682.89959 | N7: =(F7+J7)-E7 -> 3.9089419 | P7: =VLOOKUP($B7,'Portfolio Allocation'!$B$2:$T$29,15,0) -> 0.26617787 | Q7: =VLOOKUP($B7,'Portfolio Allocation'!$B$2:$T$29,16,0) -> 0.055932598 | S7: =VLOOKUP($B7,'Portfolio Allocation'!$B$2:$T$29,18,0) -> 0.17558801 | T7: =VLOOKUP($B7,'Portfolio Allocation'!$B$2:$T$29,19,0) -> 0.038443562
B8: Direct Equity - Unlisted | D8: ='Portfolio Allocation'!D8 -> Dec-22 - Feb-25 | E8: =VLOOKUP($B8,'Portfolio Allocation'!$B$2:$T$29,4,0) -> 27.086596 | F8: =VLOOKUP($B8,'Portfolio Allocation'!$B$2:$T$29,5,0) -> 64.328516 | G8: =IFERROR(F8/$F$16,0) -> 0.062759597 | H8: =IFERROR(G8/$G$4,0) -> 0.062759597 | J8: =VLOOKUP($B8,'Portfolio Allocation'!$B$2:$T$29,9,0) -> 0 | L8: ='Portfolio Allocation'!L8 -> 3724.192 | N8: =(F8+J8)-E8 -> 37.24192 | P8: =VLOOKUP($B8,'Portfolio Allocation'!$B$2:$T$29,15,0) -> 1.3749206 | Q8: =VLOOKUP($B8,'Portfolio Allocation'!$B$2:$T$29,16,0) -> 0.29941829 | S8: =VLOOKUP($B8,'Portfolio Allocation'!$B$2:$T$29,18,0) -> 0.5395584 | T8: =VLOOKUP($B8,'Portfolio Allocation'!$B$2:$T$29,19,0) -> 0.15761568
B9: Direct Equity - Non MO | D9: ='Portfolio Allocation'!D9 -> Jul-23 - Jun-26 | E9: =VLOOKUP($B9,'Portfolio Allocation'!$B$2:$T$29,4,0) -> 150.41406 | F9: =VLOOKUP($B9,'Portfolio Allocation'!$B$2:$T$29,5,0) -> 222.35865 | G9: =IFERROR(F9/$F$16,0) -> 0.21693551 | H9: =IFERROR(G9/$G$4,0) -> 0.21693551 | J9: =VLOOKUP($B9,'Portfolio Allocation'!$B$2:$T$29,9,0) -> 1.8273252 | L9: ='Portfolio Allocation'!L9 -> 6887.3804 | N9: =(F9+J9)-E9 -> 73.771919 | P9: =VLOOKUP($B9,'Portfolio Allocation'!$B$2:$T$29,15,0) -> 0.43578585 | Q9: =VLOOKUP($B9,'Portfolio Allocation'!$B$2:$T$29,16,0) -> 0.069273635 | S9: =VLOOKUP($B9,'Portfolio Allocation'!$B$2:$T$29,18,0) -> 0.32026554 | T9: =VLOOKUP($B9,'Portfolio Allocation'!$B$2:$T$29,19,0) -> 0.072169986
B10: Multi Cap | D10: ='Portfolio Allocation'!D10 -> March 20 - Aug 25 | E10: =VLOOKUP($B10,'Portfolio Allocation'!$B$2:$T$29,4,0) -> 332.69671 | F10: =VLOOKUP($B10,'Portfolio Allocation'!$B$2:$T$29,5,0) -> 361.70793 | G10: =IFERROR(F10/$F$16,0) -> 0.35288618 | H10: =IFERROR(G10/$G$4,0) -> 0.35288618 | J10: =VLOOKUP($B10,'Portfolio Allocation'!$B$2:$T$29,9,0) -> 0 | L10: ='Portfolio Allocation'!L10 -> 2945.7612 | N10: =(F10+J10)-E10 -> 29.011228 | P10: =VLOOKUP($B10,'Portfolio Allocation'!$B$2:$T$29,15,0) -> 0.087685415 | Q10: =VLOOKUP($B10,'Portfolio Allocation'!$B$2:$T$29,16,0) -> 0.024078156 | S10: =VLOOKUP($B10,'Portfolio Allocation'!$B$2:$T$29,18,0) -> 0.093634906 | T10: =VLOOKUP($B10,'Portfolio Allocation'!$B$2:$T$29,19,0) -> 0.026127818
B11: Equity Hybrid | D11: ='Portfolio Allocation'!D11 -> May-22 - Jan-26 | E11: =VLOOKUP($B11,'Portfolio Allocation'!$B$2:$T$29,4,0) -> 96.675688 | F11: =VLOOKUP($B11,'Portfolio Allocation'!$B$2:$T$29,5,0) -> 105.98628 | G11: =IFERROR(F11/$F$16,0) -> 0.10340136 | H11: =IFERROR(G11/$G$4,0) -> 0.10340136 | J11: =VLOOKUP($B11,'Portfolio Allocation'!$B$2:$T$29,9,0) -> 0 | L11: ='Portfolio Allocation'!L11 -> 188.74821 | N11: =(F11+J11)-E11 -> 9.310592 | P11: =VLOOKUP($B11,'Portfolio Allocation'!$B$2:$T$29,15,0) -> 0.10094745 | Q11: =VLOOKUP($B11,'Portfolio Allocation'!$B$2:$T$29,16,0) -> 0.038213701 | S11: =VLOOKUP($B11,'Portfolio Allocation'!$B$2:$T$29,18,0) -> 0.016414568 | T11: =VLOOKUP($B11,'Portfolio Allocation'!$B$2:$T$29,19,0) -> 0.034314373
B12: Mid & Small Cap | D12: ='Portfolio Allocation'!D12 -> Sep-24 - Dec-25 | E12: =VLOOKUP($B12,'Portfolio Allocation'!$B$2:$T$29,4,0) -> 183.99973 | F12: =VLOOKUP($B12,'Portfolio Allocation'!$B$2:$T$29,5,0) -> 246.75783 | G12: =IFERROR(F12/$F$16,0) -> 0.24073962 | H12: =IFERROR(G12/$G$4,0) -> 0.24073962 | J12: =VLOOKUP($B12,'Portfolio Allocation'!$B$2:$T$29,9,0) -> 0.015907185 | L12: ='Portfolio Allocation'!L12 -> 6277.4015 | N12: =(F12+J12)-E12 -> 62.774015 | P12: =VLOOKUP($B12,'Portfolio Allocation'!$B$2:$T$29,15,0) -> 0.34116363 | Q12: =VLOOKUP($B12,'Portfolio Allocation'!$B$2:$T$29,16,0) -> 0.045401409 | S12: =VLOOKUP($B12,'Portfolio Allocation'!$B$2:$T$29,18,0) -> 0.4334171 | T12: =VLOOKUP($B12,'Portfolio Allocation'!$B$2:$T$29,19,0) -> 0.056590232
B13: Small Cap | D13: ='Portfolio Allocation'!D13 -> Oct-24 - Oct-24 | E13: =VLOOKUP($B13,'Portfolio Allocation'!$B$2:$T$29,4,0) -> 1 | F13: =VLOOKUP($B13,'Portfolio Allocation'!$B$2:$T$29,5,0) -> 1.1248249 | G13: =IFERROR(F13/$F$16,0) -> 0.0010973914 | H13: =IFERROR(G13/$G$4,0) -> 0.0010973914 | J13: =VLOOKUP($B13,'Portfolio Allocation'!$B$2:$T$29,9,0) -> 0 | L13: ='Portfolio Allocation'!L13 -> 12.48249 | N13: =(F13+J13)-E13 -> 0.1248249 | P13: =VLOOKUP($B13,'Portfolio Allocation'!$B$2:$T$29,15,0) -> 0.1248249 | Q13: =VLOOKUP($B13,'Portfolio Allocation'!$B$2:$T$29,16,0) -> 0.018808085 | S13: =VLOOKUP($B13,'Portfolio Allocation'!$B$2:$T$29,18,0) -> 0.072427824 | T13: =VLOOKUP($B13,'Portfolio Allocation'!$B$2:$T$29,19,0) -> 0.011138436
B14: SLBM | E14: =VLOOKUP($B14,'Portfolio Allocation'!$B$2:$T$29,4,0) -> 0 | F14: =VLOOKUP($B14,'Portfolio Allocation'!$B$2:$T$29,5,0) -> 0.24478595 | G14: =IFERROR(F14/$F$16,0) -> 0.00023881583 | H14: =IFERROR(G14/$G$4,0) -> 0.00023881583 | J14: =VLOOKUP($B14,'Portfolio Allocation'!$B$2:$T$29,9,0) -> 0 | L14: ='Portfolio Allocation'!L14 -> 24.478595 | N14: =(F14+J14)-E14 -> 0.24478595
B15: LKP Sec Portfolio | D15: ='Portfolio Allocation'!D15 -> Mar-25 - May-26 | E15: =VLOOKUP($B15,'Portfolio Allocation'!$B$2:$T$29,4,0) -> 1.0963805 | F15: =VLOOKUP($B15,'Portfolio Allocation'!$B$2:$T$29,5,0) -> 0.84977725 | G15: =IFERROR(F15/$F$16,0) -> 0.0008290519 | H15: =IFERROR(G15/$G$4,0) -> 0.0008290519 | J15: =VLOOKUP($B15,'Portfolio Allocation'!$B$2:$T$29,9,0) -> 0.00195 | L15: ='Portfolio Allocation'!L15 -> -8.7961095 | N15: =(F15+J15)-E15 -> -0.24465325 | P15: =VLOOKUP($B15,'Portfolio Allocation'!$B$2:$T$29,15,0) -> -0.072034374 | Q15: =VLOOKUP($B15,'Portfolio Allocation'!$B$2:$T$29,16,0) -> 0.069722837 | S15: =VLOOKUP($B15,'Portfolio Allocation'!$B$2:$T$29,18,0) -> -0.10054799 | T15: =VLOOKUP($B15,'Portfolio Allocation'!$B$2:$T$29,19,0) -> 0.09777804
B16: Total | E16: =E4 -> 810.70047 | F16: =F4 -> 1024.9989 | G16: =G4 -> 1 | J16: =J4 -> 1.8451824 | L16: =L4 -> 20734.548 | N16: =N4 -> 216.14357 | P16: ='Portfolio Allocation'!P4 -> 0.26003127 | Q16: ='Portfolio Allocation'!Q4 -> 0.049233916 | S16: ='Portfolio Allocation'!S4 -> 0.22988721 | T16: ='Portfolio Allocation'!T4 -> 0.051674172
B17: * Direct Equity advised by MOSL adds Onesource from unlisted to listed and annualized returns reflect performance of the same; swiggy has been redeemed in May -June 2025.

Sheet Asset Allocation
B1: from Live consol | C1: 2 | D1: 3 | E1: 4 | F1: 6 | G1: Post adjusted value of liquidity in Debt / cash to be allocated from
B2: Asset Class | C2: Market Value in Lakhs | D2: Allocation (%) | E2: Effective Allocation (%) | F2: Liquidity to be assigned | G2: Adjusted Value | H2: Allocation (%) | I2: Effective Allocation (%)
B3: Equity | C3: 1024.9989 | D3: 0.78843032 | E3: 0.72003376 | G3: =C3-F3 -> 1024.9989 | H3: 0.81768588 | I3: 0.7467514
B4: Debt | C4: 45.889164 | D4: 0.035297998 | E4: 0.075495493 | F4: 41.077278 | G4: =C4-F4 -> 4.8118854 | H4: 0.003838649 | I4: 0.045527715
B5: Alternate* | C5: 223.72546 | D5: 0.17208988 | E5: 0.19066432 | G5: =C5-F5 -> 223.72546 | H5: 0.17847547 | I5: 0.19773913
B6: Cash | C6: 5.4365436 | D6: 0.0041817957 | E6: 0.013806424 | F6: 5.4365436 | G6: =C6-F6 -> 0 | H6: 0 | I6: 0.0099817607
B7: Total | C7: =SUM(C3:C6) -> 1300.05 | D7: =SUM(D3:D6) -> 1 | E7: =SUM(E3:E6) -> 1 | F7: =SUM(F3:F6) -> 46.513822 | G7: =SUM(G3:G6) -> 1253.5362 | H7: =SUM(H3:H6) -> 1 | I7: =SUM(I3:I6) -> 1
B9: Note: Pvt investments for Asset allocation are taken at cost. This reflects the actual allocation closer to current realized value.
B12: Particulars | C12: Total Portfolio AUM | D12: Total Portfolio Allocation | E12: Equity Aum in Cr (Sheet) | F12: Allocation of Equity Portfolio | G12: Debt AUM in Cr (Sheet) | H12: Allocation of Debt Portfolio | I12: Cash AUM in Cr (sheet) | J12: Allocation of Cash portfolio | K12: Alternate AUM in Cr (Sheet) | L12: Allocation of Alternate Portfolio
B13: Growth
A14: SG | B14: Stable | C14: =E14+G14+I14+K14 -> 541.90311 | D14: =C14/$C$18 -> 0.41691101 | E14: =SUMIF(Equity!$A:$A,'Asset Allocation'!A14,Equity!$H:$H) -> 538.13468 | F14: =E14/$E$18 -> 0.52513544 | G14: =SUMIF(Debt!$A:$A,'Asset Allocation'!A14,Debt!$F:$F) -> 3.768427 | H14: =G14/$G$18 -> 0.082120193 | I14: 0 | J14: =I14/$I$18 -> 0 | K14: =SUMIF(Alternate!$A:$A,'Asset Allocation'!A14,Alternate!$E:$E) -> 0 | L14: =K14/$K$18 -> 0
A15: EG | B15: Entrepreneur | C15: =E15+G15+I15+K15 -> 191.70115 | D15: =C15/$C$18 -> 0.14748452 | E15: =SUMIF(Equity!$A:$A,'Asset Allocation'!A15,Equity!$H:$H) -> 22.828516 | F15: =E15/$E$18 -> 0.022277068 | G15: =SUMIF(Debt!$A:$A,'Asset Allocation'!A15,Debt!$F:$F) -> 0 | H15: =G15/$G$18 -> 0 | I15: 0 | J15: =I15/$I$18 -> 0 | K15: =SUMIF(Alternate!$A:$A,'Asset Allocation'!A15,Alternate!$E:$E) -> 168.87263 | L15: =K15/$K$18 -> 0.7548208
A16: Liquid | B16: Liquid | C16: =E16+G16+I16+K16 -> 152.5001 | D16: =C16/$C$18 -> 0.11732535 | E16: =SUMIF(Equity!$A:$A,'Asset Allocation'!A16,Equity!$H:$H) -> 105.98628 | F16: =E16/$E$18 -> 0.10342606 | G16: =SUMIF(Debt!$A:$A,'Asset Allocation'!A16,Debt!$F:$F) -> 41.077278 | H16: =G16/$G$18 -> 0.89514114 | I16: =SUMIF(Cash!$A:$A,'Asset Allocation'!A16,Cash!$F:$F) -> 5.4365436 | J16: =I16/$I$18 -> 1 | K16: =SUMIF(Alternate!$A:$A,'Asset Allocation'!A16,Alternate!$E:$E) -> 0 | L16: =K16/$K$18 -> 0
A17: TT | B17: Thematic/Tactical | C17: =E17+G17+I17+K17 -> 413.70088 | D17: =C17/$C$18 -> 0.31827913 | E17: =SUMIF(Equity!$A:$A,'Asset Allocation'!A17,Equity!$H:$H) -> 357.80459 | F17: =E17/$E$18 -> 0.34916143 | G17: =SUMIF(Debt!$A:$A,'Asset Allocation'!A17,Debt!$F:$F) -> 1.0434584 | H17: =G17/$G$18 -> 0.022738668 | I17: 0 | J17: =I17/$I$18 -> 0 | K17: =SUMIF(Alternate!$A:$A,'Asset Allocation'!A17,Alternate!$E:$E) -> 54.852829 | L17: =K17/$K$18 -> 0.2451792
B18: Total | C18: =SUM(C14:C17) -> 1299.8052 | D18: =SUM(D14:D17) -> 1 | E18: =SUM(E13:E17) -> 1024.7541 | F18: =SUM(F13:F17) -> 1 | G18: =SUM(G13:G17) -> 45.889164 | H18: =SUM(H13:H17) -> 1 | I18: =SUM(I13:I17) -> 5.4365436 | J18: =SUM(J13:J17) -> 1 | K18: =SUM(K13:K17) -> 223.72546 | L18: =SUM(L13:L17) -> 1

Sheet Stable Growth
C2: Product | D2: Investment Date Range | E2: Advisor | F2: Investor | G2: Investment at Cost (in crores) | H2: Market Value (in crores) | I2: Allocation (%) | J2: Benchmark | K2: Scheme Absolute (%) | L2: Index Absolute (%) | M2: Scheme XIRR (%) | N2: Index XIRR (%)
C3: Motilal Oswal Founders Fund II | D3: Aug-24 - Oct-24 | E3: MOPWM | F3: Ajay Jaisinghani / Ankita Jaisinghani | G3: 29.9985 | H3: 32.706287 | I3: =H3/$H$16 -> 0.060354492 | J3: S&P BSE 500 TR | K3: 0.090264064 | L3: 0.0078803335 | M3: 0.049043646 | N3: 0.0043587536
C4: Carnelian Bespoke Portfolio | D4: Jan-25 - Dec-25 | E4: Carnelian | F4: Ajay Jaisinghani | G4: 33 | H4: 40.047568 | I4: =H4/$H$16 -> 0.073901713 | J4: S&P BSE 500 TR | K4: 0.21356266 | L4: 0.019115723 | M4: 0.17886855 | N4: 0.016431174
C5: Buoyant Opportunities Portfolio AIF | D5: May-24 - Jun-26 | E5: MOPWM | F5: Ajay Jaisinghani / Ankita Jaisinghani | G5: 70.855886 | H5: 76.047925 | I5: =H5/$H$16 -> 0.14033491 | J5: S&P BSE 500 TR | K5: 0.073276036 | L5: 0.028688756 | M5: 0.11424926 | N5: 0.045162562
C6: 3P India Equity Fund 1 | D6: Apr-23 - Nov-25 | E6: MOPWM | F6: Ajay Jaisinghani / Ankita Jaisinghani | G6: 47.49516 | H6: 52.115602 | I6: =H6/$H$16 -> 0.096171439 | J6: S&P BSE 500 TR | K6: 0.097282361 | L6: 0.094633109 | M6: 0.072618744 | N6: 0.070717308
C7: Helios Flexi Cap Fund Direct (G) | D7: Aug-24 - Nov-25 | E7: MOPWM | F7: Ajay Jaisinghani / Ankita Jaisinghani / Bharat Jaisinghani / Bharat Jaisinghani Family Trust II / Bharat Jaisinghani Family Trust III | G7: 25.318415 | H7: 27.174766 | I7: =H7/$H$16 -> 0.05014691 | J7: Nifty 500 TRI | K7: 0.073320214 | L7: -0.0038231602 | M7: 0.066808715 | N7: -0.0035201839
C8: ICICI Pru India Opportunities Fund | D8: Mar-25 - Mar-26 | E8: MOPWM Dir | F8: Ajay Jaisinghani / Ankita Jaisinghani / Bharat Jaisinghani | G8: 24.854421 | H8: 25.418104 | I8: =H8/$H$16 -> 0.046905255 | J8: Nifty 500 TRI | K8: 0.035939998 | L8: 0.048954901 | M8: 0.055750164 | N8: 0.076058045
C9: Kotak Large & Midcap Fund - Direct- Growth | D9: Mar-20 | E9: MOPWM Dir | F9: Ajay Jaisinghani | G9: 1.5860418 | H9: 2.5003334 | I9: =H9/$H$16 -> 0.0046139861 | J9: Nifty 500 TRI | K9: 0.57646126 | L9: 0.49445855 | M9: 0.23195326 | N9: 0.20958738
C10: Bandhan Large & Mid Cap Fund - Direct Plan - Growth | D10: Apr-26 | E10: MOPWM | F10: Aarti Ajay Jaisinghani / Ajay Jaisinghani / Ankita Jaisinghani | G10: 24.380016 | H10: 24.782832 | I10: =H10/$H$16 -> 0.045732958 | J10: Nifty 500 TRI | K10: 0.016522376 | L10: 0.019394611
C11: Kotak Multicap Fund-Direct Plan-Growth | D11: Apr-26 | E11: MOPWM | F11: Aarti Ajay Jaisinghani / Ajay Jaisinghani | G11: 9.9995 | H11: 10.236297 | I11: =H11/$H$16 -> 0.018889534 | J11: Nifty 500 TRI | K11: 0.023680902 | L11: 0.012127361
C12: Sanshi Fund 1 | D12: Mar-25 | E12: Mukul Agarwal | F12: Aarti Ajay Jaisinghani / Ajay Jaisinghani / Ankita Jaisinghani / Bharat Jaisinghani | G12: 147.49973 | H12: 204.48014 | I12: =H12/$H$16 -> 0.37733709 | J12: Nifty Mid & Smallcap 400 TR | K12: 0.38630864 | L12: 0.051790642 | M12: 0.59185677 | N12: 0.074412158
C13: Molecule Growth Strategy | D13: Oct-24 | E13: Molecule Venture | F13: Ajay Jaisinghani | G13: 1 | H13: 1.1248249 | I13: =H13/$H$16 -> 0.0020756938 | J13: S&P BSE 500 TR | K13: 0.1248249 | L13: 0.018808085 | M13: 0.072427824 | N13: 0.011138436
C14: National Stock Exchange | D14: Dec-22 - Aug-23 | E14: ICICI Bank / MOPWM | F14: Ajay Jaisinghani / Ankita Jaisinghani | G14: 12.085 | H14: 41.5 | I14: =H14/$H$16 -> 0.076581956 | J14: Nifty 500 TRI | K14: 2.4340091 | L14: 0.51558469 | M14: 0.46641998 | N14: 0.13803429
C15: Neo Infra Income Opportunities Fund Share Class A5 | D15: Oct-23 - Feb-26 | G15: 3.5 | H15: 3.768427 | I15: =H15/$H$16 -> 0.0069540605 | J15: CRISIL Short Term | K15: 0.21981394 | L15: 0.10395107 | M15: 0.14966583 | N15: 0.069996265
C16: Total | G16: =SUM(G3:G15) -> 431.57267 | H16: =SUM(H3:H15) -> 541.90311 | I16: =SUM(I3:I15) -> 1

Sheet Entrepreneruial Growth
C2: Product | D2: Investment Date Range | E2: Advisor | F2: Investor | G2: Investment at Cost (in crores) | H2: Market Value (in crores) | I2: Allocation (%) | J2: Benchmark | K2: Scheme Absolute (%) | L2: Index Absolute (%) | M2: Scheme XIRR (%) | N2: Index XIRR (%)
C3: Zepto | D3: Feb-25 | E3: MOPWM | F3: Ajay Jaisinghani | G3: 15.001596 | H3: 22.828516 | I3: =H3/$H$11 -> 0.11510555 | J3: Nifty 500 TRI | K3: 0.52173913 | L3: 0.12527876
C4: Private Equity | D4: 43984 | G4: 136.1593 | H4: 142.78496 | I4: =H4/$H$11 -> 0.71994788
C5: India SME | D5: Sep-24 - Mar-26 | G5: 13.5 | H5: 15.93 | I5: =H5/$H$11 -> 0.080321972 | J5: Nifty 500 TRI | K5: 0.18300652 | L5: -0.096401407 | M5: 0.22696287 | N5: -0.12429736
C6: Baring PE India Fund 6 | D6: Oct-24 - Sep-25 | G6: 2.025 | H6: 1.8842209 | I6: =H6/$H$11 -> 0.009500586 | J6: Nifty 500 TRI | K6: 0 | L6: 0 | M6: 0 | N6: 0
C7: 360 One Special Opportunities Fund - Series 8 - Class A3 (AIF Category II) | D7: Apr-21 - Apr-21 | G7: 1.984236 | H7: 2.9160826 | I7: =H7/$H$11 -> 0.014703421 | J7: Nifty 500 TRI | K7: 0.65590367 | L7: 0.99829501 | M7: 0.10584796 | N7: 0.14302306
C8: Sky Capital Titan Rising Funds 1 | D8: May-25 - Feb-26 | G8: 4.715 | H8: 4.715 | I8: =H8/$H$11 -> 0.023773892 | J8: Alternate Index | K8: 0 | L8: 0 | M8: 0 | N8: 0
C9: Assetgro Fintech Private Limited | D9: Nov-25 - Nov-25 | G9: 0 | H9: 5.0032848 | I9: =H9/$H$11 -> 0.025227476 | J9: Alternate Index | K9: 0 | L9: 0.048322712
C10: Transition Venture Capital fund I | D10: Aug-25 - Oct-25 | G10: 0 | H10: 2.2647385 | I10: =H10/$H$11 -> 0.011419225 | J10: Alternate Index | K10: 0.29413629 | L10: 0.030877525
C11: Total | G11: =SUM(G3:G10) -> 173.38513 | H11: =SUM(H3:H10) -> 198.32681 | I11: =SUM(I3:I10) -> 1

Sheet Thematic,Tactical
C2: Product | D2: Investment Date Range | E2: Advisor | F2: Investor | G2: Investment at Cost (in crores) | H2: Market Value (in crores) | I2: Allocation (%) | J2: Benchmark | K2: Scheme Absolute (%) | L2: Index Absolute (%) | M2: Scheme XIRR (%) | N2: Index XIRR (%)
C3: Aristos Equity Potrfolio - SB | D3: Dec-25 - Dec-25 | E3: Sanjay Bhattacharya | F3: Ajay Jaisinghani / Ankita Jaisinghani | G3: 25 | H3: 25.922903 | I3: =H3/$H$47 -> 0.062958399 | J3: Nifty 50 TRI | K3: 0.03691612 | L3: -0.073733021
C4: Green Lantern Growth Strategy | D4: Jan-25 | E4: Green Lantern | F4: Ajay Jaisinghani / Ankita Jaisinghani | G4: 15.208723 | H4: 17.617651 | I4: =H4/$H$47 -> 0.042787612 | J4: S&P BSE 500 TR | K4: 0.15839126 | L4: 0.079591185 | M4: 0.10670952 | N4: 0.05422844
C5: Fund of Funds (VEC+ Carnelian+Girik Cap+Insightful) | D5: Nov-24 - Nov-24 | E5: MOPWM | F5: Ajay Jaisinghani | G5: 10 | H5: 11.128744 | I5: =H5/$H$47 -> 0.027028141 | J5: Nifty 500 TRI | K5: 0.11287435 | L5: 0.019793346 | M5: 0.080529395 | N5: 0.01429567
C6: Carnelian Bharat Amritkaal Fund | D6: Aug-25 | E6: MOPWM | F6: Ankita Jaisinghani | G6: 15.000043 | H6: 16.008922 | I6: =H6/$H$47 -> 0.038880526 | J6: Nifty 500 TRI | K6: 0.067258447 | L6: -0.10187298 | M6: 0.14816979 | N6: -0.20571077
C7: Svan Investment | D7: Sep-24 - Oct-25 | E7: Svan | F7: Ajay Jaisinghani / Bharat Jaisinghani | G7: 24 | H7: 26.383247 | I7: =H7/$H$47 -> 0.064076426 | J7: S&P BSE 500 TR | K7: 0.099964747 | L7: 0.027818461 | M7: 0.071813414 | N7: 0.02022101
C8: VEC Small and Mid cap fund | D8: Jul-25 | E8: MOPWM | F8: Ajay Jaisinghani / Ankita Jaisinghani | G8: 12.5 | H8: 15.894442 | I8: =H8/$H$47 -> 0.038602491 | J8: S&P BSE 500 TR | K8: 0.27155537 | L8: 0.0037678631
C9: DSP Silver ETF | D9: Sep-25 - Sep-25 | G9: 4.2561917 | H9: 6.5449619 | I9: =H9/$H$47 -> 0.015895609 | J9: MCX Silver | K9: 0.74830014 | L9: 0.82390612
C10: DSP Gold ETF | D10: Jan-26 - Jan-26 | G10: 53.585434 | H10: 48.307867 | I10: =H10/$H$47 -> 0.11732428 | J10: MCX GOLD SPOT | K10: -0.098488836 | L10: -0.091201257
C11: 15% K M Global - Credit Private Limited | D11: Sep-20 - Mar-24 | G11: 0.70001498 | H11: 1.0434584 | I11: =H11/$H$47 -> 0.0025342252 | J11: CRISIL Short Term | K11: 0.49062302 | L11: 0.24620557 | M11: 0.12367324 | N11: 0.067806676
C12: LKP Sec Portfolio | D12: 0 | E12: LKP | F12: Bharat Jaisinghani | G12: 1.0963805 | H12: 0.84977725 | I12: =H12/$H$47 -> 0.0020638358 | J12: 0 | K12: -0.072034374 | L12: 0.069722837 | M12: -0.10054799 | N12: 0.09777804
C13: Bharat Parenterals Ltd | D13: Nov-24 | E13: MOPWM | F13: Ankita Jaisinghani | G13: 0.090745032 | H13: 0.08442 | I13: =H13/$H$47 -> 0.00020502904 | J13: Nifty Mid & Smallcap 400 TR | K13: -0.066140798 | L13: 0.077828824 | M13: -0.041599378 | N13: 0.047544053
C14: Birla Cable Ltd. | D14: Aug-23 - Jan-24 | E14: MOPWM | F14: Ajay Jaisinghani / Bharat Jaisinghani | G14: 0.36973099 | H14: 0.3127479 | I14: =H14/$H$47 -> 0.00075956413 | J14: Nifty Mid & Smallcap 400 TR | K14: -0.29805272 | L14: 0.47520331 | M14: -0.16933851 | N14: 0.2278928
C15: BSE Ltd. | D15: Jul-23 - Oct-24 | E15: MOPWM | F15: Ajay Jaisinghani | G15: 0 | H15: 15.4624 | I15: =H15/$H$47 -> 0.037553199 | J15: Nifty Mid & Smallcap 400 TR | K15: 3.3766661 | L15: 0.15307721 | M15: 1.3370817 | N15: 0.092957088
C16: Deepak Fert | D16: Jul-24 - Aug-24 | E16: HDFC Bank / MOPWM | F16: Ajay Jaisinghani | G16: 2.5226066 | H16: 4.0400237 | I16: =H16/$H$47 -> 0.0098119188 | J16: Nifty Mid & Smallcap 400 TR | K16: 0.62054365 | L16: 0.056710201 | M16: 0.29264398 | N16: 0.029473165
C17: Fractal Analytics Limited | D17: Jul-25 - Jul-25 | E17: ICICI Bank | F17: Ajay Jaisinghani | G17: 17.687888 | H17: 16.032861 | I17: =H17/$H$47 -> 0.038938666 | J17: Nifty Mid & Smallcap 400 TR | K17: -0.093568367 | L17: 0.030529841
C18: IFB Inds. | D18: Sep-25 - Sep-25 | E18: MOPWM | F18: Ajay Jaisinghani | G18: 2.386564 | H18: 2.0363229 | I18: =H18/$H$47 -> 0.0049455738 | J18: Nifty Mid & Smallcap 400 TR | K18: -0.26925924 | L18: -0.013144243
C19: Infinium Pharmachem Ltd. | D19: Nov-24 | E19: MOPWM | F19: Ankita Jaisinghani | G19: 0.297729 | H19: 0.15424 | I19: =H19/$H$47 -> 0.00037459938 | J19: Nifty Mid & Smallcap 400 TR | K19: -0.40075965 | L19: 0.074973291 | M19: -0.2797844 | N19: 0.04712806
C20: Insolation Energy Ltd | D20: Dec-24 | E20: ICICI Bank | F20: Ajay Jaisinghani / Bharat Jaisinghani | G20: 9.9681562 | H20: 3.5238812 | I20: =H20/$H$47 -> 0.0085583747 | J20: Nifty Mid & Smallcap 400 TR | K20: -0.64648616 | L20: 0.018308548 | M20: -0.48857966 | N20: 0.011768684
C21: Jaro Education | D21: May-24 | E21: ICICI Bank | F21: Ajay Jaisinghani | G21: 7.500035 | H21: 5.7957246 | I21: =H21/$H$47 -> 0.014075952 | J21: Nifty Mid & Smallcap 400 TR | K21: -0.22724033 | L21: 0.13100728 | M21: -0.14457367 | N21: 0.07557573
C22: Kingfa Science & Technology Ltd. | D22: Jul-24 - Jun-25 | E22: HDFC Bank / MOPWM | F22: Ajay Jaisinghani | G22: 5.4945529 | H22: 10.05693 | I22: =H22/$H$47 -> 0.02442505 | J22: Nifty Mid & Smallcap 400 TR | K22: 0.8319563 | L22: 0.063249664 | M22: 0.50014291 | N22: 0.042839798
C23: Man Industries | D23: May-24 - Jul-25 | E23: HDFC Bank / MOPWM | F23: Ajay Jaisinghani | G23: 19.271126 | H23: 33.899698 | I23: =H23/$H$47 -> 0.082331469 | J23: Nifty Mid & Smallcap 400 TR | K23: 0.75909275 | L23: 0.065319298 | M23: 0.63026349 | N23: 0.058052889
C24: Manorama Industries Ltd. | D24: Aug-23 - Jan-26 | E24: HDFC Bank / MOPWM | F24: Ajay Jaisinghani | G24: 15.182156 | H24: 25.053337 | I24: =H24/$H$47 -> 0.060846503 | J24: Nifty Mid & Smallcap 400 TR | K24: 0.65085739 | L24: -0.11210566 | M24: 0.50582085 | N24: 0.050758591
C25: Neuland Labs. | D25: Jan-24 - May-25 | E25: MOPWM | F25: Ajay Jaisinghani | G25: 4.5809307 | H25: 8.6164675 | I25: =H25/$H$47 -> 0.02092663 | J25: Nifty Mid & Smallcap 400 TR | K25: 0.88248264 | L25: 0.11527542 | M25: 0.60834972 | N25: 0.08869355
C26: Nuvama Wealth Management Ltd | D26: Jun-24 - Jun-24 | E26: MOPWM | F26: Ajay Jaisinghani | G26: 0.9468099 | H26: 1.7165075 | I26: =H26/$H$47 -> 0.004168845 | J26: Nifty Mid & Smallcap 400 TR | K26: 0.85578171 | L26: 0.089868933 | M26: 0.36995774 | N26: 0.043723109
C27: Parth Electrical & Engineering | D27: Apr-25 - Apr-25 | E27: ICICI Bank | F27: Ajay Jaisinghani | G27: 1.003 | H27: 3.683075 | I27: =H27/$H$47 -> 0.0089450053 | J27: Nifty Mid & Smallcap 400 TR | K27: 2.6720588 | L27: 0.17715311
C28: PG Electro. | D28: Mar-26 | E28: MOPWM | F28: Aarti Ajay Jaisinghani | G28: 9.4396845 | H28: 10.03806 | I28: =H28/$H$47 -> 0.024379221 | J28: Nifty Mid & Smallcap 400 TR | K28: 0.063389351 | L28: 0.14383958
C29: Smart Works | D29: Sep-24 | E29: HDFC Bank | F29: Ajay Jaisinghani / Bharat Jaisinghani | G29: 13.000005 | H29: 14.025561 | I29: =H29/$H$47 -> 0.034063579 | J29: Nifty Mid & Smallcap 400 TR | K29: 0.078888889 | L29: 0.0088763045 | M29: 0.043697998 | N29: 0.0049901217
C30: Sterlite Grid 5 | E30: HDFC Bank | F30: Ajay Jaisinghani | G30: 0.036594 | H30: 0.036594 | I30: =H30/$H$47 -> 8.8875063e-05 | J30: Nifty Mid & Smallcap 400 TR
C31: Sterlite Power Transmission | E31: HDFC Bank | F31: Ajay Jaisinghani | G31: 0.05586 | H31: 0.05586 | I31: =H31/$H$47 -> 0.00013566598 | J31: Nifty Mid & Smallcap 400 TR
C32: Sterlite Tech | E32: HDFC Bank | F32: Ajay Jaisinghani | G32: 0.11361775 | H32: 0.11361775 | I32: =H32/$H$47 -> 0.00027594099 | J32: Nifty Mid & Smallcap 400 TR
C33: STLNETWORK | E33: HDFC Bank | F33: Ajay Jaisinghani | G33: 0.0042476 | H33: 0.0042476 | I33: =H33/$H$47 -> 1.0316055e-05 | J33: Nifty Mid & Smallcap 400 TR
C34: Tatva Chintan Pharma Chem Limi | D34: Aug-25 | E34: MOPWM | F34: Ajay Jaisinghani | G34: 2.230075 | H34: 2.5301246 | I34: =H34/$H$47 -> 0.0061448592 | J34: Nifty Mid & Smallcap 400 TR | K34: 0.13509478 | L34: 0.066167369 | M34: 0.16837136 | N34: 0.081823936
C35: Tech Mahindra Ltd. | D35: Jul-23 - Oct-23 | E35: MOPWM | F35: Ajay Jaisinghani | G35: 2.4795522 | H35: 3.05631 | I35: =H35/$H$47 -> 0.0074227946 | J35: Nifty Mid & Smallcap 400 TR | K35: 0.33677765 | L35: 0.64391933 | M35: 0.11336035 | N35: 0.19020486
C36: Vedanta | D36: Jul-24 | E36: HDFC Bank / MOPWM | F36: Ajay Jaisinghani | G36: 6.8212228 | H36: 8.19936 | I36: =H36/$H$47 -> 0.01991361 | J36: Nifty Mid & Smallcap 400 TR | K36: 0.39313878 | L36: 0.065394196 | M36: 0.27076382 | N36: 0.042134789
C37: Yash High Voltage Ltd. | D37: Apr-24 - Apr-24 | E37: ICICI Bank | F37: Ajay Jaisinghani | G37: 0.84112173 | H37: 10.207312 | I37: =H37/$H$47 -> 0.02479028 | J37: Nifty Mid & Smallcap 400 TR | K37: 12.20719 | L37: 0.23510572 | M37: 1.4417536 | N37: 0.10043599
C38: Zaggle Prepaid Ocean Services Ltd. | D38: Sep-23 - Nov-24 | E38: MOPWM | F38: Ajay Jaisinghani / Ankita Jaisinghani | G38: 1.323394 | H38: 1.28371 | I38: =H38/$H$47 -> 0.0031177189 | J38: Nifty Mid & Smallcap 400 TR | K38: -0.029986535 | L38: 0.34356441 | M38: -0.012906021 | N38: 0.13305877
C39: Clean Max Enviro Energy Solutions Ltd | D39: Jan-26 | E39: ICICI Bank / MOPWM | F39: Ajay Jaisinghani / Ankita Jaisinghani | G39: 18.771598 | H39: 25.917444 | I39: =H39/$H$47 -> 0.06294514 | J39: Nifty Mid & Smallcap 400 TR | K39: 0.38067328 | L39: 0.083451406 | M39: 1.180873 | N39: 0.2137857
C40: M/S Grand Continent Hotels | D40: Feb-24 | E40: Private Investments | F40: Ajay Jaisinghani | G40: 1.627725 | H40: 1.627725 | I40: =H40/$H$47 -> 0.0039532208 | J40: Nifty Mid & Smallcap 400 TR | K40: 2.220446e-16 | L40: 0.2784901
C41: Vedanta Oil & Gas Ltd | D41: Aug-25 | E41: HDFC Bank / MOPWM | F41: Ajay Jaisinghani | G41: 1.0672525 | H41: 0.7429 | I41: =H41/$H$47 -> 0.0018042653 | J41: Nifty Mid & Smallcap 400 TR | K41: -0.7342847 | L41: 0.074920279
C42: Vedanta Power Ltd | D42: Aug-25 | E42: HDFC Bank / MOPWM | F42: Ajay Jaisinghani | G42: 1.5938776 | H42: 0.9269 | I42: =H42/$H$47 -> 0.0022511422 | J42: Nifty Mid & Smallcap 400 TR | K42: -0.41846225 | L42: 0.05602371
C43: Vedanta Aluminium Metal Ltd | D43: Aug-25 - May-26 | E43: HDFC Bank / MOPWM | F43: Ajay Jaisinghani | G43: 0.93182543 | H43: 10.3592 | I43: =H43/$H$47 -> 0.025159167 | J43: Nifty Mid & Smallcap 400 TR | K43: 10.117104 | L43: 0.05602371
C44: Vedanta Iron & Steel Ltd | D44: Aug-25 - May-26 | E44: HDFC Bank / MOPWM | F44: Ajay Jaisinghani | G44: 0.88490834 | H44: 0.81075 | I44: =H44/$H$47 -> 0.0019690511 | J44: Nifty Mid & Smallcap 400 TR | K44: -0.083803418 | L44: 0.05602371
C45: Onesource Specialty Pharma | D45: Nov-24 | E45: MOPWM | F45: Ajay Jaisinghani / Bharat Jaisinghani | G45: 12.0757 | H45: 15.029105 | I45: =H45/$H$47 -> 0.036500865 | J45: Nifty 500 TRI | K45: 0.29367081 | L45: 0.058244655 | M45: 0.1767736 | N45: 0.036360618
C46: Kaynes Technology India ltd | D46: Nov-22 | E46: MOPWM | F46: Ajay Jaisinghani / Ankita Jaisinghani | G46: 5.6556157 | H46: 6.6111526 | I46: =H46/$H$47 -> 0.016056365 | J46: Nifty 500 TRI | K46: 0.16895365 | L46: 0.047756394 | M46: 0.16892191 | N46: 0.050939485
C47: Total | G47: =SUM(G3:G11) -> 160.25041 | H47: =SUM(H3:H46) -> 411.74654 | I47: =SUM(I3:I46) -> 1

Sheet Liquid
C2: Product | D2: Investment Date Range | E2: Advisor | F2: Investor | G2: Investment at Cost (in crores) | H2: Market Value (in crores) | I2: Allocation (%) | J2: Benchmark | K2: Scheme Absolute (%) | L2: Index Absolute (%) | M2: Scheme XIRR (%) | N2: Index XIRR (%)
C3: Aditya Birla SL Balanced Advantage Fund(G) | D3: Jun-23 - Nov-25 | E3: MOPWM / MOPWM Dir | F3: Aarti Ajay Jaisinghani / Ankita Jaisinghani / Bharat Jaisinghani / Ajay Jaisinghani | G3: 26.867902 | H3: 29.582027 | I3: =H3/$H$20 -> 0.19559271 | J3: Balanced Index | K3: 0.10101738 | L3: 0.065388883 | M3: 0.083728281 | N3: 0.055001131
C4: HDFC Balanced Advantage Fund | D4: May-22 - Jul-24 | E4: MOPWM Dir / MOPWM Reg | F4: Bharat Jaisinghani / Ajay Jaisinghani / Ankita Jaisinghani | G4: 7.2297465 | H4: 10.869689 | I4: =H4/$H$20 -> 0.071869039 | J4: Balanced Index | K4: 0.49988855 | L4: 0.35274615 | M4: 0.1349234 | N4: 0.099197882
C5: ICICI Pru Balanced Advantage Fund | D5: Sep-22 | E5: MOPWM Dir / MOPWM Reg | F5: Ajay Jaisinghani / Bharat Jaisinghani / Ankita Jaisinghani | G5: 21.597723 | H5: 22.317241 | I5: =H5/$H$20 -> 0.14755884 | J5: Balanced Index | K5: 0.037451584 | L5: 0.016809687 | M5: 0.04462271 | N5: 0.020225558
C6: ICICI Prudential Equity Savings Fund - Direct Plan | D6: Nov-25 | E6: MOPWM | F6: Ajay Jaisinghani | G6: 23.281984 | H6: 23.179461 | I6: =H6/$H$20 -> 0.15325974 | J6: Equity Savings Index | K6: -0.0040276689 | L6: -0.061122933 | M6: -0.47355465 | N6: -0.10196347
C7: WhiteOak Capital Multi Asset Allocation Fund-Direct(G) | D7: Jul-24 | E7: MOPWM | F7: Ajay Jaisinghani / Ankita Jaisinghani / Bharat Jaisinghani | G7: 17.698332 | H7: 20.037862 | I7: =H7/$H$20 -> 0.13248787 | J7: Balanced Index | K7: 0.13218928 | L7: 0.011121138 | M7: 0.12581871 | N7: 0.010808691
C8: Aditya Birla SL Liquid Fund-(DD)-Direct | D8: Jul-19 - Sep-25 | G8: 0 | H8: 0.07624559 | I8: =H8/$H$20 -> 0.00050412642 | J8: CRISIL Liquid Fund Index | M8: 0.0075873286 | N8: 0.057610968
C9: Aditya Birla SL Liquid Fund-Direct (G) | D9: Jul-19 - Jul-19 | G9: 0.053714628 | H9: 0.079441248 | I9: =H9/$H$20 -> 0.00052525572 | J9: CRISIL Liquid Fund Index | M9: 0.057565376 | N9: 0.057437971
C10: HDFC Liquid Fund -Direct(G) | D10: Mar-20 - Mar-20 | G10: 0.014284307 | H10: 0.019483298 | I10: =H10/$H$20 -> 0.00012882116 | J10: CRISIL Liquid Fund Index | M10: 0.030159518 | N10: 0.046286681
C11: HDFC Overnight Fund - Direct - G | D11: Jul-19 - Jul-19 | G11: 0.054356288 | H11: 0.06067928 | I11: =H11/$H$20 -> 0.00040120391 | J11: CRISIL Liquid Fund Index | M11: 0.015894654 | N11: 0.057519111
C12: HSBC Liquid Fund-Direct(DD) | D12: Jul-25 - Apr-26 | G12: 2.744886 | H12: 2.8740049 | I12: =H12/$H$20 -> 0.019002565 | J12: CRISIL Liquid Fund Index | M12: 0.063692632 | N12: 0.059854713
C13: ICICI Pru Liquid Fund-Direct(G) | D13: Jul-19 - Jul-19 | G13: 0.055192263 | H13: 0.077342732 | I13: =H13/$H$20 -> 0.0005113806 | J13: CRISIL Liquid Fund Index | M13: 0.049542978 | N13: 0.057519111
C14: Kotak Liquid-Direct (DD) | D14: Jul-19 - Jul-19 | G14: 0.063572507 | H14: 0.093638682 | I14: =H14/$H$20 -> 0.0006191274 | J14: CRISIL Liquid Fund Index | M14: 0.057088867 | N14: 0.057512018
C15: Mirae Asset Cash Management Fund-Direct(G) | D15: Apr-26 - Apr-26 | G15: 0.8972947 | H15: 0.8986005 | I15: =H15/$H$20 -> 0.0059414355 | J15: CRISIL Liquid Fund Index | M15: 0 | N15: 0
C16: Nippon India ETF Nifty 1D Rate Liquid Bees-IDCW | D16: Jul-25 - Jul-25 | G16: 3.7698115 | H16: 4.0189932 | I16: =H16/$H$20 -> 0.026573087 | J16: Nifty 50 Arbitrage | K16: 0.033220446 | L16: 0.033721467 | M16: 0.072971854 | N16: 0.074066815
C17: Kotak Equity Arbitrage Scheme(G) | D17: May-25 - May-25 | G17: 2.3963149 | H17: 2.5510449 | I17: =H17/$H$20 -> 0.016867194 | J17: Nifty 50 Arbitrage | K17: 0.033220446 | L17: 0.033721467 | M17: 0.072971854 | N17: 0.074066815
C18: Invesco India Arbitrage Fund(G) | D18: Nov-25 - Nov-25 | G18: 2.6026159 | H18: 2.7030789 | I18: =H18/$H$20 -> 0.017872424 | J18: Nifty 50 Arbitrage | K18: 0.033220446 | L18: 0.033721467 | M18: 0.072971854 | N18: 0.074066815
C19: Motilal Oswal Arbitrage Fund Direct (G) | D19: May-25 - May-26 | G19: 30.985244 | H19: 31.804161 | I19: =H19/$H$20 -> 0.21028519 | J19: Nifty 50 Arbitrage | K19: 0.033220446 | L19: 0.033721467 | M19: 0.072971854 | N19: 0.074066815
C20: Total | G20: =SUM(G3:G19) -> 140.31297 | H20: =SUM(H3:H19) -> 151.24299 | I20: =SUM(I3:I19) -> 1

Sheet Equity
E1: Highlighted Dates represent investments < 1 year
A2: Allocation | B2: Product | C2: Advisor | D2: Investor | E2: Investment Date Range | F2: Quantity | G2: Investment at Cost (in crores) | H2: Market Value (in crores) | I2: Allocation (%) | J2: Benchmark | K2: Scheme Absolute (%) | L2: Index Absolute (%) | M2: Scheme XIRR (%) | N2: Index XIRR (%) | R2: =19456-19522 -> -66
B3: Multi Cap | E3: 395322 | G3: =SUM(G4:G16) -> 332.69671 | H3: =SUM(H4:H16) -> 361.70793 | I3: =SUM(I4:I16) -> 0.35288618 | K3: 0.087685415 | L3: 0.024078156 | M3: 0.093634906 | N3: 0.026127818
A4: SG | B4: Motilal Oswal Founders Fund II | C4: MOPWM | D4: Ajay Jaisinghani / Ankita Jaisinghani | E4: Aug-24 - Oct-24 | F4: 28410850 | G4: 29.9985 | H4: 32.706287 | I4: =H4/$H$73 -> 0.031908608 | J4: S&P BSE 500 TR | K4: 0.090264064 | L4: 0.0078803335 | M4: 0.049043646 | N4: 0.0043587536
A5: SG | B5: Carnelian Bespoke Portfolio | C5: Carnelian | D5: Ajay Jaisinghani | E5: Jan-25 - Dec-25 | F5: 0 | G5: 33 | H5: 40.047568 | I5: =H5/$H$73 -> 0.039070841 | J5: S&P BSE 500 TR | K5: 0.21356266 | L5: 0.019115723 | M5: 0.17886855 | N5: 0.016431174
A6: SG | B6: Buoyant Opportunities Portfolio AIF | C6: MOPWM | D6: Ajay Jaisinghani / Ankita Jaisinghani | E6: May-24 - Jun-26 | F6: 5335610.6 | G6: 70.855886 | H6: 76.047925 | I6: =H6/$H$73 -> 0.07419318 | J6: S&P BSE 500 TR | K6: 0.073276036 | L6: 0.028688756 | M6: 0.11424926 | N6: 0.045162562
A7: SG | B7: 3P India Equity Fund 1 | C7: MOPWM | D7: Ajay Jaisinghani / Ankita Jaisinghani | E7: Apr-23 - Nov-25 | F7: 3470532.7 | G7: 47.49516 | H7: 52.115602 | I7: =H7/$H$73 -> 0.050844546 | J7: S&P BSE 500 TR | K7: 0.097282361 | L7: 0.094633109 | M7: 0.072618744 | N7: 0.070717308
A8: TT | B8: Aristos Equity Potrfolio - SB | C8: Sanjay Bhattacharya | D8: Ajay Jaisinghani / Ankita Jaisinghani | E8: Dec-25 - Dec-25 | F8: 0 | G8: 25 | H8: 25.922903 | I8: =H8/$H$73 -> 0.025290665 | J8: Nifty 50 TRI | K8: 0.03691612 | L8: -0.073733021
A9: TT | B9: Green Lantern Growth Strategy | C9: Green Lantern | D9: Ajay Jaisinghani / Ankita Jaisinghani | E9: Jan-25 | F9: 0 | G9: 15.208723 | H9: 17.617651 | I9: =H9/$H$73 -> 0.017187972 | J9: S&P BSE 500 TR | K9: 0.15839126 | L9: 0.079591185 | M9: 0.10670952 | N9: 0.05422844
A10: TT | B10: Fund of Funds (VEC+ Carnelian+Girik Cap+Insightful) | C10: MOPWM | D10: Ajay Jaisinghani | E10: Nov-24 - Nov-24 | F10: 99995 | G10: 10 | H10: 11.128744 | I10: =H10/$H$73 -> 0.010857323 | J10: Nifty 500 TRI | K10: 0.11287435 | L10: 0.019793346 | M10: 0.080529395 | N10: 0.01429567
A11: TT | B11: Carnelian Bharat Amritkaal Fund | C11: MOPWM | D11: Ankita Jaisinghani | E11: Aug-25 | F11: 12993095 | G11: 15.000043 | H11: 16.008922 | I11: =H11/$H$73 -> 0.015618478 | J11: Nifty 500 TRI | K11: 0.067258447 | L11: -0.10187298 | M11: 0.14816979 | N11: -0.20571077
A12: SG | B12: Helios Flexi Cap Fund Direct (G) | C12: MOPWM | D12: Ajay Jaisinghani / Ankita Jaisinghani / Bharat Jaisinghani / Bharat Jaisinghani Family Trust II / Bharat Jaisinghani Family Trust III | E12: Aug-24 - Nov-25 | F12: 17123356 | G12: 25.318415 | H12: 27.174766 | I12: =H12/$H$73 -> 0.026511997 | J12: Nifty 500 TRI | K12: 0.073320214 | L12: -0.0038231602 | M12: 0.066808715 | N12: -0.0035201839
A13: SG | B13: ICICI Pru India Opportunities Fund | C13: MOPWM Dir | D13: Ajay Jaisinghani / Ankita Jaisinghani / Bharat Jaisinghani | E13: Mar-25 - Mar-26 | F13: 6446386.9 | G13: 24.854421 | H13: 25.418104 | I13: =H13/$H$73 -> 0.024798178 | J13: Nifty 500 TRI | K13: 0.035939998 | L13: 0.048954901 | M13: 0.055750164 | N13: 0.076058045
A14: SG | B14: Kotak Large & Midcap Fund - Direct- Growth | C14: MOPWM Dir | D14: Ajay Jaisinghani | E14: Mar-20 | F14: 61946.481 | G14: 1.5860418 | H14: 2.5003334 | I14: =H14/$H$73 -> 0.0024393524 | J14: Nifty 500 TRI | K14: 0.57646126 | L14: 0.49445855 | M14: 0.23195326 | N14: 0.20958738
A15: SG | B15: Bandhan Large & Mid Cap Fund - Direct Plan - Growth | C15: MOPWM | D15: Aarti Ajay Jaisinghani / Ajay Jaisinghani / Ankita Jaisinghani | E15: Apr-26 | F15: 1517142.9 | G15: 24.380016 | H15: 24.782832 | I15: =H15/$H$73 -> 0.0241784 | J15: Nifty 500 TRI | K15: 0.016522376 | L15: 0.019394611
A16: SG | B16: Kotak Multicap Fund-Direct Plan-Growth | C16: MOPWM | D16: Aarti Ajay Jaisinghani / Ajay Jaisinghani | E16: Apr-26 | F16: 4795641.7 | G16: 9.9995 | H16: 10.236297 | I16: =H16/$H$73 -> 0.0099866426 | J16: Nifty 500 TRI | K16: 0.023680902 | L16: 0.012127361
B17: Mid & Small Cap | E17: 42997 | G17: =SUM(G18:G20) -> 183.99973 | H17: =SUM(H18:H20) -> 246.75783 | I17: =SUM(I18:I20) -> 0.24073962 | K17: 0.34116363 | L17: 0.045401409 | M17: 0.4334171 | N17: 0.056590232
A18: TT | B18: Svan Investment | C18: Svan | D18: Ajay Jaisinghani / Bharat Jaisinghani | E18: Sep-24 - Oct-25 | F18: 0 | G18: 24 | H18: 26.383247 | I18: =H18/$H$73 -> 0.025739782 | J18: S&P BSE 500 TR | K18: 0.099964747 | L18: 0.027818461 | M18: 0.071813414 | N18: 0.02022101
A19: SG | B19: Sanshi Fund 1 | C19: Mukul Agarwal | D19: Aarti Ajay Jaisinghani / Ajay Jaisinghani / Ankita Jaisinghani / Bharat Jaisinghani | E19: Mar-25 | F19: 0 | G19: 147.49973 | H19: 204.48014 | I19: =H19/$H$73 -> 0.19949305 | J19: Nifty Mid & Smallcap 400 TR | K19: 0.38630864 | L19: 0.051790642 | M19: 0.59185677 | N19: 0.074412158
A20: TT | B20: VEC Small and Mid cap fund | C20: MOPWM | D20: Ajay Jaisinghani / Ankita Jaisinghani | E20: Jul-25 | F20: 0 | G20: 12.5 | H20: 15.894442 | I20: =H20/$H$73 -> 0.01550679 | J20: S&P BSE 500 TR | K20: 0.27155537 | L20: 0.0037678631
B21: Equity Hybrid | E21: 42997 | G21: =SUM(G22:G26) -> 96.675688 | H21: =SUM(H22:H26) -> 105.98628 | I21: =SUM(I22:I26) -> 0.10340136 | K21: 0.10094745 | L21: 0.038213701 | M21: 0.016414568 | N21: 0.034314373
A22: Liquid | B22: Aditya Birla SL Balanced Advantage Fund(G) | C22: MOPWM / MOPWM Dir | D22: Aarti Ajay Jaisinghani / Ankita Jaisinghani / Bharat Jaisinghani / Ajay Jaisinghani | E22: Jun-23 - Nov-25 | F22: 2437030.6 | G22: 26.867902 | H22: 29.582027 | I22: =H22/$H$73 -> 0.028860546 | J22: Balanced Index | K22: 0.10101738 | L22: 0.065388883 | M22: 0.083728281 | N22: 0.055001131
A23: Liquid | B23: HDFC Balanced Advantage Fund | C23: MOPWM Dir / MOPWM Reg | D23: Bharat Jaisinghani / Ajay Jaisinghani / Ankita Jaisinghani | E23: May-22 - Jul-24 | F23: 206861.5 | G23: 7.2297465 | H23: 10.869689 | I23: =H23/$H$73 -> 0.010604586 | J23: Balanced Index | K23: 0.49988855 | L23: 0.35274615 | M23: 0.1349234 | N23: 0.099197882
A24: Liquid | B24: ICICI Pru Balanced Advantage Fund | C24: MOPWM Dir / MOPWM Reg | D24: Ajay Jaisinghani / Bharat Jaisinghani / Ankita Jaisinghani | E24: Sep-22 | F24: 2610585.5 | G24: 21.597723 | H24: 22.317241 | I24: =H24/$H$73 -> 0.021772942 | J24: Balanced Index | K24: 0.037451584 | L24: 0.016809687 | M24: 0.04462271 | N24: 0.020225558
A25: Liquid | B25: ICICI Prudential Equity Savings Fund - Direct Plan | C25: MOPWM | D25: Ajay Jaisinghani | E25: Nov-25 | F25: 9320249.9 | G25: 23.281984 | H25: 23.179461 | I25: =H25/$H$73 -> 0.022614134 | J25: Equity Savings Index | K25: -0.0040276689 | L25: -0.061122933
A26: Liquid | B26: WhiteOak Capital Multi Asset Allocation Fund-Direct(G) | C26: MOPWM | D26: Ajay Jaisinghani / Ankita Jaisinghani / Bharat Jaisinghani | E26: Jul-24 | F26: 12334787 | G26: 17.698332 | H26: 20.037862 | I26: =H26/$H$73 -> 0.019549155 | J26: Balanced Index | K26: 0.13218928 | L26: 0.011121138 | M26: 0.12581871 | N26: 0.010808691
B27: Small Cap | E27: 173635 | G27: =G28 -> 1 | H27: =H28 -> 1.1248249 | I27: =SUM(I28) -> 0.0010973914 | K27: 0.1248249 | L27: 0.018808085 | M27: 0.072427824 | N27: 0.011138436
A28: SG | B28: Molecule Growth Strategy | C28: Molecule Venture | D28: Ajay Jaisinghani | E28: Oct-24 | F28: 0 | G28: 1 | H28: 1.1248249 | I28: =H28/$H$73 -> 0.0010973914 | J28: S&P BSE 500 TR | K28: 0.1248249 | L28: 0.018808085 | M28: 0.072427824 | N28: 0.011138436
A29: TT | B29: Direct Equity - Non MO | C29: Demat | E29: 882055 | G29: =SUM(G30:G63) -> 150.41406 | H29: =SUM(H30:H63) -> 222.35865 | I29: =SUM(I30:I63) -> 0.21693551 | K29: 0.43578585 | L29: 0.069273635 | M29: 0.32026554 | N29: 0.072169986
B30: Bharat Parenterals Ltd | C30: MOPWM | D30: Ankita Jaisinghani | E30: Nov-24 | F30: 603 | G30: 0.090745032 | H30: 0.08442 | I30: =H30/$H$73 -> 8.2361068e-05 | J30: Nifty Mid & Smallcap 400 TR | K30: -0.066140798 | L30: 0.077828824 | M30: -0.041599378 | N30: 0.047544053
B31: Birla Cable Ltd. | C31: MOPWM | D31: Ajay Jaisinghani / Bharat Jaisinghani | E31: Aug-23 - Jan-24 | F31: 15193 | G31: 0.36973099 | H31: 0.3127479 | I31: =H31/$H$73 -> 0.00030512025 | J31: Nifty Mid & Smallcap 400 TR | K31: -0.29805272 | L31: 0.47520331 | M31: -0.16933851 | N31: 0.2278928
B32: BSE Ltd. | C32: MOPWM | D32: Ajay Jaisinghani | E32: Jul-23 - Oct-24 | F32: 40000 | G32: 0 | H32: 15.4624 | I32: =H32/$H$73 -> 0.015085285 | J32: Nifty Mid & Smallcap 400 TR | K32: 3.3766661 | L32: 0.15307721 | M32: 1.3370817 | N32: 0.092957088
B33: Clean Max Enviro Energy Solutions Ltd | C33: ICICI Bank / MOPWM | D33: Ajay Jaisinghani / Ankita Jaisinghani | E33: Jan-26 | F33: 189934 | G33: 18.771598 | H33: 25.917444 | I33: =H33/$H$73 -> 0.025285339 | J33: Nifty Mid & Smallcap 400 TR | K33: 0.38067328 | L33: 0.083451406
B34: Deepak Fert | C34: HDFC Bank / MOPWM | D34: Ajay Jaisinghani | E34: Jul-24 - Aug-24 | F34: 25930 | G34: 2.5226066 | H34: 4.0400237 | I34: =H34/$H$73 -> 0.0039414909 | J34: Nifty Mid & Smallcap 400 TR | K34: 0.62054365 | L34: 0.056710201 | M34: 0.29264398 | N34: 0.029473165
B35: Fractal Analytics Limited | C35: ICICI Bank | D35: Ajay Jaisinghani | E35: Jul-25 - Jul-25 | F35: 180185 | G35: 17.687888 | H35: 16.032861 | I35: =H35/$H$73 -> 0.015641833 | J35: Nifty Mid & Smallcap 400 TR | K35: -0.093568367 | L35: 0.030529841
B36: M/S Grand Continent Hotels | C36: Private Investments | D36: Ajay Jaisinghani | E36: Feb-24 | F36: 262125 | G36: 1.627725 | H36: 1.627725 | I36: =H36/$H$73 -> 0.0015880262 | J36: Nifty Mid & Smallcap 400 TR | K36: 2.220446e-16 | L36: 0.2784901 | M36: -0.20421218 | N36: 0.11246662
B37: IFB Inds. | C37: MOPWM | D37: Ajay Jaisinghani | E37: Sep-25 - Sep-25 | F37: 15772 | G37: 2.386564 | H37: 2.0363229 | I37: =H37/$H$73 -> 0.0019866587 | J37: Nifty Mid & Smallcap 400 TR | K37: -0.26925924 | L37: -0.013144243
B38: Infinium Pharmachem Ltd. | C38: MOPWM | D38: Ankita Jaisinghani | E38: Nov-24 | F38: 8000 | G38: 0.297729 | H38: 0.15424 | I38: =H38/$H$73 -> 0.00015047822 | J38: Nifty Mid & Smallcap 400 TR | K38: -0.40075965 | L38: 0.074973291 | M38: -0.2797844 | N38: 0.04712806
B39: Insolation Energy Ltd | C39: ICICI Bank | D39: Ajay Jaisinghani / Bharat Jaisinghani | E39: Dec-24 | F39: 303260 | G39: 9.9681562 | H39: 3.5238812 | I39: =H39/$H$73 -> 0.0034379367 | J39: Nifty Mid & Smallcap 400 TR | K39: -0.64648616 | L39: 0.018308548 | M39: -0.48857966 | N39: 0.011768684
B40: Jaro Education | C40: ICICI Bank | D40: Ajay Jaisinghani | E40: May-24 | F40: 116979 | G40: 7.500035 | H40: 5.7957246 | I40: =H40/$H$73 -> 0.0056543717 | J40: Nifty Mid & Smallcap 400 TR | K40: -0.22724033 | L40: 0.13100728 | M40: -0.14457367 | N40: 0.07557573
B41: Kingfa Science & Technology Ltd. | C41: HDFC Bank / MOPWM | D41: Ajay Jaisinghani | E41: Jul-24 - Jun-25 | F41: 19483 | G41: 5.4945529 | H41: 10.05693 | I41: =H41/$H$73 -> 0.0098116497 | J41: Nifty Mid & Smallcap 400 TR | K41: 0.8319563 | L41: 0.063249664 | M41: 0.50014291 | N41: 0.042839798
B42: Man Industries | C42: HDFC Bank / MOPWM | D42: Ajay Jaisinghani | E42: May-24 - Jul-25 | F42: 583020 | G42: 19.271126 | H42: 33.899698 | I42: =H42/$H$73 -> 0.033072913 | J42: Nifty Mid & Smallcap 400 TR | K42: 0.75909275 | L42: 0.065319298 | M42: 0.63026349 | N42: 0.058052889
B43: Manorama Industries Ltd. | C43: HDFC Bank / MOPWM | D43: Ajay Jaisinghani | E43: Aug-23 - Jan-26 | F43: 151270 | G43: 15.182156 | H43: 25.053337 | I43: =H43/$H$73 -> 0.024442308 | J43: Nifty Mid & Smallcap 400 TR | K43: 0.65085739 | L43: -0.11210566 | M43: 0.50582085 | N43: 0.050758591
B44: MPS | C44: MOPWM | D44: Ajay Jaisinghani | E44: Jun-26 - Jun-26 | F44: 4878 | G44: 0.88606171 | H44: 0.92313711 | I44: =H44/$H$73 -> 0.00090062258 | J44: Nifty Mid & Smallcap 400 TR | K44: 0.041842912 | L44: 0.0020436538 | M44: 2.2833663 | N44: 0.061001721
B45: NLC INDIA | C45: MOPWM | D45: Ajay Jaisinghani | E45: Jun-26 - Jun-26 | F45: 32000 | G45: 1.0034019 | H45: 1.0312 | I45: =H45/$H$73 -> 0.0010060499 | J45: Nifty Mid & Smallcap 400 TR | K45: 0.0277039 | L45: 0.0042888947 | M45: 1.153858 | N45: 0.12767892
B46: Neuland Labs. | C46: MOPWM | D46: Ajay Jaisinghani | E46: Jan-24 - May-25 | F46: 4625 | G46: 4.5809307 | H46: 8.6164675 | I46: =H46/$H$73 -> 0.0084063191 | J46: Nifty Mid & Smallcap 400 TR | K46: 0.88248264 | L46: 0.11527542 | M46: 0.60834972 | N46: 0.08869355
B47: Nuvama Wealth Management Ltd | C47: MOPWM | D47: Ajay Jaisinghani | E47: Jun-24 - Jun-24 | F47: 9500 | G47: 0.9468099 | H47: 1.7165075 | I47: =H47/$H$73 -> 0.0016746433 | J47: Nifty Mid & Smallcap 400 TR | K47: 0.85578171 | L47: 0.089868933 | M47: 0.36995774 | N47: 0.043723109
B48: Parth Electrical & Engineering | C48: ICICI Bank | D48: Ajay Jaisinghani | E48: Apr-25 - Apr-25 | F48: 59000 | G48: 1.003 | H48: 3.683075 | I48: =H48/$H$73 -> 0.0035932479 | J48: Nifty Mid & Smallcap 400 TR | K48: 2.6720588 | L48: 0.17715311 | M48: 1.9418344 | N48: 0.14487786
B49: PG Electro. | C49: MOPWM | D49: Aarti Ajay Jaisinghani | E49: Mar-26 | F49: 180000 | G49: 9.4396845 | H49: 10.03806 | I49: =H49/$H$73 -> 0.0097932402 | J49: Nifty Mid & Smallcap 400 TR | K49: 0.063389351 | L49: 0.14383958
B50: Smart Works | C50: HDFC Bank | D50: Ajay Jaisinghani / Bharat Jaisinghani | E50: Sep-24 | F50: 288889 | G50: 13.000005 | H50: 14.025561 | I50: =H50/$H$73 -> 0.013683489 | J50: Nifty Mid & Smallcap 400 TR | K50: 0.078888889 | L50: 0.0088763045 | M50: 0.043697998 | N50: 0.0049901217
B51: Sterlite Grid 5 | C51: HDFC Bank | D51: Ajay Jaisinghani | E51: -- | F51: 1140 | G51: 0.036594 | H51: 0.036594 | I51: =H51/$H$73 -> 3.5701503e-05 | J51: Nifty Mid & Smallcap 400 TR
B52: Sterlite Power Transmission | C52: HDFC Bank | D52: Ajay Jaisinghani | E52: -- | F52: 1140 | G52: 0.05586 | H52: 0.05586 | I52: =H52/$H$73 -> 5.4497622e-05 | J52: Nifty Mid & Smallcap 400 TR
B53: Sterlite Tech | C53: HDFC Bank | D53: Ajay Jaisinghani | E53: -- | F53: 1850 | G53: 0.11361775 | H53: 0.11361775 | I53: =H53/$H$73 -> 0.00011084671 | J53: Nifty Mid & Smallcap 400 TR
B54: STLNETWORK | C54: HDFC Bank | D54: Ajay Jaisinghani | E54: -- | F54: 1850 | G54: 0.0042476 | H54: 0.0042476 | I54: =H54/$H$73 -> 4.1440046e-06 | J54: Nifty Mid & Smallcap 400 TR
B55: Tatva Chintan Pharma Chem Limi | C55: MOPWM | D55: Ajay Jaisinghani | E55: Aug-25 | F55: 21185 | G55: 2.230075 | H55: 2.5301246 | I55: =H55/$H$73 -> 0.0024684169 | J55: Nifty Mid & Smallcap 400 TR | K55: 0.13509478 | L55: 0.066167369
B56: Tech Mahindra Ltd. | C56: MOPWM | D56: Ajay Jaisinghani | E56: Jul-23 - Oct-23 | F56: 21750 | G56: 2.4795522 | H56: 3.05631 | I56: =H56/$H$73 -> 0.0029817692 | J56: Nifty Mid & Smallcap 400 TR | K56: 0.33677765 | L56: 0.64391933 | M56: 0.11336035 | N56: 0.19020486
B57: Vedanta | C57: HDFC Bank / MOPWM | D57: Ajay Jaisinghani | E57: Jul-24 | F57: 292000 | G57: 6.8212228 | H57: 8.19936 | I57: =H57/$H$73 -> 0.0079993845 | J57: Nifty Mid & Smallcap 400 TR | K57: 0.39313878 | L57: 0.065394196 | M57: 0.27076382 | N57: 0.042134789
B58: Vedanta Oil & Gas Ltd | C58: HDFC Bank / MOPWM | D58: Ajay Jaisinghani | E58: Aug-25 | F58: 230000 | G58: 1.0672525 | H58: 0.7429 | I58: =H58/$H$73 -> 0.0007247813 | J58: Nifty Mid & Smallcap 400 TR | K58: -0.7342847 | L58: 0.074920279
B59: Vedanta Power Ltd | C59: HDFC Bank / MOPWM | D59: Ajay Jaisinghani | E59: Aug-25 | F59: 230000 | G59: 1.5938776 | H59: 0.9269 | I59: =H59/$H$73 -> 0.00090429369 | J59: Nifty Mid & Smallcap 400 TR | K59: -0.41846225 | L59: 0.05602371
B60: Vedanta Aluminium Metal Ltd | C60: HDFC Bank / MOPWM | D60: Ajay Jaisinghani | E60: Aug-25 - May-26 | F60: 230000 | G60: 0.93182543 | H60: 10.3592 | I60: =H60/$H$73 -> 0.010106548 | J60: Nifty Mid & Smallcap 400 TR | K60: 10.117104 | L60: 0.05602371
B61: Vedanta Iron & Steel Ltd | C61: HDFC Bank / MOPWM | D61: Ajay Jaisinghani | E61: Aug-25 - May-26 | F61: 230000 | G61: 0.88490834 | H61: 0.81075 | I61: =H61/$H$73 -> 0.00079097649 | J61: Nifty Mid & Smallcap 400 TR | K61: -0.083803418 | L61: 0.05602371
B62: Yash High Voltage Ltd. | C62: ICICI Bank | D62: Ajay Jaisinghani | E62: Apr-24 - Apr-24 | F62: 116462 | G62: 0.84112173 | H62: 10.207312 | I62: =H62/$H$73 -> 0.0099583643 | J62: Nifty Mid & Smallcap 400 TR | K62: 12.20719 | L62: 0.23510572 | M62: 1.4417536 | N62: 0.10043599
B63: Zaggle Prepaid Ocean Services Ltd. | C63: MOPWM | D63: Ajay Jaisinghani / Ankita Jaisinghani | E63: Sep-23 - Nov-24 | F63: 62000 | G63: 1.323394 | H63: 1.28371 | I63: =H63/$H$73 -> 0.0012524014 | J63: Nifty Mid & Smallcap 400 TR | K63: -0.029986535 | L63: 0.34356441 | M63: -0.012906021 | N63: 0.13305877
A64: TT | B64: LKP Sec Portfolio | G64: 1.0963805 | H64: 0.84977725 | I64: =H64/$H$73 -> 0.0008290519 | K64: -0.072034374 | L64: 0.069722837 | M64: -0.10054799 | N64: 0.09777804
A65: TT | B65: Direct Equity - MO | G65: =SUM(G66:G67) -> 17.731316 | H65: =SUM(H66:H67) -> 21.640258 | I65: =SUM(I66:I67) -> 0.02111247 | K65: 0.26617787 | L65: 0.055932598 | M65: 0.17558801 | N65: 0.038443562
B66: Onesource Specialty Pharma | C66: MOPWM | D66: Ajay Jaisinghani / Bharat Jaisinghani | E66: Nov-24 | F66: 91000 | G66: 12.0757 | H66: 15.029105 | I66: =H66/$H$73 -> 0.014662558 | J66: Nifty 500 TRI | K66: 0.29367081 | L66: 0.058244655 | M66: 0.1767736 | N66: 0.036360618
B67: Kaynes Technology India ltd | C67: MOPWM | D67: Ajay Jaisinghani / Ankita Jaisinghani | E67: Nov-22 | F67: 21175 | G67: 5.6556157 | H67: 6.6111526 | I67: =H67/$H$73 -> 0.0064499122 | J67: Nifty 500 TRI | K67: 0.16895365 | L67: 0.047756394 | M67: 0.16892191 | N67: 0.050939485
B68: Direct Equity - Unlisted | E68: 173635 | G68: =SUM(G69:G70) -> 27.086596 | H68: =SUM(H69:H70) -> 64.328516 | I68: =SUM(I69:I70) -> 0.062759597 | K68: 1.3749206 | L68: 0.29941829 | M68: 0.5395584 | N68: 0.15761568
A69: SG | B69: National Stock Exchange | C69: ICICI Bank / MOPWM | D69: Ajay Jaisinghani / Ankita Jaisinghani | E69: Dec-22 - Aug-23 | F69: 200000 | G69: 12.085 | H69: 41.5 | I69: =H69/$H$73 -> 0.04048785 | J69: Nifty 500 TRI | K69: 2.4340091 | L69: 0.51558469 | M69: 0.46641998 | N69: 0.13803429
A70: EG | B70: Zepto | C70: MOPWM | D70: Ajay Jaisinghani | E70: Feb-25 | F70: 4716 | G70: 15.001596 | H70: 22.828516 | I70: =H70/$H$73 -> 0.022271747 | J70: Nifty 500 TRI | K70: 0.52173913 | L70: 0.12527876
B71: SLBM | E71: 44407 | G71: =G72 -> 0 | H71: =H72 -> 0.24478595 | I71: =I72 -> 0.00023881583
B72: SLBM | C72: 0 | D72: 0 | E72: 44407 | F72: 0 | G72: 0 | H72: 0.24478595 | I72: =H72/$H$73 -> 0.00023881583
B73: Equity | E73: 2638063 | G73: =G71+G21+G17+G68+G65+G29+G3+G64+G27 -> 810.70047 | H73: =H71+H21+H17+H68+H65+H29+H3+H64+H27 -> 1024.9989 | I73: =I71+I21+I17+I68+I65+I29+I3+I64+I27 -> 1 | K73: ='Portfolio Allocation'!P4 -> 0.26003127 | L73: ='Portfolio Allocation'!Q4 -> 0.049233916 | M73: ='Portfolio Allocation'!S4 -> 0.22988721 | N73: ='Portfolio Allocation'!T4 -> 0.051674172
B74: Note: 1.The AIF return are post tax (adjusted for realized gain / losses on portfolio churn) | H74: =H73-'Live Equity Performance'!F16 -> 0
B75: 2.For hybrid category, direct and indirect plans have been consolidated
B76: 3.Highlighted stocks represent new stocks added
B77: 4.Zepto at 7BN valuation , returns as on July 2025
B78: 5. Highlighted represents investments added this month

Sheet Month on Month Equity Change
C1: Valuations as on 30th June 2026 | D1: =10^2 -> 100 | O1: Linked | P1: Linked
C2: Category | D2: Market Value as on 31st May 2026 (in Cr) | E2: Investments (in Cr) | F2: Redemptions (in Cr) | G2: Dividend / Interest | H2: Market Value as on 30th June 2026 (in Crs) | I2: Aboslute Gain (loss) M-o-M (in Cr) | J2: % Change (M-o-M) | K2: Benchmark Performance | L2: Index Benchmarked | O2: 46203 | P2: 46171 | Q2: % Change | R2: 45911 | S2: % Change | T2: 45933 | U2: % Change
C3: Managed Equity | D3: =SUM(D4:D12) -> 714.11115 | E3: =SUM(E4:E12) -> 32.499625 | F3: =SUM(F4:F12) -> 24.877565 | G3: =SUM(G4:G12) -> 0.00195 | H3: =SUM(H4:H12) -> 759.42288 | I3: =H3+G3+F3-E3-D3 -> 37.691628 | J3: =((H3+G3+F3)/(E3+D3))-1 -> 0.050483639 | K3: =SUMPRODUCT(K4:K12,H4:H12)/SUM(H4:H12) -> 0.018400797 | N3: Nifty 500 TRI | O3: 36880.75 | P3: 36261.8 | Q3: =(O3-P3)/P3 -> 0.017068927 | R3: 23102.65 | S3: =(R3-O3)/O3 -> -0.37358514 | T3: 23027.7 | U3: =(T3-R3)/R3 -> -0.0032442166
B4: * | C4: Direct Equity - MO | D4: 23.147697 | E4: =SUMIFS(Transactions!L:L,Transactions!J:J,'Month on Month Equity Change'!C4) -> 0 | F4: =SUMIFS(Transactions!F:F,Transactions!D:D,'Month on Month Equity Change'!C4) -> 0 | H4: =VLOOKUP(C4,'Live Equity Performance'!$B$7:$F$15,5,0) -> 21.640258 | I4: =H4+F4+G4-E4-D4 -> -1.5074395 | J4: =((H4+G4+F4)/(E4+D4))-1 -> -0.065122655 | K4: =Q3 -> 0.017068927 | L4: =$N$3 -> Nifty 500 TRI | N4: Nifty 50 TRI | O4: 36145.88 | P4: 35552.64 | Q4: =(O4-P4)/P4 -> 0.016686243 | R4: 25005.5 | S4: =(R4-O4)/O4 -> -0.30820608 | T4: 24894.25 | U4: =(T4-R4)/R4 -> -0.0044490212
C5: Direct Equity - Unlisted | D5: 62.828516 | E5: =SUMIFS(Transactions!L:L,Transactions!J:J,'Month on Month Equity Change'!C5) -> 0 | F5: =SUMIFS(Transactions!F:F,Transactions!D:D,'Month on Month Equity Change'!C5) -> 0 | H5: =VLOOKUP(C5,'Live Equity Performance'!$B$7:$F$15,5,0) -> 64.328516 | I5: =H5+F5+G5-E5-D5 -> 1.5 | J5: =((H5+G5+F5)/(E5+D5))-1 -> 0.02387451 | K5: =Q4 -> 0.016686243 | L5: =$N$3 -> Nifty 500 TRI | N5: Nifty Next 50 | O5: 71629.45 | P5: 71073.65 | Q5: =(O5-P5)/P5 -> 0.0078200571 | R5: 67974.7 | S5: =(R5-O5)/O5 -> -0.051023008 | T5: 68355.9 | U5: =(T5-R5)/R5 -> 0.0056079688
C6: LKP Sec Portfolio | D6: 0.8976215 | E6: =SUMIFS(Transactions!L:L,Transactions!J:J,'Month on Month Equity Change'!C6) -> 0 | F6: =SUMIFS(Transactions!F:F,Transactions!D:D,'Month on Month Equity Change'!C6) -> 0.3055521 | G6: ='Portfolio Allocation'!J15 -> 0.00195 | H6: =VLOOKUP(C6,'Live Equity Performance'!$B$7:$F$15,5,0) -> 0.84977725 | I6: =H6+F6+G6-E6-D6 -> 0.25965785 | J6: =((H6+G6+F6)/(E6+D6))-1 -> 0.28927321 | K6: =Q11 -> 0.021063079 | L6: Nifty Mid & Smallcap 400 TR
C7: Multi Cap | D7: 332.0286 | E7: =SUMIFS(Transactions!L:L,Transactions!J:J,'Month on Month Equity Change'!C7) -> 32.499625 | F7: =SUMIFS(Transactions!F:F,Transactions!D:D,'Month on Month Equity Change'!C7) -> 15.53989 | H7: =VLOOKUP(C7,'Live Equity Performance'!$B$7:$F$15,5,0) -> 361.70793 | I7: =H7+F7+G7-E7-D7 -> 12.719603 | J7: =((H7+G7+F7)/(E7+D7))-1 -> 0.03489333 | K7: =Q3 -> 0.017068927 | L7: =$N$3 -> Nifty 500 TRI | N7: Balanced Index | O7: 21017.898 | P7: 20658.15 | Q7: =(O7-P7)/P7 -> 0.017414367 | R7: 20787.813 | S7: =(R7-O7)/O7 -> -0.010947122 | T7: 20786.171 | U7: =(T7-R7)/R7 -> -7.8998209e-05
C8: Equity Hybrid | D8: 70.26721 | E8: =SUMIFS(Transactions!L:L,Transactions!J:J,'Month on Month Equity Change'!C8) -> 0 | F8: =SUMIFS(Transactions!F:F,Transactions!D:D,'Month on Month Equity Change'!C8)-4.31 -> 9.0321225 | H8: ='Attribution Analysis'!B25 -> 62.768957 | I8: =H8+F8+G8-E8-D8 -> 1.5338696 | J8: ='Attribution Analysis'!F25 -> 0.021823773 | K8: =Q7 -> 0.017414367 | L8: Balanced Index | N8: Nifty Midcap 150 TR | O8: 29049.9 | P8: 28766.84 | Q8: =(O8-P8)/P8 -> 0.0098398017 | R8: 27323.85 | S8: =(R8-O8)/O8 -> -0.059416728 | T8: 27191.96 | U8: =(T8-R8)/R8 -> -0.0048269186
B9: * | C9: Mid & Small Cap | D9: 223.51739 | E9: =SUMIFS(Transactions!L:L,Transactions!J:J,'Month on Month Equity Change'!C9) -> 0 | F9: =SUMIFS(Transactions!F:F,Transactions!D:D,'Month on Month Equity Change'!C9) -> 0 | H9: =VLOOKUP(C9,'Live Equity Performance'!$B$7:$F$15,5,0) -> 246.75783 | I9: =H9+F9+G9-E9-D9 -> 23.240438 | J9: =((H9+G9+F9)/(E9+D9))-1 -> 0.10397597 | K9: =Q11 -> 0.021063079 | L9: Nifty Mid & Smallcap 400 TR | N9: Nifty Smallcap 250 TR | O9: 22573.38 | P9: 21635.09 | Q9: =(O9-P9)/P9 -> 0.043368897 | R9: 21706.21 | S9: =(R9-O9)/O9 -> -0.038415603 | T9: 21614.49 | U9: =(T9-R9)/R9 -> -0.0042255189
C10: Small Cap | D10: 1.1531672 | E10: =SUMIFS(Transactions!L:L,Transactions!J:J,'Month on Month Equity Change'!C10) -> 0 | F10: =SUMIFS(Transactions!F:F,Transactions!D:D,'Month on Month Equity Change'!C10) -> 0 | H10: =VLOOKUP(C10,'Live Equity Performance'!$B$7:$F$15,5,0) -> 1.1248249 | I10: =H10+F10+G10-E10-D10 -> -0.0283423 | J10: =((H10+G10+F10)/(E10+D10))-1 -> -0.024577789 | K10: =Q9 -> 0.043368897 | L10: Nifty Small Cap | N10: Nifty Bank TR | O10: 80622.93 | P10: 75764.06 | Q10: =(O10-P10)/P10 -> 0.064131595 | R10: 76239.59 | S10: =(R10-O10)/O10 -> -0.054368404 | T10: 77522.14 | U10: =(T10-R10)/R10 -> 0.016822625
C11: Long-Short Fund | D11: - | E11: =SUMIFS(Transactions!L:L,Transactions!J:J,'Month on Month Equity Change'!C11) -> 0 | F11: =SUMIFS(Transactions!F:F,Transactions!D:D,'Month on Month Equity Change'!C11) -> 0 | H11: - | I11: - | J11: - | K11: =Q3 -> 0.017068927 | L11: =$N$3 -> Nifty 500 TRI | N11: Nifty Mid & Smallcap 400 TR | O11: 26687.25 | P11: 26136.73 | Q11: =(O11-P11)/P11 -> 0.021063079 | R11: 25311.39 | S11: =(R11-O11)/O11 -> -0.051554956 | T11: 25194.89 | U11: =(T11-R11)/R11 -> -0.004602671
C12: SLBM | D12: 0.27094463 | E12: =SUMIFS(Transactions!L:L,Transactions!J:J,'Month on Month Equity Change'!C12) -> 0 | F12: =SUMIFS(Transactions!F:F,Transactions!D:D,'Month on Month Equity Change'!C12) -> 0 | H12: =VLOOKUP(C12,'Live Equity Performance'!$B$7:$F$15,5,0) -> 0.24478595
C13: Direct Equity - Personal | D13: =D14 -> 202.82711 | E13: =SUM(E14:E14) -> 1.8894636 | F13: =SUM(F14:F14) -> 3.000036 | G13: =SUM(G14:G14) -> 1.8273252 | H13: =SUM(H14:H14) -> 222.35865 | I13: =SUM(I14:I14) -> 22.46944 | J13: =((H13+G13+F13)/(E13+D13))-1 -> 0.10975877 | K13: =K14 -> 0.021063079
C14: Direct Equity - Non MO | D14: 202.82711 | E14: =SUMIFS(Transactions!L:L,Transactions!J:J,'Month on Month Equity Change'!C14) -> 1.8894636 | F14: =SUMIFS(Transactions!F:F,Transactions!D:D,'Month on Month Equity Change'!C14) -> 3.000036 | G14: ='Portfolio Allocation'!J9 -> 1.8273252 | H14: =VLOOKUP(C14,'Live Equity Performance'!$B$7:$F$14,5,0) -> 222.35865 | I14: =H14+G14+F14-E14-D14 -> 22.46944 | J14: =((H14+G14+F14)/(E14+D14))-1 -> 0.10975877 | K14: =Q11 -> 0.021063079 | L14: Nifty Mid & Smallcap 400 TR
B15: * | C15: Total | D15: =D13+D3 -> 916.93825 | E15: =E13+E3 -> 34.389089 | F15: =F13+F3 -> 27.877601 | G15: =G13+G3 -> 1.8292752 | H15: =H13+H3 -> 981.78153 | I15: =H15+G15+F15-E15-D15 -> 60.161068 | J15: =((H15+G15+F15)/(E15+D15))-1 -> 0.063239083 | K15: =K3*(H3/H15)+K13*(H13/H15) -> 0.019003763
C16: Managed - Excl Unlisted | D16: =D3-D5 -> 651.28263 | E16: =E3-E5 -> 32.499625 | F16: =F3-F5 -> 24.877565 | G16: =G3-G5 -> 0.00195 | H16: =H3-H5 -> 695.09437 | I16: =H16+G16+F16-E16-D16 -> 36.191628 | J16: =((H16+G16+F16)/(E16+D16))-1 -> 0.052928587 | K16: =K3*((H3-H5)/(H15-H5))+K13*((H13)/(H15-H5)) -> 0.019046041
C17: Note: Direct Equity - Unlisted includes NSE and Zepto
C18: Note: Direct Equity MO includes Onesource and Kaynes Technology
C19: Note: Any incremental sale/ purchase after 30th April has been shown in the analysis , transactions upto 30th April have been captured under previous month market value
C20: *Equity Savings & Multi Asset excluded from equity hybrid

Sheet Equity Quants
B1: As on 30th June 2026
B2: Top 20 Stocks | C2: Allocation in % | D2: No of Schemes in | E2: Nifty 50 Allocation | F2: Nifty 500 Allocation | H2: Top 10 Sectors | I2: Allocation in Portfolio | J2: Allocation in Nifty 50 | K2: Allocation in Nifty 500
B3: National Stock Exchange | C3: 5.3414948 | D3: 1 | E3: - | F3: - | H3: Financials | I3: 26.473946 | J3: =_xlfn.XLOOKUP(H3,'[5]Index data'!$O:$O,'[5]Index data'!$P:$P) -> 35.147029 | K3: =_xlfn.XLOOKUP(H3,'[5]Index data'!$O:$O,'[5]Index data'!$Q:$Q) -> 29.857506 | M3: Particulars | N3: PE | O3: PB | P3: ROE
B4: Man Industries | C4: 4.3632545 | D4: 1 | E4: - | F4: - | H4: Consumer Goods | I4: 13.889776 | J4: =_xlfn.XLOOKUP(H4,'[5]Index data'!$O:$O,'[5]Index data'!$P:$P) -> 6.3912783 | K4: =_xlfn.XLOOKUP(H4,'[5]Index data'!$O:$O,'[5]Index data'!$Q:$Q) -> 6.8445651 | M4: Portfolio (Incl Direct Equity) | N4: 37.5 | O4: 4.8 | P4: =O4/N4 -> 0.128
B5: Clean Max Enviro Energy Solutions Ltd | C5: 3.3358529 | D5: 1 | E5: - | F5: - | H5: Pharma / Healthcare | I5: 10.300489 | J5: =_xlfn.XLOOKUP(H5,'[5]Index data'!$O:$O,'[5]Index data'!$P:$P) -> 4.6909382 | K5: =_xlfn.XLOOKUP(H5,'[5]Index data'!$O:$O,'[5]Index data'!$Q:$Q) -> 6.9219397 | M5: Managed Strategies | N5: 28.3 | O5: 3.4 | P5: =O5/N5 -> 0.12014134
B6: Manorama Industries Ltd. | C6: 3.2246331 | D6: 1 | E6: - | F6: - | H6: Metals / Mining | I6: 8.7243219 | J6: =_xlfn.XLOOKUP(H6,'[5]Index data'!$O:$O,'[5]Index data'!$P:$P) -> 5.9511902 | K6: =_xlfn.XLOOKUP(H6,'[5]Index data'!$O:$O,'[5]Index data'!$Q:$Q) -> 5.7023078 | M6: Nifty 50 | N6: 22.2 | O6: 3.7 | P6: =O6/N6 -> 0.16666667
B7: Zepto | C7: 2.9382747 | D7: 1 | E7: - | F7: - | H7: IT | I7: 6.5293359 | J7: =_xlfn.XLOOKUP(H7,'[5]Index data'!$O:$O,'[5]Index data'!$P:$P) -> 8.4816963 | K7: =_xlfn.XLOOKUP(H7,'[5]Index data'!$O:$O,'[5]Index data'!$Q:$Q) -> 7.1389652 | M7: Nifty 500 | N7: 20.6 | O7: 3.1 | P7: =O7/N7 -> 0.15048544
B8: ICICI Bank Ltd. | C8: 2.3436241 | D8: 10 | E8: 8.3216643 | F8: 4.6601942 | H8: Capital Goods | I8: 5.2468871 | J8: =_xlfn.XLOOKUP(H8,'[5]Index data'!$O:$O,'[5]Index data'!$P:$P) -> 1.3602721 | K8: =_xlfn.XLOOKUP(H8,'[5]Index data'!$O:$O,'[5]Index data'!$Q:$Q) -> 5.1408984
B9: Onesource Specialty Pharma | C9: 2.3049674 | D9: 3 | E9: - | F9: - | H9: Auto / Ancillaries | I9: 4.4690561 | J9: =_xlfn.XLOOKUP(H9,'[5]Index data'!$O:$O,'[5]Index data'!$P:$P) -> 6.8713743 | K9: =_xlfn.XLOOKUP(H9,'[5]Index data'!$O:$O,'[5]Index data'!$Q:$Q) -> 8.2997903
B10: BSE Ltd. | C10: 2.0688932 | D10: 3 | E10: - | F10: - | H10: Engineering / Construction | I10: 2.1033411 | J10: =_xlfn.XLOOKUP(H10,'[5]Index data'!$O:$O,'[5]Index data'!$P:$P) -> 4.4308862 | K10: =_xlfn.XLOOKUP(H10,'[5]Index data'!$O:$O,'[5]Index data'!$Q:$Q) -> 2.8379583
B11: Fractal Analytics Limited | C11: 2.0636011 | D11: 1 | E11: - | F11: - | H11: Services | I11: 1.9267573 | J11: - | K11: -
B12: Smart Works | C12: 1.9267573 | D12: 2 | E12: - | F12: - | H12: Telecom | I12: 1.9154583 | J12: =_xlfn.XLOOKUP(H12,'[5]Index data'!$O:$O,'[5]Index data'!$P:$P) -> 5.2010402 | K12: =_xlfn.XLOOKUP(H12,'[5]Index data'!$O:$O,'[5]Index data'!$Q:$Q) -> 4.2540049
B13: State Bank Of India | C13: 1.739017 | D13: 15 | E13: 3.7107421 | F13: 2.0763359 | H13: Total | I13: =SUM(I3:I12) -> 81.579368 | J13: =SUM(J3:J12) -> 78.525705 | K13: =SUM(K3:K12) -> 76.997936
B14: HDFC Bank Ltd. | C14: 1.7018502 | D14: 10 | E14: 10.562112 | F14: 5.9119537
B15: Vedanta Aluminium Metal Ltd | C15: 1.4674367 | D15: 5 | E15: - | F15: - | H15: Market Cap Orientation
B16: Axis Bank Ltd. | C16: 1.4067422 | D16: 9 | E16: 3.4206841 | F16: 1.9152643 | H16: 30th June 2026 | J16: 31st May 2026 | L16: 30th April 2026 | N16: 30th March 26 | U16: Large Cap | V16: 0.264
B17: Aditya Birla Capital Ltd | C17: 1.3823664 | D17: 2 | E17: - | F17: 0.15540644 | U17: Mid Cap | V17: 0.22
B18: Yash High Voltage Ltd. | C18: 1.3137905 | D18: 1 | E18: - | F18: - | U18: Small Cap | V18: =100%-V16-V17 -> 0.516
B19: PG Electro. | C19: 1.3030525 | D19: 2 | E19: - | F19: 0.040242496
B20: Kingfa Science & Technology Ltd. | C20: 1.2944347 | D20: 1 | E20: - | F20: -
B21: Neuland Labs. | C21: 1.2381266 | D21: 3 | E21: - | F21: 0.076425843
B22: Larsen & Toubro Ltd. | C22: 1.1897627 | D22: 10 | E22: 4.4308862 | F22: 2.4832436
B23: Total | C23: 41.707661 | E23: 31.18 | F23: 19.154565
H29: *Smallcap stocks includes microcap stocks
J34: No of Stocks | K34: 30th June'26 | L34: 31st May'26 | M34: 30th April'26 | N34: 30th March'26 | O34: % Change from 30th June '26 to 31st May'26 | P34: % Change from 31st May '26 to 30th April'26 | Q34: % Chg from 30th April'26 to 30th March'26
J35: Total Stocks | K35: 1172 | L35: 1251 | M35: 1284 | N35: 1051 | O35: =K35/L35-1 -> -0.06314948 | P35: =L35/M35-1 -> -0.025700935 | Q35: =M35/N35-1 -> 0.22169363
J36: Unique Stocks | K36: 567 | L36: 550 | M36: 551 | N36: 530 | O36: =K36/L36-1 -> 0.030909091 | P36: =L36/M36-1 -> -0.001814882 | Q36: =M36/N36-1 -> 0.039622642
J37: Direct Equity | K37: 41 | L37: 37 | M37: 44 | N37: 44 | O37: =K37/L37-1 -> 0.10810811 | P37: =L37/M37-1 -> -0.15909091 | Q37: =M37/N37-1 -> 0
J38: Managed Strategies | K38: =K35-K37-K39 -> 917 | L38: =L35-L37-L39 -> 872 | M38: =M35-M37-M39 -> 901 | N38: =N35-N37-N39 -> 677 | O38: =K38/L38-1 -> 0.051605505 | P38: =L38/M38-1 -> -0.032186459 | Q38: =M38/N38-1 -> 0.33087149
J39: Balance Adv / Index funds | K39: 214 | L39: 342 | M39: 339 | N39: 330 | O39: =K39/L39-1 -> -0.37426901 | P39: =L39/M39-1 -> 0.0088495575 | Q39: =M39/N39-1 -> 0.027272727
J41: Unique Strategies | K41: 30th June'26 | L41: 31st May'26 | M41: 30th April'26 | N41: 30th March'26 | O41: % Change from 30th June '26 to 31st May'26 | P41: % Change from 31st May '26 to 30th April'26 | Q41: % Chg from 30th April'26 to 30th March'26
J42: Managed | K42: 16 | L42: 17 | M42: 18 | N42: 15 | P42: =L42-M42 -> -1 | Q42: =M42-N42 -> 3
J43: Balance Adv / Index funds | K43: 3 | L43: 3 | M43: 3 | N43: 3 | P43: =L43-M43 -> 0 | Q43: =M43-N43 -> 0
J44: Total | K44: =SUM(K42:K43) -> 19 | L44: =SUM(L42:L43) -> 20 | M44: =SUM(M42:M43) -> 21 | N44: =SUM(N42:N43) -> 18 | P44: =SUM(P42:P43) -> -1 | Q44: =SUM(Q42:Q43) -> 3
J45: *HDFC value fund complete exit in June'26

Sheet Attribution Analysis
A1: *Sanshi Fund valuation in previous month is as on 30th June'26
C2: Previous month | E2: 100 | I2: =265.4-264.4 -> 1
A3: Equity Funds / Strategies | B3: Current Value as on 30th June 2026 | C3: Market Value as on 31st May 2026 | D3: Purchase | E3: Sale | F3: M-o-M | G3: Benchmark | H3: Alpha M-o-M | I3: Alpha Since inception | J3: Remarks
A4: Multi Cap | B4: =SUM(B5:B18) -> 361.70793 | C4: =SUM(C5:C18) -> 331.99511 | D4: =SUM(D5:D18) -> 32.499625 | E4: =SUM(E5:E18) -> 15.53989 | F4: =(B4+E4)/(C4+D4)-1 -> 0.034988411 | G4: =SUMPRODUCT(G5:G18,C5:C18)/C4 -> 0.017068927 | H4: =F4-G4 -> 0.017919484 | I4: =IF((VLOOKUP(A4,Equity!$B$2:$O$73,14,0)="A"),(VLOOKUP(A4,Equity!$B$2:$N$73,9,0)-VLOOKUP(A4,Equity!$B$2:$N$73,10,0)),(VLOOKUP(A4,Equity!$B$2:$N$73,11,0)-VLOOKUP(A4,Equity!$B$2:$N$73,12,0))) -> -0.06955675
A5: Motilal Oswal Founders Fund II | B5: =VLOOKUP(A5,Equity!$B$2:$H$73,7,0) -> 32.706287 | C5: 31.419559 | D5: =SUMIFS(Transactions!L:L,Transactions!K:K,A5) -> 0 | E5: =SUMIFS(Transactions!F:F,Transactions!E:E,A5) -> 0 | F5: =(B5+E5)/(C5+D5)-1 -> 0.04095307 | G5: ='Month on Month Equity Change'!$Q$3 -> 0.017068927 | H5: =F5-G5 -> 0.023884143 | I5: =IF((VLOOKUP(A5,Equity!$B$2:$O$73,14,0)="A"),(VLOOKUP(A5,Equity!$B$2:$N$73,9,0)-VLOOKUP(A5,Equity!$B$2:$N$73,10,0)),(VLOOKUP(A5,Equity!$B$2:$N$73,11,0)-VLOOKUP(A5,Equity!$B$2:$N$73,12,0))) -> -0.041163313
A6: Carnelian Bespoke Portfolio | B6: =VLOOKUP(A6,Equity!$B$2:$H$73,7,0) -> 40.047568 | C6: 36.932103 | D6: =SUMIFS(Transactions!L:L,Transactions!K:K,A6) -> 0 | E6: =SUMIFS(Transactions!F:F,Transactions!E:E,A6) -> 0 | F6: =(B6+E6)/(C6+D6)-1 -> 0.084356547 | G6: ='Month on Month Equity Change'!$Q$3 -> 0.017068927 | H6: =F6-G6 -> 0.067287621 | I6: =IF((VLOOKUP(A6,Equity!$B$2:$O$73,14,0)="A"),(VLOOKUP(A6,Equity!$B$2:$N$73,9,0)-VLOOKUP(A6,Equity!$B$2:$N$73,10,0)),(VLOOKUP(A6,Equity!$B$2:$N$73,11,0)-VLOOKUP(A6,Equity!$B$2:$N$73,12,0))) -> -0.15975283
A7: Green Lantern Growth Strategy | B7: =VLOOKUP(A7,Equity!$B$2:$H$73,7,0) -> 17.617651 | C7: 17.200352 | D7: =SUMIFS(Transactions!L:L,Transactions!K:K,A7) -> 0 | E7: =SUMIFS(Transactions!F:F,Transactions!E:E,A7) -> 0 | F7: =(B7+E7)/(C7+D7)-1 -> 0.024261108 | G7: ='Month on Month Equity Change'!$Q$3 -> 0.017068927 | H7: =F7-G7 -> 0.0071921819 | I7: =IF((VLOOKUP(A7,Equity!$B$2:$O$73,14,0)="A"),(VLOOKUP(A7,Equity!$B$2:$N$73,9,0)-VLOOKUP(A7,Equity!$B$2:$N$73,10,0)),(VLOOKUP(A7,Equity!$B$2:$N$73,11,0)-VLOOKUP(A7,Equity!$B$2:$N$73,12,0))) -> -0.027118337
A8: 3P India Equity Fund 1 | B8: =VLOOKUP(A8,Equity!$B$2:$H$73,7,0) -> 52.115602 | C8: 51.010896 | D8: =SUMIFS(Transactions!L:L,Transactions!K:K,A8) -> 0 | E8: =SUMIFS(Transactions!F:F,Transactions!E:E,A8) -> 0 | F8: =(B8+E8)/(C8+D8)-1 -> 0.021656261 | G8: ='Month on Month Equity Change'!$Q$3 -> 0.017068927 | H8: =F8-G8 -> 0.0045873342 | I8: =IF((VLOOKUP(A8,Equity!$B$2:$O$73,14,0)="A"),(VLOOKUP(A8,Equity!$B$2:$N$73,9,0)-VLOOKUP(A8,Equity!$B$2:$N$73,10,0)),(VLOOKUP(A8,Equity!$B$2:$N$73,11,0)-VLOOKUP(A8,Equity!$B$2:$N$73,12,0))) -> 0.022014366
A9: Fund of Funds (VEC+ Carnelian+Girik Cap+Insightful) | B9: =VLOOKUP(A9,Equity!$B$2:$H$73,7,0) -> 11.128744 | C9: 10.645768 | D9: =SUMIFS(Transactions!L:L,Transactions!K:K,A9) -> 0 | E9: =SUMIFS(Transactions!F:F,Transactions!E:E,A9) -> 0 | F9: =(B9+E9)/(C9+D9)-1 -> 0.045367874 | G9: ='Month on Month Equity Change'!$Q$3 -> 0.017068927 | H9: =F9-G9 -> 0.028298948 | I9: =IF((VLOOKUP(A9,Equity!$B$2:$O$73,14,0)="A"),(VLOOKUP(A9,Equity!$B$2:$N$73,9,0)-VLOOKUP(A9,Equity!$B$2:$N$73,10,0)),(VLOOKUP(A9,Equity!$B$2:$N$73,11,0)-VLOOKUP(A9,Equity!$B$2:$N$73,12,0))) -> -0.060736049
A10: Carnelian Bharat Amritkaal Fund | B10: =VLOOKUP(A10,Equity!$B$2:$H$73,7,0) -> 16.008922 | C10: 15.390581 | D10: =SUMIFS(Transactions!L:L,Transactions!K:K,A10) -> 0 | E10: =SUMIFS(Transactions!F:F,Transactions!E:E,A10) -> 0 | F10: =(B10+E10)/(C10+D10)-1 -> 0.040176612 | G10: ='Month on Month Equity Change'!$Q$3 -> 0.017068927 | H10: =F10-G10 -> 0.023107685 | I10: =IF((VLOOKUP(A10,Equity!$B$2:$O$73,14,0)="A"),(VLOOKUP(A10,Equity!$B$2:$N$73,9,0)-VLOOKUP(A10,Equity!$B$2:$N$73,10,0)),(VLOOKUP(A10,Equity!$B$2:$N$73,11,0)-VLOOKUP(A10,Equity!$B$2:$N$73,12,0))) -> -0.25004277
A11: Aristos Equity Potrfolio - SB | B11: =VLOOKUP(A11,Equity!$B$2:$H$73,7,0) -> 25.922903 | C11: 24.324255 | D11: =SUMIFS(Transactions!L:L,Transactions!K:K,A11) -> 0 | E11: =SUMIFS(Transactions!F:F,Transactions!E:E,A11) -> 0 | F11: =(B11+E11)/(C11+D11)-1 -> 0.06572237 | G11: ='Month on Month Equity Change'!$Q$3 -> 0.017068927 | H11: =F11-G11 -> 0.048653443 | I11: =IF((VLOOKUP(A11,Equity!$B$2:$O$73,14,0)="A"),(VLOOKUP(A11,Equity!$B$2:$N$73,9,0)-VLOOKUP(A11,Equity!$B$2:$N$73,10,0)),(VLOOKUP(A11,Equity!$B$2:$N$73,11,0)-VLOOKUP(A11,Equity!$B$2:$N$73,12,0))) -> -0.073733021
A12: Buoyant Opportunities Portfolio AIF | B12: =VLOOKUP(A12,Equity!$B$2:$H$73,7,0) -> 76.047925 | C12: 49.2 | D12: =SUMIFS(Transactions!L:L,Transactions!K:K,A12) -> 25 | E12: =SUMIFS(Transactions!F:F,Transactions!E:E,A12) -> 0 | F12: =(B12+E12)/(C12+D12)-1 -> 0.024904644 | G12: ='Month on Month Equity Change'!$Q$3 -> 0.017068927 | H12: =F12-G12 -> 0.0078357176 | I12: =IF((VLOOKUP(A12,Equity!$B$2:$O$73,14,0)="A"),(VLOOKUP(A12,Equity!$B$2:$N$73,9,0)-VLOOKUP(A12,Equity!$B$2:$N$73,10,0)),(VLOOKUP(A12,Equity!$B$2:$N$73,11,0)-VLOOKUP(A12,Equity!$B$2:$N$73,12,0))) -> -0.085560503
A13: HDFC Capital Builder Value Fund | B13: 0 | C13: 9.2693367 | D13: =SUMIFS(Transactions!L:L,Transactions!K:K,A13) -> 0 | E13: =SUMIFS(Transactions!F:F,Transactions!E:E,A13) -> 9.6021604 | F13: =(B13+E13)/(C13+D13)-1 -> 0.035905877 | G13: ='Month on Month Equity Change'!$Q$3 -> 0.017068927 | H13: =F13-G13 -> 0.018836951 | I13: =IF((VLOOKUP(A13,Equity!$B$2:$O$73,14,0)="A"),(VLOOKUP(A13,Equity!$B$2:$N$73,9,0)-VLOOKUP(A13,Equity!$B$2:$N$73,10,0)),(VLOOKUP(A13,Equity!$B$2:$N$73,11,0)-VLOOKUP(A13,Equity!$B$2:$N$73,12,0))) -> #N/A
A14: Helios Flexi Cap Fund Direct (G) | B14: =VLOOKUP(A14,Equity!$B$2:$H$73,7,0) -> 27.174766 | C14: 26.147365 | D14: =SUMIFS(Transactions!L:L,Transactions!K:K,A14) -> 0 | E14: =SUMIFS(Transactions!F:F,Transactions!E:E,A14) -> 0 | F14: =(B14+E14)/(C14+D14)-1 -> 0.039292731 | G14: ='Month on Month Equity Change'!$Q$3 -> 0.017068927 | H14: =F14-G14 -> 0.022223804 | I14: =IF((VLOOKUP(A14,Equity!$B$2:$O$73,14,0)="A"),(VLOOKUP(A14,Equity!$B$2:$N$73,9,0)-VLOOKUP(A14,Equity!$B$2:$N$73,10,0)),(VLOOKUP(A14,Equity!$B$2:$N$73,11,0)-VLOOKUP(A14,Equity!$B$2:$N$73,12,0))) -> -0.070631876
A15: Bandhan Large & Mid Cap Fund - Direct Plan - Growth | B15: =VLOOKUP(A15,Equity!$B$2:$H$73,7,0) -> 24.782832 | C15: 17.072486 | D15: =SUMIFS(Transactions!L:L,Transactions!K:K,A15) -> 7.499625 | E15: =SUMIFS(Transactions!F:F,Transactions!E:E,A15) -> 0 | F15: =(B15+E15)/(C15+D15)-1 -> 0.0085756188 | G15: ='Month on Month Equity Change'!$Q$3 -> 0.017068927 | H15: =F15-G15 -> -0.0084933077 | I15: =IF((VLOOKUP(A15,Equity!$B$2:$O$73,14,0)="A"),(VLOOKUP(A15,Equity!$B$2:$N$73,9,0)-VLOOKUP(A15,Equity!$B$2:$N$73,10,0)),(VLOOKUP(A15,Equity!$B$2:$N$73,11,0)-VLOOKUP(A15,Equity!$B$2:$N$73,12,0))) -> 0.019394611
A16: Kotak Large & Midcap Fund - Direct- Growth | B16: =VLOOKUP(A16,Equity!$B$2:$H$73,7,0) -> 2.5003334 | C16: 2.4220826 | D16: =SUMIFS(Transactions!L:L,Transactions!K:K,A16) -> 0 | E16: =SUMIFS(Transactions!F:F,Transactions!E:E,A16) -> 0 | F16: =(B16+E16)/(C16+D16)-1 -> 0.032307236 | G16: ='Month on Month Equity Change'!$Q$3 -> 0.017068927 | H16: =F16-G16 -> 0.015238309 | I16: =IF((VLOOKUP(A16,Equity!$B$2:$O$73,14,0)="A"),(VLOOKUP(A16,Equity!$B$2:$N$73,9,0)-VLOOKUP(A16,Equity!$B$2:$N$73,10,0)),(VLOOKUP(A16,Equity!$B$2:$N$73,11,0)-VLOOKUP(A16,Equity!$B$2:$N$73,12,0))) -> 0.2625053
A17: Kotak Multicap Fund-Direct Plan-Growth | B17: =VLOOKUP(A17,Equity!$B$2:$H$73,7,0) -> 10.236297 | C17: 9.9509565 | D17: =SUMIFS(Transactions!L:L,Transactions!K:K,A17) -> 0 | E17: =SUMIFS(Transactions!F:F,Transactions!E:E,A17) -> 0 | F17: =(B17+E17)/(C17+D17)-1 -> 0.028674699 | G17: ='Month on Month Equity Change'!$Q$3 -> 0.017068927 | H17: =F17-G17 -> 0.011605772 | I17: =IF((VLOOKUP(A17,Equity!$B$2:$O$73,14,0)="A"),(VLOOKUP(A17,Equity!$B$2:$N$73,9,0)-VLOOKUP(A17,Equity!$B$2:$N$73,10,0)),(VLOOKUP(A17,Equity!$B$2:$N$73,11,0)-VLOOKUP(A17,Equity!$B$2:$N$73,12,0))) -> 0.012127361
A18: ICICI Pru India Opportunities Fund | B18: =VLOOKUP(A18,Equity!$B$2:$H$73,7,0) -> 25.418104 | C18: 31.009366 | D18: =SUMIFS(Transactions!L:L,Transactions!K:K,A18) -> 0 | E18: =SUMIFS(Transactions!F:F,Transactions!E:E,A18) -> 5.9377299 | F18: =(B18+E18)/(C18+D18)-1 -> 0.011172987 | G18: ='Month on Month Equity Change'!$Q$3 -> 0.017068927 | H18: =F18-G18 -> -0.0058959394 | I18: =IF((VLOOKUP(A18,Equity!$B$2:$O$73,14,0)="A"),(VLOOKUP(A18,Equity!$B$2:$N$73,9,0)-VLOOKUP(A18,Equity!$B$2:$N$73,10,0)),(VLOOKUP(A18,Equity!$B$2:$N$73,11,0)-VLOOKUP(A18,Equity!$B$2:$N$73,12,0))) -> -0.0067952634
A19: Small Cap | B19: =B20 -> 1.1248249 | C19: =C20 -> 1.1531672 | D19: =SUM(D20:D20) -> 0 | E19: =SUM(E20:E20) -> 0 | F19: =(B19+E19)/(C19+D19)-1 -> -0.024577789 | G19: ='Month on Month Equity Change'!$K$10 -> 0.043368897 | H19: =F19-G19 -> -0.067946686 | I19: =IF((VLOOKUP(A19,Equity!$B$2:$O$73,14,0)="A"),(VLOOKUP(A19,Equity!$B$2:$N$73,9,0)-VLOOKUP(A19,Equity!$B$2:$N$73,10,0)),(VLOOKUP(A19,Equity!$B$2:$N$73,11,0)-VLOOKUP(A19,Equity!$B$2:$N$73,12,0))) -> -0.053619739
A20: Molecule Growth Strategy | B20: ='Month on Month Equity Change'!H10 -> 1.1248249 | C20: 1.1531672 | D20: =SUMIFS(Transactions!L:L,Transactions!K:K,A20) -> 0 | E20: =SUMIFS(Transactions!F:F,Transactions!E:E,A20) -> 0 | F20: =(B20+E20)/(C20+D20)-1 -> -0.024577789 | G20: ='Month on Month Equity Change'!$K$10 -> 0.043368897 | H20: =F20-G20 -> -0.067946686 | I20: =IF((VLOOKUP(A20,Equity!$B$2:$O$73,14,0)="A"),(VLOOKUP(A20,Equity!$B$2:$N$73,9,0)-VLOOKUP(A20,Equity!$B$2:$N$73,10,0)),(VLOOKUP(A20,Equity!$B$2:$N$73,11,0)-VLOOKUP(A20,Equity!$B$2:$N$73,12,0))) -> -0.053619739
A21: Mid & Small Cap | B21: =VLOOKUP(A21,Equity!$B$2:$H$73,7,0) -> 246.75783 | C21: =SUM(C22:C24) -> 223.51739 | D21: =SUM(D22:D24) -> 0 | E21: =SUM(E22:E24) -> 0 | F21: =(B21+E21)/(C21+D21)-1 -> 0.10397597 | G21: =SUMPRODUCT(G22:G24,C22:C24)/C21 -> 0.021063079 | H21: =F21-G21 -> 0.082912892 | I21: =IF((VLOOKUP(A21,Equity!$B$2:$O$73,14,0)="A"),(VLOOKUP(A21,Equity!$B$2:$N$73,9,0)-VLOOKUP(A21,Equity!$B$2:$N$73,10,0)),(VLOOKUP(A21,Equity!$B$2:$N$73,11,0)-VLOOKUP(A21,Equity!$B$2:$N$73,12,0))) -> -0.38801569
A22: Sanshi Fund 1 | B22: =VLOOKUP(A22,Equity!$B$2:$H$73,7,0) -> 204.48014 | C22: 184.19403 | D22: =SUMIFS(Transactions!L:L,Transactions!K:K,A22) -> 0 | E22: =SUMIFS(Transactions!F:F,Transactions!E:E,'Attribution Analysis'!A22) -> 0 | F22: =(B22+E22)/(C22+D22)-1 -> 0.11013451 | G22: ='Month on Month Equity Change'!$Q$11 -> 0.021063079 | H22: =F22-G22 -> 0.089071428 | I22: =IF((VLOOKUP(A22,Equity!$B$2:$O$73,14,0)="A"),(VLOOKUP(A22,Equity!$B$2:$N$73,9,0)-VLOOKUP(A22,Equity!$B$2:$N$73,10,0)),(VLOOKUP(A22,Equity!$B$2:$N$73,11,0)-VLOOKUP(A22,Equity!$B$2:$N$73,12,0))) -> -0.54006613
A23: VEC Small and Mid cap fund | B23: =VLOOKUP(A23,Equity!$B$2:$H$73,7,0) -> 15.894442 | C23: 14.910847 | D23: =SUMIFS(Transactions!L:L,Transactions!K:K,A23) -> 0 | E23: =SUMIFS(Transactions!F:F,Transactions!E:E,'Attribution Analysis'!A23) -> 0 | F23: =(B23+E23)/(C23+D23)-1 -> 0.065965049 | G23: ='Month on Month Equity Change'!$Q$11 -> 0.021063079 | H23: =F23-G23 -> 0.04490197 | I23: =IF((VLOOKUP(A23,Equity!$B$2:$O$73,14,0)="A"),(VLOOKUP(A23,Equity!$B$2:$N$73,9,0)-VLOOKUP(A23,Equity!$B$2:$N$73,10,0)),(VLOOKUP(A23,Equity!$B$2:$N$73,11,0)-VLOOKUP(A23,Equity!$B$2:$N$73,12,0))) -> 0.0037678631
A24: Svan Investment | B24: =VLOOKUP(A24,Equity!$B$2:$H$73,7,0) -> 26.383247 | C24: 24.412522 | D24: =SUMIFS(Transactions!L:L,Transactions!K:K,A24) -> 0 | E24: =SUMIFS(Transactions!F:F,Transactions!E:E,'Attribution Analysis'!A24) -> 0 | F24: =(B24+E24)/(C24+D24)-1 -> 0.080725998 | G24: ='Month on Month Equity Change'!$Q$11 -> 0.021063079 | H24: =F24-G24 -> 0.05966292 | I24: =IF((VLOOKUP(A24,Equity!$B$2:$O$73,14,0)="A"),(VLOOKUP(A24,Equity!$B$2:$N$73,9,0)-VLOOKUP(A24,Equity!$B$2:$N$73,10,0)),(VLOOKUP(A24,Equity!$B$2:$N$73,11,0)-VLOOKUP(A24,Equity!$B$2:$N$73,12,0))) -> -0.043994952
A25: Equity Hybrid | B25: =SUM(B26:B28) -> 62.768957 | C25: =SUM(C26:C28) -> 70.26721 | D25: =SUM(D26:D28) -> 0 | E25: =SUM(E26:E28) -> 9.0317486 | F25: =(B25+E25)/(C25+D25)-1 -> 0.021823773 | G25: =SUMPRODUCT(G26:G28,C26:C28)/C25 -> 0.017414367 | H25: =F25-G25 -> 0.0044094065 | I25: =IF((VLOOKUP(A25,Equity!$B$2:$O$73,14,0)="A"),(VLOOKUP(A25,Equity!$B$2:$N$73,9,0)-VLOOKUP(A25,Equity!$B$2:$N$73,10,0)),(VLOOKUP(A25,Equity!$B$2:$N$73,11,0)-VLOOKUP(A25,Equity!$B$2:$N$73,12,0))) -> 0.021799133
A26: Aditya Birla SL Balanced Advantage Fund(G) | B26: =VLOOKUP(A26,Equity!$B$2:$H$73,7,0) -> 29.582027 | C26: 29.05427 | D26: =SUMIFS(Transactions!L:L,Transactions!K:K,A26) -> 0 | E26: =SUMIFS(Transactions!F:F,Transactions!E:E,'Attribution Analysis'!A26) -> 0 | F26: =(B26+E26)/(C26+D26)-1 -> 0.018164515 | G26: ='Month on Month Equity Change'!$Q$7 -> 0.017414367 | H26: =F26-G26 -> 0.00075014852
A27: HDFC Balanced Advantage Fund | B27: =VLOOKUP(A27,Equity!$B$2:$H$73,7,0) -> 10.869689 | C27: 13.835908 | D27: =SUMIFS(Transactions!L:L,Transactions!K:K,A27) -> 0 | E27: =SUMIFS(Transactions!F:F,Transactions!E:E,'Attribution Analysis'!A27) -> 3.3040294 | F27: =(B27+E27)/(C27+D27)-1 -> 0.024415492 | G27: ='Month on Month Equity Change'!$Q$7 -> 0.017414367 | H27: =F27-G27 -> 0.0070011248
A28: ICICI Pru Balanced Advantage Fund | B28: =VLOOKUP(A28,Equity!$B$2:$H$73,7,0) -> 22.317241 | C28: 27.377032 | D28: =SUMIFS(Transactions!L:L,Transactions!K:K,A28) -> 0 | E28: =SUMIFS(Transactions!F:F,Transactions!E:E,'Attribution Analysis'!A28) -> 5.7277192 | F28: =(B28+E28)/(C28+D28)-1 -> 0.024397401 | G28: ='Month on Month Equity Change'!$Q$7 -> 0.017414367 | H28: =F28-G28 -> 0.0069830345
A29: Direct Equity - MO | B29: =VLOOKUP(A29,Equity!$B$2:$H$73,7,0) -> 21.640258 | C29: =SUM(C30:C31) -> 23.147697 | D29: =SUM(D30:D31) -> 0 | E29: =SUM(E30:E31) -> 0 | F29: =(B29+E29)/(C29+D29)-1 -> -0.065122655 | G29: ='Month on Month Equity Change'!K4 -> 0.017068927 | H29: =F29-G29 -> -0.082191582 | I29: =IF((VLOOKUP(A29,Equity!$B$2:$O$73,14,0)="A"),(VLOOKUP(A29,Equity!$B$2:$N$73,9,0)-VLOOKUP(A29,Equity!$B$2:$N$73,10,0)),(VLOOKUP(A29,Equity!$B$2:$N$73,11,0)-VLOOKUP(A29,Equity!$B$2:$N$73,12,0))) -> -0.11965541
A30: Onesource Specialty Pharma | B30: =VLOOKUP(A30,Equity!$B$2:$H$73,7,0) -> 15.029105 | C30: 16.512405 | D30: 0 | E30: =SUMIFS(Transactions!F:F,Transactions!E:E,'Attribution Analysis'!A30) -> 0 | F30: =(B30+E30)/(C30+D30)-1 -> -0.089829434 | G30: ='Month on Month Equity Change'!$K$4 -> 0.017068927 | H30: =F30-G30 -> -0.10689836 | I30: =IF((VLOOKUP(A30,Equity!$B$2:$O$73,14,0)="A"),(VLOOKUP(A30,Equity!$B$2:$N$73,9,0)-VLOOKUP(A30,Equity!$B$2:$N$73,10,0)),(VLOOKUP(A30,Equity!$B$2:$N$73,11,0)-VLOOKUP(A30,Equity!$B$2:$N$73,12,0))) -> -0.11852895
A31: Kaynes Technology India ltd | B31: =VLOOKUP(A31,Equity!$B$2:$H$73,7,0) -> 6.6111526 | C31: 6.6352921 | D31: =SUMIFS(Transactions!L:L,Transactions!K:K,A31) -> 0 | E31: =SUMIFS(Transactions!F:F,Transactions!E:E,'Attribution Analysis'!A31) -> 0 | F31: =(B31+E31)/(C31+D31)-1 -> -0.0036380463 | G31: ='Month on Month Equity Change'!$K$4 -> 0.017068927 | H31: =F31-G31 -> -0.020706973 | I31: =IF((VLOOKUP(A31,Equity!$B$2:$O$73,14,0)="A"),(VLOOKUP(A31,Equity!$B$2:$N$73,9,0)-VLOOKUP(A31,Equity!$B$2:$N$73,10,0)),(VLOOKUP(A31,Equity!$B$2:$N$73,11,0)-VLOOKUP(A31,Equity!$B$2:$N$73,12,0))) -> -0.12116551
A32: Direct Equity - Unlisted | B32: =VLOOKUP(A32,Equity!$B$2:$H$73,7,0) -> 64.328516 | C32: =SUM(C33:C34) -> 62.828516 | D32: =SUM(D33:D34) -> 0 | E32: =SUM(E33:E34) -> 0 | F32: =(B32+E32)/(C32+D32)-1 -> 0.02387451 | G32: ='Month on Month Equity Change'!K5 -> 0.016686243 | H32: =F32-G32 -> 0.0071882663 | I32: =IF((VLOOKUP(A32,Equity!$B$2:$O$73,14,0)="A"),(VLOOKUP(A32,Equity!$B$2:$N$73,9,0)-VLOOKUP(A32,Equity!$B$2:$N$73,10,0)),(VLOOKUP(A32,Equity!$B$2:$N$73,11,0)-VLOOKUP(A32,Equity!$B$2:$N$73,12,0))) -> -0.24014011
A33: National Stock Exchange | B33: =VLOOKUP(A33,Equity!$B$2:$H$73,7,0) -> 41.5 | C33: 40 | D33: =SUMIFS(Transactions!L:L,Transactions!K:K,A33) -> 0 | E33: =SUMIFS(Transactions!F:F,Transactions!E:E,'Attribution Analysis'!A33) -> 0 | F33: =(B33+E33)/(C33+D33)-1 -> 0.0375 | G33: ='Month on Month Equity Change'!$K$5 -> 0.016686243 | H33: =F33-G33 -> 0.020813757 | I33: =IF((VLOOKUP(A33,Equity!$B$2:$O$73,14,0)="A"),(VLOOKUP(A33,Equity!$B$2:$N$73,9,0)-VLOOKUP(A33,Equity!$B$2:$N$73,10,0)),(VLOOKUP(A33,Equity!$B$2:$N$73,11,0)-VLOOKUP(A33,Equity!$B$2:$N$73,12,0))) -> 0.049164709 | J33: Basis Last traded price
A34: Zepto | B34: =VLOOKUP(A34,Equity!$B$2:$H$73,7,0) -> 22.828516 | C34: 22.828516 | D34: =SUMIFS(Transactions!L:L,Transactions!K:K,A34) -> 0 | E34: =SUMIFS(Transactions!F:F,Transactions!E:E,'Attribution Analysis'!A34) -> 0 | F34: =(B34+E34)/(C34+D34)-1 -> 0 | G34: ='Month on Month Equity Change'!$K$5 -> 0.016686243
A35: LKP Sec Portfolio | B35: ='Live Equity Performance'!F15 -> 0.84977725 | C35: ='Month on Month Equity Change'!D6 -> 0.8976215 | D35: =SUMIFS(Transactions!L:L,Transactions!J:J,A35) -> 0 | E35: ='Month on Month Equity Change'!F6 -> 0.3055521 | F35: ='Month on Month Equity Change'!J6 -> 0.28927321 | G35: ='Month on Month Equity Change'!$Q$11 -> 0.021063079 | H35: =F35-G35 -> 0.26821013 | I35: =IF((VLOOKUP(A35,Equity!$B$2:$O$73,14,0)="A"),(VLOOKUP(A35,Equity!$B$2:$N$73,9,0)-VLOOKUP(A35,Equity!$B$2:$N$73,10,0)),(VLOOKUP(A35,Equity!$B$2:$N$73,11,0)-VLOOKUP(A35,Equity!$B$2:$N$73,12,0))) -> 0.17027083
A36: Direct Equity - Non MO | B36: =VLOOKUP(A36,Equity!$B$2:$H$73,7,0) -> 222.35865 | C36: =SUM(C37:C70) -> 202.82711 | D36: =SUM(D37:D67) -> 1.8894636 | E36: =SUM(E37:E70) -> 3.000036 | F36: =(B36+E36+'Month on Month Equity Change'!G14)/(C36+D36)-1 -> 0.10975877 | G36: ='Month on Month Equity Change'!$Q$11 -> 0.021063079 | H36: =F36-G36 -> 0.088695696 | I36: =IF((VLOOKUP(A36,Equity!$B$2:$O$73,14,0)="A"),(VLOOKUP(A36,Equity!$B$2:$N$73,9,0)-VLOOKUP(A36,Equity!$B$2:$N$73,10,0)),(VLOOKUP(A36,Equity!$B$2:$N$73,11,0)-VLOOKUP(A36,Equity!$B$2:$N$73,12,0))) -> -0.2509919
A37: Bharat Parenterals Ltd | B37: =VLOOKUP(A37,Equity!$B$2:$H$73,7,0) -> 0.08442 | C37: 0.081118575 | D37: =SUMIFS(Transactions!L:L,Transactions!K:K,A37) -> 0 | E37: =SUMIFS(Transactions!F:F,Transactions!E:E,'Attribution Analysis'!A37) -> 0 | F37: =(B37+E37)/(C37+D37)-1 -> 0.040698755 | G37: ='Month on Month Equity Change'!$Q$11 -> 0.021063079 | H37: =F37-G37 -> 0.019635676 | I37: =IF((VLOOKUP(A37,Equity!$B$2:$O$73,14,0)="A"),(VLOOKUP(A37,Equity!$B$2:$N$73,9,0)-VLOOKUP(A37,Equity!$B$2:$N$73,10,0)),(VLOOKUP(A37,Equity!$B$2:$N$73,11,0)-VLOOKUP(A37,Equity!$B$2:$N$73,12,0))) -> 0.1194282
A38: Birla Cable Ltd. | B38: =VLOOKUP(A38,Equity!$B$2:$H$73,7,0) -> 0.3127479 | C38: 0.29573174 | D38: =SUMIFS(Transactions!L:L,Transactions!K:K,A38) -> 0 | E38: =SUMIFS(Transactions!F:F,Transactions!E:E,'Attribution Analysis'!A38) -> 0 | F38: =(B38+E38)/(C38+D38)-1 -> 0.057539173 | G38: ='Month on Month Equity Change'!$Q$11 -> 0.021063079 | H38: =F38-G38 -> 0.036476094 | I38: =IF((VLOOKUP(A38,Equity!$B$2:$O$73,14,0)="A"),(VLOOKUP(A38,Equity!$B$2:$N$73,9,0)-VLOOKUP(A38,Equity!$B$2:$N$73,10,0)),(VLOOKUP(A38,Equity!$B$2:$N$73,11,0)-VLOOKUP(A38,Equity!$B$2:$N$73,12,0))) -> 0.64454183
A39: BSE Ltd. | B39: =VLOOKUP(A39,Equity!$B$2:$H$73,7,0) -> 15.4624 | C39: 16.5844 | D39: =SUMIFS(Transactions!L:L,Transactions!K:K,A39) -> 0 | E39: =SUMIFS(Transactions!F:F,Transactions!E:E,'Attribution Analysis'!A39) -> 0 | F39: =(B39+E39)/(C39+D39)-1 -> -0.06765394 | G39: ='Month on Month Equity Change'!$Q$11 -> 0.021063079 | H39: =F39-G39 -> -0.088717019 | I39: =IF((VLOOKUP(A39,Equity!$B$2:$O$73,14,0)="A"),(VLOOKUP(A39,Equity!$B$2:$N$73,9,0)-VLOOKUP(A39,Equity!$B$2:$N$73,10,0)),(VLOOKUP(A39,Equity!$B$2:$N$73,11,0)-VLOOKUP(A39,Equity!$B$2:$N$73,12,0))) -> -1.1840044
A40: Clean Max Enviro Energy Solutions Ltd | B40: =VLOOKUP(A40,Equity!$B$2:$H$73,7,0) -> 25.917444 | C40: 21.062731 | D40: =SUMIFS(Transactions!L:L,Transactions!K:K,A40) -> 0 | E40: =SUMIFS(Transactions!F:F,Transactions!E:E,'Attribution Analysis'!A40) -> 0 | G40: ='Month on Month Equity Change'!$Q$11 -> 0.021063079 | I40: =IF((VLOOKUP(A40,Equity!$B$2:$O$73,14,0)="A"),(VLOOKUP(A40,Equity!$B$2:$N$73,9,0)-VLOOKUP(A40,Equity!$B$2:$N$73,10,0)),(VLOOKUP(A40,Equity!$B$2:$N$73,11,0)-VLOOKUP(A40,Equity!$B$2:$N$73,12,0))) -> 0.083451406 | J40: Added from Pvt
A41: Deepak Fert | B41: =VLOOKUP(A41,Equity!$B$2:$H$73,7,0) -> 4.0400237 | C41: 3.658723 | D41: =SUMIFS(Transactions!L:L,Transactions!K:K,A41) -> 0 | E41: =SUMIFS(Transactions!F:F,Transactions!E:E,'Attribution Analysis'!A41) -> 0 | F41: =(B41+E41)/(C41+D41)-1 -> 0.10421687 | G41: ='Month on Month Equity Change'!$Q$11 -> 0.021063079 | H41: =F41-G41 -> 0.083153789 | I41: =IF((VLOOKUP(A41,Equity!$B$2:$O$73,14,0)="A"),(VLOOKUP(A41,Equity!$B$2:$N$73,9,0)-VLOOKUP(A41,Equity!$B$2:$N$73,10,0)),(VLOOKUP(A41,Equity!$B$2:$N$73,11,0)-VLOOKUP(A41,Equity!$B$2:$N$73,12,0))) -> -0.23593378
A42: Fractal Analytics Limited | B42: =VLOOKUP(A42,Equity!$B$2:$H$73,7,0) -> 16.032861 | C42: 18.03832 | D42: =SUMIFS(Transactions!L:L,Transactions!K:K,A42) -> 0 | E42: =SUMIFS(Transactions!F:F,Transactions!E:E,'Attribution Analysis'!A42) -> 0 | F42: =(B42+E42)/(C42+D42)-1 -> -0.1111777 | G42: ='Month on Month Equity Change'!$Q$11 -> 0.021063079 | H42: =F42-G42 -> -0.13224078 | I42: =IF((VLOOKUP(A42,Equity!$B$2:$O$73,14,0)="A"),(VLOOKUP(A42,Equity!$B$2:$N$73,9,0)-VLOOKUP(A42,Equity!$B$2:$N$73,10,0)),(VLOOKUP(A42,Equity!$B$2:$N$73,11,0)-VLOOKUP(A42,Equity!$B$2:$N$73,12,0))) -> 0.030529841 | J42: Added from Pvt
A43: M/S Grand Continent Hotels | B43: =VLOOKUP(A43,Equity!$B$2:$H$73,7,0) -> 1.627725 | C43: 1.627725 | D43: =SUMIFS(Transactions!L:L,Transactions!K:K,A43) -> 0 | E43: =SUMIFS(Transactions!F:F,Transactions!E:E,'Attribution Analysis'!A43) -> 0 | G43: ='Month on Month Equity Change'!$Q$11 -> 0.021063079 | I43: =IF((VLOOKUP(A43,Equity!$B$2:$O$73,14,0)="A"),(VLOOKUP(A43,Equity!$B$2:$N$73,9,0)-VLOOKUP(A43,Equity!$B$2:$N$73,10,0)),(VLOOKUP(A43,Equity!$B$2:$N$73,11,0)-VLOOKUP(A43,Equity!$B$2:$N$73,12,0))) -> 0.48270227 | J43: Added from Pvt
A44: IFB Inds. | B44: =VLOOKUP(A44,Equity!$B$2:$H$73,7,0) -> 2.0363229 | C44: 1.9718154 | D44: =SUMIFS(Transactions!L:L,Transactions!K:K,A44) -> 0 | E44: =SUMIFS(Transactions!F:F,Transactions!E:E,'Attribution Analysis'!A44) -> 0 | F44: =(B44+E44)/(C44+D44)-1 -> 0.032714766 | G44: ='Month on Month Equity Change'!$Q$11 -> 0.021063079 | H44: =F44-G44 -> 0.011651687 | I44: =IF((VLOOKUP(A44,Equity!$B$2:$O$73,14,0)="A"),(VLOOKUP(A44,Equity!$B$2:$N$73,9,0)-VLOOKUP(A44,Equity!$B$2:$N$73,10,0)),(VLOOKUP(A44,Equity!$B$2:$N$73,11,0)-VLOOKUP(A44,Equity!$B$2:$N$73,12,0))) -> -0.013144243
A45: Infinium Pharmachem Ltd. | B45: =VLOOKUP(A45,Equity!$B$2:$H$73,7,0) -> 0.15424 | C45: 0.15424 | D45: =SUMIFS(Transactions!L:L,Transactions!K:K,A45) -> 0 | E45: =SUMIFS(Transactions!F:F,Transactions!E:E,'Attribution Analysis'!A45) -> 0 | F45: =(B45+E45)/(C45+D45)-1 -> 0 | G45: ='Month on Month Equity Change'!$Q$11 -> 0.021063079 | H45: =F45-G45 -> -0.021063079 | I45: =IF((VLOOKUP(A45,Equity!$B$2:$O$73,14,0)="A"),(VLOOKUP(A45,Equity!$B$2:$N$73,9,0)-VLOOKUP(A45,Equity!$B$2:$N$73,10,0)),(VLOOKUP(A45,Equity!$B$2:$N$73,11,0)-VLOOKUP(A45,Equity!$B$2:$N$73,12,0))) -> 0.35475769
A46: Insolation Energy Ltd | B46: =VLOOKUP(A46,Equity!$B$2:$H$73,7,0) -> 3.5238812 | C46: 3.8241086 | D46: =SUMIFS(Transactions!L:L,Transactions!K:K,A46) -> 0 | E46: =SUMIFS(Transactions!F:F,Transactions!E:E,'Attribution Analysis'!A46) -> 0 | F46: =(B46+E46)/(C46+D46)-1 -> -0.07850912 | G46: ='Month on Month Equity Change'!$Q$11 -> 0.021063079 | H46: =F46-G46 -> -0.099572198 | I46: =IF((VLOOKUP(A46,Equity!$B$2:$O$73,14,0)="A"),(VLOOKUP(A46,Equity!$B$2:$N$73,9,0)-VLOOKUP(A46,Equity!$B$2:$N$73,10,0)),(VLOOKUP(A46,Equity!$B$2:$N$73,11,0)-VLOOKUP(A46,Equity!$B$2:$N$73,12,0))) -> 0.50688821
A47: Jaro Education | B47: =VLOOKUP(A47,Equity!$B$2:$H$73,7,0) -> 5.7957246 | C47: 6.5595974 | D47: =SUMIFS(Transactions!L:L,Transactions!K:K,A47) -> 0 | E47: =SUMIFS(Transactions!F:F,Transactions!E:E,'Attribution Analysis'!A47) -> 0 | F47: =(B47+E47)/(C47+D47)-1 -> -0.11645118 | G47: ='Month on Month Equity Change'!$Q$11 -> 0.021063079 | H47: =F47-G47 -> -0.13751426 | I47: =IF((VLOOKUP(A47,Equity!$B$2:$O$73,14,0)="A"),(VLOOKUP(A47,Equity!$B$2:$N$73,9,0)-VLOOKUP(A47,Equity!$B$2:$N$73,10,0)),(VLOOKUP(A47,Equity!$B$2:$N$73,11,0)-VLOOKUP(A47,Equity!$B$2:$N$73,12,0))) -> 0.27558095 | J47: Added from Pvt
A48: Kingfa Science & Technology Ltd. | B48: =VLOOKUP(A48,Equity!$B$2:$H$73,7,0) -> 10.05693 | C48: 10.626223 | D48: =SUMIFS(Transactions!L:L,Transactions!K:K,A48) -> 0 | E48: =SUMIFS(Transactions!F:F,Transactions!E:E,'Attribution Analysis'!A48) -> 0 | F48: =(B48+E48)/(C48+D48)-1 -> -0.053574375 | G48: ='Month on Month Equity Change'!$Q$11 -> 0.021063079 | H48: =F48-G48 -> -0.074637454 | I48: =IF((VLOOKUP(A48,Equity!$B$2:$O$73,14,0)="A"),(VLOOKUP(A48,Equity!$B$2:$N$73,9,0)-VLOOKUP(A48,Equity!$B$2:$N$73,10,0)),(VLOOKUP(A48,Equity!$B$2:$N$73,11,0)-VLOOKUP(A48,Equity!$B$2:$N$73,12,0))) -> -0.43689325
A49: Man Industries | B49: =VLOOKUP(A49,Equity!$B$2:$H$73,7,0) -> 33.899698 | C49: 29.200557 | D49: =SUMIFS(Transactions!L:L,Transactions!K:K,A49) -> 0 | E49: =SUMIFS(Transactions!F:F,Transactions!E:E,'Attribution Analysis'!A49) -> 0 | F49: =(B49+E49)/(C49+D49)-1 -> 0.16092643 | G49: ='Month on Month Equity Change'!$Q$11 -> 0.021063079 | H49: =F49-G49 -> 0.13986335 | I49: =IF((VLOOKUP(A49,Equity!$B$2:$O$73,14,0)="A"),(VLOOKUP(A49,Equity!$B$2:$N$73,9,0)-VLOOKUP(A49,Equity!$B$2:$N$73,10,0)),(VLOOKUP(A49,Equity!$B$2:$N$73,11,0)-VLOOKUP(A49,Equity!$B$2:$N$73,12,0))) -> -0.56494419
A50: Manorama Industries Ltd. | B50: =VLOOKUP(A50,Equity!$B$2:$H$73,7,0) -> 25.053337 | C50: 21.533285 | D50: =SUMIFS(Transactions!L:L,Transactions!K:K,A50) -> 0 | E50: =SUMIFS(Transactions!F:F,Transactions!E:E,'Attribution Analysis'!A50) -> 0 | F50: =(B50+E50)/(C50+D50)-1 -> 0.16347032 | G50: ='Month on Month Equity Change'!$Q$11 -> 0.021063079 | H50: =F50-G50 -> 0.14240724 | I50: =IF((VLOOKUP(A50,Equity!$B$2:$O$73,14,0)="A"),(VLOOKUP(A50,Equity!$B$2:$N$73,9,0)-VLOOKUP(A50,Equity!$B$2:$N$73,10,0)),(VLOOKUP(A50,Equity!$B$2:$N$73,11,0)-VLOOKUP(A50,Equity!$B$2:$N$73,12,0))) -> -0.61792651
A51: MPS | B51: =VLOOKUP(A51,Equity!$B$2:$H$73,7,0) -> 0.92313711 | C51: 0 | D51: =SUMIFS(Transactions!L:L,Transactions!K:K,A51) -> 0.88606171 | E51: =SUMIFS(Transactions!F:F,Transactions!E:E,'Attribution Analysis'!A51) -> 0 | G51: ='Month on Month Equity Change'!$Q$11 -> 0.021063079 | I51: =IF((VLOOKUP(A51,Equity!$B$2:$O$73,14,0)="A"),(VLOOKUP(A51,Equity!$B$2:$N$73,9,0)-VLOOKUP(A51,Equity!$B$2:$N$73,10,0)),(VLOOKUP(A51,Equity!$B$2:$N$73,11,0)-VLOOKUP(A51,Equity!$B$2:$N$73,12,0))) -> -2.2813227
A52: NLC INDIA | B52: =VLOOKUP(A52,Equity!$B$2:$H$73,7,0) -> 1.0312 | C52: 0 | D52: =SUMIFS(Transactions!L:L,Transactions!K:K,A52) -> 1.0034019 | E52: =SUMIFS(Transactions!F:F,Transactions!E:E,'Attribution Analysis'!A52) -> 0 | G52: ='Month on Month Equity Change'!$Q$11 -> 0.021063079
A53: Neuland Labs. | B53: =VLOOKUP(A53,Equity!$B$2:$H$73,7,0) -> 8.6164675 | C53: 7.8939037 | D53: =SUMIFS(Transactions!L:L,Transactions!K:K,A53) -> 0 | E53: =SUMIFS(Transactions!F:F,Transactions!E:E,'Attribution Analysis'!A53) -> 0 | F53: =(B53+E53)/(C53+D53)-1 -> 0.091534401 | G53: ='Month on Month Equity Change'!$Q$11 -> 0.021063079 | H53: =F53-G53 -> 0.070471322 | I53: =IF((VLOOKUP(A53,Equity!$B$2:$O$73,14,0)="A"),(VLOOKUP(A53,Equity!$B$2:$N$73,9,0)-VLOOKUP(A53,Equity!$B$2:$N$73,10,0)),(VLOOKUP(A53,Equity!$B$2:$N$73,11,0)-VLOOKUP(A53,Equity!$B$2:$N$73,12,0))) -> -0.4930743
A54: Nuvama Wealth Management Ltd | B54: =VLOOKUP(A54,Equity!$B$2:$H$73,7,0) -> 1.7165075 | C54: 1.47687 | D54: =SUMIFS(Transactions!L:L,Transactions!K:K,A54) -> 0 | E54: =SUMIFS(Transactions!F:F,Transactions!E:E,'Attribution Analysis'!A54) -> 0 | F54: =(B54+E54)/(C54+D54)-1 -> 0.16226039 | G54: ='Month on Month Equity Change'!$Q$11 -> 0.021063079 | H54: =F54-G54 -> 0.14119731 | I54: =IF((VLOOKUP(A54,Equity!$B$2:$O$73,14,0)="A"),(VLOOKUP(A54,Equity!$B$2:$N$73,9,0)-VLOOKUP(A54,Equity!$B$2:$N$73,10,0)),(VLOOKUP(A54,Equity!$B$2:$N$73,11,0)-VLOOKUP(A54,Equity!$B$2:$N$73,12,0))) -> -0.28008881
A55: Parth Electrical & Engineering | B55: =VLOOKUP(A55,Equity!$B$2:$H$73,7,0) -> 3.683075 | C55: 2.03314 | D55: =SUMIFS(Transactions!L:L,Transactions!K:K,A55) -> 0 | E55: =SUMIFS(Transactions!F:F,Transactions!E:E,'Attribution Analysis'!A55) -> 0 | F55: =(B55+E55)/(C55+D55)-1 -> 0.8115206 | G55: ='Month on Month Equity Change'!$Q$11 -> 0.021063079 | H55: =F55-G55 -> 0.79045752 | I55: =IF((VLOOKUP(A55,Equity!$B$2:$O$73,14,0)="A"),(VLOOKUP(A55,Equity!$B$2:$N$73,9,0)-VLOOKUP(A55,Equity!$B$2:$N$73,10,0)),(VLOOKUP(A55,Equity!$B$2:$N$73,11,0)-VLOOKUP(A55,Equity!$B$2:$N$73,12,0))) -> -1.7646813 | J55: Added from Pvt
A56: PG Electro. | B56: =VLOOKUP(A56,Equity!$B$2:$H$73,7,0) -> 10.03806 | C56: 10.03806 | D56: =SUMIFS(Transactions!L:L,Transactions!K:K,A56) -> 0 | E56: =SUMIFS(Transactions!F:F,Transactions!E:E,'Attribution Analysis'!A56) -> 0 | F56: =(B56+E56)/(C56+D56)-1 -> 0 | G56: ='Month on Month Equity Change'!$Q$11 -> 0.021063079 | H56: =F56-G56 -> -0.021063079 | I56: =IF((VLOOKUP(A56,Equity!$B$2:$O$73,14,0)="A"),(VLOOKUP(A56,Equity!$B$2:$N$73,9,0)-VLOOKUP(A56,Equity!$B$2:$N$73,10,0)),(VLOOKUP(A56,Equity!$B$2:$N$73,11,0)-VLOOKUP(A56,Equity!$B$2:$N$73,12,0))) -> 0.14383958
A57: Smart Works | B57: =VLOOKUP(A57,Equity!$B$2:$H$73,7,0) -> 14.025561 | C57: 12.524783 | D57: =SUMIFS(Transactions!L:L,Transactions!K:K,A57) -> 0 | E57: =SUMIFS(Transactions!F:F,Transactions!E:E,'Attribution Analysis'!A57) -> 0 | F57: =(B57+E57)/(C57+D57)-1 -> 0.1198247 | G57: ='Month on Month Equity Change'!$Q$11 -> 0.021063079 | H57: =F57-G57 -> 0.098761624 | I57: =IF((VLOOKUP(A57,Equity!$B$2:$O$73,14,0)="A"),(VLOOKUP(A57,Equity!$B$2:$N$73,9,0)-VLOOKUP(A57,Equity!$B$2:$N$73,10,0)),(VLOOKUP(A57,Equity!$B$2:$N$73,11,0)-VLOOKUP(A57,Equity!$B$2:$N$73,12,0))) -> -0.034821693 | J57: Added from Pvt
A58: Sterlite Grid 5 | B58: =VLOOKUP(A58,Equity!$B$2:$H$73,7,0) -> 0.036594 | C58: 0.036594 | D58: =SUMIFS(Transactions!L:L,Transactions!K:K,A58) -> 0 | E58: =SUMIFS(Transactions!F:F,Transactions!E:E,'Attribution Analysis'!A58) -> 0 | F58: =(B58+E58)/(C58+D58)-1 -> 0 | G58: ='Month on Month Equity Change'!$Q$11 -> 0.021063079 | H58: =F58-G58 -> -0.021063079 | I58: =IF((VLOOKUP(A58,Equity!$B$2:$O$73,14,0)="A"),(VLOOKUP(A58,Equity!$B$2:$N$73,9,0)-VLOOKUP(A58,Equity!$B$2:$N$73,10,0)),(VLOOKUP(A58,Equity!$B$2:$N$73,11,0)-VLOOKUP(A58,Equity!$B$2:$N$73,12,0))) -> 0
A59: Sterlite Power Transmission | B59: =VLOOKUP(A59,Equity!$B$2:$H$73,7,0) -> 0.05586 | C59: 0.05586 | D59: =SUMIFS(Transactions!L:L,Transactions!K:K,A59) -> 0 | E59: =SUMIFS(Transactions!F:F,Transactions!E:E,'Attribution Analysis'!A59) -> 0 | F59: =(B59+E59)/(C59+D59)-1 -> 0 | G59: ='Month on Month Equity Change'!$Q$11 -> 0.021063079 | H59: =F59-G59 -> -0.021063079 | I59: =IF((VLOOKUP(A59,Equity!$B$2:$O$73,14,0)="A"),(VLOOKUP(A59,Equity!$B$2:$N$73,9,0)-VLOOKUP(A59,Equity!$B$2:$N$73,10,0)),(VLOOKUP(A59,Equity!$B$2:$N$73,11,0)-VLOOKUP(A59,Equity!$B$2:$N$73,12,0))) -> 0
A60: Sterlite Tech | B60: =VLOOKUP(A60,Equity!$B$2:$H$73,7,0) -> 0.11361775 | C60: 0.099234 | D60: =SUMIFS(Transactions!L:L,Transactions!K:K,A60) -> 0 | E60: =SUMIFS(Transactions!F:F,Transactions!E:E,'Attribution Analysis'!A60) -> 0 | F60: =(B60+E60)/(C60+D60)-1 -> 0.1449478 | G60: ='Month on Month Equity Change'!$Q$11 -> 0.021063079 | H60: =F60-G60 -> 0.12388472 | I60: =IF((VLOOKUP(A60,Equity!$B$2:$O$73,14,0)="A"),(VLOOKUP(A60,Equity!$B$2:$N$73,9,0)-VLOOKUP(A60,Equity!$B$2:$N$73,10,0)),(VLOOKUP(A60,Equity!$B$2:$N$73,11,0)-VLOOKUP(A60,Equity!$B$2:$N$73,12,0))) -> 0
A61: STLNETWORK | B61: =VLOOKUP(A61,Equity!$B$2:$H$73,7,0) -> 0.0042476 | C61: 0.0042476 | D61: =SUMIFS(Transactions!L:L,Transactions!K:K,A61) -> 0 | E61: =SUMIFS(Transactions!F:F,Transactions!E:E,'Attribution Analysis'!A61) -> 0 | F61: =(B61+E61)/(C61+D61)-1 -> 0 | G61: ='Month on Month Equity Change'!$Q$11 -> 0.021063079 | H61: =F61-G61 -> -0.021063079 | I61: =IF((VLOOKUP(A61,Equity!$B$2:$O$73,14,0)="A"),(VLOOKUP(A61,Equity!$B$2:$N$73,9,0)-VLOOKUP(A61,Equity!$B$2:$N$73,10,0)),(VLOOKUP(A61,Equity!$B$2:$N$73,11,0)-VLOOKUP(A61,Equity!$B$2:$N$73,12,0))) -> 0
A62: Tatva Chintan Pharma Chem Limi | B62: =VLOOKUP(A62,Equity!$B$2:$H$73,7,0) -> 2.5301246 | C62: 2.4006842 | D62: =SUMIFS(Transactions!L:L,Transactions!K:K,A62) -> 0 | E62: =SUMIFS(Transactions!F:F,Transactions!E:E,'Attribution Analysis'!A62) -> 0 | F62: =(B62+E62)/(C62+D62)-1 -> 0.053918108 | G62: ='Month on Month Equity Change'!$Q$11 -> 0.021063079 | H62: =F62-G62 -> 0.032855029 | I62: =IF((VLOOKUP(A62,Equity!$B$2:$O$73,14,0)="A"),(VLOOKUP(A62,Equity!$B$2:$N$73,9,0)-VLOOKUP(A62,Equity!$B$2:$N$73,10,0)),(VLOOKUP(A62,Equity!$B$2:$N$73,11,0)-VLOOKUP(A62,Equity!$B$2:$N$73,12,0))) -> 0.066167369
A63: Tech Mahindra Ltd. | B63: =VLOOKUP(A63,Equity!$B$2:$H$73,7,0) -> 3.05631 | C63: 3.22596 | D63: =SUMIFS(Transactions!L:L,Transactions!K:K,A63) -> 0 | E63: =SUMIFS(Transactions!F:F,Transactions!E:E,'Attribution Analysis'!A63) -> 0 | F63: =(B63+E63)/(C63+D63)-1 -> -0.052588997 | G63: ='Month on Month Equity Change'!$Q$11 -> 0.021063079 | H63: =F63-G63 -> -0.073652075 | I63: =IF((VLOOKUP(A63,Equity!$B$2:$O$73,14,0)="A"),(VLOOKUP(A63,Equity!$B$2:$N$73,9,0)-VLOOKUP(A63,Equity!$B$2:$N$73,10,0)),(VLOOKUP(A63,Equity!$B$2:$N$73,11,0)-VLOOKUP(A63,Equity!$B$2:$N$73,12,0))) -> 0.53055898
A64: Vedanta | B64: =VLOOKUP(A64,Equity!$B$2:$H$73,7,0) -> 8.19936 | C64: 10.29738 | D64: =SUMIFS(Transactions!L:L,Transactions!K:K,A64) -> 0 | E64: =SUMIFS(Transactions!F:F,Transactions!E:E,'Attribution Analysis'!A64) -> 0 | F64: =(B64+E64)/(C64+D64)-1 -> -0.20374309 | G64: ='Month on Month Equity Change'!$Q$11 -> 0.021063079 | H64: =F64-G64 -> -0.22480617 | I64: =IF((VLOOKUP(A64,Equity!$B$2:$O$73,14,0)="A"),(VLOOKUP(A64,Equity!$B$2:$N$73,9,0)-VLOOKUP(A64,Equity!$B$2:$N$73,10,0)),(VLOOKUP(A64,Equity!$B$2:$N$73,11,0)-VLOOKUP(A64,Equity!$B$2:$N$73,12,0))) -> -0.20536962
A65: Vedanta Oil & Gas Ltd | B65: =VLOOKUP(A65,Equity!$B$2:$H$73,7,0) -> 0.7429 | C65: 2.7958495 | D65: =SUMIFS(Transactions!L:L,Transactions!K:K,A65) -> 0 | E65: =SUMIFS(Transactions!F:F,Transactions!E:E,'Attribution Analysis'!A65) -> 0 | G65: ='Month on Month Equity Change'!$Q$11 -> 0.021063079 | I65: =IF((VLOOKUP(A65,Equity!$B$2:$O$73,14,0)="A"),(VLOOKUP(A65,Equity!$B$2:$N$73,9,0)-VLOOKUP(A65,Equity!$B$2:$N$73,10,0)),(VLOOKUP(A65,Equity!$B$2:$N$73,11,0)-VLOOKUP(A65,Equity!$B$2:$N$73,12,0))) -> 0.074920279
A66: Vedanta Power Ltd | B66: =VLOOKUP(A66,Equity!$B$2:$H$73,7,0) -> 0.9269 | C66: 1.5938776 | D66: =SUMIFS(Transactions!L:L,Transactions!K:K,A66) -> 0 | E66: =SUMIFS(Transactions!F:F,Transactions!E:E,'Attribution Analysis'!A66) -> 0 | G66: ='Month on Month Equity Change'!$Q$11 -> 0.021063079 | I66: =IF((VLOOKUP(A66,Equity!$B$2:$O$73,14,0)="A"),(VLOOKUP(A66,Equity!$B$2:$N$73,9,0)-VLOOKUP(A66,Equity!$B$2:$N$73,10,0)),(VLOOKUP(A66,Equity!$B$2:$N$73,11,0)-VLOOKUP(A66,Equity!$B$2:$N$73,12,0))) -> 0.05602371
A67: Vedanta Aluminium Metal Ltd | B67: =VLOOKUP(A67,Equity!$B$2:$H$73,7,0) -> 10.3592 | C67: 0.93182543 | D67: =SUMIFS(Transactions!L:L,Transactions!K:K,A67) -> 0 | E67: =SUMIFS(Transactions!F:F,Transactions!E:E,'Attribution Analysis'!A67) -> 0 | G67: ='Month on Month Equity Change'!$Q$11 -> 0.021063079 | I67: =IF((VLOOKUP(A67,Equity!$B$2:$O$73,14,0)="A"),(VLOOKUP(A67,Equity!$B$2:$N$73,9,0)-VLOOKUP(A67,Equity!$B$2:$N$73,10,0)),(VLOOKUP(A67,Equity!$B$2:$N$73,11,0)-VLOOKUP(A67,Equity!$B$2:$N$73,12,0))) -> 0.05602371
A68: Vedanta Iron & Steel Ltd | B68: =VLOOKUP(A68,Equity!$B$2:$H$73,7,0) -> 0.81075 | C68: 0.88490834 | D68: =SUMIFS(Transactions!L:L,Transactions!K:K,A68) -> 0 | E68: =SUMIFS(Transactions!F:F,Transactions!E:E,'Attribution Analysis'!A68) -> 0 | G68: ='Month on Month Equity Change'!$Q$11 -> 0.021063079 | I68: =IF((VLOOKUP(A68,Equity!$B$2:$O$73,14,0)="A"),(VLOOKUP(A68,Equity!$B$2:$N$73,9,0)-VLOOKUP(A68,Equity!$B$2:$N$73,10,0)),(VLOOKUP(A68,Equity!$B$2:$N$73,11,0)-VLOOKUP(A68,Equity!$B$2:$N$73,12,0))) -> 0.05602371
A69: Yash High Voltage Ltd. | B69: =VLOOKUP(A69,Equity!$B$2:$H$73,7,0) -> 10.207312 | C69: 10.011495 | D69: =SUMIFS(Transactions!L:L,Transactions!K:K,A69) -> 0 | E69: =SUMIFS(Transactions!F:F,Transactions!E:E,'Attribution Analysis'!A69) -> 3.000036 | F69: =(B69+E69)/(C69+D69)-1 -> 0.31921837 | G69: ='Month on Month Equity Change'!$Q$11 -> 0.021063079 | H69: =F69-G69 -> 0.29815529 | I69: =IF((VLOOKUP(A69,Equity!$B$2:$O$73,14,0)="A"),(VLOOKUP(A69,Equity!$B$2:$N$73,9,0)-VLOOKUP(A69,Equity!$B$2:$N$73,10,0)),(VLOOKUP(A69,Equity!$B$2:$N$73,11,0)-VLOOKUP(A69,Equity!$B$2:$N$73,12,0))) -> -1.2066479
A70: Zaggle Prepaid Ocean Services Ltd. | B70: =VLOOKUP(A70,Equity!$B$2:$H$73,7,0) -> 1.28371 | C70: 1.30386 | D70: =SUMIFS(Transactions!L:L,Transactions!K:K,A70) -> 0 | E70: =SUMIFS(Transactions!F:F,Transactions!E:E,'Attribution Analysis'!A70) -> 0 | F70: =(B70+E70)/(C70+D70)-1 -> -0.015454113 | G70: ='Month on Month Equity Change'!$Q$11 -> 0.021063079 | H70: =F70-G70 -> -0.036517192 | I70: =IF((VLOOKUP(A70,Equity!$B$2:$O$73,14,0)="A"),(VLOOKUP(A70,Equity!$B$2:$N$73,9,0)-VLOOKUP(A70,Equity!$B$2:$N$73,10,0)),(VLOOKUP(A70,Equity!$B$2:$N$73,11,0)-VLOOKUP(A70,Equity!$B$2:$N$73,12,0))) -> 0.35647043
A71: *Equity Savings & Multi Asset excluded.

Sheet Sheet1
E7: =13*42.5% -> 5.525
E8: =13-E7 -> 7.475

Sheet Cash
B1: from Live consol
B2: Product | C2: Investment Date Range | D2: Quantity | E2: Investment at Cost | F2: Market Value | G2: Benchmark | H2: Allocation (%) | I2: Scheme Absolute (%) | J2: Index Absolute (%) | K2: Scheme XIRR (%) | L2: Index XIRR (%)
A3: Liquid | B3: Liquid | C3: 434002 | E3: =SUM(E4:E12) -> 5.1332383 | F3: =SUM(F4:F12) -> 5.4365436 | H3: =SUM(H4:H12) -> 1 | I3: 0 | J3: 0.021945572 | K3: 0.040795717 | L3: 0.052750632
B4: Aditya Birla SL Liquid Fund-(DD)-Direct | C4: Jul-19 - Sep-25 | D4: 7609.72 | E4: 0 | F4: 0.07624559 | G4: CRISIL Liquid Fund Index | H4: =F4/$F$13 -> 0.014024644 | I4: 0 | J4: 0.041839495 | K4: 0.0075873286 | L4: 0.057610968
B5: Aditya Birla SL Liquid Fund-Direct (G) | C5: Jul-19 - Jul-19 | D5: 1752.565 | E5: 0.053714628 | F5: 0.079441248 | G5: CRISIL Liquid Fund Index | H5: =F5/$F$13 -> 0.014612455 | I5: 0 | J5: 0.41685334 | K5: 0.057565376 | L5: 0.057437971
B6: HDFC Liquid Fund -Direct(G) | C6: Mar-20 - Mar-20 | D6: 2282.178 | E6: 1.2499376 | F6: 1.2571074 | G6: CRISIL Liquid Fund Index | H6: =F6/$F$13 -> 0.23123283 | I6: 0 | J6: 0.0057361117 | K6: 0.087093863 | L6: 0.068809101
B7: HDFC Overnight Fund - Direct - G | C7: Mar-20 - Mar-20 | D7: 48.183 | E7: 0.014284307 | F7: 0.019483298 | G7: CRISIL Liquid Fund Index | H7: =F7/$F$13 -> 0.0035837657 | I7: 0 | J7: 0.015542141 | K7: 0.030159518 | L7: 0.046286681
B8: HSBC Liquid Fund-Direct(DD) | C8: Mar-20 - Mar-20 | D8: 605.838 | E8: 0.054356288 | F8: 0.06067928 | G8: CRISIL Liquid Fund Index | H8: =F8/$F$13 -> 0.011161371 | I8: 0 | J8: 0.11632494 | K8: 0.015894654 | L8: 0.057519111
B9: ICICI Pru Liquid Fund-Direct(G) | C9: Jul-25 - Apr-26 | D9: 69235.278 | E9: 2.744886 | F9: 2.8740049 | G9: CRISIL Liquid Fund Index | H9: =F9/$F$13 -> 0.5286456 | I9: 0 | J9: 0.020728396 | K9: 0.063692632 | L9: 0.059854713
B10: Kotak Liquid-Direct (DD) | C10: Jul-19 - Jul-19 | D10: 632.5 | E10: 0.055192263 | F10: 0.077342732 | G10: CRISIL Liquid Fund Index | H10: =F10/$F$13 -> 0.014226453 | I10: 0 | J10: 0.40133287 | K10: 0.049542978 | L10: 0.057519111
B11: Mirae Asset Cash Management Fund-Direct(G) | C11: Jul-19 - Jul-19 | D11: 316.19 | E11: 0.063572507 | F11: 0.093638682 | G11: CRISIL Liquid Fund Index | H11: =F11/$F$13 -> 0.017223937 | I11: 0 | J11: 0.47294305 | K11: 0.057088867 | L11: 0.057512018
B12: Nippon India ETF Nifty 1D Rate Liquid Bees-IDCW | C12: Apr-26 - Apr-26 | D12: 8986.005 | E12: 0.8972947 | F12: 0.8986005 | G12: CRISIL Liquid Fund Index | H12: =F12/$F$13 -> 0.16528894 | I12: 0 | J12: 0.006476217 | K12: 0 | L12: 0
B13: Total | C13: 522816 | E13: =E3 -> 5.1332383 | F13: =F3 -> 5.4365436 | H13: =H3 -> 1 | I13: 0 | J13: 0.021945572 | K13: 0.040795717 | L13: 0.052750632

Sheet Debt
B1: from Live consol
A2: Refer Note | B2: Product | C2: Investment Date Range | D2: Quantity | E2: Investment at Cost | F2: Market Value | G2: Dividend / Interest | H2: Benchmark | I2: Allocation (%) | J2: Commitment Amount | K2: Scheme Absolute (%) | L2: Index Absolute (%) | M2: Scheme XIRR (%) | N2: Index XIRR (%)
B3: Arbitrage | C3: 219849 | E3: =SUM(E4:E7) -> 39.753986 | F3: =SUM(F4:F7) -> 41.077278 | G3: =SUM(G4:G5) -> 0 | I3: =SUM(I4:I7) -> 0.89514114 | K3: 0.035409577 | L3: 0.036478848 | M3: 0.07125822 | N3: 0.073410103
A4: Liquid | B4: Invesco India Arbitrage Fund-Direct(G) | C4: Jul-25 - Jul-25 | D4: 1092471 | E4: 3.7698115 | F4: 4.0189932 | G4: 0 | H4: Nifty 50 Arbitrage | I4: =F4/$F$12 -> 0.087580442 | K4: 0.066099249 | L4: 0.070181568 | M4: 0.066286728 | N4: 0.070381007
A5: Liquid | B5: Kotak Equity Arbitrage Scheme(G) | C5: May-25 - May-25 | D5: 642940.09 | E5: 2.3963149 | F5: 2.5510449 | G5: 0 | H5: Nifty 50 Arbitrage | I5: =F5/$F$12 -> 0.055591443 | K5: 0.064569963 | L5: 0.076142071 | M5: 0.059368208 | N5: 0.069977799
A6: Liquid | B6: Invesco India Arbitrage Fund(G) | C6: Nov-25 - Nov-25 | D6: 799864.75 | E6: 2.6026159 | F6: 2.7030789 | G6: 0 | H6: Nifty 50 Arbitrage | I6: =F6/$F$12 -> 0.058904515 | K6: 0.038600783 | L6: 0.044972222 | M6: 0.059804758 | N6: 0.069791874
A7: Liquid | B7: Motilal Oswal Arbitrage Fund Direct (G) | C7: May-25 - May-26 | D7: 28614760 | E7: 30.985244 | F7: 31.804161 | G7: 0 | H7: Nifty 50 Arbitrage | I7: =F7/$F$12 -> 0.69306474 | K7: 0.033220446 | L7: 0.033721467 | M7: 0.072971854 | N7: 0.074066815
B8: High Yield Fund | C8: 44095 | E8: =E9 -> 3.5 | F8: =F9 -> 3.768427 | G8: =G9 -> 0.3592938 | I8: =I9 -> 0.082120193 | K8: 0.21981394 | L8: 0.10395107 | M8: 0.14966583 | N8: 0.069996265
A9: SG | B9: Neo Infra Income Opportunities Fund Share Class A5 | C9: Oct-23 - Feb-26 | E9: 3.5 | F9: 3.768427 | G9: 0.3592938 | H9: CRISIL Short Term | I9: =F9/$F$12 -> 0.082120193 | J9: =50000000/10^5 -> 500 | K9: 0.21981394 | L9: 0.10395107 | M9: 0.14966583 | N9: 0.069996265
B10: PP Structures | C10: 44095 | E10: =E11 -> 0.70001498 | F10: =F11 -> 1.0434584 | G10: =G11 -> 0 | I10: =I11 -> 0.022738668 | K10: 0.49062302 | L10: 0.24620557 | M10: 0.12367324 | N10: 0.067806676
A11: TT | B11: 15% K M Global - Credit Private Limited | C11: Sept 20 - March 24 | E11: 0.70001498 | F11: 1.0434584 | G11: 0 | H11: CRISIL Short Term | I11: =F11/$F$12 -> 0.022738668 | K11: 0.49062302 | L11: 0.24620557 | M11: 0.12367324 | N11: 0.067806676
B12: Total | C12: 263944 | E12: =E10+E8+E3 -> 43.954001 | F12: =F10+F8+F3 -> 45.889164 | G12: =G10+G8+G3 -> 0.3592938 | I12: =I10+I8+I3 -> 1 | K12: 0.044904795 | L12: 0.040250698 | M12: 0.081715778 | N12: 0.072796813
C13: *Note: Neo Infra Income Opportunities fund , valuation as on 31st March'26 return are Net of Expense and tax
B16: Debt Investment Plan | C16: Recommendation
B17: Neo Special Credit Opportunities Fund | C17: Add 20 Cr
B18: Venture Soul Capital Fund | C18: Add 10 Cr

Sheet Alternate
B1: from Live consol
B2: Product | C2: Investment Date Range | D2: Investment at Cost | E2: Market Value | F2: Dividend / Interest | G2: Benchmark | H2: Allocation (%) | I2: Scheme Absolute (%) | J2: Index Absolute (%) | K2: Scheme XIRR (%) | L2: Index XIRR (%)
B3: Gold | C3: 43997 | D3: =D4 -> 0 | E3: =E4 -> 0 | F3: =F4 -> 0 | H3: =H4 -> 0 | I3: =I4 -> 0 | J3: =J4 -> 0 | K3: =K4 -> 0 | L3: =L4 -> 0
B4: Kotak Gold Fund Growth | C4: #N/A | D4: 0 | E4: 0 | F4: 0 | H4: =E4/$E$18 -> 0 | I4: 0 | J4: 0 | K4: 0 | L4: 0
B5: Private Equity | C5: 43984 | D5: =D6 -> 136.1593 | E5: =E6 -> 136.1593 | F5: =F6 -> 0 | H5: =H6 -> 0.60859995
A6: EG | B6: Private Equity | C6: 43983 | D6: 136.1593 | E6: =D6 -> 136.1593 | F6: 0 | H6: =E6/$E$18 -> 0.60859995
A7: EG | B7: PE Funds | C7: 43984 | D7: =SUM(D8:D13) -> 22.224236 | E7: =SUM(E8:E13) -> 32.713327 | F7: =SUM(F8:F11) -> 0.4347699 | H7: =SUM(H8:H11) -> 0.1137345 | I7: 0 | J7: 0.14384676 | K7: ='Portfolio Allocation'!S25 -> 0.13349357 | L7: ='Portfolio Allocation'!T25 -> 0.030562511
B8: India SME | C8: Sep-24 - Mar-26 | D8: 13.5 | E8: 15.93 | F8: 0.040588 | G8: Nifty 500 TRI | H8: =E8/$E$18 -> 0.071203341 | I8: 0.18300652 | J8: -0.096401407 | K8: 0.22696287 | L8: -0.12429736
B9: Baring PE India Fund 6 | C9: Oct 24- Sep 25 | D9: 2.025 | E9: 1.8842209 | F9: 0.0142867 | G9: Nifty 500 TRI | H9: =E9/$E$18 -> 0.0084220226 | I9: 0 | J9: 0 | K9: 0 | L9: 0
B10: 360 One Special Opportunities Fund - Series 8 - Class A3 (AIF Category II) | C10: Apr-21 - Apr-21 | D10: 1.984236 | E10: 2.9160826 | F10: 0.3798952 | G10: Nifty 500 TRI | H10: =E10/$E$18 -> 0.013034201 | I10: 0.65590367 | J10: 0.99829501 | K10: 0.10584796 | L10: 0.14302306
B11: Sky Capital Titan Rising Funds 1 | C11: May-25 - Feb-26 | D11: 4.715 | E11: 4.715 | F11: 0 | G11: Alternate Index | H11: =E11/$E$18 -> 0.021074937 | I11: 0 | J11: 0 | K11: 0 | L11: 0
B12: Assetgro Fintech Private Limited | C12: Nov-25 - Nov-25 | D12: 0 | E12: 5.0032848 | F12: 0 | G12: Alternate Index | H12: =E12/$E$18 -> 0.022363502 | I12: 0 | J12: 0.048322712
B13: Transition Venture Capital fund I | C13: Aug-25 - Oct-25 | D13: 0 | E13: 2.2647385 | F13: 0 | G13: Alternate Index | H13: =E13/$E$18 -> 0.010122847 | I13: 0.29413629 | J13: 0.030877525
B14: Silver | D14: =D15 -> 4.2561917 | E14: =E15 -> 6.5449619 | F14: =F15 -> 0 | H14: =H15 -> 0.029254435 | I14: 0.74830014 | J14: 0.82390612
A15: TT | B15: DSP Silver ETF | C15: Sep-25 - Sep-25 | D15: 4.2561917 | E15: 6.5449619 | F15: 0 | G15: MCX Silver | H15: =E15/$E$18 -> 0.029254435 | I15: 0.74830014 | J15: 0.82390612
B16: Gold | D16: =D17 -> 53.585434 | E16: =E17 -> 48.307867 | F16: =F17 -> 0 | H16: =H17 -> 0.21592476 | I16: 0 | J16: 0
A17: TT | B17: DSP Gold ETF | C17: Jan-26 - Jan-26 | D17: 53.585434 | E17: 48.307867 | F17: 0 | G17: MCX GOLD SPOT | H17: =E17/$E$18 -> 0.21592476 | I17: -0.098488836 | J17: -0.091201257
B18: Total | C18: 132206 | D18: =D3+D5+D7+D14+D16 -> 216.22516 | E18: =E3+E5+E7+E14+E16 -> 223.72546 | F18: =F3+F5+F7+F14+F16 -> 0.4347699 | H18: =H3+H5+H7+H14+H16 -> 0.96751365 | I18: 0.055646167 | J18: 0.03088796 | K18: 0.091461167 | L18: 0.050356653
B19: *Note: Baring PE fund valuation as on 31st March'26
B20: India SME valuation at 1.18x MOIC as on 31st March'26
B21: 360 One Special Opportunities Fund - Series 8 - Class A3 (AIF Category II) - valuation as on 31st May'26
B22: Assetgro Fintech Private ltd shown at cost, hence performance not shown
B23: Sky Capital Titan Rising Funds 1 - Valuation as on 31st Dec (Nav basis)& 31st March 2026 for new investments added in Feb'26 - (shown at face value)
B24: Transition Venture Capital fund I valuation as on 28th Feb'26

Sheet Private Investments 
B2: Product | C2: Date Investment Range | D2: Investment at Cost | E2: Market Value | F2: Allocation (%) | G2: Remarks
B3: Private Equity | C3: x | D3: 136.1593 | E3: 136.1593
B4: Everest Fleet Private Ltd - SIDDHARTH LADSARIYA | C4: Jan 22 - May 23 | D4: 4.7607824 | E4: 4.7607824 | F4: =E4/$E$91 -> 0.034964797 | H4: =D3-D91 -> 0
B5: URB Ventures Pvt Ltd - ANUJ MUNOT | C5: Jun 22 - Feb 23 | D5: 2.25 | E5: 2.25 | F5: =E5/$E$91 -> 0.016524761
B6: Waterwala Labs Private Limited - Drink Prime | C6: Feb 20 - Jul 23 | D6: 8.1001152 | E6: 8.1001152 | F6: =E6/$E$91 -> 0.059489987
B7: Integris | C7: 45631 | D7: 15.999746 | E7: 15.999746 | F7: =E7/$E$91 -> 0.11750755
B8: MOTHER INDIA FORMING PRIVATE LIMITED | C8: 45681 | D8: 7.999996 | E8: 7.999996 | F8: =E8/$E$91 -> 0.058754678
B9: SKS Fastener | C9: 45741 | D9: 2.99584 | E9: 2.99584 | F9: =E9/$E$91 -> 0.022002463
B10: Transigo Fleet LLP | C10: May 21 - Jan 23 | D10: 5.7557 | E10: 5.7557 | F10: =E10/$E$91 -> 0.042271809
B11: FH Enable LLP - Aakash Sachdev | C11: Jul 20 - Oct 20 | D11: 0.5 | E11: 0.5 | F11: =E11/$E$91 -> 0.0036721692
B12: PROCYON ENTERPRISE LLP - ABHISHEK MURARKA | C12: May 23 - Aug 23 | D12: 4.0128 | E12: 4.0128 | F12: =E12/$E$91 -> 0.029471361
B13: Spray Engineering Devices Ltd. | C13: 45420 | D13: 4.7517442 | E13: 4.7517442 | F13: =E13/$E$91 -> 0.034898418
B14: Matrix Gas And Renewables Limited | C14: 45352 | D14: 4.5 | E14: 4.5 | F14: =E14/$E$91 -> 0.033049523
B15: Telawne Power | C15: 45650 | D15: 4 | E15: 4 | F15: =E15/$E$91 -> 0.029377354
B16: ESDS | C16: 45544 | D16: 5.0000024 | E16: 5.0000024 | F16: =E16/$E$91 -> 0.03672171
B17: Innoviti Payment Solutions Private Ltd - PRANAV KORANNE | C17: 44554 | D17: 1.9999974 | E17: 1.9999974 | F17: =E17/$E$91 -> 0.014688658
B18: Oil Max | C18: 45700 | D18: 3.876 | E18: 3.876 | F18: =E18/$E$91 -> 0.028466656
B19: Borosil Renewables | C19: 45700 | D19: 3.7499885 | E19: 3.7499885 | F19: =E19/$E$91 -> 0.027541185
B20: BIG BANG BOOM | C20: 45544 | D20: 4.032 | E20: 4.032 | F20: =E20/$E$91 -> 0.029612373
B21: RAY's | C21: 45462 | D21: 2.006 | E21: 2.006 | F21: =E21/$E$91 -> 0.014732743
B22: Pivot Ventures - ISHA KEDIA | C22: Dec 21 - Aug 22 | D22: 1.6 | E22: 1.6 | F22: =E22/$E$91 -> 0.011750941
B23: Stay Vista Private Limited - ARTHA ENERGY PROJECTS PVT LTD | C23: 44236 | D23: 0.4773404 | E23: 0.4773404 | F23: =E23/$E$91 -> 0.0035057494
B24: M/S Grand Continent Hotels | C24: Feb 24 - Mar 24 | D24: 0 | E24: 0 | F24: =E24/$E$91 -> 0
B25: Incred Holdings Ltd. | C25: 45260 | D25: 1.5029264 | E25: 1.5029264 | F25: =E25/$E$91 -> 0.011038
B26: Autocracy Machinery Pvt Ltd. | C26: Oct 23 - Mar 24 | D26: 1.5000018 | E26: 1.5000018 | F26: =E26/$E$91 -> 0.011016521
B27: The OAKS Consumer Fund I - SANTOSH PARAB | C27: Sep 21 - Mar 23 | D27: 1.3 | E27: 1.3 | F27: =E27/$E$91 -> 0.00954764
B28: SOTEFIN | C28: 45485 | D28: 2.00004 | E28: 2.00004 | F28: =E28/$E$91 -> 0.014688971
B29: WE VOISE | C29: 45544 | D29: 1.0106085 | E29: 1.0106085 | F29: =E29/$E$91 -> 0.0074222508
B30: Zenith | C30: 45491 | D30: 1.0001255 | E30: 1.0001255 | F30: =E30/$E$91 -> 0.0073452601
B31: Radiant | C31: 45491 | D31: 0.9996 | E31: 0.9996 | F31: =E31/$E$91 -> 0.0073414007
B32: Vineet Sethia - Drink Prime | C32: 45085 | D32: 0.790803 | E32: 0.790803 | F32: =E32/$E$91 -> 0.0058079249
B33: Third Eye Distillery Holdings Pvt Ltd (SKYVENTURES - LV ANGEL FUND - AAKASH SACHDEV) | C33: 44690 | D33: 0.25 | E33: 0.25 | F33: =E33/$E$91 -> 0.0018360846
B34: HYPRKYTCHEN Foodtech Private Limited - Mr. Bansi | C34: Dec 20 - Dec 21 | D34: 2.5608348 | E34: 2.5608348 | F34: =E34/$E$91 -> 0.018807637
B35: Inflexor Technologies - (RAJESHWARI - AVENDUS) | C35: Nov 20 - Nov 22 | D35: 0.795 | E35: 0.795 | F35: =E35/$E$91 -> 0.005838749
B36: SWAPECO SOLUTIONS PRIVATE LIMITED - (SCRAP UNCLE - MUKUL CHABRA) | C36: 45160 | D36: 0.50203 | E36: 0.50203 | F36: =E36/$E$91 -> 0.0036870782
B37: A K Enterprises - Polycab | C37: 43891 | D37: 0.5 | E37: 0.5 | F37: =E37/$E$91 -> 0.0036721692
B38: Sky Enable Tech Llp | C38: 45337 | D38: 0.8 | E38: 0.8 | F38: =E38/$E$91 -> 0.0058754707
B39: Since 99 Apparel Pvt Limited - PUNIT SEHGAL / DEXTER CAPITAL | C39: 45006 | D39: 0.4999071 | E39: 0.4999071 | F39: =E39/$E$91 -> 0.0036714869
B40: EMA Preferred Shares | C40: 45534 | D40: 0.4642872 | E40: 0.4642872 | F40: =E40/$E$91 -> 0.0034098823
B41: Stay Vista Private Limited - Anandkumar Radhakrishna Ladsariya | C41: 44963 | D41: 0.4212804 | E41: 0.4212804 | F41: =E41/$E$91 -> 0.0030940258
B42: Ajay Jain - Drink Prime | C42: 45085 | D42: 0.4098207 | E42: 0.4098207 | F42: =E42/$E$91 -> 0.0030098619
B43: Hanok Reuben Medhari - Drink Prime | C43: 43922 | D43: 0.2500024 | E43: 0.2500024 | F43: =E43/$E$91 -> 0.0018361022
B44: Head Infotech | C44: 44602 | D44: 2.25 | E44: 2.25 | F44: =E44/$E$91 -> 0.016524761
B45: Nopo Nanotechnologies India Pvt Ltd - Gadhadar Reddy | C45: 45295 | D45: 0.25 | E45: 0.25 | F45: =E45/$E$91 -> 0.0018360846
B46: Credit Fair-K M Global Credit Private Limited | C46: Sep 20 - Jun 21 | D46: 0.2000046 | E46: 0.2000046 | F46: =E46/$E$91 -> 0.0014689015
B47: FH Edutech LLP | C47: 44375 | D47: 0.2 | E47: 0.2 | F47: =E47/$E$91 -> 0.0014688677
B48: Home Pecked E-Marketplace Services Ltd | C48: 44531 | D48: 0.1540769 | E48: 0.1540769 | F48: =E48/$E$91 -> 0.0011315929
B49: AL Trust - Collabmates Pvt Ltd - (ANGELLIST - LIKEMINDS) | C49: 44971 | D49: 0.153 | E49: 0.153 | F49: =E49/$E$91 -> 0.0011236838
B50: Aksum Trademart Pvt Ltd - ANKIT JAIN | C50: 45061 | D50: 0.150015 | E50: 0.150015 | F50: =E50/$E$91 -> 0.0011017609
B51: AL Trust - Karban Envirotech (RUV) - Nilesh Angelist | C51: 45272 | D51: 0.102 | E51: 0.102 | F51: =E51/$E$91 -> 0.00074912252
B52: Zippmat Private Ltd - ABHIJEET KUDVA | C52: 44602 | D52: 0.1015 | E52: 0.1015 | F52: =E52/$E$91 -> 0.00074545035
B53: LV Angel Fund - Lets Venture (HOOPR) - VAIBHAV KARNAVAT | C53: 44610 | D53: 0.101 | E53: 0.101 | F53: =E53/$E$91 -> 0.00074177818
B54: Rurash Financials Private Ltd - Reliance Retail | C54: 44061 | D54: 0.100122 | E54: 0.100122 | F54: =E54/$E$91 -> 0.00073532985
B55: Variance PT Ventures LLP - Romil Kapadia | C55: 44610 | D55: 0.1 | E55: 0.1 | F55: =E55/$E$91 -> 0.00073443384
B56: LANDCRAFT RETAIL PVT LTD. - FOOD SQUARE | C56: 45524 | D56: 3.0015 | E56: 3.0015 | F56: =E56/$E$91 -> 0.022044032
B57: Sky Vision Cure LLP | C57: 45743 | D57: 4.409262 | E57: 4.409262 | F57: =E57/$E$91 -> 0.032383112
B58: Parth Electrical & Engineering | C58: 45763 | D58: 0 | E58: 0 | F58: =E58/$E$91 -> 0 | G58: Listed in Aug'25
B59: Fractual Analytics | C59: 45845 | D59: 0 | E59: 0 | F59: =E59/$E$91 -> 0
B60: Blue Ashva India Pool Account | C60: 45889 | D60: 3.7408 | E60: 3.7408 | F60: =E60/$E$91 -> 0.027473701
B61: Electromech Infraprojects Pvt Ltd | C61: 45875 | D61: 5.0000016 | E61: 5.0000016 | F61: =E61/$E$91 -> 0.036721704
B62: Swapeco Solutions Private Limited | C62: 45900 | D62: 2.700175 | E62: 2.700175 | F62: =E62/$E$91 -> 0.019830999
B63: PERPLEXITY INVESTMENT | C63: 45854 | D63: =E63 -> 0.2583 | E63: 0.2583 | F63: =E63/$E$91 -> 0.0018970426
B64: RUNABLE INVESTMENT | C64: 45860 | D64: =E64 -> 0.0451 | E64: 0.0451 | F64: =E64/$E$91 -> 0.00033122966
B65: Blue Ashva Varenya Account | C65: 45889 | D65: 0.02 | E65: 0.02 | F65: =E65/$E$91 -> 0.00014688677
B66: EDUGORILLA COMMUNITY PRIVATE LIMITED | C66: 45889 | D66: 2.1971253 | E66: 2.1971253 | F66: =E66/$E$91 -> 0.016136432
B67: Onix Renewable | C67: 45689 | D67: 5 | E67: 5 | F67: =E67/$E$91 -> 0.036721692
B68: Clean Max Solar | C68: 46060 | D68: 0 | E68: 0 | F68: =E68/$E$91 -> 0
B69: Vecino Fitness Pvt Ltd - DOPAMINE | C69: 45001 | D69: 0 | E69: 0 | F69: =E69/$E$91 -> 0 | G69: Written Off
B70: BETR Tech Privated Limited - Venture Catalyst | C70: Dec 20 - Jun 21 | D70: 0 | E70: 0 | F70: =E70/$E$91 -> 0 | G70: Written Off
B71: Bitcipher LLP | C71: Feb 21 - Jun 22 | D71: 0 | E71: 0 | F71: =E71/$E$91 -> 0 | G71: Written Off
B72: Cheelizza - ANIMESH LODHA | C72: 44780 | D72: 0 | E72: 0 | F72: =E72/$E$91 -> 0 | G72: Written Off
B73: Crypto | C73: Feb 21 - Nov 22 | D73: 0 | E73: 0 | F73: =E73/$E$91 -> 0 | G73: Written Off
B74: Crypto Matic | C74: 44256 | D74: 0 | E74: 0 | F74: =E74/$E$91 -> 0 | G74: Written Off
B75: DCX Deposits | C75: Mar 21 - May 21 | D75: 0 | E75: 0 | F75: =E75/$E$91 -> 0 | G75: Written Off
B76: Falconbrick Technologies Private Limited - Shashi Kiran | C76: 43860 | D76: 0 | E76: 0 | F76: =E76/$E$91 -> 0 | G76: Written Off
B77: Moneyclub Technologies Private Limited - Venture Catalyst | C77: 44064 | D77: 0 | E77: 0 | F77: =E77/$E$91 -> 0 | G77: Written Off
B78: Neblio Technologies Pvt Ltd | C78: Dec 21 - Jan 22 | D78: 0 | E78: 0 | F78: =E78/$E$91 -> 0 | G78: Written Off
B79: One Eight Technologies Private Limited - Ram | C79: 44131 | D79: 0 | E79: 0 | F79: =E79/$E$91 -> 0 | G79: Written Off
B80: Reflexical | C80: 44757 | D80: 0 | E80: 0 | F80: =E80/$E$91 -> 0 | G80: Written Off
B81: Tamasha - Angel List | C81: 44063 | D81: 0 | E81: 0 | F81: =E81/$E$91 -> 0 | G81: Written Off
B82: UE Lifesciences - SHIKHA JAISINGHANI | C82: 44560 | D82: 0 | E82: 0 | F82: =E82/$E$91 -> 0 | G82: Written Off
B83: Wazir | C83: 44285 | D83: 0 | E83: 0 | F83: =E83/$E$91 -> 0 | G83: Written Off
B84: Zaamo E Commerce Pvt Ltd - PRADEEP KUMAR | C84: 44868 | D84: 0 | E84: 0 | F84: =E84/$E$91 -> 0 | G84: Written Off
B85: AL Trust - Forbidden Foods - BRB | C85: 43752 | D85: 0 | E85: 0 | F85: =E85/$E$91 -> 0 | G85: Written Off
B86: Faraway Foods Private Limited | C86: Sep 19 - Aug 20 | D86: 0 | E86: 0 | F86: =E86/$E$91 -> 0 | G86: Written Off
B87: Kylo Edutech Private Ltd | C87: 44287 | D87: 0 | E87: 0 | F87: =E87/$E$91 -> 0 | G87: Written Off
B88: Rang Technovations LLP | C88: 43699 | D88: 0 | E88: 0 | F88: =E88/$E$91 -> 0 | G88: Written Off
B89: Synergistic Financial Networks Pvt Ltd (Equity Shares) - MOSAMBEE | C89: Nov 12 - Sep 18 | D89: 0 | E89: 0 | F89: =E89/$E$91 -> 0 | G89: Written Off
B90: Transigo OPC Pvt Ltd | C90: Mar 20 - Jun 20 | D90: 0 | E90: 0 | F90: =E90/$E$91 -> 0 | G90: Written Off
B91: Total | C91: 921871 | D91: =SUM(D4:D90) -> 136.1593 | E91: =SUM(E4:E90) -> 136.1593 | F91: =SUM(F4:F90) -> 1
D92: ='Private Equity Excl Pre IPO'!D86+'Pre IPO '!E5 -> 136.1593

Sheet Investorwise Summary
B1: from Live consol
B2: The Summary,below, takes Private investments at Cost
B3: Category | C3: Ajay Jaisinghani | D3: Allocation (%) | E3: Aarti Ajay Jaisinghani | F3: Allocation (%) | G3: Bharat Jaisinghani | H3: Allocation (%) | I3: Ankita Jaisinghani | J3: Allocation (%) | K3: Hope India Trust | L3: Allocation (%) | M3: Bharat Jaisinghani Family Trust | N3: Allocation (%) | O3: Bharat Jaisinghani Family Trust II | P3: Allocation (%) | Q3: Bharat Jaisinghani Family Trust III | R3: Allocation (%)
B6: Equity - Managed Strategies | C6: =SUM(C7:C17) -> 463.86684 | D6: =SUM(D7:D17) -> 0.56049665 | E6: =SUM(E7:E17) -> 103.83746 | F6: =SUM(F7:F17) -> 0.78908909 | G6: =SUM(G7:G17) -> 51.170917 | H6: =SUM(H7:H17) -> 0.48506701 | I6: =SUM(I7:I17) -> 172.80744 | J6: =SUM(J7:J17) -> 0.81214429 | ... R6: =SUM(R7:R17) -> 0.62224281
B7: Direct Equity - MO | C7: 12.19077 | D7: =C7/C$40 -> 0.014730274 | E7: 0 | F7: =E7/E$40 -> 0 | G7: 7.92744 | H7: =G7/G$40 -> 0.075146974 | I7: 1.5220481 | J7: =I7/I$40 -> 0.0071531799 | K7: 0 | L7: =K7/K$40 -> 0 | M7: 0 | N7: =M7/M$40 -> 0 | O7: 0 | P7: =O7/O$40 -> 0 | Q7: 0 | R7: =Q7/Q$40 -> 0
B8: Direct Equity - Unlisted | C8: 48.766016 | D8: =C8/C$40 -> 0.058924644 | E8: 0 | F8: =E8/E$40 -> 0 | G8: 0 | H8: =G8/G$40 -> 0 | I8: 15.5625 | J8: =I8/I$40 -> 0.073139187 | K8: 0 | L8: =K8/K$40 -> 0 | M8: 0 | N8: =M8/M$40 -> 0 | O8: 0 | P8: =O8/O$40 -> 0 | Q8: 0 | R8: =Q8/Q$40 -> 0
B9: Large Cap | C9: 0 | D9: =C9/C$40 -> 0 | E9: 0 | F9: =E9/E$40 -> 0 | G9: 0 | H9: =G9/G$40 -> 0 | I9: 0 | J9: =I9/I$40 -> 0 | K9: 0 | L9: =K9/K$40 -> 0 | M9: 0 | N9: =M9/M$40 -> 0 | O9: 0 | P9: =O9/O$40 -> 0 | Q9: 0 | R9: =Q9/Q$40 -> 0
B10: Mid Cap | C10: 0 | D10: =C10/C$40 -> 0 | E10: 0 | F10: =E10/E$40 -> 0 | G10: 0 | H10: =G10/G$40 -> 0 | I10: 0 | J10: =I10/I$40 -> 0 | K10: 0 | L10: =K10/K$40 -> 0 | M10: 0 | N10: =M10/M$40 -> 0 | O10: 5.0538874 | P10: =O10/O$40 -> 0.62224281 | Q10: 5.0538874 | R10: =Q10/Q$40 -> 0.62224281
B11: Multi Cap | C11: 240.23011 | D11: =C11/C$40 -> 0.29027333 | E11: 3.4742772 | F11: =E11/E$40 -> 0.026401977 | G11: 6.1968931 | H11: =G11/G$40 -> 0.058742516 | I11: 101.69888 | J11: =I11/I$40 -> 0.4779549 | K11: 0 | L11: =K11/K$40 -> 0 | M11: 0 | N11: =M11/M$40 -> 0 | O11: 0 | P11: =O11/O$40 -> 0 | Q11: 0 | R11: =Q11/Q$40 -> 0
B12: Equity Hybrid | C12: 78.254968 | D12: =C12/C$40 -> 0.094556549 | E12: 2.6808357 | F12: =E12/E$40 -> 0.020372399 | G12: 7.0887256 | H12: =G12/G$40 -> 0.067196507 | I12: 17.961751 | J12: =I12/I$40 -> 0.084414962 | K12: 0 | L12: =K12/K$40 -> 0 | M12: 0 | N12: =M12/M$40 -> 0 | O12: 0 | P12: =O12/O$40 -> 0 | Q12: 0 | R12: =Q12/Q$40 -> 0
B13: Mid & Small Cap | C13: 83.130731 | D13: =C13/C$40 -> 0.100448 | E13: 97.68235 | F13: =E13/E$40 -> 0.74231472 | G13: 29.957858 | H13: =G13/G$40 -> 0.28398101 | I13: 35.986894 | J13: =I13/I$40 -> 0.16912785 | K13: 0 | L13: =K13/K$40 -> 0 | M13: 0 | N13: =M13/M$40 -> 0 | O13: 0 | P13: =O13/O$40 -> 0 | Q13: 0 | R13: =Q13/Q$40 -> 0
B14: Thematic/Sectoral | C14: 0 | D14: =C14/C$40 -> 0 | E14: 0 | F14: =E14/E$40 -> 0 | G14: 0 | H14: =G14/G$40 -> 0 | I14: 0 | J14: =I14/I$40 -> 0 | K14: 0 | L14: =K14/K$40 -> 0 | M14: 0 | N14: =M14/M$40 -> 0 | O14: 0 | P14: =O14/O$40 -> 0 | Q14: 0 | R14: =Q14/Q$40 -> 0
B15: Long-Short Fund | C15: 0 | D15: =C15/C$40 -> 0 | E15: 0 | F15: =E15/E$40 -> 0 | G15: 0 | H15: =G15/G$40 -> 0 | I15: 0 | J15: =I15/I$40 -> 0 | K15: 0 | L15: =K15/K$40 -> 0 | M15: 0 | N15: =M15/M$40 -> 0 | O15: 0 | P15: =O15/O$40 -> 0 | Q15: 0 | R15: =Q15/Q$40 -> 0
B16: SLBM | C16: 0.16941783 | D16: =C16/C$40 -> 0.00020470988 | E16: 0 | F16: =E16/E$40 -> 0 | G16: 0 | H16: =G16/G$40 -> 0 | I16: 0.075368125 | J16: =I16/I$40 -> 0.00035420809 | K16: 0 | L16: =K16/K$40 -> 0 | M16: 0 | N16: =M16/M$40 -> 0 | O16: 0 | P16: =O16/O$40 -> 0 | Q16: 0 | R16: =Q16/Q$40 -> 0
B17: Small Cap | C17: 1.1248249 | D17: =C17/C$40 -> 0.0013591413 | E17: 0 | F17: =E17/E$40 -> 0 | G17: 0 | H17: =G17/G$40 -> 0 | I17: 0 | J17: =I17/I$40 -> 0 | K17: 0 | L17: =K17/K$40 -> 0 | M17: 0 | N17: =M17/M$40 -> 0 | O17: 0 | P17: =O17/O$40 -> 0 | Q17: 0 | R17: =Q17/Q$40 -> 0
B19: Direct Equity - Personal | C19: =SUM(C20:C21) -> 192.66041 | D19: =SUM(D20:D21) -> 0.2327942 | E19: =SUM(E20:E21) -> 10.03806 | F19: =SUM(F20:F21) -> 0.076281945 | G19: =SUM(G20:G21) -> 6.2143417 | H19: =SUM(H20:H21) -> 0.058907917 | I19: =SUM(I20:I21) -> 13.445842 | J19: =SUM(J20:J21) -> 0.063191515 | ... R19: =SUM(R20:R21) -> 0
B20: Direct Equity - Non MO | C20: 192.66041 | D20: =C20/C$40 -> 0.2327942 | E20: 10.03806 | F20: =E20/E$40 -> 0.076281945 | G20: 6.2143417 | H20: =G20/G$40 -> 0.058907917 | I20: 13.445842 | J20: =I20/I$40 -> 0.063191515 | K20: 0 | L20: =K20/K$40 -> 0 | M20: 0 | N20: =M20/M$40 -> 0 | O20: 0 | P20: =O20/O$40 -> 0 | Q20: 0 | R20: =Q20/Q$40 -> 0
B21: Direct Equity - HDFC | C21: 0 | D21: =C21/C$40 -> 0 | E21: 0 | F21: =E21/E$40 -> 0 | G21: 0 | H21: =G21/G$40 -> 0 | I21: 0 | J21: =I21/I$40 -> 0 | K21: 0 | L21: =K21/K$40 -> 0 | M21: 0 | N21: =M21/M$40 -> 0 | O21: 0 | P21: =O21/O$40 -> 0 | Q21: 0 | R21: =Q21/Q$40 -> 0
B23: LKP Sec Portfolio | C23: 0 | D23: =C23/C$40 -> 0 | E23: 0 | F23: =E23/E$40 -> 0 | G23: 0.84977725 | H23: =G23/G$40 -> 0.0080553356 | I23: 0 | J23: =I23/I$40 -> 0 | K23: 0 | L23: =K23/K$40 -> 0 | M23: 0 | N23: =M23/M$40 -> 0 | O23: 0 | P23: =O23/O$40 -> 0 | Q23: 0 | R23: =Q23/Q$40 -> 0
B25: Debt | C25: =SUM(C26:C29) -> 40.826712 | D25: =SUM(D26:D29) -> 0.049331475 | E25: =SUM(E26:E29) -> 0 | F25: =SUM(F26:F29) -> 0 | G25: =SUM(G26:G30) -> 1.0434584 | H25: =SUM(H26:H30) -> 0.0098913073 | I25: =SUM(I26:I30) -> 0 | J25: =SUM(J26:J29) -> 0 | K25: =SUM(K26:K29) -> 0 | L25: =SUM(L26:L29) -> 0 | M25: =SUM(M26:M29) -> 4.0189932 | N25: =SUM(N26:N29) -> 0.67482035 | O25: =SUM(O26:O29) -> 0 | P25: =SUM(P26:P29) -> 0 | Q25: =SUM(Q26:Q29) -> 0 | R25: =SUM(R26:R29) -> 0
B26: Debt AIF | C26: 0 | D26: =C26/C$40 -> 0 | E26: 0 | F26: =E26/E$40 -> 0 | G26: 0 | H26: =G26/G$40 -> 0 | I26: 0 | J26: =I26/I$40 -> 0 | K26: 0 | L26: =K26/K$40 -> 0 | M26: 0 | N26: =M26/M$40 -> 0 | O26: 0 | P26: =O26/O$40 -> 0 | Q26: 0 | R26: =Q26/Q$40 -> 0
B27: High Yield Fund | C27: 3.768427 | D27: =C27/C$40 -> 0.0045534419 | E27: 0 | F27: =E27/E$40 -> 0 | G27: 0 | H27: =G27/G$40 -> 0 | I27: 0 | J27: =I27/I$40 -> 0 | K27: 0 | L27: =K27/K$40 -> 0 | M27: 0 | N27: =M27/M$40 -> 0 | O27: 0 | P27: =O27/O$40 -> 0 | Q27: 0 | R27: =Q27/Q$40 -> 0
B28: Hybrid | C28: 0 | D28: =C28/C$40 -> 0 | E28: 0 | F28: =E28/E$40 -> 0 | G28: 0 | H28: =G28/G$40 -> 0 | I28: 0 | J28: =I28/I$40 -> 0 | K28: 0 | L28: =K28/K$40 -> 0 | M28: 0 | N28: =M28/M$40 -> 0 | O28: 0 | P28: =O28/O$40 -> 0 | Q28: 0 | R28: =Q28/Q$40 -> 0
B29: Arbitrage | C29: 37.058285 | D29: =C29/C$40 -> 0.044778033 | E29: 0 | F29: =E29/E$40 -> 0 | G29: 0 | H29: =G29/G$40 -> 0 | I29: 0 | J29: =I29/I$40 -> 0 | K29: 0 | L29: =K29/K$40 -> 0 | M29: 4.0189932 | N29: =M29/M$40 -> 0.67482035 | O29: 0 | P29: =O29/O$40 -> 0 | Q29: 0 | R29: =Q29/Q$40 -> 0
B30: PP Structures | C30: 0 | D30: =C30/C$40 -> 0 | E30: 0 | F30: =E30/E$40 -> 0 | G30: 1.0434584 | H30: =G30/G$40 -> 0.0098913073 | I30: 0 | J30: =I30/I$40 -> 0 | K30: 0 | L30: =K30/K$40 -> 0 | M30: 0 | N30: =M30/M$40 -> 0 | O30: 0 | P30: =O30/O$40 -> 0 | Q30: 0 | R30: =Q30/Q$40 -> 0
B31: Cash | C31: =SUM(C32:C33) -> 1.2571074 | D31: =SUM(D32:D32) -> 0.00151898 | E31: =SUM(E32:E33) -> 1.4087183 | F31: =SUM(F32:F32) -> 0.010705233 | G31: =SUM(G32:G33) -> 0.3816251 | H31: =SUM(H32:H32) -> 0.0036175577 | I31: =SUM(I32:I33) -> 0.065089317 | J31: =SUM(J32:J32) -> 0.00030590071 | K31: =SUM(K32:K33) -> 0.38734753 | L31: =SUM(L32:L32) -> 1 | M31: =SUM(M32:M33) -> 1.9366559 | N31: =SUM(N32:N32) -> 0.32517965 | O31: =SUM(O32:O33) -> 0 | P31: =SUM(P32:P32) -> 0 | Q31: =SUM(Q32:Q33) -> 0 | R31: =SUM(R32:R32) -> 0
B32: Liquid | C32: 1.2571074 | D32: =C32/C$40 -> 0.00151898 | E32: 1.4087183 | F32: =E32/E$40 -> 0.010705233 | G32: 0.3816251 | H32: =G32/G$40 -> 0.0036175577 | I32: 0.065089317 | J32: =I32/I$40 -> 0.00030590071 | K32: 0.38734753 | L32: =K32/K$40 -> 1 | M32: 1.9366559 | N32: =M32/M$40 -> 0.32517965 | O32: 0 | P32: =O32/O$40 -> 0 | Q32: 0 | R32: =Q32/Q$40 -> 0
B33: Money Market | C33: 0 | D33: =C33/C$40 -> 0 | E33: 0 | F33: =E33/E$40 -> 0 | G33: 0 | H33: =G33/G$40 -> 0 | I33: 0 | J33: =I33/I$40 -> 0 | K33: 0 | L33: =K33/K$40 -> 0 | M33: 0 | N33: =M33/M$40 -> 0 | O33: 0 | P33: =O33/O$40 -> 0 | Q33: 0 | R33: =Q33/Q$40 -> 0
B34: Alternate | C34: =SUM(C35:C38) -> 128.9886 | D34: =SUM(D35:D38) -> 0.15585869 | E34: =SUM(E35:E38) -> 16.307317 | F34: =SUM(F35:F38) -> 0.12392373 | G34: =SUM(G35:G38) -> 45.832351 | H34: =SUM(H35:H38) -> 0.43446088 | I34: =SUM(I35:I38) -> 26.460863 | J34: =SUM(J35:J38) -> 0.1243583 | ... R34: =SUM(R35:R38) -> 0.37775719
B35: Silver | C35: 3.8968359 | D35: =C35/C$40 -> 0.0047086001 | E35: 0 | F35: =E35/E$40 -> 0 | G35: 0 | H35: =G35/G$40 -> 0 | I35: 2.648126 | J35: =I35/I$40 -> 0.012445416 | K35: 0 | L35: =K35/K$40 -> 0 | M35: 0 | N35: =M35/M$40 -> 0 | O35: 0 | P35: =O35/O$40 -> 0 | Q35: 0 | R35: =Q35/Q$40 -> 0
B36: Gold | C36: 29.203061 | D36: =C36/C$40 -> 0.035286458 | E36: 16.307317 | F36: =E36/E$40 -> 0.12392373 | G36: 0 | H36: =G36/G$40 -> 0 | I36: 2.7974894 | J36: =I36/I$40 -> 0.01314738 | K36: 0 | L36: =K36/K$40 -> 0 | M36: 0 | N36: =M36/M$40 -> 0 | O36: 0 | P36: =O36/O$40 -> 0 | Q36: 0 | R36: =Q36/Q$40 -> 0
B37: PE Funds | C37: 17.519326 | D37: =C37/C$40 -> 0.021168841 | E37: 0 | F37: =E37/E$40 -> 0 | G37: 6.3590413 | H37: =G37/G$40 -> 0.060279575 | I37: 5.3988086 | J37: =I37/I$40 -> 0.025372817 | K37: 0 | L37: =K37/K$40 -> 0 | M37: 0 | N37: =M37/M$40 -> 0 | O37: 1.7180754 | P37: =O37/O$40 -> 0.21153223 | Q37: 1.7180754 | R37: =Q37/Q$40 -> 0.21153223
B38: Private Equity ( at Cost ) | C38: 78.369379 | D38: =C38/C$40 -> 0.094694793 | E38: 0 | F38: =E38/E$40 -> 0 | G38: 39.47331 | H38: =G38/G$40 -> 0.3741813 | I38: 15.616439 | J38: =I38/I$40 -> 0.073392686 | K38: 0 | L38: =K38/K$40 -> 0 | M38: 0 | N38: =M38/M$40 -> 0 | O38: 1.3500875 | P38: =O38/O$40 -> 0.16622496 | Q38: 1.3500875 | R38: =Q38/Q$40 -> 0.16622496
B40: Total | C40: =C34+C31+C25+C19+C6 -> 827.59966 | D40: =D34+D31+D25+D19+D6 -> 1 | E40: =E34+E31+E25+E19+E6 -> 131.59156 | F40: =F34+F31+F25+F19+F6 -> 1 | G40: =G34+G31+G25+G19+G6+G23 -> 105.49247 | H40: =H34+H31+H25+H19+H6 -> 0.99194466 | I40: =I34+I31+I25+I19+I6 -> 212.77923 | J40: =J34+J31+J25+J19+J6 -> 1 | K40: =K34+K31+K25+K19+K6 -> 0.38734753 | L40: =L34+L31+L25+L19+L6 -> 1 | M40: =M34+M31+M25+M19+M6 -> 5.9556491 | N40: =N34+N31+N25+N19+N6 -> 1 | O40: =O34+O31+O25+O19+O6 -> 8.1220503 | ... R40: =R34+R31+R25+R19+R6 -> 1
B41: Data Check | C41: =C40+E40+G40+O40+Q40+I40+K40+M40-('Portfolio Allocation'!F28-'Portfolio Allocation'!F26+'Portfolio Allocation'!E26) -> 0
B43: Aarti & Ajay Jaisinghani | C43: =C40+E40 -> 959.19122
B44: Bharat, Ankita, Hope, BJT | C44: =G40+I40+K40+M40+O40+Q40 -> 340.8588

Sheet Transactions
B1: Redemptions from 31st May 2026 to 30th June'2026 | H1: Purchases from 31st May 2026 to 30th June 2026
B2: Investor | C2: Date | D2: Category | E2: Fund Name | F2: Sale | H2: Investor | I2: Date | J2: Category | K2: Fund Name | L2: Purchase
B3: Bharat Jaisinghani | C3: 46188 | D3: LKP Sec Portfolio | E3: Capri Global Capital Pvt Ltd | F3: 0.076062 | H3: Ajay Jaisinghani | I3: 46190 | J3: Direct Equity - Non MO | K3: MPS | L3: 0.51789155
B4: Bharat Jaisinghani | C4: 46192 | D4: LKP Sec Portfolio | E4: Capri Global Capital Pvt Ltd | F4: 0.0785925 | H4: Ajay Jaisinghani | I4: 46191 | J4: Direct Equity - Non MO | K4: MPS | L4: 0.36817016
B5: Ajay Jaisinghani | C5: 46197 | D5: Direct Equity - Non MO | E5: Yash High Voltage Ltd. | F5: 1.000012 | H5: Ajay Jaisinghani | I5: 46190 | J5: Direct Equity - Non MO | K5: NLC INDIA | L5: 1.0034019
B6: Ajay Jaisinghani | C6: 46198 | D6: Direct Equity - Non MO | E6: Yash High Voltage Ltd. | F6: 1.000012 | H6: Ajay Jaisinghani | I6: 46177 | J6: Multi Cap | K6: Bandhan Large & Mid Cap Fund - Direct Plan - Growth | L6: 1.8749063
B7: Ajay Jaisinghani | C7: 46203 | D7: Direct Equity - Non MO | E7: Yash High Voltage Ltd. | F7: 1.000012 | H7: Ajay Jaisinghani | I7: 46184 | J7: Multi Cap | K7: Bandhan Large & Mid Cap Fund - Direct Plan - Growth | L7: 1.8749063
B8: Ankita Jaisinghani | C8: 46195 | D8: Equity Hybrid | E8: HDFC Balanced Advantage Fund | F8: 3.3040294 | H8: Ajay Jaisinghani | I8: 46191 | J8: Multi Cap | K8: Bandhan Large & Mid Cap Fund - Direct Plan - Growth | L8: 1.8749063
B9: Bharat Jaisinghani | C9: 46195 | D9: Equity Hybrid | E9: ICICI Pru Balanced Advantage Fund | F9: 1.0035851 | H9: Ajay Jaisinghani | I9: 46198 | J9: Multi Cap | K9: Bandhan Large & Mid Cap Fund - Direct Plan - Growth | L9: 1.8749063
B10: Ankita Jaisinghani | C10: 46195 | D10: Equity Hybrid | E10: ICICI Pru Balanced Advantage Fund | F10: 4.7241341 | H10: Ajay Jaisinghani | I10: 46174 | J10: Multi Cap | K10: Buoyant Opportunities Portfolio AIF | L10: 25
B11: Ankita Jaisinghani | C11: 46202 | D11: Multi Cap | E11: HDFC Capital Builder Value Fund | F11: 3.3278911
B12: Ankita Jaisinghani | C12: 46202 | D12: Multi Cap | E12: HDFC Capital Builder Value Fund | F12: 0.5073839
B13: Bharat Jaisinghani | C13: 46203 | D13: Multi Cap | E13: HDFC Capital Builder Value Fund | F13: 0.96253226
B14: Ajay Jaisinghani | C14: 46202 | D14: Multi Cap | E14: HDFC Capital Builder Value Fund | F14: 3.9526521
B15: Ajay Jaisinghani | C15: 46202 | D15: Multi Cap | E15: HDFC Capital Builder Value Fund | F15: 0.85170102
B16: Ajay Jaisinghani | C16: 46202 | D16: Multi Cap | E16: ICICI Pru India Opportunities Fund | F16: 3.6962218
B17: Ajay Jaisinghani | C17: 46202 | D17: Multi Cap | E17: ICICI Pru India Opportunities Fund | F17: 1.0250608
B18: Ankita Jaisinghani | C18: 46202 | D18: Multi Cap | E18: ICICI Pru India Opportunities Fund | F18: 0.92550869
B19: Bharat Jaisinghani | C19: 46202 | D19: Multi Cap | E19: ICICI Pru India Opportunities Fund | F19: 0.2909386
B20: Bharat Jaisinghani | C20: 46198 | D20: LKP Sec Portfolio | E20: Belrise Industries | F20: 0.1508976
B21: Ajay Jaisinghani | C21: 46197 | D21: Equity Hybrid | E21: ICICI Prudential Equity Savings Fund - Direct Plan | F21: 4.3103739

Sheet Private Equity Excl Pre IPO
B1: Copy pasted (not linked)
B2: Product | C2: Date Investment Range | D2: Investment at Cost | E2: Market Value | F2: Allocation (%) | G2: Remarks | H2: Private Equity
B3: Private Equity | C3: x | D3: 112.96243 | E3: 112.96243 | F3: 1
B4: Everest Fleet Private Ltd - SIDDHARTH LADSARIYA | C4: Jan 22 - May 23 | D4: 4.7607824 | E4: 4.7607824 | F4: 0.04214483 | G4: 25CR | H4: Private Equity
B5: URB Ventures Pvt Ltd - ANUJ MUNOT | C5: Jun 22 - Feb 23 | D5: 2.25 | E5: 2.25 | F5: 0.019918127 | G5: 6X | H5: Private Equity
B6: Waterwala Labs Private Limited - Drink Prime | C6: Feb 20 - Jul 23 | D6: 8.1001152 | E6: 8.1001152 | F6: 0.071706277 | G6: 12CR | H6: Private Equity
B7: MOTHER INDIA FORMING PRIVATE LIMITED | C7: 45681 | D7: 7.999996 | E7: 7.999996 | F7: 0.070819972 | H7: Private Equity
B8: SKS Fastener | C8: 45741 | D8: 2.99584 | E8: 2.99584 | F8: 0.026520676 | H8: Private Equity
B9: Transigo Fleet LLP | C9: May 21 - Jan 23 | D9: 5.7557 | E9: 5.7557 | F9: 0.050952339 | G9: 20% irr | H9: Private Equity
B10: FH Enable LLP - Aakash Sachdev | C10: Jul 20 - Oct 20 | D10: 0.5 | E10: 0.5 | F10: 0.0044262504 | G10: 5CR | H10: Private Equity
B11: PROCYON ENTERPRISE LLP - ABHISHEK MURARKA | C11: May 23 - Aug 23 | D11: 4.0128 | E11: 4.0128 | F11: 0.035523315 | G11: 20%IRR | H11: Private Equity
B12: Insolation Energy PP | C12: 45637 | D12: 0 | E12: 0 | F12: 0 | H12: Private Equity
B13: Spray Engineering Devices Ltd. | C13: 45420 | D13: 4.7517442 | E13: 4.7517442 | F13: 0.04206482 | H13: Private Equity
B14: Matrix Gas And Renewables Limited | C14: 45352 | D14: 4.5 | E14: 4.5 | F14: 0.039836254 | H14: Private Equity
B15: Telawne Power | C15: 45650 | D15: 4 | E15: 4 | F15: 0.035410003 | H15: Private Equity
B16: Innoviti Payment Solutions Private Ltd - PRANAV KORANNE | C16: 44554 | D16: 1.9999974 | E16: 1.9999974 | F16: 0.017704979 | G16: 2X | H16: Private Equity
B17: Oil Max | C17: 45700 | D17: 3.876 | E17: 3.876 | F17: 0.034312293 | H17: Private Equity
B18: Borosil Renewables | C18: 45700 | D18: 3.7499885 | E18: 3.7499885 | F18: 0.033196776 | H18: Private Equity
B19: BIG BANG BOOM | C19: 45544 | D19: 4.032 | E19: 4.032 | F19: 0.035693283 | H19: Private Equity
B20: Pivot Ventures - ISHA KEDIA | C20: Dec 21 - Aug 22 | D20: 1.6 | E20: 1.6 | F20: 0.014164001 | G20: 2CR | H20: Private Equity
B21: Stay Vista Private Limited - ARTHA ENERGY PROJECTS PVT LTD | C21: 44236 | D21: 0.4773404 | E21: 0.4773404 | F21: 0.0042256563 | G21: 2CR | H21: Private Equity
B22: M/S Grand Continent Hotels | C22: Feb 24 - Mar 24 | D22: 0 | E22: 0 | F22: 0 | H22: Private Equity
B23: Incred Holdings Ltd. | C23: 45260 | D23: 1.5029264 | E23: 1.5029264 | F23: 0.013304657 | H23: Private Equity
B24: Autocracy Machinery Pvt Ltd. | C24: Oct 23 - Mar 24 | D24: 1.5000018 | E24: 1.5000018 | F24: 0.013278767 | H24: Private Equity
B25: The OAKS Consumer Fund I - SANTOSH PARAB | C25: Sep 21 - Mar 23 | D25: 1.3 | E25: 1.3 | F25: 0.011508251 | G25: 1.4CR | H25: Private Equity
B26: SOTEFIN | C26: 45485 | D26: 2.00004 | E26: 2.00004 | F26: 0.017705356 | H26: Private Equity
B27: WE VOISE | C27: 45544 | D27: 1.0106085 | E27: 1.0106085 | F27: 0.0089464126 | H27: Private Equity
B28: Zenith | C28: 45491 | D28: 1.0001255 | E28: 1.0001255 | F28: 0.0088536119 | H28: Private Equity
B29: Radiant | C29: 45491 | D29: 0.9996 | E29: 0.9996 | F29: 0.0088489599 | H29: Private Equity
B30: Vineet Sethia - Drink Prime | C30: 45085 | D30: 0.790803 | E30: 0.790803 | F30: 0.0070005842 | G30: 1X | H30: Private Equity
B31: Third Eye Distillery Holdings Pvt Ltd (SKYVENTURES - LV ANGEL FUND - AAKASH SACHDEV) | C31: 44690 | D31: 0.25 | E31: 0.25 | F31: 0.0022131252 | G31: 0.60CR | H31: Private Equity
B32: HYPRKYTCHEN Foodtech Private Limited - Mr. Bansi | C32: Dec 20 - Dec 21 | D32: 2.5608348 | E32: 2.5608348 | F32: 0.022669792 | H32: Private Equity
B33: Inflexor Technologies - (RAJESHWARI - AVENDUS) | C33: Nov 20 - Nov 22 | D33: 0.795 | E33: 0.795 | F33: 0.0070377382 | H33: Private Equity
B34: SWAPECO SOLUTIONS PRIVATE LIMITED - (SCRAP UNCLE - MUKUL CHABRA) | C34: 45160 | D34: 0.50203 | E34: 0.50203 | F34: 0.004444221 | H34: Private Equity
B35: A K Enterprises - Polycab | C35: 43891 | D35: 0.5 | E35: 0.5 | F35: 0.0044262504 | H35: Private Equity
B36: Sky Enable Tech Llp | C36: 45337 | D36: 0.8 | E36: 0.8 | F36: 0.0070820007 | H36: Private Equity
B37: Since 99 Apparel Pvt Limited - PUNIT SEHGAL / DEXTER CAPITAL | C37: 45006 | D37: 0.4999071 | E37: 0.4999071 | F37: 0.004425428 | H37: Private Equity
B38: EMA Preferred Shares | C38: 45534 | D38: 0.4642872 | E38: 0.4642872 | F38: 0.0041101028 | H38: Private Equity
B39: Stay Vista Private Limited - Anandkumar Radhakrishna Ladsariya | C39: 44963 | D39: 0.4212804 | E39: 0.4212804 | F39: 0.0037293851 | H39: Private Equity
B40: Ajay Jain - Drink Prime | C40: 45085 | D40: 0.4098207 | E40: 0.4098207 | F40: 0.0036279381 | H40: Private Equity
B41: Hanok Reuben Medhari - Drink Prime | C41: 43922 | D41: 0.2500024 | E41: 0.2500024 | F41: 0.0022131465 | H41: Private Equity
B42: Head Infotech | C42: 44602 | D42: 2.25 | E42: 2.25 | F42: 0.019918127 | H42: Private Equity
B43: Nopo Nanotechnologies India Pvt Ltd - Gadhadar Reddy | C43: 45295 | D43: 0.25 | E43: 0.25 | F43: 0.0022131252 | H43: Private Equity
B44: Credit Fair-K M Global Credit Private Limited | C44: Sep 20 - Jun 21 | D44: 0.2000046 | E44: 0.2000046 | F44: 0.0017705409 | G44: 2CR | H44: Private Equity
B45: FH Edutech LLP | C45: 44375 | D45: 0.2 | E45: 0.2 | F45: 0.0017705002 | H45: Private Equity
B46: Home Pecked E-Marketplace Services Ltd | C46: 44531 | D46: 0.1540769 | E46: 0.1540769 | F46: 0.0013639659 | H46: Private Equity
B47: AL Trust - Collabmates Pvt Ltd - (ANGELLIST - LIKEMINDS) | C47: 44971 | D47: 0.153 | E47: 0.153 | F47: 0.0013544326 | H47: Private Equity
B48: Aksum Trademart Pvt Ltd - ANKIT JAIN | C48: 45061 | D48: 0.150015 | E48: 0.150015 | F48: 0.0013280079 | H48: Private Equity
B49: AL Trust - Karban Envirotech (RUV) - Nilesh Angelist | C49: 45272 | D49: 0.102 | E49: 0.102 | F49: 0.00090295509 | H49: Private Equity
B50: Zippmat Private Ltd - ABHIJEET KUDVA | C50: 44602 | D50: 0.1015 | E50: 0.1015 | F50: 0.00089852884 | H50: Private Equity
B51: LV Angel Fund - Lets Venture (HOOPR) - VAIBHAV KARNAVAT | C51: 44610 | D51: 0.101 | E51: 0.101 | F51: 0.00089410259 | H51: Private Equity
B52: Rurash Financials Private Ltd - Reliance Retail | C52: 44061 | D52: 0.100122 | E52: 0.100122 | F52: 0.00088633009 | H52: Private Equity
B53: Variance PT Ventures LLP - Romil Kapadia | C53: 44610 | D53: 0.1 | E53: 0.1 | F53: 0.00088525009 | H53: Private Equity
B54: LANDCRAFT RETAIL PVT LTD. - FOOD SQUARE | C54: 45524 | D54: 3.0015 | E54: 3.0015 | F54: 0.026570781 | H54: Private Equity
B55: Sky Vision Cure LLP | C55: 45743 | D55: 4.409262 | E55: 4.409262 | F55: 0.039032996 | H55: Private Equity
B56: PERPLEXITY INVESTMENT | C56: 45854 | D56: 0.2583 | E56: 0.2583 | F56: 0.002286601 | G56: Investments done in USD | H56: Private Equity
B57: RUNABLE INVESTMENT | C57: 45860 | D57: 0.0451 | E57: 0.0451 | F57: 0.00039924779 | G57: Investments done in USD | H57: Private Equity
B58: RAY's | C58: 45863 | D58: 2.006 | E58: 2.006 | F58: 0.017758117 | G58: Preferance shares locked in for 6 months | H58: Private Equity
B59: Blue Ashva Varenya Account | C59: 45889 | D59: 0.02 | E59: 0.02 | F59: 0.00017705002 | H59: Private Equity
B60: Blue Ashva India Pool Account | C60: 45889 | D60: 3.7408 | E60: 3.7408 | F60: 0.033115435 | H60: Private Equity
B61: Electromech Infraprojects Pvt Ltd | C61: 45875 | D61: 5.0000016 | E61: 5.0000016 | F61: 0.044262518 | H61: Private Equity
B62: Swapeco Solutions Private Limited | C62: 45900 | D62: 2.700175 | E62: 2.700175 | F62: 0.023903302 | H62: Private Equity
B63: Onix Renewable | C63: 45947 | D63: 5 | E63: 5 | F63: 0.044262504 | G63: New Investment | H63: Private Equity
B64: EDUGORILLA COMMUNITY PRIVATE LIMITED | C64: 45889 | D64: 2.1971253 | E64: 2.1971253 | F64: 0.019450053 | G64: New Investment | H64: Private Equity
B65: BETR Tech Privated Limited - Venture Catalyst | C65: Dec 20 - Jun 21 | D65: 0 | E65: 0 | F65: 0 | G65: Written Off
B66: Bitcipher LLP | C66: Feb 21 - Jun 22 | D66: 0 | E66: 0 | F66: 0 | G66: Written Off
B67: Cheelizza - ANIMESH LODHA | C67: 44780 | D67: 0 | E67: 0 | F67: 0 | G67: Written Off
B68: Crypto | C68: Feb 21 - Nov 22 | D68: 0 | E68: 0 | F68: 0 | G68: Written Off
B69: Crypto Matic | C69: 44256 | D69: 0 | E69: 0 | F69: 0 | G69: Written Off
B70: DCX Deposits | C70: Mar 21 - May 21 | D70: 0 | E70: 0 | F70: 0 | G70: Written Off
B71: Falconbrick Technologies Private Limited - Shashi Kiran | C71: 43860 | D71: 0 | E71: 0 | F71: 0 | G71: Written Off
B72: Moneyclub Technologies Private Limited - Venture Catalyst | C72: 44064 | D72: 0 | E72: 0 | F72: 0 | G72: Written Off
B73: Neblio Technologies Pvt Ltd | C73: Dec 21 - Jan 22 | D73: 0 | E73: 0 | F73: 0 | G73: Written Off
B74: One Eight Technologies Private Limited - Ram | C74: 44131 | D74: 0 | E74: 0 | F74: 0 | G74: Written Off
B75: Reflexical | C75: 44757 | D75: 0 | E75: 0 | F75: 0 | G75: Written Off
B76: Tamasha - Angel List | C76: 44063 | D76: 0 | E76: 0 | F76: 0 | G76: Written Off
B77: UE Lifesciences - SHIKHA JAISINGHANI | C77: 44560 | D77: 0 | E77: 0 | F77: 0 | G77: Written Off
B78: Wazir | C78: 44285 | D78: 0 | E78: 0 | F78: 0 | G78: Written Off
B79: Zaamo E Commerce Pvt Ltd - PRADEEP KUMAR | C79: 44868 | D79: 0 | E79: 0 | F79: 0 | G79: Written Off
B80: AL Trust - Forbidden Foods - BRB | C80: 43752 | D80: 0 | E80: 0 | F80: 0 | G80: Written Off
B81: Faraway Foods Private Limited | C81: Sep 19 - Aug 20 | D81: 0 | E81: 0 | F81: 0 | G81: Written Off
B82: Kylo Edutech Private Ltd | C82: 44287 | D82: 0 | E82: 0 | F82: 0 | G82: Written Off
B83: Rang Technovations LLP | C83: 43699 | D83: 0 | E83: 0 | F83: 0 | G83: Written Off
B84: Synergistic Financial Networks Pvt Ltd (Equity Shares) - MOSAMBEE | C84: Nov 12 - Sep 18 | D84: 0 | E84: 0 | F84: 0 | G84: Written Off
B85: Transigo OPC Pvt Ltd | C85: Mar 20 - Jun 20 | D85: 0 | E85: 0 | F85: 0 | G85: Written Off
B86: Total | C86: 921871 | D86: =SUM(D4:D85) -> 115.15955 | E86: =SUM(E4:E85) -> 115.15955 | F86: =SUM(F4:F85) -> 1.0194501

Sheet Pre IPO 
C4: Product | D4: Date Investment Range | E4: Investment at Cost | F4: Market Value | G4: Allocation (%) | H4: Remarks | I4: Pre IPO
C5: Private Equity | D5: x | E5: =SUM(E6:E9) -> 20.999749 | F5: =SUM(F6:F9) -> 20.999749 | G5: =SUM(G6:G8) -> 0.51604502
C6: Integris | D6: 45631 | E6: =1599.9746265/(10^2) -> 15.999746 | F6: =1599.9746265/(10^2) -> 15.999746 | G6: 0.39317563 | H6: Filed for IPO | I6: Pre Ipo
C7: ESDS | D7: 45544 | E7: =500.00024/(10^2) -> 5.0000024 | F7: =500.00024/(10^2) -> 5.0000024 | G7: 0.12286939 | H7: Filed for IPO | I7: Pre Ipo

Sheet Transactions since inception
B2: Live File transactions since Inception upto 30th June'26
B3: *Purchase has been shown as a Negative number
B4: Investor | C4: Advisor | D4: Asset Class | E4: Category | F4: Product | G4: Transaction | H4: Date | I4: Quantity | J4: Rate | K4: Value
B5: Aarti Ajay Jaisinghani | C5: MOPWM | D5: Alternate | E5: Gold | F5: DSP Gold ETF | G5: Purchase | H5: 46051 | I5: 1056498 | J5: 170.99054 | K5: -1.8065116e+08
B6: Aarti Ajay Jaisinghani | C6: MOPWM | D6: Alternate | E6: Gold | F6: DSP Gold ETF | G6: Purchase | H6: 46052 | I6: 138502 | J6: 166.29107 | K6: -23031645
B7: Aarti Ajay Jaisinghani | C7: MOPWM | D7: Alternate | E7: Gold | F7: DSP Gold ETF | G7: Closing | H7: 46203 | I7: 1195000 | J7: 136.4629 | K7: 1.6307317e+08
B8: Ajay Jaisinghani | C8: MOPWM | D8: Alternate | E8: Gold | F8: DSP Gold ETF | G8: Purchase | H8: 46041 | I8: 1800000 | J8: 139.94444 | K8: -251900000
B9: Ajay Jaisinghani | C9: MOPWM | D9: Alternate | E9: Gold | F9: DSP Gold ETF | G9: Purchase | H9: 46044 | I9: 340000 | J9: 147.28774 | K9: -50077831
B10: Ajay Jaisinghani | C10: MOPWM | D10: Alternate | E10: Gold | F10: DSP Gold ETF | G10: Closing | H10: 46203 | I10: 2140000 | J10: 136.4629 | K10: 292030606
B11: Ankita Jaisinghani | C11: MOPWM | D11: Alternate | E11: Gold | F11: DSP Gold ETF | G11: Purchase | H11: 46044 | I11: 205000 | J11: 147.28634 | K11: -30193699
B12: Ankita Jaisinghani | C12: MOPWM | D12: Alternate | E12: Gold | F12: DSP Gold ETF | G12: Closing | H12: 46203 | I12: 205000 | J12: 136.4629 | K12: 27974894
B13: Ajay Jaisinghani | C13: L&T Financial | D13: Alternate | E13: PE Funds | F13: 360 One Special Opportunities Fund - Series 8 - Class A3 (AIF Category II) | G13: Purchase | H13: 44308 | I13: 999950 | J13: 10 | K13: -9999500
B14: Ajay Jaisinghani | C14: L&T Financial | D14: Alternate | E14: PE Funds | F14: 360 One Special Opportunities Fund - Series 8 - Class A3 (AIF Category II) | G14: Div / Int | H14: 44651 | K14: 18908
B15: Ajay Jaisinghani | C15: L&T Financial | D15: Alternate | E15: PE Funds | F15: 360 One Special Opportunities Fund - Series 8 - Class A3 (AIF Category II) | G15: Div / Int | H15: 45016 | K15: 14547
B16: Ajay Jaisinghani | C16: L&T Financial | D16: Alternate | E16: PE Funds | F16: 360 One Special Opportunities Fund - Series 8 - Class A3 (AIF Category II) | G16: Sale | H16: 45412 | I16: 5751.2961 | J16: 13.6178 | K16: 78320
B17: Ajay Jaisinghani | C17: L&T Financial | D17: Alternate | E17: PE Funds | F17: 360 One Special Opportunities Fund - Series 8 - Class A3 (AIF Category II) | G17: Div / Int | H17: 45470 | K17: 1150402
B18: Ajay Jaisinghani | C18: L&T Financial | D18: Alternate | E18: PE Funds | F18: 360 One Special Opportunities Fund - Series 8 - Class A3 (AIF Category II) | G18: Div / Int | H18: 46160 | K18: 715619
B19: Ajay Jaisinghani | C19: L&T Financial | D19: Alternate | E19: PE Funds | F19: 360 One Special Opportunities Fund - Series 8 - Class A3 (AIF Category II) | G19: Closing | H19: 46203 | I19: 990429.68 | J19: 15.06 | K19: 14580413
B20: Bharat Jaisinghani | C20: L&T Financial | D20: Alternate | E20: PE Funds | F20: 360 One Special Opportunities Fund - Series 8 - Class A3 (AIF Category II) | G20: Purchase | H20: 44308 | I20: 999950 | J20: 10 | K20: -9999500
B21: Bharat Jaisinghani | C21: L&T Financial | D21: Alternate | E21: PE Funds | F21: 360 One Special Opportunities Fund - Series 8 - Class A3 (AIF Category II) | G21: Div / Int | H21: 44651 | K21: 18908
B22: Bharat Jaisinghani | C22: L&T Financial | D22: Alternate | E22: PE Funds | F22: 360 One Special Opportunities Fund - Series 8 - Class A3 (AIF Category II) | G22: Div / Int | H22: 45016 | K22: 14547
B23: Bharat Jaisinghani | C23: L&T Financial | D23: Alternate | E23: PE Funds | F23: 360 One Special Opportunities Fund - Series 8 - Class A3 (AIF Category II) | G23: Sale | H23: 45412 | I23: 5751.2961 | J23: 13.6178 | K23: 78320
B24: Bharat Jaisinghani | C24: L&T Financial | D24: Alternate | E24: PE Funds | F24: 360 One Special Opportunities Fund - Series 8 - Class A3 (AIF Category II) | G24: Div / Int | H24: 45470 | K24: 1150402
B25: Bharat Jaisinghani | C25: L&T Financial | D25: Alternate | E25: PE Funds | F25: 360 One Special Opportunities Fund - Series 8 - Class A3 (AIF Category II) | G25: Div / Int | H25: 46160 | K25: 715619
B26: Bharat Jaisinghani | C26: L&T Financial | D26: Alternate | E26: PE Funds | F26: 360 One Special Opportunities Fund - Series 8 - Class A3 (AIF Category II) | G26: Closing | H26: 46203 | I26: 990429.68 | J26: 15.06 | K26: 14580413
B27: Ajay Jaisinghani | C27: ICICI Bank | D27: Alternate | E27: PE Funds | F27: Assetgro Fintech Private Limited | G27: Purchase | H27: 45987 | I27: 636 | J27: 78668 | K27: -50032848
B28: Ajay Jaisinghani | C28: ICICI Bank | D28: Alternate | E28: PE Funds | F28: Assetgro Fintech Private Limited | G28: Closing | H28: 46203 | I28: 0 | J28: 78668 | K28: 50032848
B29: Ankita Jaisinghani | C29: MOPWM | D29: Alternate | E29: PE Funds | F29: Baring PE India Fund 6 | G29: Purchase | H29: 45568 | I29: 65 | J29: 100000 | K29: -6500000
B30: Ankita Jaisinghani | C30: MOPWM | D30: Alternate | E30: PE Funds | F30: Baring PE India Fund 6 | G30: Purchase | H30: 45631 | I30: 50 | J30: 100000 | K30: -5000000
B31: Ankita Jaisinghani | C31: MOPWM | D31: Alternate | E31: PE Funds | F31: Baring PE India Fund 6 | G31: Purchase | H31: 45860 | I31: 25 | J31: 100000 | K31: -2500000
B32: Ankita Jaisinghani | C32: MOPWM | D32: Alternate | E32: PE Funds | F32: Baring PE India Fund 6 | G32: Purchase | H32: 45925 | I32: 62.5 | J32: 100000 | K32: -6250000
B33: Ankita Jaisinghani | C33: MOPWM | D33: Alternate | E33: PE Funds | F33: Baring PE India Fund 6 | G33: Div / Int | H33: 45930 | I33: 62.5 | K33: 2046
B34: Ankita Jaisinghani | C34: MOPWM | D34: Alternate | E34: PE Funds | F34: Baring PE India Fund 6 | G34: Div / Int | H34: 45930 | I34: 62.5 | K34: 18909
B35: Ankita Jaisinghani | C35: MOPWM | D35: Alternate | E35: PE Funds | F35: Baring PE India Fund 6 | G35: Div / Int | H35: 46022 | I35: 62.5 | K35: 83
B36: Ankita Jaisinghani | C36: MOPWM | D36: Alternate | E36: PE Funds | F36: Baring PE India Fund 6 | G36: Div / Int | H36: 46112 | I36: 62.5 | K36: 121829
B37: Ankita Jaisinghani | C37: MOPWM | D37: Alternate | E37: PE Funds | F37: Baring PE India Fund 6 | G37: Closing | H37: 46112 | I37: 202.5 | J37: 93047.944 | K37: 18842209
B38: Ajay Jaisinghani | C38: ICICI Bank | D38: Alternate | E38: PE Funds | F38: India SME | G38: Purchase | H38: 45546 | I38: 15000 | J38: 1000 | K38: -15000000
B39: Ajay Jaisinghani | C39: ICICI Bank | D39: Alternate | E39: PE Funds | F39: India SME | G39: Purchase | H39: 45582 | I39: 7500 | J39: 1000 | K39: -7500000
B40: Ajay Jaisinghani | C40: ICICI Bank | D40: Alternate | E40: PE Funds | F40: India SME | G40: Purchase | H40: 45625 | I40: 7500 | J40: 1000 | K40: -7500000
B41: Ajay Jaisinghani | C41: ICICI Bank | D41: Alternate | E41: PE Funds | F41: India SME | G41: Div / Int | H41: 45746 | K41: 121437
B42: Ajay Jaisinghani | C42: ICICI Bank | D42: Alternate | E42: PE Funds | F42: India SME | G42: Div / Int | H42: 45746 | K42: 40479
B43: Ajay Jaisinghani | C43: ICICI Bank | D43: Alternate | E43: PE Funds | F43: India SME | G43: Purchase | H43: 45852 | I43: 15000 | J43: 1000 | K43: -15000000
B44: Ajay Jaisinghani | C44: ICICI Bank | D44: Alternate | E44: PE Funds | F44: India SME | G44: Purchase | H44: 45924 | I44: 9000 | J44: 1000 | K44: -9000000
B45: Ajay Jaisinghani | C45: ICICI Bank | D45: Alternate | E45: PE Funds | F45: India SME | G45: Purchase | H45: 46022 | K45: -6000000
B46: Ajay Jaisinghani | C46: ICICI Bank | D46: Alternate | E46: PE Funds | F46: India SME | G46: Purchase | H46: 46066 | K46: -7500000
B47: Ajay Jaisinghani | C47: ICICI Bank | D47: Alternate | E47: PE Funds | F47: India SME | G47: Purchase | H47: 46104 | K47: -13500000
B48: Ajay Jaisinghani | C48: ICICI Bank | D48: Alternate | E48: PE Funds | F48: India SME | G48: Div / Int | H48: 46112 | K48: 122091
B49: Ajay Jaisinghani | C49: ICICI Bank | D49: Alternate | E49: PE Funds | F49: India SME | G49: Closing | H49: 46112 | I49: 54000 | J49: 1000 | K49: 95580000
B50: Ankita Jaisinghani | C50: Private Investments | D50: Alternate | E50: PE Funds | F50: India SME | G50: Purchase | H50: 45582 | I50: 7500 | J50: 1000 | K50: -7500000
B51: Ankita Jaisinghani | C51: Private Investments | D51: Alternate | E51: PE Funds | F51: India SME | G51: Purchase | H51: 45625 | I51: 2500 | J51: 1000 | K51: -2500000
B52: Ankita Jaisinghani | C52: Private Investments | D52: Alternate | E52: PE Funds | F52: India SME | G52: Purchase | H52: 45625 | I52: 5000 | J52: 1000 | K52: -5000000
B53: Ankita Jaisinghani | C53: Private Investments | D53: Alternate | E53: PE Funds | F53: India SME | G53: Purchase | H53: 45924 | I53: 3000 | J53: 1000 | K53: -3000000
B54: Ankita Jaisinghani | C54: Private Investments | D54: Alternate | E54: PE Funds | F54: India SME | G54: Purchase | H54: 46022 | K54: -2000000
B55: Ankita Jaisinghani | C55: Private Investments | D55: Alternate | E55: PE Funds | F55: India SME | G55: Purchase | H55: 46066 | K55: -2500000
B56: Ankita Jaisinghani | C56: Private Investments | D56: Alternate | E56: PE Funds | F56: India SME | G56: Purchase | H56: 46105 | K56: -4500000
B57: Ankita Jaisinghani | C57: Private Investments | D57: Alternate | E57: PE Funds | F57: India SME | G57: Div / Int | H57: 46112 | K57: 40697
B58: Ankita Jaisinghani | C58: Private Investments | D58: Alternate | E58: PE Funds | F58: India SME | G58: Closing | H58: 46112 | I58: 18000 | J58: 1000 | K58: 31860000
B59: Bharat Jaisinghani | C59: Private Investments | D59: Alternate | E59: PE Funds | F59: India SME | G59: Purchase | H59: 45546 | I59: 5000 | J59: 1000 | K59: -5000000
B60: Bharat Jaisinghani | C60: Private Investments | D60: Alternate | E60: PE Funds | F60: India SME | G60: Purchase | H60: 45579 | I60: 2500 | J60: 1000 | K60: -2500000
B61: Bharat Jaisinghani | C61: Private Investments | D61: Alternate | E61: PE Funds | F61: India SME | G61: Purchase | H61: 45625 | I61: 2500 | J61: 1000 | K61: -2500000
B62: Bharat Jaisinghani | C62: Private Investments | D62: Alternate | E62: PE Funds | F62: India SME | G62: Div / Int | H62: 45746 | K62: 40479
B63: Bharat Jaisinghani | C63: Private Investments | D63: Alternate | E63: PE Funds | F63: India SME | G63: Purchase | H63: 45852 | I63: 5000 | J63: 1000 | K63: -5000000
B64: Bharat Jaisinghani | C64: Private Investments | D64: Alternate | E64: PE Funds | F64: India SME | G64: Purchase | H64: 45924 | I64: 3000 | J64: 1000 | K64: -3000000
B65: Bharat Jaisinghani | C65: Private Investments | D65: Alternate | E65: PE Funds | F65: India SME | G65: Purchase | H65: 46022 | K65: -2000000
B66: Bharat Jaisinghani | C66: Private Investments | D66: Alternate | E66: PE Funds | F66: India SME | G66: Purchase | H66: 46066 | K66: -2500000
B67: Bharat Jaisinghani | C67: Private Investments | D67: Alternate | E67: PE Funds | F67: India SME | G67: Purchase | H67: 46107 | K67: -4500000
B68: Bharat Jaisinghani | C68: Private Investments | D68: Alternate | E68: PE Funds | F68: India SME | G68: Div / Int | H68: 46112 | K68: 40697
B69: Bharat Jaisinghani | C69: Private Investments | D69: Alternate | E69: PE Funds | F69: India SME | G69: Closing | H69: 46112 | I69: 18000 | J69: 1000 | K69: 31860000
B70: Ajay Jaisinghani | C70: Sky Capital | D70: Alternate | E70: PE Funds | F70: Sky Capital Titan Rising Funds 1 | G70: Purchase | H70: 46056 | K70: -15000000
B71: Ajay Jaisinghani | C71: Sky Capital | D71: Alternate | E71: PE Funds | F71: Sky Capital Titan Rising Funds 1 | G71: Closing | H71: 46112 | I71: 15000 | J71: 1000 | K71: 15000000
B72: Bharat Jaisinghani | C72: Sky Capital | D72: Alternate | E72: PE Funds | F72: Sky Capital Titan Rising Funds 1 | G72: Purchase | H72: 45786 | K72: -5000000
B73: Bharat Jaisinghani | C73: Sky Capital | D73: Alternate | E73: PE Funds | F73: Sky Capital Titan Rising Funds 1 | G73: Purchase | H73: 45791 | K73: -5000000
B74: Bharat Jaisinghani | C74: Sky Capital | D74: Alternate | E74: PE Funds | F74: Sky Capital Titan Rising Funds 1 | G74: Purchase | H74: 45812 | K74: -3000000
B75: Bharat Jaisinghani | C75: Sky Capital | D75: Alternate | E75: PE Funds | F75: Sky Capital Titan Rising Funds 1 | G75: Purchase | H75: 45862 | K75: -4000000
B76: Bharat Jaisinghani | C76: Sky Capital | D76: Alternate | E76: PE Funds | F76: Sky Capital Titan Rising Funds 1 | G76: Purchase | H76: 45925 | K76: -150000
B77: Bharat Jaisinghani | C77: Sky Capital | D77: Alternate | E77: PE Funds | F77: Sky Capital Titan Rising Funds 1 | G77: Closing | H77: 46112 | I77: 17000 | J77: 1000 | K77: 17150000
B78: Bharat Jaisinghani Family Trust II | C78: Sky Capital | D78: Alternate | E78: PE Funds | F78: Sky Capital Titan Rising Funds 1 | G78: Purchase | H78: 46056 | I78: 7500 | J78: 1000 | K78: -7500000
B79: Bharat Jaisinghani Family Trust II | C79: Sky Capital | D79: Alternate | E79: PE Funds | F79: Sky Capital Titan Rising Funds 1 | G79: Closing | H79: 46112 | I79: 7500 | J79: 1000 | K79: 7500000
B80: Bharat Jaisinghani Family Trust III | C80: Sky Capital | D80: Alternate | E80: PE Funds | F80: Sky Capital Titan Rising Funds 1 | G80: Purchase | H80: 46056 | I80: 7500 | J80: 1000 | K80: -7500000
B81: Bharat Jaisinghani Family Trust III | C81: Sky Capital | D81: Alternate | E81: PE Funds | F81: Sky Capital Titan Rising Funds 1 | G81: Closing | H81: 46112 | I81: 7500 | J81: 1000 | K81: 7500000
B82: Ankita Jaisinghani | C82: Private Investments | D82: Alternate | E82: PE Funds | F82: Transition Venture Capital fund I | G82: Purchase | H82: 45870 | I82: 2500 | J82: 1000 | K82: -2500000
B83: Ankita Jaisinghani | C83: Private Investments | D83: Alternate | E83: PE Funds | F83: Transition Venture Capital fund I | G83: Closing | H83: 46081 | I83: 2500 | J83: 1314.3508 | K83: 3285877
B84: Bharat Jaisinghani Family Trust II | C84: Private Investments | D84: Alternate | E84: PE Funds | F84: Transition Venture Capital fund I | G84: Purchase | H84: 45947 | I84: 7500 | J84: 1000 | K84: -7500000
B85: Bharat Jaisinghani Family Trust II | C85: Private Investments | D85: Alternate | E85: PE Funds | F85: Transition Venture Capital fund I | G85: Closing | H85: 46081 | I85: 7500 | J85: 1290.7672 | K85: 9680754
B86: Bharat Jaisinghani Family Trust III | C86: Private Investments | D86: Alternate | E86: PE Funds | F86: Transition Venture Capital fund I | G86: Purchase | H86: 45947 | I86: 7500 | J86: 1000 | K86: -7500000
B87: Bharat Jaisinghani Family Trust III | C87: Private Investments | D87: Alternate | E87: PE Funds | F87: Transition Venture Capital fund I | G87: Closing | H87: 46081 | I87: 7500 | J87: 1290.7672 | K87: 9680754
B88: Ajay Jaisinghani | C88: MOPWM Reg | D88: Alternate | E88: Silver | F88: DSP Silver ETF | G88: Purchase | H88: 45930 | I88: 358000 | J88: 139.99917 | K88: -50119704
... B93: Ankita Jaisinghani | C93: MOPWM Reg | D93: Alternate | E93: Silver | F93: DSP Silver ETF | G93: Closing | H93: 46203 | I93: 123000 | J93: 215.2948 | K93: 26481260
B94: Aarti Ajay Jaisinghani | C94: MOPWM | D94: Cash | E94: Bank Balance | F94: Bank Balance | G94: Purchase | H94: 46203 | K94: 0
B95: Aarti Ajay Jaisinghani | C95: MOPWM | D95: Cash | E95: Bank Balance | F95: Bank Balance | G95: Closing | H95: 46203 | K95: 0
B96: Ajay Jaisinghani | C96: MOPWM | D96: Cash | E96: Bank Balance | F96: Bank Balance | G96: Purchase | H96: 46203 | K96: 0
B97: Ajay Jaisinghani | C97: MOPWM | D97: Cash | E97: Bank Balance | F97: Bank Balance | G97: Closing | H97: 46203 | K97: 0
B98: Ankita Jaisinghani | C98: MOPWM | D98: Cash | E98: Bank Balance | F98: Bank Balance | G98: Purchase | H98: 46203 | K98: 0
B99: Ankita Jaisinghani | C99: MOPWM | D99: Cash | E99: Bank Balance | F99: Bank Balance | G99: Closing | H99: 46203 | K99: 0
B100: Bharat Jaisinghani | C100: MOPWM | D100: Cash | E100: Bank Balance | F100: Bank Balance | G100: Purchase | H100: 46203 | K100: 0
B101: Bharat Jaisinghani | C101: MOPWM | D101: Cash | E101: Bank Balance | F101: Bank Balance | G101: Closing | H101: 46203 | K101: 0
B102: HOPE INDIA TRUST | C102: MOPWM | D102: Cash | E102: Bank Balance | F102: Bank Balance | G102: Purchase | H102: 46203 | K102: 0
B103: HOPE INDIA TRUST | C103: MOPWM | D103: Cash | E103: Bank Balance | F103: Bank Balance | G103: Closing | H103: 46203 | K103: 0
B104: Aarti Ajay Jaisinghani | C104: MOPWM | D104: Cash | E104: Ledger Balance | F104: Ledger Balance | G104: Purchase | H104: 46203 | K104: 0
B105: Aarti Ajay Jaisinghani | C105: MOPWM | D105: Cash | E105: Ledger Balance | F105: Ledger Balance | G105: Closing | H105: 46203 | K105: 0
...

Sheet Transactions all Asset class
B1: Equity
B2: Redemptions from 31st May 2026 to 30th June'2026 | H2: Purchases from 31st May 2026 to 30th June'2026
B3: Investor | C3: Date | D3: Category | E3: Fund Name | F3: Sale | H3: Investor | I3: Date | J3: Category | K3: Fund Name | L3: Purchase
B4: Bharat Jaisinghani | C4: 46188 | D4: LKP Sec Portfolio | E4: Capri Global Capital Pvt Ltd | F4: 0.076062 | H4: Ajay Jaisinghani | I4: 46174 | J4: Multi Cap | K4: Buoyant Opportunities Portfolio AIF | L4: 25
B5: Bharat Jaisinghani | C5: 46192 | D5: LKP Sec Portfolio | E5: Capri Global Capital Pvt Ltd | F5: 0.0785925 | H5: Ajay Jaisinghani | I5: 46177 | J5: Multi Cap | K5: Bandhan Large & Mid Cap Fund - Direct Plan - Growth | L5: 1.8749063
B6: Ankita Jaisinghani | C6: 46195 | D6: Equity Hybrid | E6: HDFC Balanced Advantage Fund | F6: 3.3040294 | H6: Ajay Jaisinghani | I6: 46184 | J6: Multi Cap | K6: Bandhan Large & Mid Cap Fund - Direct Plan - Growth | L6: 1.8749063
B7: Bharat Jaisinghani | C7: 46195 | D7: Equity Hybrid | E7: ICICI Pru Balanced Advantage Fund | F7: 1.0035851 | H7: Ajay Jaisinghani | I7: 46190 | J7: Direct Equity - Non MO | K7: MPS | L7: 0.51789155
B8: Ankita Jaisinghani | C8: 46195 | D8: Equity Hybrid | E8: ICICI Pru Balanced Advantage Fund | F8: 4.7241341 | H8: Ajay Jaisinghani | I8: 46190 | J8: Direct Equity - Non MO | K8: NLC INDIA | L8: 1.0034019
B9: Ajay Jaisinghani | C9: 46197 | D9: Direct Equity - Non MO | E9: Yash High Voltage Ltd. | F9: 1.000012 | H9: Ajay Jaisinghani | I9: 46191 | J9: Direct Equity - Non MO | K9: MPS | L9: 0.36817016
B10: Ajay Jaisinghani | C10: 46197 | D10: Equity Hybrid | E10: ICICI Prudential Equity Savings Fund - Direct Plan | F10: 4.3103739 | H10: Ajay Jaisinghani | I10: 46191 | J10: Multi Cap | K10: Bandhan Large & Mid Cap Fund - Direct Plan - Growth | L10: 1.8749063
B11: Ajay Jaisinghani | C11: 46198 | D11: Direct Equity - Non MO | E11: Yash High Voltage Ltd. | F11: 1.000012 | H11: Ajay Jaisinghani | I11: 46198 | J11: Multi Cap | K11: Bandhan Large & Mid Cap Fund - Direct Plan - Growth | L11: 1.8749063
B12: Bharat Jaisinghani | C12: 46198 | D12: LKP Sec Portfolio | E12: Belrise Industries | F12: 0.1508976
B13: Ankita Jaisinghani | C13: 46202 | D13: Multi Cap | E13: HDFC Capital Builder Value Fund | F13: 3.3278911
B14: Ankita Jaisinghani | C14: 46202 | D14: Multi Cap | E14: HDFC Capital Builder Value Fund | F14: 0.5073839
B15: Ajay Jaisinghani | C15: 46202 | D15: Multi Cap | E15: HDFC Capital Builder Value Fund | F15: 3.9526521
B16: Ajay Jaisinghani | C16: 46202 | D16: Multi Cap | E16: HDFC Capital Builder Value Fund | F16: 0.85170102
B17: Ajay Jaisinghani | C17: 46202 | D17: Multi Cap | E17: ICICI Pru India Opportunities Fund | F17: 3.6962218
B18: Ajay Jaisinghani | C18: 46202 | D18: Multi Cap | E18: ICICI Pru India Opportunities Fund | F18: 1.0250608
B19: Ankita Jaisinghani | C19: 46202 | D19: Multi Cap | E19: ICICI Pru India Opportunities Fund | F19: 0.92550869
B20: Bharat Jaisinghani | C20: 46202 | D20: Multi Cap | E20: ICICI Pru India Opportunities Fund | F20: 0.2909386
B21: Ajay Jaisinghani | C21: 46203 | D21: Direct Equity - Non MO | E21: Yash High Voltage Ltd. | F21: 1.000012
B22: Bharat Jaisinghani | C22: 46203 | D22: Multi Cap | E22: HDFC Capital Builder Value Fund | F22: 0.96253226
A24: Debt
B25: Redemptions from 31st May 2026 to 13th July'2026 | H25: Purchases from 31st May 2026 to 13th July'2026
B26: Investor | C26: Date | D26: Category | E26: Fund Name | F26: Sale | H26: Investor | I26: Date | J26: Category | K26: Fund Name | L26: Purchase
B27: Ajay Jaisinghani | C27: 46175 | D27: Arbitrage | E27: Motilal Oswal Arbitrage Direct-G | F27: =31220025.06/(10^7) -> 3.1220025 | H27: Ajay Jaisinghani | I27: 46178 | J27: Liquid | K27: HDFC Liquid Direct-G | L27: =12499375.94/(10^7) -> 1.2499376
B28: Ajay Jaisinghani | C28: 46182 | D28: Arbitrage | E28: Motilal Oswal Arbitrage Direct-G | F28: =18721747.52/(10^7) -> 1.8721748 | H28: Bharat Jaisinghani | I28: 46204 | J28: Liquid | K28: Aditya Birla SL Liquid Direct-G | L28: =119994000.19/(10^7) -> 11.9994
B29: Ajay Jaisinghani | C29: 46189 | D29: Arbitrage | E29: Motilal Oswal Arbitrage Direct-G | F29: =18757606.01/10^7 -> 1.8757606 | H29: Ajay Jaisinghani | I29: 46205 | J29: Arbitrage | K29: Bandhan Arbitrage Direct-G | L29: =149992500.38/(10^7) -> 14.99925
B30: Ajay Jaisinghani | C30: 46196 | D30: Arbitrage | E30: Motilal Oswal Arbitrage Direct-G | F30: =18761810.28/(10^7) -> 1.876181 | H30: Ajay Jaisinghani | I30: 46205 | J30: Liquid | K30: Bandhan Overnight Direct-G | L30: =49997500.58/(10^7) -> 4.9997501
B31: Ajay Jaisinghani | C31: 46203 | D31: Arbitrage | E31: Motilal Oswal Arbitrage Direct-G | F31: =18746289.4/(10^7) -> 1.8746289 | H31: Ajay Jaisinghani | I31: 46205 | J31: Arbitrage | K31: Kotak Arbitrage Direct-G | L31: =177991100.44/(10^7) -> 17.79911
B32: Ajay Jaisinghani | C32: 46210 | D32: Liquid | E32: BANDHAN Overnight Fund - Direct Plan - Growth | F32: 2.5 | H32: Aarti Jaisinghani | I32: 46206 | J32: Liquid | K32: Nippon India ETF Nifty 1D Rate Liquid BeES-IDCWD Reinvestment | L32: =2488491.15/(10^7) -> 0.24884911
H33: Ankita Jaisinghani | I33: 46206 | J33: Liquid | K33: Nippon India ETF Nifty 1D Rate Liquid BeES-IDCWD Reinvestment | L33: =250049.35/(10^7) -> 0.025004935
B37: Redemptions from 31st May 2026 to 30th June'2026 | H37: Purchases from 31st May 2026 to 30th June'2026
B38: Investor | C38: Date | D38: Category | E38: Fund Name | F38: Sale | H38: Investor | I38: Date | J38: Category | K38: Fund Name | L38: Purchase
A40: Alternate
B42: Redemptions from 31st May 2026 to 30th June'2026 | H42: Purchases from 31st May 2026 to 30th June'2026
B43: Investor | C43: Date | D43: Category | E43: Fund Name | F43: Sale | H43: Investor | I43: Date | J43: Category | K43: Fund Name | L43: Purchase
A45: Private Equity

Sheet Equity Scheme details
B2: Product
B3: Multi Cap | C3: Fund Manager | D3: AUM (in Crs) | E3: Investment Style | F3: Regular expense ratio | G3: Direct Expense Ratio | H3: Management fee | I3: Exit Load | J3: Lock in / No Lock in
B4: Motilal Oswal Founders Fund II | C4: Vaibhav Agarwal | D4: 1248 | E4: Growth | F4: -- | G4: -- | H4: 0.0105 | I4: 3%- 36 to 48 months, 2%- 48 to 60 months, nil thereafter | J4: Locked in
B5: Carnelian Bespoke Portfolio | C5: Manoj Bahety | D5: 2742 | E5: GARP | F5: -- | G5: -- | H5: 0.025 | I5: 1st Year-3,% 2nd Year-2%, 3rd Year-1% | J5: No lock in
B6: Buoyant Opportunities Portfolio AIF A1 | C6: Jigar Mistry | D6: 189737.65 | E6: GARP | F6: -- | G6: -- | H6: 0.015 | I6: No exit load | J6: No lock in
B7: 3P India Equity Fund 1 | C7: Prashant Jain | D7: 23050 | E7: GARP | F7: -- | G7: -- | H7: 0.7% - wef 01/04/2026 | I7: No exit load | J7: No lock in
B8: Aristos Equity Potrfolio - SB | C8: NA | D8: NA | E8: NA | F8: -- | G8: -- | H8: NA | I8: NA | J8: No lock in
B9: Green Lantern Growth Strategy | C9: Abhishek Bharadwaj | D9: 1242 | E9: NA | F9: -- | G9: Mgmt Fee-1.5%, Performance fee-10%,set up fee-0.15% | H9: NA | I9: NA | J9: No lock in
B10: Helios Flexi Cap Fund Direct (G) | C10: Alok Bahl,Pratik Singh | D10: 6211.4513 | E10: Growth | F10: 1.78 | G10: 0.51 | H10: -- | I10: Nil upto 10% of units and 1% for remaining units on or before 3M, Nil after 3M | J10: No lock in
B11: ICICI Pru India Opportunities Fund | C11: Sankaran Naren | D11: 35665.816 | E11: Blended | F11: 1.56 | G11: 0.67 | H11: -- | I11: 1% on or before 12M, Nil after 12M | J11: No lock in
B12: Kotak Large & Midcap Fund | C12: Harsha Upadhyaya | D12: 30712.48 | E12: GARP | F12: -- | G12: 0.55 | H12: -- | I12: Nil upto 10% of investment and 1% for remaining investment on or before 1Y, Nil after 1Y | J12: No lock in
B13: Fund of Funds (VEC+ Carnelian+Girik Cap+Insightful) | C13: Nitin Shanbag | D13: 20339 | E13: Blended | F13: -- | G13: -- | H13: 0.0127 | J13: No lock in
B14: Carnelian Bharat Amritkaal Fund | C14: Vikas Khemani, Manoj Bahety | D14: 15400 | E14: GARP | F14: -- | G14: -- | H14: 0.02 | I14: 12months-2%, nil thereafter | J14: Locked in
B15: Bandhan Large & Midcap Fund | C15: Manish Gunwani | D15: 16671.94 | E15: GARP | F15: -- | G15: 1.29 | H15: -- | I15: Nil upto 10% of investment and 1% for remaining investment on or before 365D, Nil after 365D | J15: No lock in
B16: Kotak Multi Cap fund | C16: Devender Singhal | D16: 25768.715 | E16: GARP | F16: -- | G16: 0.52 | H16: -- | I16: Nil upto 10% of investment and 1% for remaining investments on or before 1Y, Nil after 1Y | J16: No lock in
B17: HDFC Capital Builder Value Fund | C17: Anand Laddha | D17: 7413.0332 | E17: Value | F17: 1.84 | G17: 1.01 | H17: -- | I17: 1% on or before 1Y, Nil after 1Y | J17: No lock in
B18: Large Cap
B19: Motilal Oswal Nifty 200 Momentum 30 ETF | C19: Swapnil P Mayekar | D19: 110.7579 | E19: Growth | F19: 0.36 | G19: -- | I19: - | J19: No lock in
B20: Mid & Small Cap | G20: 0
B21: Svan Investment | C21: Sachin Kasera | D21: 256.6 | E21: NA | F21: -- | G21: -- | H21: Performance fee-14% Plus GST Profit | I21: No exit load | J21: No lock in
B22: Sanshi Fund 1 | C22: Saranya Agarwal | D22: NA | E22: NA | F22: -- | G22: -- | H22: Mgmt Fee-0.5%,Operatimg Fee-0.5%,Performance Fee-20%,set up fee -2% | I22: -- | J22: Locked in
B23: VEC Small and Mid cap fund | C23: Arun Mehra | D23: 1123 | E23: NA | F23: -- | G23: -- | H23: NA | I23: NA | J23: No lock in
B24: Equity Hybrid | G24: 0
B25: Aditya Birla SL Balanced Advantage Fund(G) | C25: Mohit Sharma | D25: 9103.6886 | E25: Blended | F25: 1.77 | G25: 0.67 | H25: -- | I25: 0.25% on or before 7D, Nil after 7D | J25: No lock in
B26: HDFC Balanced Advantage Fund | C26: Gopal Agrawal | D26: 107589.67 | E26: Blended | F26: 1.35 | G26: 0.75 | H26: -- | I26: Nil upto 15% of Units, For excess Units 1% on or before 1Y and Nil after 1Y | J26: No lock in
B27: ICICI Pru Balanced Advantage Fund | C27: Rajat Chandak | D27: 71150.75 | E27: Blended | F27: 1.43 | G27: 0.88 | H27: -- | I27: Nil upto 30% of units and 1% for remaining units on or before 1Y, Nil after 1Y | J27: No lock in
B28: Small Cap | G28: 0
B29: Molecule Growth Strategy | C29: Nirav Parikh | D29: 777 | E29: NA | G29: 0 | H29: Performance fee-15% of profit with 8% catch up | I29: NA | J29: No lock in

Sheet Plan of Action - Equity
A1: Scheme Name | B1: Recommendation
A2: Buoyant Opportunities Portfolio AIF A1 | B2: Add 10 Cr
A3: 3P India Equity Fund 1 - B1 | B3: Add 8 Cr
A4: Abakkus Personalised Opportunity Specific Strategy | B4: Exit
A5: Green Lantern Growth Strategy | B5: Exit
A6: Helios Flexi Cap Fund Direct (G) | B6: Add 10 Cr
A7: Invesco India Contra Fund | B7: Exit
A8: ICICI Pru India Opportunities Fund | B8: Add 16 Cr
A9: 360 One Flexicap Direct (G) | B9: Exit
A10: Kotak Equity Opportunities Fund | B10: Exit
A11: Molecule Growth Strategy | B11: Exit
A12: Kotak Emerging Equity Scheme-Direct (G) | B12: Exit
... A14: WhiteSpace Alpha Equity Plus (Fund 1) | B14: Exit
