Workbook

Sheet Start Here
B1: Consolidated Client Data Template
B2: One workbook for any client's portfolio: the registers hold the data in one standard shape, the views present it the way the family reads it.
B3: DEMO DATA — illustrative only: a fictional family, fictional securities and figures.
B5: SETTINGS
B6: Client / family name | C6: Malhotra Family Office (DEMO) | D6: Printed at the top of every view.
B7: Valuation date | C7: 46203 | D7: The date the market values are struck at.
B8: Previous valuation date | C8: 46112 | D8: Start of the window the Period Change view measures.
B9: Show figures in | C9: ₹ Crore | D9: ₹ Crore, ₹ Lakh or ₹. The registers always hold full rupees.
B10: Divide ₹ by | C10: =IFERROR(INDEX(L_UnitDiv,MATCH(UnitLabel,L_Unit,0)),1) -> 10000000 | D10: Set by 'Show figures in'; every view divides by it.
B11: Grandfathering date (s.112A) | C11: 43131 | D11: Listed equity bought on or before this date is taxed from its FMV on this date.
B12: Overall status | C12: =OverallStatus -> ALL CHECKS PASS · 6 note(s) to read | D12: =HYPERLINK("#'Checks'!A1","Open the Checks sheet →") -> Open the Checks sheet →
B14: WHAT IS IN THIS WORKBOOK — click a name to open it
B15: =HYPERLINK("#'Portfolio Allocation'!A1","Portfolio Allocation") -> Portfolio Allocation | C15: View | D15: What the family owns by asset class and category: cost, value, allocation, gains and returns against the benchmark.
B16: =HYPERLINK("#'Basket Allocation'!A1","Basket Allocation") -> Basket Allocation | C16: View | D16: Stable Growth, Entrepreneurial Growth, Liquidity, Thematic & Tactical against the family's targets.
B17: =HYPERLINK("#'Basket Detail'!A1","Basket Detail") -> Basket Detail | C17: View | D17: Every holding in each basket, largest first, with its return.
B18: =HYPERLINK("#'Investor Summary'!A1","Investor Summary") -> Investor Summary | C18: View | D18: Each entity's money by category, and its share of that entity's portfolio.
B19: =HYPERLINK("#'Period Change'!A1","Period Change") -> Period Change | C19: View | D19: What moved since the previous valuation date: invested, redeemed, market gain, income.
B20: =HYPERLINK("#'Tax Summary'!A1","Tax Summary") -> Tax Summary | C20: View | D20: Capital gains by taxpayer: book and taxable, long- and short-term, grandfathered; lots about to turn long-term.
B21: =HYPERLINK("#'Checks'!A1","Checks") -> Checks | C21: Check | D21: Does everything tie? Every view against the registers, every row check.
B22: =HYPERLINK("#'Holdings'!A1","Holdings") -> Holdings | C22: Register | D22: One row per security per account: the position the views are built from.
B23: =HYPERLINK("#'Tax Lots'!A1","Tax Lots") -> Tax Lots | C23: Register | D23: One row per purchase lot: purchase, sale, grandfathering, taxable gain.
B24: =HYPERLINK("#'Transactions'!A1","Transactions") -> Transactions | C24: Register | D24: Dated money movements: buys, sells, SIPs, calls, distributions, income.
B25: =HYPERLINK("#'Commitments'!A1","Commitments") -> Commitments | C25: Register | D25: Money promised to AIFs and private deals: committed, called, paid, uncalled, TVPI.
B26: =HYPERLINK("#'Entities'!A1","Entities") -> Entities | C26: Master data | D26: The family's taxpayers.
B27: =HYPERLINK("#'Accounts'!A1","Accounts") -> Accounts | C27: Master data | D27: Where each holding sits, and the date of each provider's statement.
B28: =HYPERLINK("#'Securities'!A1","Securities") -> Securities | C28: Master data | D28: What each holding is: category, basket, benchmark, price.
B29: =HYPERLINK("#'Lists'!A1","Lists") -> Lists | C29: Reference | D29: The standard classification and every dropdown's values.
B30: =HYPERLINK("#'Column Mapping'!A1","Column Mapping") -> Column Mapping | C30: Reference | D30: Where each column comes from in the two source formats, and how to convert it.
B32: HOW TO READ A SHEET
B33: Typed value | C33: Yellow cell, blue text: a figure or choice someone types.
B34: Calculated | C34: Grey cell, black text: a formula. Do not type over it.
B35: Header | C35: Navy: column names. Gold rows on the views are group totals.
B36: Row check | C36: Red when a row has a problem; green OK when it ties.
B38: HOW TO LOAD A NEW CLIENT
B39: Step 1 | C39: Set the client name, the valuation date and the previous valuation date above.
B40: Step 2 | C40: Entities: one row per taxpayer. Accounts: one row per demat, PMS, folio, bank account or platform, with its statement date.
B41: Step 3 | C41: Securities: one row per security or scheme. Pick its category from the dropdown — that sets asset class, basket and benchmark. Type the price at the valuation date.
B42: Step 4 | C42: Holdings: one row per security per account. Type quantity and invested cost; the market value is quantity × price (or type the statement value in the override column).
B43: Step 5 | C43: Tax Lots (listed shares and funds): one row per purchase lot, with any sale against it. Leave quantity, cost and realised gain on Holdings equal to the lots' totals.
B44: Step 6 | C44: Transactions: every dated flow since the previous valuation date, at least. Commitments: every AIF or private deal with a drawdown.
B45: Step 7 | C45: Open Checks. Every line must read OK before the views are shared. A red row check on a register names the problem on that row.
B46: Step 8 | C46: Read the views. Change 'Show figures in' to switch between ₹ Crore, ₹ Lakh and ₹.
B47: Step 9 | C47: Moving from another format? Column Mapping shows where each column comes from.
B49: CONVENTIONS
B50: • | C50: Registers hold full rupees. Views divide by the unit chosen above.
B51: • | C51: Dates are real dates (dd-mmm-yyyy), never text. Percentages are fractions (0.125 = 12.5%).
B52: • | C52: A blank means 'not reported'; 0 means a measured zero. Never type 0 for a figure you do not have.
B53: • | C53: IDs join the sheets: E01 entity, A01 account, S01 security, H001 holding, L001 lot, T001 transaction, C01 commitment. Keep them unique and keep each list without gaps.
B54: • | C54: Returns: holdings under a year show an absolute return; a year or more, the XIRR from the statement. Category and portfolio XIRRs are value-weighted and indicative.
B55: • | C55: Private equity and pre-IPO shares are shown at cost until a priced round or a listing.
B56: • | C56: Store PANs and account numbers masked. This file should never hold a full PAN.

Sheet Portfolio Allocation
A1: ="Portfolio Allocation — "&ClientName -> Portfolio Allocation — Malhotra Family Office (DEMO) | T1: =HYPERLINK("#'Start Here'!A1","← Start Here") -> ← Start Here
A2: ="Figures in "&UnitLabel&" · market values as at "&TEXT(ValDate,"dd-mmm-yyyy") -> Figures in ₹ Crore · market values as at 30-Jun-2026
A3: DEMO DATA — illustrative only: a fictional family, fictional securities and figures.
B5: Category | C5: Investment date range | D5: Investment at cost | E5: Market value | F5: Allocation (% of portfolio) | G5: Allocation (% of asset class) | I5: Dividend / interest | K5: Gain / (loss) including redeemed | M5: Gain / (loss) on what is held | O5: Absolute return (%) | R5: Annualised return — XIRR (%)
O6: Portfolio | P6: Blended index | R6: Portfolio | S6: Blended index | T6: Share of value covered
B7: =Lists!$A$6 -> Equity | C7: =IF(COUNTIFS(Holdings!$G$6:$G$205,$B7,Holdings!$J$6:$J$205,">0")=0,"",TEXT(_xlfn.MINIFS(Holdings!$J$6:$J$205,Holdings!$G$6:$G$205,$B7),"mmm-yy")&" – "&TEXT(MAX(_xlfn.MAXIFS(Holdings!$J$6:$J$205,Holdings!$G$6:$G$205,$B7),_xlfn.MAXIFS(Holdings!$K$6:$K$205,Holdings!$G$6:$G$205,$B7)),"mmm-yy")) -> Mar-16 – Jun-26 | D7: =SUMIFS(Holdings!$M$6:$M$205,Holdings!$G$6:$G$205,$B7)/Divisor -> 59.67793 | E7: =SUMIFS(Holdings!$R$6:$R$205,Holdings!$G$6:$G$205,$B7)/Divisor -> 84.35414 | F7: =IF(N($E$31)=0,"",E7/$E$31) -> 0.60916718 | I7: =SUMIFS(Holdings!$U$6:$U$205,Holdings!$G$6:$G$205,$B7)/Divisor -> 0.415 | K7: =(SUMIFS(Holdings!$V$6:$V$205,Holdings!$G$6:$G$205,$B7)+SUMIFS(Holdings!$S$6:$S$205,Holdings!$G$6:$G$205,$B7))/Divisor -> 29.07521 | M7: =SUMIFS(Holdings!$S$6:$S$205,Holdings!$G$6:$G$205,$B7)/Divisor -> 24.67621 | O7: =IF(N(D7)=0,"",M7/D7) -> 0.41348971 | P7: =IF(SUMIFS(Holdings!$AQ$6:$AQ$205,Holdings!$G$6:$G$205,$B7)=0,"",SUMIFS(Holdings!$AP$6:$AP$205,Holdings!$G$6:$G$205,$B7)/SUMIFS(Holdings!$AQ$6:$AQ$205,Holdings!$G$6:$G$205,$B7)) -> 0.50594734 | R7: =IF(SUMIFS(Holdings!$AN$6:$AN$205,Holdings!$G$6:$G$205,$B7)=0,"",SUMIFS(Holdings!$AM$6:$AM$205,Holdings!$G$6:$G$205,$B7)/SUMIFS(Holdings!$AN$6:$AN$205,Holdings!$G$6:$G$205,$B7)) -> 0.14574724 | S7: =IF(SUMIFS(Holdings!$AN$6:$AN$205,Holdings!$G$6:$G$205,$B7)=0,"",SUMIFS(Holdings!$AO$6:$AO$205,Holdings!$G$6:$G$205,$B7)/SUMIFS(Holdings!$AN$6:$AN$205,Holdings!$G$6:$G$205,$B7)) -> 0.13020211 | T7: =IF(N(E7)=0,"",SUMIFS(Holdings!$AN$6:$AN$205,Holdings!$G$6:$G$205,$B7)/Divisor/E7) -> 0.92837909
B8: =Lists!$D$6 -> Direct Equity | C8: =IF(COUNTIFS(Holdings!$H$6:$H$205,$B8,Holdings!$J$6:$J$205,">0")=0,"",TEXT(_xlfn.MINIFS(Holdings!$J$6:$J$205,Holdings!$H$6:$H$205,$B8),"mmm-yy")&" – "&TEXT(MAX(_xlfn.MAXIFS(Holdings!$J$6:$J$205,Holdings!$H$6:$H$205,$B8),_xlfn.MAXIFS(Holdings!$K$6:$K$205,Holdings!$H$6:$H$205,$B8)),"mmm-yy")) -> Mar-16 – Feb-26 | D8: =SUMIFS(Holdings!$M$6:$M$205,Holdings!$H$6:$H$205,$B8)/Divisor -> 18.38913 | E8: =SUMIFS(Holdings!$R$6:$R$205,Holdings!$H$6:$H$205,$B8)/Divisor -> 26.036545 | F8: =IF(N($E$31)=0,"",E8/$E$31) -> 0.18802407 | G8: =IF(N($E$7)=0,"",E8/$E$7) -> 0.30865758 | I8: =SUMIFS(Holdings!$U$6:$U$205,Holdings!$H$6:$H$205,$B8)/Divisor -> 0.303 | K8: =(SUMIFS(Holdings!$V$6:$V$205,Holdings!$H$6:$H$205,$B8)+SUMIFS(Holdings!$S$6:$S$205,Holdings!$H$6:$H$205,$B8))/Divisor -> 10.081415 | M8: =SUMIFS(Holdings!$S$6:$S$205,Holdings!$H$6:$H$205,$B8)/Divisor -> 7.647415 | O8: =IF(N(D8)=0,"",M8/D8) -> 0.41586606 | P8: =IF(SUMIFS(Holdings!$AQ$6:$AQ$205,Holdings!$H$6:$H$205,$B8)=0,"",SUMIFS(Holdings!$AP$6:$AP$205,Holdings!$H$6:$H$205,$B8)/SUMIFS(Holdings!$AQ$6:$AQ$205,Holdings!$H$6:$H$205,$B8)) -> 0.57144073 | R8: =IF(SUMIFS(Holdings!$AN$6:$AN$205,Holdings!$H$6:$H$205,$B8)=0,"",SUMIFS(Holdings!$AM$6:$AM$205,Holdings!$H$6:$H$205,$B8)/SUMIFS(Holdings!$AN$6:$AN$205,Holdings!$H$6:$H$205,$B8)) -> 0.11957614 | S8: =IF(SUMIFS(Holdings!$AN$6:$AN$205,Holdings!$H$6:$H$205,$B8)=0,"",SUMIFS(Holdings!$AO$6:$AO$205,Holdings!$H$6:$H$205,$B8)/SUMIFS(Holdings!$AN$6:$AN$205,Holdings!$H$6:$H$205,$B8)) -> 0.12442964 | T8: =IF(N(E8)=0,"",SUMIFS(Holdings!$AN$6:$AN$205,Holdings!$H$6:$H$205,$B8)/Divisor/E8) -> 0.76796
B9: =Lists!$D$7 -> Equity MF – Large / Flexi / Multi Cap | C9: =IF(COUNTIFS(Holdings!$H$6:$H$205,$B9,Holdings!$J$6:$J$205,">0")=0,"",TEXT(_xlfn.MINIFS(Holdings!$J$6:$J$205,Holdings!$H$6:$H$205,$B9),"mmm-yy")&" – "&TEXT(MAX(_xlfn.MAXIFS(Holdings!$J$6:$J$205,Holdings!$H$6:$H$205,$B9),_xlfn.MAXIFS(Holdings!$K$6:$K$205,Holdings!$H$6:$H$205,$B9)),"mmm-yy")) -> Jan-18 – Jan-18 | D9: =SUMIFS(Holdings!$M$6:$M$205,Holdings!$H$6:$H$205,$B9)/Divisor -> 3.84 | E9: =SUMIFS(Holdings!$R$6:$R$205,Holdings!$H$6:$H$205,$B9)/Divisor -> 9.64312 | F9: =IF(N($E$31)=0,"",E9/$E$31) -> 0.069638221 | G9: =IF(N($E$7)=0,"",E9/$E$7) -> 0.11431709 | I9: =SUMIFS(Holdings!$U$6:$U$205,Holdings!$H$6:$H$205,$B9)/Divisor -> 0 | K9: =(SUMIFS(Holdings!$V$6:$V$205,Holdings!$H$6:$H$205,$B9)+SUMIFS(Holdings!$S$6:$S$205,Holdings!$H$6:$H$205,$B9))/Divisor -> 7.12312 | M9: =SUMIFS(Holdings!$S$6:$S$205,Holdings!$H$6:$H$205,$B9)/Divisor -> 5.80312 | O9: =IF(N(D9)=0,"",M9/D9) -> 1.5112292 | P9: =IF(SUMIFS(Holdings!$AQ$6:$AQ$205,Holdings!$H$6:$H$205,$B9)=0,"",SUMIFS(Holdings!$AP$6:$AP$205,Holdings!$H$6:$H$205,$B9)/SUMIFS(Holdings!$AQ$6:$AQ$205,Holdings!$H$6:$H$205,$B9)) -> 1.318 | R9: =IF(SUMIFS(Holdings!$AN$6:$AN$205,Holdings!$H$6:$H$205,$B9)=0,"",SUMIFS(Holdings!$AM$6:$AM$205,Holdings!$H$6:$H$205,$B9)/SUMIFS(Holdings!$AN$6:$AN$205,Holdings!$H$6:$H$205,$B9)) -> 0.112 | S9: =IF(SUMIFS(Holdings!$AN$6:$AN$205,Holdings!$H$6:$H$205,$B9)=0,"",SUMIFS(Holdings!$AO$6:$AO$205,Holdings!$H$6:$H$205,$B9)/SUMIFS(Holdings!$AN$6:$AN$205,Holdings!$H$6:$H$205,$B9)) -> 0.126 | T9: =IF(N(E9)=0,"",SUMIFS(Holdings!$AN$6:$AN$205,Holdings!$H$6:$H$205,$B9)/Divisor/E9) -> 1
B10: =Lists!$D$8 -> Equity MF – Mid & Small Cap | C10: =IF(COUNTIFS(Holdings!$H$6:$H$205,$B10,Holdings!$J$6:$J$205,">0")=0,"",TEXT(_xlfn.MINIFS(Holdings!$J$6:$J$205,Holdings!$H$6:$H$205,$B10),"mmm-yy")&" – "&TEXT(MAX(_xlfn.MAXIFS(Holdings!$J$6:$J$205,Holdings!$H$6:$H$205,$B10),_xlfn.MAXIFS(Holdings!$K$6:$K$205,Holdings!$H$6:$H$205,$B10)),"mmm-yy")) -> Apr-23 – Jun-26 | D10: =SUMIFS(Holdings!$M$6:$M$205,Holdings!$H$6:$H$205,$B10)/Divisor -> 4.25 | E10: =SUMIFS(Holdings!$R$6:$R$205,Holdings!$H$6:$H$205,$B10)/Divisor -> 5.8950699 | F10: =IF(N($E$31)=0,"",E10/$E$31) -> 0.04257151 | G10: =IF(N($E$7)=0,"",E10/$E$7) -> 0.069884772 | I10: =SUMIFS(Holdings!$U$6:$U$205,Holdings!$H$6:$H$205,$B10)/Divisor -> 0 | K10: =(SUMIFS(Holdings!$V$6:$V$205,Holdings!$H$6:$H$205,$B10)+SUMIFS(Holdings!$S$6:$S$205,Holdings!$H$6:$H$205,$B10))/Divisor -> 1.6450699 | M10: =SUMIFS(Holdings!$S$6:$S$205,Holdings!$H$6:$H$205,$B10)/Divisor -> 1.6450699 | O10: =IF(N(D10)=0,"",M10/D10) -> 0.38707526 | P10: =IF(SUMIFS(Holdings!$AQ$6:$AQ$205,Holdings!$H$6:$H$205,$B10)=0,"",SUMIFS(Holdings!$AP$6:$AP$205,Holdings!$H$6:$H$205,$B10)/SUMIFS(Holdings!$AQ$6:$AQ$205,Holdings!$H$6:$H$205,$B10)) -> 0.362 | R10: =IF(SUMIFS(Holdings!$AN$6:$AN$205,Holdings!$H$6:$H$205,$B10)=0,"",SUMIFS(Holdings!$AM$6:$AM$205,Holdings!$H$6:$H$205,$B10)/SUMIFS(Holdings!$AN$6:$AN$205,Holdings!$H$6:$H$205,$B10)) -> 0.214 | S10: =IF(SUMIFS(Holdings!$AN$6:$AN$205,Holdings!$H$6:$H$205,$B10)=0,"",SUMIFS(Holdings!$AO$6:$AO$205,Holdings!$H$6:$H$205,$B10)/SUMIFS(Holdings!$AN$6:$AN$205,Holdings!$H$6:$H$205,$B10)) -> 0.189 | T10: =IF(N(E10)=0,"",SUMIFS(Holdings!$AN$6:$AN$205,Holdings!$H$6:$H$205,$B10)/Divisor/E10) -> 1
B11: =Lists!$D$9 -> Equity MF – Hybrid / BAF | C11: =IF(COUNTIFS(Holdings!$H$6:$H$205,$B11,Holdings!$J$6:$J$205,">0")=0,"",TEXT(_xlfn.MINIFS(Holdings!$J$6:$J$205,Holdings!$H$6:$H$205,$B11),"mmm-yy")&" – "&TEXT(MAX(_xlfn.MAXIFS(Holdings!$J$6:$J$205,Holdings!$H$6:$H$205,$B11),_xlfn.MAXIFS(Holdings!$K$6:$K$205,Holdings!$H$6:$H$205,$B11)),"mmm-yy")) -> Oct-23 – Oct-23 | D11: =SUMIFS(Holdings!$M$6:$M$205,Holdings!$H$6:$H$205,$B11)/Divisor -> 3.5 | E11: =SUMIFS(Holdings!$R$6:$R$205,Holdings!$H$6:$H$205,$B11)/Divisor -> 4.013205 | F11: =IF(N($E$31)=0,"",E11/$E$31) -> 0.028981539 | G11: =IF(N($E$7)=0,"",E11/$E$7) -> 0.047575673 | I11: =SUMIFS(Holdings!$U$6:$U$205,Holdings!$H$6:$H$205,$B11)/Divisor -> 0 | K11: =(SUMIFS(Holdings!$V$6:$V$205,Holdings!$H$6:$H$205,$B11)+SUMIFS(Holdings!$S$6:$S$205,Holdings!$H$6:$H$205,$B11))/Divisor -> 0.513205 | M11: =SUMIFS(Holdings!$S$6:$S$205,Holdings!$H$6:$H$205,$B11)/Divisor -> 0.513205 | O11: =IF(N(D11)=0,"",M11/D11) -> 0.14663 | P11: =IF(SUMIFS(Holdings!$AQ$6:$AQ$205,Holdings!$H$6:$H$205,$B11)=0,"",SUMIFS(Holdings!$AP$6:$AP$205,Holdings!$H$6:$H$205,$B11)/SUMIFS(Holdings!$AQ$6:$AQ$205,Holdings!$H$6:$H$205,$B11)) -> 0.241 | R11: =IF(SUMIFS(Holdings!$AN$6:$AN$205,Holdings!$H$6:$H$205,$B11)=0,"",SUMIFS(Holdings!$AM$6:$AM$205,Holdings!$H$6:$H$205,$B11)/SUMIFS(Holdings!$AN$6:$AN$205,Holdings!$H$6:$H$205,$B11)) -> 0.108 | S11: =IF(SUMIFS(Holdings!$AN$6:$AN$205,Holdings!$H$6:$H$205,$B11)=0,"",SUMIFS(Holdings!$AO$6:$AO$205,Holdings!$H$6:$H$205,$B11)/SUMIFS(Holdings!$AN$6:$AN$205,Holdings!$H$6:$H$205,$B11)) -> 0.115 | T11: =IF(N(E11)=0,"",SUMIFS(Holdings!$AN$6:$AN$205,Holdings!$H$6:$H$205,$B11)/Divisor/E11) -> 1
B12: =Lists!$D$10 -> Equity ETF / Index Fund | C12: =IF(COUNTIFS(Holdings!$H$6:$H$205,$B12,Holdings!$J$6:$J$205,">0")=0,"",TEXT(_xlfn.MINIFS(Holdings!$J$6:$J$205,Holdings!$H$6:$H$205,$B12),"mmm-yy")&" – "&TEXT(MAX(_xlfn.MAXIFS(Holdings!$J$6:$J$205,Holdings!$H$6:$H$205,$B12),_xlfn.MAXIFS(Holdings!$K$6:$K$205,Holdings!$H$6:$H$205,$B12)),"mmm-yy")) | D12: =SUMIFS(Holdings!$M$6:$M$205,Holdings!$H$6:$H$205,$B12)/Divisor -> 0 | E12: =SUMIFS(Holdings!$R$6:$R$205,Holdings!$H$6:$H$205,$B12)/Divisor -> 0 | F12: =IF(N($E$31)=0,"",E12/$E$31) -> 0 | G12: =IF(N($E$7)=0,"",E12/$E$7) -> 0 | I12: =SUMIFS(Holdings!$U$6:$U$205,Holdings!$H$6:$H$205,$B12)/Divisor -> 0 | K12: =(SUMIFS(Holdings!$V$6:$V$205,Holdings!$H$6:$H$205,$B12)+SUMIFS(Holdings!$S$6:$S$205,Holdings!$H$6:$H$205,$B12))/Divisor -> 0 | M12: =SUMIFS(Holdings!$S$6:$S$205,Holdings!$H$6:$H$205,$B12)/Divisor -> 0 | O12: =IF(N(D12)=0,"",M12/D12) | P12: =IF(SUMIFS(Holdings!$AQ$6:$AQ$205,Holdings!$H$6:$H$205,$B12)=0,"",SUMIFS(Holdings!$AP$6:$AP$205,Holdings!$H$6:$H$205,$B12)/SUMIFS(Holdings!$AQ$6:$AQ$205,Holdings!$H$6:$H$205,$B12)) | R12: =IF(SUMIFS(Holdings!$AN$6:$AN$205,Holdings!$H$6:$H$205,$B12)=0,"",SUMIFS(Holdings!$AM$6:$AM$205,Holdings!$H$6:$H$205,$B12)/SUMIFS(Holdings!$AN$6:$AN$205,Holdings!$H$6:$H$205,$B12)) | S12: =IF(SUMIFS(Holdings!$AN$6:$AN$205,Holdings!$H$6:$H$205,$B12)=0,"",SUMIFS(Holdings!$AO$6:$AO$205,Holdings!$H$6:$H$205,$B12)/SUMIFS(Holdings!$AN$6:$AN$205,Holdings!$H$6:$H$205,$B12)) | T12: =IF(N(E12)=0,"",SUMIFS(Holdings!$AN$6:$AN$205,Holdings!$H$6:$H$205,$B12)/Divisor/E12)
B13: =Lists!$D$11 -> PMS – Equity | C13: =IF(COUNTIFS(Holdings!$H$6:$H$205,$B13,Holdings!$J$6:$J$205,">0")=0,"",TEXT(_xlfn.MINIFS(Holdings!$J$6:$J$205,Holdings!$H$6:$H$205,$B13),"mmm-yy")&" – "&TEXT(MAX(_xlfn.MAXIFS(Holdings!$J$6:$J$205,Holdings!$H$6:$H$205,$B13),_xlfn.MAXIFS(Holdings!$K$6:$K$205,Holdings!$H$6:$H$205,$B13)),"mmm-yy")) -> Apr-22 – Jan-25 | D13: =SUMIFS(Holdings!$M$6:$M$205,Holdings!$H$6:$H$205,$B13)/Divisor -> 15 | E13: =SUMIFS(Holdings!$R$6:$R$205,Holdings!$H$6:$H$205,$B13)/Divisor -> 18.124 | F13: =IF(N($E$31)=0,"",E13/$E$31) -> 0.13088327 | G13: =IF(N($E$7)=0,"",E13/$E$7) -> 0.21485608 | I13: =SUMIFS(Holdings!$U$6:$U$205,Holdings!$H$6:$H$205,$B13)/Divisor -> 0.112 | K13: =(SUMIFS(Holdings!$V$6:$V$205,Holdings!$H$6:$H$205,$B13)+SUMIFS(Holdings!$S$6:$S$205,Holdings!$H$6:$H$205,$B13))/Divisor -> 3.769 | M13: =SUMIFS(Holdings!$S$6:$S$205,Holdings!$H$6:$H$205,$B13)/Divisor -> 3.124 | O13: =IF(N(D13)=0,"",M13/D13) -> 0.20826667 | P13: =IF(SUMIFS(Holdings!$AQ$6:$AQ$205,Holdings!$H$6:$H$205,$B13)=0,"",SUMIFS(Holdings!$AP$6:$AP$205,Holdings!$H$6:$H$205,$B13)/SUMIFS(Holdings!$AQ$6:$AQ$205,Holdings!$H$6:$H$205,$B13)) -> 0.385 | R13: =IF(SUMIFS(Holdings!$AN$6:$AN$205,Holdings!$H$6:$H$205,$B13)=0,"",SUMIFS(Holdings!$AM$6:$AM$205,Holdings!$H$6:$H$205,$B13)/SUMIFS(Holdings!$AN$6:$AN$205,Holdings!$H$6:$H$205,$B13)) -> 0.142 | S13: =IF(SUMIFS(Holdings!$AN$6:$AN$205,Holdings!$H$6:$H$205,$B13)=0,"",SUMIFS(Holdings!$AO$6:$AO$205,Holdings!$H$6:$H$205,$B13)/SUMIFS(Holdings!$AN$6:$AN$205,Holdings!$H$6:$H$205,$B13)) -> 0.121 | T13: =IF(N(E13)=0,"",SUMIFS(Holdings!$AN$6:$AN$205,Holdings!$H$6:$H$205,$B13)/Divisor/E13) -> 1
B14: =Lists!$D$12 -> AIF Cat III – Listed Equity | C14: =IF(COUNTIFS(Holdings!$H$6:$H$205,$B14,Holdings!$J$6:$J$205,">0")=0,"",TEXT(_xlfn.MINIFS(Holdings!$J$6:$J$205,Holdings!$H$6:$H$205,$B14),"mmm-yy")&" – "&TEXT(MAX(_xlfn.MAXIFS(Holdings!$J$6:$J$205,Holdings!$H$6:$H$205,$B14),_xlfn.MAXIFS(Holdings!$K$6:$K$205,Holdings!$H$6:$H$205,$B14)),"mmm-yy")) -> Jan-23 – May-26 | D14: =SUMIFS(Holdings!$M$6:$M$205,Holdings!$H$6:$H$205,$B14)/Divisor -> 14.6988 | E14: =SUMIFS(Holdings!$R$6:$R$205,Holdings!$H$6:$H$205,$B14)/Divisor -> 20.6422 | F14: =IF(N($E$31)=0,"",E14/$E$31) -> 0.14906857 | G14: =IF(N($E$7)=0,"",E14/$E$7) -> 0.2447088 | I14: =SUMIFS(Holdings!$U$6:$U$205,Holdings!$H$6:$H$205,$B14)/Divisor -> 0 | K14: =(SUMIFS(Holdings!$V$6:$V$205,Holdings!$H$6:$H$205,$B14)+SUMIFS(Holdings!$S$6:$S$205,Holdings!$H$6:$H$205,$B14))/Divisor -> 5.9434 | M14: =SUMIFS(Holdings!$S$6:$S$205,Holdings!$H$6:$H$205,$B14)/Divisor -> 5.9434 | O14: =IF(N(D14)=0,"",M14/D14) -> 0.40434593 | P14: =IF(SUMIFS(Holdings!$AQ$6:$AQ$205,Holdings!$H$6:$H$205,$B14)=0,"",SUMIFS(Holdings!$AP$6:$AP$205,Holdings!$H$6:$H$205,$B14)/SUMIFS(Holdings!$AQ$6:$AQ$205,Holdings!$H$6:$H$205,$B14)) -> 0.44 | R14: =IF(SUMIFS(Holdings!$AN$6:$AN$205,Holdings!$H$6:$H$205,$B14)=0,"",SUMIFS(Holdings!$AM$6:$AM$205,Holdings!$H$6:$H$205,$B14)/SUMIFS(Holdings!$AN$6:$AN$205,Holdings!$H$6:$H$205,$B14)) -> 0.178 | S14: =IF(SUMIFS(Holdings!$AN$6:$AN$205,Holdings!$H$6:$H$205,$B14)=0,"",SUMIFS(Holdings!$AO$6:$AO$205,Holdings!$H$6:$H$205,$B14)/SUMIFS(Holdings!$AN$6:$AN$205,Holdings!$H$6:$H$205,$B14)) -> 0.132 | T14: =IF(N(E14)=0,"",SUMIFS(Holdings!$AN$6:$AN$205,Holdings!$H$6:$H$205,$B14)/Divisor/E14) -> 1
B15: =Lists!$A$7 -> Debt | C15: =IF(COUNTIFS(Holdings!$G$6:$G$205,$B15,Holdings!$J$6:$J$205,">0")=0,"",TEXT(_xlfn.MINIFS(Holdings!$J$6:$J$205,Holdings!$G$6:$G$205,$B15),"mmm-yy")&" – "&TEXT(MAX(_xlfn.MAXIFS(Holdings!$J$6:$J$205,Holdings!$G$6:$G$205,$B15),_xlfn.MAXIFS(Holdings!$K$6:$K$205,Holdings!$G$6:$G$205,$B15)),"mmm-yy")) -> Mar-24 – May-26 | D15: =SUMIFS(Holdings!$M$6:$M$205,Holdings!$G$6:$G$205,$B15)/Divisor -> 13 | E15: =SUMIFS(Holdings!$R$6:$R$205,Holdings!$G$6:$G$205,$B15)/Divisor -> 13.595184 | F15: =IF(N($E$31)=0,"",E15/$E$31) -> 0.098178228 | I15: =SUMIFS(Holdings!$U$6:$U$205,Holdings!$G$6:$G$205,$B15)/Divisor -> 0.43 | K15: =(SUMIFS(Holdings!$V$6:$V$205,Holdings!$G$6:$G$205,$B15)+SUMIFS(Holdings!$S$6:$S$205,Holdings!$G$6:$G$205,$B15))/Divisor -> 0.595184 | M15: =SUMIFS(Holdings!$S$6:$S$205,Holdings!$G$6:$G$205,$B15)/Divisor -> 0.595184 | O15: =IF(N(D15)=0,"",M15/D15) -> 0.045783385 | P15: =IF(SUMIFS(Holdings!$AQ$6:$AQ$205,Holdings!$G$6:$G$205,$B15)=0,"",SUMIFS(Holdings!$AP$6:$AP$205,Holdings!$G$6:$G$205,$B15)/SUMIFS(Holdings!$AQ$6:$AQ$205,Holdings!$G$6:$G$205,$B15)) -> 0.15638462 | R15: =IF(SUMIFS(Holdings!$AN$6:$AN$205,Holdings!$G$6:$G$205,$B15)=0,"",SUMIFS(Holdings!$AM$6:$AM$205,Holdings!$G$6:$G$205,$B15)/SUMIFS(Holdings!$AN$6:$AN$205,Holdings!$G$6:$G$205,$B15)) -> 0.083031223 | S15: =IF(SUMIFS(Holdings!$AN$6:$AN$205,Holdings!$G$6:$G$205,$B15)=0,"",SUMIFS(Holdings!$AO$6:$AO$205,Holdings!$G$6:$G$205,$B15)/SUMIFS(Holdings!$AN$6:$AN$205,Holdings!$G$6:$G$205,$B15)) -> 0.074806245 | T15: =IF(N(E15)=0,"",SUMIFS(Holdings!$AN$6:$AN$205,Holdings!$G$6:$G$205,$B15)/Divisor/E15) -> 0.92363472
B16: =Lists!$D$13 -> Debt MF | C16: =IF(COUNTIFS(Holdings!$H$6:$H$205,$B16,Holdings!$J$6:$J$205,">0")=0,"",TEXT(_xlfn.MINIFS(Holdings!$J$6:$J$205,Holdings!$H$6:$H$205,$B16),"mmm-yy")&" – "&TEXT(MAX(_xlfn.MAXIFS(Holdings!$J$6:$J$205,Holdings!$H$6:$H$205,$B16),_xlfn.MAXIFS(Holdings!$K$6:$K$205,Holdings!$H$6:$H$205,$B16)),"mmm-yy")) -> Jul-24 – Jul-24 | D16: =SUMIFS(Holdings!$M$6:$M$205,Holdings!$H$6:$H$205,$B16)/Divisor -> 7 | E16: =SUMIFS(Holdings!$R$6:$R$205,Holdings!$H$6:$H$205,$B16)/Divisor -> 7.494984 | F16: =IF(N($E$31)=0,"",E16/$E$31) -> 0.054125361 | G16: =IF(N($E$15)=0,"",E16/$E$15) -> 0.55129699 | I16: =SUMIFS(Holdings!$U$6:$U$205,Holdings!$H$6:$H$205,$B16)/Divisor -> 0 | K16: =(SUMIFS(Holdings!$V$6:$V$205,Holdings!$H$6:$H$205,$B16)+SUMIFS(Holdings!$S$6:$S$205,Holdings!$H$6:$H$205,$B16))/Divisor -> 0.494984 | M16: =SUMIFS(Holdings!$S$6:$S$205,Holdings!$H$6:$H$205,$B16)/Divisor -> 0.494984 | O16: =IF(N(D16)=0,"",M16/D16) -> 0.070712 | P16: =IF(SUMIFS(Holdings!$AQ$6:$AQ$205,Holdings!$H$6:$H$205,$B16)=0,"",SUMIFS(Holdings!$AP$6:$AP$205,Holdings!$H$6:$H$205,$B16)/SUMIFS(Holdings!$AQ$6:$AQ$205,Holdings!$H$6:$H$205,$B16)) -> 0.156 | R16: =IF(SUMIFS(Holdings!$AN$6:$AN$205,Holdings!$H$6:$H$205,$B16)=0,"",SUMIFS(Holdings!$AM$6:$AM$205,Holdings!$H$6:$H$205,$B16)/SUMIFS(Holdings!$AN$6:$AN$205,Holdings!$H$6:$H$205,$B16)) -> 0.079 | S16: =IF(SUMIFS(Holdings!$AN$6:$AN$205,Holdings!$H$6:$H$205,$B16)=0,"",SUMIFS(Holdings!$AO$6:$AO$205,Holdings!$H$6:$H$205,$B16)/SUMIFS(Holdings!$AN$6:$AN$205,Holdings!$H$6:$H$205,$B16)) -> 0.074 | T16: =IF(N(E16)=0,"",SUMIFS(Holdings!$AN$6:$AN$205,Holdings!$H$6:$H$205,$B16)/Divisor/E16) -> 1
B17: =Lists!$D$14 -> Bonds / NCDs | C17: =IF(COUNTIFS(Holdings!$H$6:$H$205,$B17,Holdings!$J$6:$J$205,">0")=0,"",TEXT(_xlfn.MINIFS(Holdings!$J$6:$J$205,Holdings!$H$6:$H$205,$B17),"mmm-yy")&" – "&TEXT(MAX(_xlfn.MAXIFS(Holdings!$J$6:$J$205,Holdings!$H$6:$H$205,$B17),_xlfn.MAXIFS(Holdings!$K$6:$K$205,Holdings!$H$6:$H$205,$B17)),"mmm-yy")) -> Mar-24 – Mar-24 | D17: =SUMIFS(Holdings!$M$6:$M$205,Holdings!$H$6:$H$205,$B17)/Divisor -> 5 | E17: =SUMIFS(Holdings!$R$6:$R$205,Holdings!$H$6:$H$205,$B17)/Divisor -> 5.062 | F17: =IF(N($E$31)=0,"",E17/$E$31) -> 0.036555459 | G17: =IF(N($E$15)=0,"",E17/$E$15) -> 0.37233773 | I17: =SUMIFS(Holdings!$U$6:$U$205,Holdings!$H$6:$H$205,$B17)/Divisor -> 0.43 | K17: =(SUMIFS(Holdings!$V$6:$V$205,Holdings!$H$6:$H$205,$B17)+SUMIFS(Holdings!$S$6:$S$205,Holdings!$H$6:$H$205,$B17))/Divisor -> 0.062 | M17: =SUMIFS(Holdings!$S$6:$S$205,Holdings!$H$6:$H$205,$B17)/Divisor -> 0.062 | O17: =IF(N(D17)=0,"",M17/D17) -> 0.0124 | P17: =IF(SUMIFS(Holdings!$AQ$6:$AQ$205,Holdings!$H$6:$H$205,$B17)=0,"",SUMIFS(Holdings!$AP$6:$AP$205,Holdings!$H$6:$H$205,$B17)/SUMIFS(Holdings!$AQ$6:$AQ$205,Holdings!$H$6:$H$205,$B17)) -> 0.182 | R17: =IF(SUMIFS(Holdings!$AN$6:$AN$205,Holdings!$H$6:$H$205,$B17)=0,"",SUMIFS(Holdings!$AM$6:$AM$205,Holdings!$H$6:$H$205,$B17)/SUMIFS(Holdings!$AN$6:$AN$205,Holdings!$H$6:$H$205,$B17)) -> 0.089 | S17: =IF(SUMIFS(Holdings!$AN$6:$AN$205,Holdings!$H$6:$H$205,$B17)=0,"",SUMIFS(Holdings!$AO$6:$AO$205,Holdings!$H$6:$H$205,$B17)/SUMIFS(Holdings!$AN$6:$AN$205,Holdings!$H$6:$H$205,$B17)) -> 0.076 | T17: =IF(N(E17)=0,"",SUMIFS(Holdings!$AN$6:$AN$205,Holdings!$H$6:$H$205,$B17)/Divisor/E17) -> 1
B18: =Lists!$D$15 -> AIF Cat II – Private Credit | C18: =IF(COUNTIFS(Holdings!$H$6:$H$205,$B18,Holdings!$J$6:$J$205,">0")=0,"",TEXT(_xlfn.MINIFS(Holdings!$J$6:$J$205,Holdings!$H$6:$H$205,$B18),"mmm-yy")&" – "&TEXT(MAX(_xlfn.MAXIFS(Holdings!$J$6:$J$205,Holdings!$H$6:$H$205,$B18),_xlfn.MAXIFS(Holdings!$K$6:$K$205,Holdings!$H$6:$H$205,$B18)),"mmm-yy")) -> Jan-26 – May-26 | D18: =SUMIFS(Holdings!$M$6:$M$205,Holdings!$H$6:$H$205,$B18)/Divisor -> 1 | E18: =SUMIFS(Holdings!$R$6:$R$205,Holdings!$H$6:$H$205,$B18)/Divisor -> 1.0382 | F18: =IF(N($E$31)=0,"",E18/$E$31) -> 0.0074974076 | G18: =IF(N($E$15)=0,"",E18/$E$15) -> 0.076365278 | I18: =SUMIFS(Holdings!$U$6:$U$205,Holdings!$H$6:$H$205,$B18)/Divisor -> 0 | K18: =(SUMIFS(Holdings!$V$6:$V$205,Holdings!$H$6:$H$205,$B18)+SUMIFS(Holdings!$S$6:$S$205,Holdings!$H$6:$H$205,$B18))/Divisor -> 0.0382 | M18: =SUMIFS(Holdings!$S$6:$S$205,Holdings!$H$6:$H$205,$B18)/Divisor -> 0.0382 | O18: =IF(N(D18)=0,"",M18/D18) -> 0.0382 | P18: =IF(SUMIFS(Holdings!$AQ$6:$AQ$205,Holdings!$H$6:$H$205,$B18)=0,"",SUMIFS(Holdings!$AP$6:$AP$205,Holdings!$H$6:$H$205,$B18)/SUMIFS(Holdings!$AQ$6:$AQ$205,Holdings!$H$6:$H$205,$B18)) -> 0.031 | R18: =IF(SUMIFS(Holdings!$AN$6:$AN$205,Holdings!$H$6:$H$205,$B18)=0,"",SUMIFS(Holdings!$AM$6:$AM$205,Holdings!$H$6:$H$205,$B18)/SUMIFS(Holdings!$AN$6:$AN$205,Holdings!$H$6:$H$205,$B18)) | S18: =IF(SUMIFS(Holdings!$AN$6:$AN$205,Holdings!$H$6:$H$205,$B18)=0,"",SUMIFS(Holdings!$AO$6:$AO$205,Holdings!$H$6:$H$205,$B18)/SUMIFS(Holdings!$AN$6:$AN$205,Holdings!$H$6:$H$205,$B18)) | T18: =IF(N(E18)=0,"",SUMIFS(Holdings!$AN$6:$AN$205,Holdings!$H$6:$H$205,$B18)/Divisor/E18) -> 0
B19: =Lists!$D$16 -> Structured Product / MLD | C19: =IF(COUNTIFS(Holdings!$H$6:$H$205,$B19,Holdings!$J$6:$J$205,">0")=0,"",TEXT(_xlfn.MINIFS(Holdings!$J$6:$J$205,Holdings!$H$6:$H$205,$B19),"mmm-yy")&" – "&TEXT(MAX(_xlfn.MAXIFS(Holdings!$J$6:$J$205,Holdings!$H$6:$H$205,$B19),_xlfn.MAXIFS(Holdings!$K$6:$K$205,Holdings!$H$6:$H$205,$B19)),"mmm-yy")) | D19: =SUMIFS(Holdings!$M$6:$M$205,Holdings!$H$6:$H$205,$B19)/Divisor -> 0 | E19: =SUMIFS(Holdings!$R$6:$R$205,Holdings!$H$6:$H$205,$B19)/Divisor -> 0 | F19: =IF(N($E$31)=0,"",E19/$E$31) -> 0 | G19: =IF(N($E$15)=0,"",E19/$E$15) -> 0 | I19: =SUMIFS(Holdings!$U$6:$U$205,Holdings!$H$6:$H$205,$B19)/Divisor -> 0 | K19: =(SUMIFS(Holdings!$V$6:$V$205,Holdings!$H$6:$H$205,$B19)+SUMIFS(Holdings!$S$6:$S$205,Holdings!$H$6:$H$205,$B19))/Divisor -> 0 | M19: =SUMIFS(Holdings!$S$6:$S$205,Holdings!$H$6:$H$205,$B19)/Divisor -> 0 | O19: =IF(N(D19)=0,"",M19/D19) | P19: =IF(SUMIFS(Holdings!$AQ$6:$AQ$205,Holdings!$H$6:$H$205,$B19)=0,"",SUMIFS(Holdings!$AP$6:$AP$205,Holdings!$H$6:$H$205,$B19)/SUMIFS(Holdings!$AQ$6:$AQ$205,Holdings!$H$6:$H$205,$B19)) | R19: =IF(SUMIFS(Holdings!$AN$6:$AN$205,Holdings!$H$6:$H$205,$B19)=0,"",SUMIFS(Holdings!$AM$6:$AM$205,Holdings!$H$6:$H$205,$B19)/SUMIFS(Holdings!$AN$6:$AN$205,Holdings!$H$6:$H$205,$B19)) | S19: =IF(SUMIFS(Holdings!$AN$6:$AN$205,Holdings!$H$6:$H$205,$B19)=0,"",SUMIFS(Holdings!$AO$6:$AO$205,Holdings!$H$6:$H$205,$B19)/SUMIFS(Holdings!$AN$6:$AN$205,Holdings!$H$6:$H$205,$B19)) | T19: =IF(N(E19)=0,"",SUMIFS(Holdings!$AN$6:$AN$205,Holdings!$H$6:$H$205,$B19)/Divisor/E19)
B20: =Lists!$A$8 -> Cash | C20: =IF(COUNTIFS(Holdings!$G$6:$G$205,$B20,Holdings!$J$6:$J$205,">0")=0,"",TEXT(_xlfn.MINIFS(Holdings!$J$6:$J$205,Holdings!$G$6:$G$205,$B20),"mmm-yy")&" – "&TEXT(MAX(_xlfn.MAXIFS(Holdings!$J$6:$J$205,Holdings!$G$6:$G$205,$B20),_xlfn.MAXIFS(Holdings!$K$6:$K$205,Holdings!$G$6:$G$205,$B20)),"mmm-yy")) -> Dec-25 – Jun-26 | D20: =SUMIFS(Holdings!$M$6:$M$205,Holdings!$G$6:$G$205,$B20)/Divisor -> 17.4556 | E20: =SUMIFS(Holdings!$R$6:$R$205,Holdings!$G$6:$G$205,$B20)/Divisor -> 17.741647 | F20: =IF(N($E$31)=0,"",E20/$E$31) -> 0.12812209 | I20: =SUMIFS(Holdings!$U$6:$U$205,Holdings!$G$6:$G$205,$B20)/Divisor -> 0.0185 | K20: =(SUMIFS(Holdings!$V$6:$V$205,Holdings!$G$6:$G$205,$B20)+SUMIFS(Holdings!$S$6:$S$205,Holdings!$G$6:$G$205,$B20))/Divisor -> 0.28604696 | M20: =SUMIFS(Holdings!$S$6:$S$205,Holdings!$G$6:$G$205,$B20)/Divisor -> 0.28604696 | O20: =IF(N(D20)=0,"",M20/D20) -> 0.016387117 | P20: =IF(SUMIFS(Holdings!$AQ$6:$AQ$205,Holdings!$G$6:$G$205,$B20)=0,"",SUMIFS(Holdings!$AP$6:$AP$205,Holdings!$G$6:$G$205,$B20)/SUMIFS(Holdings!$AQ$6:$AQ$205,Holdings!$G$6:$G$205,$B20)) -> 0.021983341 | R20: =IF(SUMIFS(Holdings!$AN$6:$AN$205,Holdings!$G$6:$G$205,$B20)=0,"",SUMIFS(Holdings!$AM$6:$AM$205,Holdings!$G$6:$G$205,$B20)/SUMIFS(Holdings!$AN$6:$AN$205,Holdings!$G$6:$G$205,$B20)) | S20: =IF(SUMIFS(Holdings!$AN$6:$AN$205,Holdings!$G$6:$G$205,$B20)=0,"",SUMIFS(Holdings!$AO$6:$AO$205,Holdings!$G$6:$G$205,$B20)/SUMIFS(Holdings!$AN$6:$AN$205,Holdings!$G$6:$G$205,$B20)) | T20: =IF(N(E20)=0,"",SUMIFS(Holdings!$AN$6:$AN$205,Holdings!$G$6:$G$205,$B20)/Divisor/E20) -> 0
B21: =Lists!$D$17 -> Liquid / Overnight Fund | C21: =IF(COUNTIFS(Holdings!$H$6:$H$205,$B21,Holdings!$J$6:$J$205,">0")=0,"",TEXT(_xlfn.MINIFS(Holdings!$J$6:$J$205,Holdings!$H$6:$H$205,$B21),"mmm-yy")&" – "&TEXT(MAX(_xlfn.MAXIFS(Holdings!$J$6:$J$205,Holdings!$H$6:$H$205,$B21),_xlfn.MAXIFS(Holdings!$K$6:$K$205,Holdings!$H$6:$H$205,$B21)),"mmm-yy")) -> Jan-26 – Jun-26 | D21: =SUMIFS(Holdings!$M$6:$M$205,Holdings!$H$6:$H$205,$B21)/Divisor -> 7.895 | E21: =SUMIFS(Holdings!$R$6:$R$205,Holdings!$H$6:$H$205,$B21)/Divisor -> 7.999143 | F21: =IF(N($E$31)=0,"",E21/$E$31) -> 0.057766168 | G21: =IF(N($E$20)=0,"",E21/$E$20) -> 0.45086812 | I21: =SUMIFS(Holdings!$U$6:$U$205,Holdings!$H$6:$H$205,$B21)/Divisor -> 0 | K21: =(SUMIFS(Holdings!$V$6:$V$205,Holdings!$H$6:$H$205,$B21)+SUMIFS(Holdings!$S$6:$S$205,Holdings!$H$6:$H$205,$B21))/Divisor -> 0.10414296 | M21: =SUMIFS(Holdings!$S$6:$S$205,Holdings!$H$6:$H$205,$B21)/Divisor -> 0.10414296 | O21: =IF(N(D21)=0,"",M21/D21) -> 0.013191003 | P21: =IF(SUMIFS(Holdings!$AQ$6:$AQ$205,Holdings!$H$6:$H$205,$B21)=0,"",SUMIFS(Holdings!$AP$6:$AP$205,Holdings!$H$6:$H$205,$B21)/SUMIFS(Holdings!$AQ$6:$AQ$205,Holdings!$H$6:$H$205,$B21)) -> 0.013868271 | R21: =IF(SUMIFS(Holdings!$AN$6:$AN$205,Holdings!$H$6:$H$205,$B21)=0,"",SUMIFS(Holdings!$AM$6:$AM$205,Holdings!$H$6:$H$205,$B21)/SUMIFS(Holdings!$AN$6:$AN$205,Holdings!$H$6:$H$205,$B21)) | S21: =IF(SUMIFS(Holdings!$AN$6:$AN$205,Holdings!$H$6:$H$205,$B21)=0,"",SUMIFS(Holdings!$AO$6:$AO$205,Holdings!$H$6:$H$205,$B21)/SUMIFS(Holdings!$AN$6:$AN$205,Holdings!$H$6:$H$205,$B21)) | T21: =IF(N(E21)=0,"",SUMIFS(Holdings!$AN$6:$AN$205,Holdings!$H$6:$H$205,$B21)/Divisor/E21) -> 0
B22: =Lists!$D$18 -> Arbitrage Fund | C22: =IF(COUNTIFS(Holdings!$H$6:$H$205,$B22,Holdings!$J$6:$J$205,">0")=0,"",TEXT(_xlfn.MINIFS(Holdings!$J$6:$J$205,Holdings!$H$6:$H$205,$B22),"mmm-yy")&" – "&TEXT(MAX(_xlfn.MAXIFS(Holdings!$J$6:$J$205,Holdings!$H$6:$H$205,$B22),_xlfn.MAXIFS(Holdings!$K$6:$K$205,Holdings!$H$6:$H$205,$B22)),"mmm-yy")) -> Dec-25 – Jun-26 | D22: =SUMIFS(Holdings!$M$6:$M$205,Holdings!$H$6:$H$205,$B22)/Divisor -> 5.8156 | E22: =SUMIFS(Holdings!$R$6:$R$205,Holdings!$H$6:$H$205,$B22)/Divisor -> 5.997504 | F22: =IF(N($E$31)=0,"",E22/$E$31) -> 0.043311243 | G22: =IF(N($E$20)=0,"",E22/$E$20) -> 0.33804663 | I22: =SUMIFS(Holdings!$U$6:$U$205,Holdings!$H$6:$H$205,$B22)/Divisor -> 0 | K22: =(SUMIFS(Holdings!$V$6:$V$205,Holdings!$H$6:$H$205,$B22)+SUMIFS(Holdings!$S$6:$S$205,Holdings!$H$6:$H$205,$B22))/Divisor -> 0.181904 | M22: =SUMIFS(Holdings!$S$6:$S$205,Holdings!$H$6:$H$205,$B22)/Divisor -> 0.181904 | O22: =IF(N(D22)=0,"",M22/D22) -> 0.03127863 | P22: =IF(SUMIFS(Holdings!$AQ$6:$AQ$205,Holdings!$H$6:$H$205,$B22)=0,"",SUMIFS(Holdings!$AP$6:$AP$205,Holdings!$H$6:$H$205,$B22)/SUMIFS(Holdings!$AQ$6:$AQ$205,Holdings!$H$6:$H$205,$B22)) -> 0.033 | R22: =IF(SUMIFS(Holdings!$AN$6:$AN$205,Holdings!$H$6:$H$205,$B22)=0,"",SUMIFS(Holdings!$AM$6:$AM$205,Holdings!$H$6:$H$205,$B22)/SUMIFS(Holdings!$AN$6:$AN$205,Holdings!$H$6:$H$205,$B22)) | S22: =IF(SUMIFS(Holdings!$AN$6:$AN$205,Holdings!$H$6:$H$205,$B22)=0,"",SUMIFS(Holdings!$AO$6:$AO$205,Holdings!$H$6:$H$205,$B22)/SUMIFS(Holdings!$AN$6:$AN$205,Holdings!$H$6:$H$205,$B22)) | T22: =IF(N(E22)=0,"",SUMIFS(Holdings!$AN$6:$AN$205,Holdings!$H$6:$H$205,$B22)/Divisor/E22) -> 0
B23: =Lists!$D$19 -> Bank / Cash Balance | C23: =IF(COUNTIFS(Holdings!$H$6:$H$205,$B23,Holdings!$J$6:$J$205,">0")=0,"",TEXT(_xlfn.MINIFS(Holdings!$J$6:$J$205,Holdings!$H$6:$H$205,$B23),"mmm-yy")&" – "&TEXT(MAX(_xlfn.MAXIFS(Holdings!$J$6:$J$205,Holdings!$H$6:$H$205,$B23),_xlfn.MAXIFS(Holdings!$K$6:$K$205,Holdings!$H$6:$H$205,$B23)),"mmm-yy")) | D23: =SUMIFS(Holdings!$M$6:$M$205,Holdings!$H$6:$H$205,$B23)/Divisor -> 3.745 | E23: =SUMIFS(Holdings!$R$6:$R$205,Holdings!$H$6:$H$205,$B23)/Divisor -> 3.745 | F23: =IF(N($E$31)=0,"",E23/$E$31) -> 0.027044685 | G23: =IF(N($E$20)=0,"",E23/$E$20) -> 0.21108525 | I23: =SUMIFS(Holdings!$U$6:$U$205,Holdings!$H$6:$H$205,$B23)/Divisor -> 0.0185 | K23: =(SUMIFS(Holdings!$V$6:$V$205,Holdings!$H$6:$H$205,$B23)+SUMIFS(Holdings!$S$6:$S$205,Holdings!$H$6:$H$205,$B23))/Divisor -> 0 | M23: =SUMIFS(Holdings!$S$6:$S$205,Holdings!$H$6:$H$205,$B23)/Divisor -> 0 | O23: =IF(N(D23)=0,"",M23/D23) -> 0 | P23: =IF(SUMIFS(Holdings!$AQ$6:$AQ$205,Holdings!$H$6:$H$205,$B23)=0,"",SUMIFS(Holdings!$AP$6:$AP$205,Holdings!$H$6:$H$205,$B23)/SUMIFS(Holdings!$AQ$6:$AQ$205,Holdings!$H$6:$H$205,$B23)) | R23: =IF(SUMIFS(Holdings!$AN$6:$AN$205,Holdings!$H$6:$H$205,$B23)=0,"",SUMIFS(Holdings!$AM$6:$AM$205,Holdings!$H$6:$H$205,$B23)/SUMIFS(Holdings!$AN$6:$AN$205,Holdings!$H$6:$H$205,$B23)) | S23: =IF(SUMIFS(Holdings!$AN$6:$AN$205,Holdings!$H$6:$H$205,$B23)=0,"",SUMIFS(Holdings!$AO$6:$AO$205,Holdings!$H$6:$H$205,$B23)/SUMIFS(Holdings!$AN$6:$AN$205,Holdings!$H$6:$H$205,$B23)) | T23: =IF(N(E23)=0,"",SUMIFS(Holdings!$AN$6:$AN$205,Holdings!$H$6:$H$205,$B23)/Divisor/E23) -> 0
B24: =Lists!$A$9 -> Alternate | C24: =IF(COUNTIFS(Holdings!$G$6:$G$205,$B24,Holdings!$J$6:$J$205,">0")=0,"",TEXT(_xlfn.MINIFS(Holdings!$J$6:$J$205,Holdings!$G$6:$G$205,$B24),"mmm-yy")&" – "&TEXT(MAX(_xlfn.MAXIFS(Holdings!$J$6:$J$205,Holdings!$G$6:$G$205,$B24),_xlfn.MAXIFS(Holdings!$K$6:$K$205,Holdings!$G$6:$G$205,$B24)),"mmm-yy")) -> Sep-23 – Apr-26 | D24: =SUMIFS(Holdings!$M$6:$M$205,Holdings!$G$6:$G$205,$B24)/Divisor -> 20.06 | E24: =SUMIFS(Holdings!$R$6:$R$205,Holdings!$G$6:$G$205,$B24)/Divisor -> 22.78356 | F24: =IF(N($E$31)=0,"",E24/$E$31) -> 0.16453249 | I24: =SUMIFS(Holdings!$U$6:$U$205,Holdings!$G$6:$G$205,$B24)/Divisor -> 0.36 | K24: =(SUMIFS(Holdings!$V$6:$V$205,Holdings!$G$6:$G$205,$B24)+SUMIFS(Holdings!$S$6:$S$205,Holdings!$G$6:$G$205,$B24))/Divisor -> 2.93356 | M24: =SUMIFS(Holdings!$S$6:$S$205,Holdings!$G$6:$G$205,$B24)/Divisor -> 2.72356 | O24: =IF(N(D24)=0,"",M24/D24) -> 0.13577069 | P24: =IF(SUMIFS(Holdings!$AQ$6:$AQ$205,Holdings!$G$6:$G$205,$B24)=0,"",SUMIFS(Holdings!$AP$6:$AP$205,Holdings!$G$6:$G$205,$B24)/SUMIFS(Holdings!$AQ$6:$AQ$205,Holdings!$G$6:$G$205,$B24)) -> 0.23628412 | R24: =IF(SUMIFS(Holdings!$AN$6:$AN$205,Holdings!$G$6:$G$205,$B24)=0,"",SUMIFS(Holdings!$AM$6:$AM$205,Holdings!$G$6:$G$205,$B24)/SUMIFS(Holdings!$AN$6:$AN$205,Holdings!$G$6:$G$205,$B24)) -> 0.13638576 | S24: =IF(SUMIFS(Holdings!$AN$6:$AN$205,Holdings!$G$6:$G$205,$B24)=0,"",SUMIFS(Holdings!$AO$6:$AO$205,Holdings!$G$6:$G$205,$B24)/SUMIFS(Holdings!$AN$6:$AN$205,Holdings!$G$6:$G$205,$B24)) -> 0.11561472 | T24: =IF(N(E24)=0,"",SUMIFS(Holdings!$AN$6:$AN$205,Holdings!$G$6:$G$205,$B24)/Divisor/E24) -> 0.67365943
B25: =Lists!$D$20 -> Gold / Silver (ETF, SGB, FoF) | C25: =IF(COUNTIFS(Holdings!$H$6:$H$205,$B25,Holdings!$J$6:$J$205,">0")=0,"",TEXT(_xlfn.MINIFS(Holdings!$J$6:$J$205,Holdings!$H$6:$H$205,$B25),"mmm-yy")&" – "&TEXT(MAX(_xlfn.MAXIFS(Holdings!$J$6:$J$205,Holdings!$H$6:$H$205,$B25),_xlfn.MAXIFS(Holdings!$K$6:$K$205,Holdings!$H$6:$H$205,$B25)),"mmm-yy")) -> Feb-24 – Aug-25 | D25: =SUMIFS(Holdings!$M$6:$M$205,Holdings!$H$6:$H$205,$B25)/Divisor -> 3.96 | E25: =SUMIFS(Holdings!$R$6:$R$205,Holdings!$H$6:$H$205,$B25)/Divisor -> 4.76676 | F25: =IF(N($E$31)=0,"",E25/$E$31) -> 0.03442337 | G25: =IF(N($E$24)=0,"",E25/$E$24) -> 0.20921928 | I25: =SUMIFS(Holdings!$U$6:$U$205,Holdings!$H$6:$H$205,$B25)/Divisor -> 0 | K25: =(SUMIFS(Holdings!$V$6:$V$205,Holdings!$H$6:$H$205,$B25)+SUMIFS(Holdings!$S$6:$S$205,Holdings!$H$6:$H$205,$B25))/Divisor -> 0.80676 | M25: =SUMIFS(Holdings!$S$6:$S$205,Holdings!$H$6:$H$205,$B25)/Divisor -> 0.80676 | O25: =IF(N(D25)=0,"",M25/D25) -> 0.20372727 | P25: =IF(SUMIFS(Holdings!$AQ$6:$AQ$205,Holdings!$H$6:$H$205,$B25)=0,"",SUMIFS(Holdings!$AP$6:$AP$205,Holdings!$H$6:$H$205,$B25)/SUMIFS(Holdings!$AQ$6:$AQ$205,Holdings!$H$6:$H$205,$B25)) -> 0.20945455 | R25: =IF(SUMIFS(Holdings!$AN$6:$AN$205,Holdings!$H$6:$H$205,$B25)=0,"",SUMIFS(Holdings!$AM$6:$AM$205,Holdings!$H$6:$H$205,$B25)/SUMIFS(Holdings!$AN$6:$AN$205,Holdings!$H$6:$H$205,$B25)) -> 0.116 | S25: =IF(SUMIFS(Holdings!$AN$6:$AN$205,Holdings!$H$6:$H$205,$B25)=0,"",SUMIFS(Holdings!$AO$6:$AO$205,Holdings!$H$6:$H$205,$B25)/SUMIFS(Holdings!$AN$6:$AN$205,Holdings!$H$6:$H$205,$B25)) -> 0.123 | T25: =IF(N(E25)=0,"",SUMIFS(Holdings!$AN$6:$AN$205,Holdings!$H$6:$H$205,$B25)/Divisor/E25) -> 0.63597916
B26: =Lists!$D$21 -> REIT / InvIT | C26: =IF(COUNTIFS(Holdings!$H$6:$H$205,$B26,Holdings!$J$6:$J$205,">0")=0,"",TEXT(_xlfn.MINIFS(Holdings!$J$6:$J$205,Holdings!$H$6:$H$205,$B26),"mmm-yy")&" – "&TEXT(MAX(_xlfn.MAXIFS(Holdings!$J$6:$J$205,Holdings!$H$6:$H$205,$B26),_xlfn.MAXIFS(Holdings!$K$6:$K$205,Holdings!$H$6:$H$205,$B26)),"mmm-yy")) -> Oct-24 – Oct-24 | D26: =SUMIFS(Holdings!$M$6:$M$205,Holdings!$H$6:$H$205,$B26)/Divisor -> 4.4 | E26: =SUMIFS(Holdings!$R$6:$R$205,Holdings!$H$6:$H$205,$B26)/Divisor -> 4.728 | F26: =IF(N($E$31)=0,"",E26/$E$31) -> 0.034143463 | G26: =IF(N($E$24)=0,"",E26/$E$24) -> 0.20751805 | I26: =SUMIFS(Holdings!$U$6:$U$205,Holdings!$H$6:$H$205,$B26)/Divisor -> 0.36 | K26: =(SUMIFS(Holdings!$V$6:$V$205,Holdings!$H$6:$H$205,$B26)+SUMIFS(Holdings!$S$6:$S$205,Holdings!$H$6:$H$205,$B26))/Divisor -> 0.328 | M26: =SUMIFS(Holdings!$S$6:$S$205,Holdings!$H$6:$H$205,$B26)/Divisor -> 0.328 | O26: =IF(N(D26)=0,"",M26/D26) -> 0.074545455 | P26: =IF(SUMIFS(Holdings!$AQ$6:$AQ$205,Holdings!$H$6:$H$205,$B26)=0,"",SUMIFS(Holdings!$AP$6:$AP$205,Holdings!$H$6:$H$205,$B26)/SUMIFS(Holdings!$AQ$6:$AQ$205,Holdings!$H$6:$H$205,$B26)) -> 0.119 | R26: =IF(SUMIFS(Holdings!$AN$6:$AN$205,Holdings!$H$6:$H$205,$B26)=0,"",SUMIFS(Holdings!$AM$6:$AM$205,Holdings!$H$6:$H$205,$B26)/SUMIFS(Holdings!$AN$6:$AN$205,Holdings!$H$6:$H$205,$B26)) -> 0.126 | S26: =IF(SUMIFS(Holdings!$AN$6:$AN$205,Holdings!$H$6:$H$205,$B26)=0,"",SUMIFS(Holdings!$AO$6:$AO$205,Holdings!$H$6:$H$205,$B26)/SUMIFS(Holdings!$AN$6:$AN$205,Holdings!$H$6:$H$205,$B26)) -> 0.091 | T26: =IF(N(E26)=0,"",SUMIFS(Holdings!$AN$6:$AN$205,Holdings!$H$6:$H$205,$B26)/Divisor/E26) -> 1
B27: =Lists!$D$22 -> AIF Cat I / II – PE / VC Fund | C27: =IF(COUNTIFS(Holdings!$H$6:$H$205,$B27,Holdings!$J$6:$J$205,">0")=0,"",TEXT(_xlfn.MINIFS(Holdings!$J$6:$J$205,Holdings!$H$6:$H$205,$B27),"mmm-yy")&" – "&TEXT(MAX(_xlfn.MAXIFS(Holdings!$J$6:$J$205,Holdings!$H$6:$H$205,$B27),_xlfn.MAXIFS(Holdings!$K$6:$K$205,Holdings!$H$6:$H$205,$B27)),"mmm-yy")) -> Sep-23 – Apr-26 | D27: =SUMIFS(Holdings!$M$6:$M$205,Holdings!$H$6:$H$205,$B27)/Divisor -> 6 | E27: =SUMIFS(Holdings!$R$6:$R$205,Holdings!$H$6:$H$205,$B27)/Divisor -> 7.5888 | F27: =IF(N($E$31)=0,"",E27/$E$31) -> 0.054802858 | G27: =IF(N($E$24)=0,"",E27/$E$24) -> 0.33308228 | I27: =SUMIFS(Holdings!$U$6:$U$205,Holdings!$H$6:$H$205,$B27)/Divisor -> 0 | K27: =(SUMIFS(Holdings!$V$6:$V$205,Holdings!$H$6:$H$205,$B27)+SUMIFS(Holdings!$S$6:$S$205,Holdings!$H$6:$H$205,$B27))/Divisor -> 1.7988 | M27: =SUMIFS(Holdings!$S$6:$S$205,Holdings!$H$6:$H$205,$B27)/Divisor -> 1.5888 | O27: =IF(N(D27)=0,"",M27/D27) -> 0.2648 | P27: =IF(SUMIFS(Holdings!$AQ$6:$AQ$205,Holdings!$H$6:$H$205,$B27)=0,"",SUMIFS(Holdings!$AP$6:$AP$205,Holdings!$H$6:$H$205,$B27)/SUMIFS(Holdings!$AQ$6:$AQ$205,Holdings!$H$6:$H$205,$B27)) -> 0.34 | R27: =IF(SUMIFS(Holdings!$AN$6:$AN$205,Holdings!$H$6:$H$205,$B27)=0,"",SUMIFS(Holdings!$AM$6:$AM$205,Holdings!$H$6:$H$205,$B27)/SUMIFS(Holdings!$AN$6:$AN$205,Holdings!$H$6:$H$205,$B27)) -> 0.151 | S27: =IF(SUMIFS(Holdings!$AN$6:$AN$205,Holdings!$H$6:$H$205,$B27)=0,"",SUMIFS(Holdings!$AO$6:$AO$205,Holdings!$H$6:$H$205,$B27)/SUMIFS(Holdings!$AN$6:$AN$205,Holdings!$H$6:$H$205,$B27)) -> 0.128 | T27: =IF(N(E27)=0,"",SUMIFS(Holdings!$AN$6:$AN$205,Holdings!$H$6:$H$205,$B27)/Divisor/E27) -> 1
B28: =Lists!$D$23 -> Private Equity – Unlisted Shares | C28: =IF(COUNTIFS(Holdings!$H$6:$H$205,$B28,Holdings!$J$6:$J$205,">0")=0,"",TEXT(_xlfn.MINIFS(Holdings!$J$6:$J$205,Holdings!$H$6:$H$205,$B28),"mmm-yy")&" – "&TEXT(MAX(_xlfn.MAXIFS(Holdings!$J$6:$J$205,Holdings!$H$6:$H$205,$B28),_xlfn.MAXIFS(Holdings!$K$6:$K$205,Holdings!$H$6:$H$205,$B28)),"mmm-yy")) -> Aug-24 – Jan-26 | D28: =SUMIFS(Holdings!$M$6:$M$205,Holdings!$H$6:$H$205,$B28)/Divisor -> 2.5 | E28: =SUMIFS(Holdings!$R$6:$R$205,Holdings!$H$6:$H$205,$B28)/Divisor -> 2.5 | F28: =IF(N($E$31)=0,"",E28/$E$31) -> 0.018053861 | G28: =IF(N($E$24)=0,"",E28/$E$24) -> 0.10972824 | I28: =SUMIFS(Holdings!$U$6:$U$205,Holdings!$H$6:$H$205,$B28)/Divisor -> 0 | K28: =(SUMIFS(Holdings!$V$6:$V$205,Holdings!$H$6:$H$205,$B28)+SUMIFS(Holdings!$S$6:$S$205,Holdings!$H$6:$H$205,$B28))/Divisor -> 0 | M28: =SUMIFS(Holdings!$S$6:$S$205,Holdings!$H$6:$H$205,$B28)/Divisor -> 0 | O28: =IF(N(D28)=0,"",M28/D28) -> 0 | P28: =IF(SUMIFS(Holdings!$AQ$6:$AQ$205,Holdings!$H$6:$H$205,$B28)=0,"",SUMIFS(Holdings!$AP$6:$AP$205,Holdings!$H$6:$H$205,$B28)/SUMIFS(Holdings!$AQ$6:$AQ$205,Holdings!$H$6:$H$205,$B28)) | R28: =IF(SUMIFS(Holdings!$AN$6:$AN$205,Holdings!$H$6:$H$205,$B28)=0,"",SUMIFS(Holdings!$AM$6:$AM$205,Holdings!$H$6:$H$205,$B28)/SUMIFS(Holdings!$AN$6:$AN$205,Holdings!$H$6:$H$205,$B28)) | S28: =IF(SUMIFS(Holdings!$AN$6:$AN$205,Holdings!$H$6:$H$205,$B28)=0,"",SUMIFS(Holdings!$AO$6:$AO$205,Holdings!$H$6:$H$205,$B28)/SUMIFS(Holdings!$AN$6:$AN$205,Holdings!$H$6:$H$205,$B28)) | T28: =IF(N(E28)=0,"",SUMIFS(Holdings!$AN$6:$AN$205,Holdings!$H$6:$H$205,$B28)/Divisor/E28) -> 0
B29: =Lists!$D$24 -> Pre-IPO | C29: =IF(COUNTIFS(Holdings!$H$6:$H$205,$B29,Holdings!$J$6:$J$205,">0")=0,"",TEXT(_xlfn.MINIFS(Holdings!$J$6:$J$205,Holdings!$H$6:$H$205,$B29),"mmm-yy")&" – "&TEXT(MAX(_xlfn.MAXIFS(Holdings!$J$6:$J$205,Holdings!$H$6:$H$205,$B29),_xlfn.MAXIFS(Holdings!$K$6:$K$205,Holdings!$H$6:$H$205,$B29)),"mmm-yy")) -> Nov-25 – Nov-25 | D29: =SUMIFS(Holdings!$M$6:$M$205,Holdings!$H$6:$H$205,$B29)/Divisor -> 3.2 | E29: =SUMIFS(Holdings!$R$6:$R$205,Holdings!$H$6:$H$205,$B29)/Divisor -> 3.2 | F29: =IF(N($E$31)=0,"",E29/$E$31) -> 0.023108943 | G29: =IF(N($E$24)=0,"",E29/$E$24) -> 0.14045215 | I29: =SUMIFS(Holdings!$U$6:$U$205,Holdings!$H$6:$H$205,$B29)/Divisor -> 0 | K29: =(SUMIFS(Holdings!$V$6:$V$205,Holdings!$H$6:$H$205,$B29)+SUMIFS(Holdings!$S$6:$S$205,Holdings!$H$6:$H$205,$B29))/Divisor -> 0 | M29: =SUMIFS(Holdings!$S$6:$S$205,Holdings!$H$6:$H$205,$B29)/Divisor -> 0 | O29: =IF(N(D29)=0,"",M29/D29) -> 0 | P29: =IF(SUMIFS(Holdings!$AQ$6:$AQ$205,Holdings!$H$6:$H$205,$B29)=0,"",SUMIFS(Holdings!$AP$6:$AP$205,Holdings!$H$6:$H$205,$B29)/SUMIFS(Holdings!$AQ$6:$AQ$205,Holdings!$H$6:$H$205,$B29)) | R29: =IF(SUMIFS(Holdings!$AN$6:$AN$205,Holdings!$H$6:$H$205,$B29)=0,"",SUMIFS(Holdings!$AM$6:$AM$205,Holdings!$H$6:$H$205,$B29)/SUMIFS(Holdings!$AN$6:$AN$205,Holdings!$H$6:$H$205,$B29)) | S29: =IF(SUMIFS(Holdings!$AN$6:$AN$205,Holdings!$H$6:$H$205,$B29)=0,"",SUMIFS(Holdings!$AO$6:$AO$205,Holdings!$H$6:$H$205,$B29)/SUMIFS(Holdings!$AN$6:$AN$205,Holdings!$H$6:$H$205,$B29)) | T29: =IF(N(E29)=0,"",SUMIFS(Holdings!$AN$6:$AN$205,Holdings!$H$6:$H$205,$B29)/Divisor/E29) -> 0
B31: Total | C31: =IF(COUNT(Holdings!$J$6:$J$205)=0,"",TEXT(MIN(Holdings!$J$6:$J$205),"mmm-yy")&" – "&TEXT(MAX(MAX(Holdings!$J$6:$J$205),MAX(Holdings!$K$6:$K$205)),"mmm-yy")) -> Mar-16 – Jun-26 | D31: =SUM(Holdings!$M$6:$M$205)/Divisor -> 110.19353 | E31: =SUM(Holdings!$R$6:$R$205)/Divisor -> 138.47453 | F31: =N(F7)+N(F15)+N(F20)+N(F24) -> 1 | I31: =SUM(Holdings!$U$6:$U$205)/Divisor -> 1.2235 | K31: =(SUM(Holdings!$V$6:$V$205)+SUM(Holdings!$S$6:$S$205))/Divisor -> 32.890001 | M31: =SUM(Holdings!$S$6:$S$205)/Divisor -> 28.281001 | O31: =IF(N(D31)=0,"",M31/D31) -> 0.25664847 | P31: =IF(SUM(Holdings!$AQ$6:$AQ$205)=0,"",SUM(Holdings!$AP$6:$AP$205)/SUM(Holdings!$AQ$6:$AQ$205)) -> 0.3565445 | R31: =IF(SUM(Holdings!$AN$6:$AN$205)=0,"",SUM(Holdings!$AM$6:$AM$205)/SUM(Holdings!$AN$6:$AN$205)) -> 0.13698029 | S31: =IF(SUM(Holdings!$AN$6:$AN$205)=0,"",SUM(Holdings!$AO$6:$AO$205)/SUM(Holdings!$AN$6:$AN$205)) -> 0.1215454 | T31: =IF(N(E31)=0,"",SUM(Holdings!$AN$6:$AN$205)/Divisor/E31) -> 0.76705776
B33: Returns: a holding held under a year shows its absolute return; a year or more, the XIRR its statement reports. A category's XIRR is value-weighted across its holdings, so read it as indicative.
B34: Private equity and pre-IPO shares are shown at cost until a priced round or a listing, so they carry no gain. Cash balances carry no return.
B35: Blended index: the benchmark return over the holdings that report one — cost-weighted for the absolute return, value-weighted for the XIRR. 'Share of value covered' is the part of the row's value that has an XIRR.
B36: Gain including redeemed = gain on what is held + realised gain on exits (Holdings). Dividend / interest is what each statement reports as received.
B38: PRIVATE MARKET COMMITMENTS — AIFs and private deals with a drawdown (first 10 rows of the Commitments sheet; the total covers every row)
B39: Fund | C39: Entity | D39: Committed | E39: Called to date | F39: % called | G39: Paid to date | I39: Uncalled | K39: Called, not yet paid | M39: Distributions received | O39: Current value | P39: TVPI (x) | R39: DPI (x) | S39: Next call date | T39: Next call amount
B40: =IF(INDEX(Commitments!$A$6:$A$35,1)="","",INDEX(Commitments!$E$6:$E$35,1)&"") -> Fernhill Ventures Fund II – Class A | C40: =IF(INDEX(Commitments!$A$6:$A$35,1)="","",INDEX(Commitments!$D$6:$D$35,1)&"") -> Malhotra Family Trust | D40: =IF(INDEX(Commitments!$A$6:$A$35,1)="","",IF(INDEX(Commitments!$G$6:$G$35,1)="","",INDEX(Commitments!$G$6:$G$35,1)/Divisor)) -> 10 | E40: =IF(INDEX(Commitments!$A$6:$A$35,1)="","",IF(INDEX(Commitments!$H$6:$H$35,1)="","",INDEX(Commitments!$H$6:$H$35,1)/Divisor)) -> 6 | F40: =IF(INDEX(Commitments!$A$6:$A$35,1)="","",IF(INDEX(Commitments!$M$6:$M$35,1)="","",INDEX(Commitments!$M$6:$M$35,1))) -> 0.6 | G40: =IF(INDEX(Commitments!$A$6:$A$35,1)="","",IF(INDEX(Commitments!$I$6:$I$35,1)="","",INDEX(Commitments!$I$6:$I$35,1)/Divisor)) -> 6 | I40: =IF(INDEX(Commitments!$A$6:$A$35,1)="","",IF(INDEX(Commitments!$K$6:$K$35,1)="","",INDEX(Commitments!$K$6:$K$35,1)/Divisor)) -> 4 | K40: =IF(INDEX(Commitments!$A$6:$A$35,1)="","",IF(INDEX(Commitments!$L$6:$L$35,1)="","",INDEX(Commitments!$L$6:$L$35,1)/Divisor)) -> 0 | M40: =IF(INDEX(Commitments!$A$6:$A$35,1)="","",IF(INDEX(Commitments!$J$6:$J$35,1)="","",INDEX(Commitments!$J$6:$J$35,1)/Divisor)) -> 0.85 | O40: =IF(INDEX(Commitments!$A$6:$A$35,1)="","",IF(INDEX(Commitments!$N$6:$N$35,1)="","",INDEX(Commitments!$N$6:$N$35,1)/Divisor)) -> 7.5888 | P40: =IF(INDEX(Commitments!$A$6:$A$35,1)="","",IF(INDEX(Commitments!$O$6:$O$35,1)="","",INDEX(Commitments!$O$6:$O$35,1))) -> 1.4064667 | R40: =IF(INDEX(Commitments!$A$6:$A$35,1)="","",IF(INDEX(Commitments!$P$6:$P$35,1)="","",INDEX(Commitments!$P$6:$P$35,1))) -> 0.14166667 | S40: =IF(INDEX(Commitments!$A$6:$A$35,1)="","",IF(INDEX(Commitments!$Q$6:$Q$35,1)="","",INDEX(Commitments!$Q$6:$Q$35,1))) -> 46280 | T40: =IF(INDEX(Commitments!$A$6:$A$35,1)="","",IF(INDEX(Commitments!$R$6:$R$35,1)="","",INDEX(Commitments!$R$6:$R$35,1)/Divisor)) -> 1
B41: =IF(INDEX(Commitments!$A$6:$A$35,2)="","",INDEX(Commitments!$E$6:$E$35,2)&"") -> Quill Robotics Pvt Ltd – Series A CCPS | C41: =IF(INDEX(Commitments!$A$6:$A$35,2)="","",INDEX(Commitments!$D$6:$D$35,2)&"") -> Rajiv Malhotra | D41: =IF(INDEX(Commitments!$A$6:$A$35,2)="","",IF(INDEX(Commitments!$G$6:$G$35,2)="","",INDEX(Commitments!$G$6:$G$35,2)/Divisor)) -> 3 | E41: =IF(INDEX(Commitments!$A$6:$A$35,2)="","",IF(INDEX(Commitments!$H$6:$H$35,2)="","",INDEX(Commitments!$H$6:$H$35,2)/Divisor)) -> 2.5 | F41: =IF(INDEX(Commitments!$A$6:$A$35,2)="","",IF(INDEX(Commitments!$M$6:$M$35,2)="","",INDEX(Commitments!$M$6:$M$35,2))) -> 0.83333333 | G41: =IF(INDEX(Commitments!$A$6:$A$35,2)="","",IF(INDEX(Commitments!$I$6:$I$35,2)="","",INDEX(Commitments!$I$6:$I$35,2)/Divisor)) -> 2.5 | I41: =IF(INDEX(Commitments!$A$6:$A$35,2)="","",IF(INDEX(Commitments!$K$6:$K$35,2)="","",INDEX(Commitments!$K$6:$K$35,2)/Divisor)) -> 0.5 | K41: =IF(INDEX(Commitments!$A$6:$A$35,2)="","",IF(INDEX(Commitments!$L$6:$L$35,2)="","",INDEX(Commitments!$L$6:$L$35,2)/Divisor)) -> 0 | M41: =IF(INDEX(Commitments!$A$6:$A$35,2)="","",IF(INDEX(Commitments!$J$6:$J$35,2)="","",INDEX(Commitments!$J$6:$J$35,2)/Divisor)) -> 0 | O41: =IF(INDEX(Commitments!$A$6:$A$35,2)="","",IF(INDEX(Commitments!$N$6:$N$35,2)="","",INDEX(Commitments!$N$6:$N$35,2)/Divisor)) -> 2.5 | P41: =IF(INDEX(Commitments!$A$6:$A$35,2)="","",IF(INDEX(Commitments!$O$6:$O$35,2)="","",INDEX(Commitments!$O$6:$O$35,2))) -> 1 | R41: =IF(INDEX(Commitments!$A$6:$A$35,2)="","",IF(INDEX(Commitments!$P$6:$P$35,2)="","",INDEX(Commitments!$P$6:$P$35,2))) -> 0 | S41: =IF(INDEX(Commitments!$A$6:$A$35,2)="","",IF(INDEX(Commitments!$Q$6:$Q$35,2)="","",INDEX(Commitments!$Q$6:$Q$35,2))) -> 46305 | T41: =IF(INDEX(Commitments!$A$6:$A$35,2)="","",IF(INDEX(Commitments!$R$6:$R$35,2)="","",INDEX(Commitments!$R$6:$R$35,2)/Divisor)) -> 0.5
B42: =IF(INDEX(Commitments!$A$6:$A$35,3)="","",INDEX(Commitments!$E$6:$E$35,3)&"") -> Rangoli Foods Pvt Ltd – Equity | C42: =IF(INDEX(Commitments!$A$6:$A$35,3)="","",INDEX(Commitments!$D$6:$D$35,3)&"") -> Malhotra Holdings LLP | D42: =IF(INDEX(Commitments!$A$6:$A$35,3)="","",IF(INDEX(Commitments!$G$6:$G$35,3)="","",INDEX(Commitments!$G$6:$G$35,3)/Divisor)) -> 3.2 | E42: =IF(INDEX(Commitments!$A$6:$A$35,3)="","",IF(INDEX(Commitments!$H$6:$H$35,3)="","",INDEX(Commitments!$H$6:$H$35,3)/Divisor)) -> 3.2 | F42: =IF(INDEX(Commitments!$A$6:$A$35,3)="","",IF(INDEX(Commitments!$M$6:$M$35,3)="","",INDEX(Commitments!$M$6:$M$35,3))) -> 1 | G42: =IF(INDEX(Commitments!$A$6:$A$35,3)="","",IF(INDEX(Commitments!$I$6:$I$35,3)="","",INDEX(Commitments!$I$6:$I$35,3)/Divisor)) -> 3.2 | I42: =IF(INDEX(Commitments!$A$6:$A$35,3)="","",IF(INDEX(Commitments!$K$6:$K$35,3)="","",INDEX(Commitments!$K$6:$K$35,3)/Divisor)) -> 0 | K42: =IF(INDEX(Commitments!$A$6:$A$35,3)="","",IF(INDEX(Commitments!$L$6:$L$35,3)="","",INDEX(Commitments!$L$6:$L$35,3)/Divisor)) -> 0 | M42: =IF(INDEX(Commitments!$A$6:$A$35,3)="","",IF(INDEX(Commitments!$J$6:$J$35,3)="","",INDEX(Commitments!$J$6:$J$35,3)/Divisor)) -> 0 | O42: =IF(INDEX(Commitments!$A$6:$A$35,3)="","",IF(INDEX(Commitments!$N$6:$N$35,3)="","",INDEX(Commitments!$N$6:$N$35,3)/Divisor)) -> 3.2 | P42: =IF(INDEX(Commitments!$A$6:$A$35,3)="","",IF(INDEX(Commitments!$O$6:$O$35,3)="","",INDEX(Commitments!$O$6:$O$35,3))) -> 1 | R42: =IF(INDEX(Commitments!$A$6:$A$35,3)="","",IF(INDEX(Commitments!$P$6:$P$35,3)="","",INDEX(Commitments!$P$6:$P$35,3))) -> 0 | S42: =IF(INDEX(Commitments!$A$6:$A$35,3)="","",IF(INDEX(Commitments!$Q$6:$Q$35,3)="","",INDEX(Commitments!$Q$6:$Q$35,3))) | T42: =IF(INDEX(Commitments!$A$6:$A$35,3)="","",IF(INDEX(Commitments!$R$6:$R$35,3)="","",INDEX(Commitments!$R$6:$R$35,3)/Divisor))
B43: =IF(INDEX(Commitments!$A$6:$A$35,4)="","",INDEX(Commitments!$E$6:$E$35,4)&"") -> Sahyadri Private Credit Fund – Series I | C43: =IF(INDEX(Commitments!$A$6:$A$35,4)="","",INDEX(Commitments!$D$6:$D$35,4)&"") -> Malhotra Family Trust | D43: =IF(INDEX(Commitments!$A$6:$A$35,4)="","",IF(INDEX(Commitments!$G$6:$G$35,4)="","",INDEX(Commitments!$G$6:$G$35,4)/Divisor)) -> 5 | E43: =IF(INDEX(Commitments!$A$6:$A$35,4)="","",IF(INDEX(Commitments!$H$6:$H$35,4)="","",INDEX(Commitments!$H$6:$H$35,4)/Divisor)) -> 1.25 | F43: =IF(INDEX(Commitments!$A$6:$A$35,4)="","",IF(INDEX(Commitments!$M$6:$M$35,4)="","",INDEX(Commitments!$M$6:$M$35,4))) -> 0.25 | G43: =IF(INDEX(Commitments!$A$6:$A$35,4)="","",IF(INDEX(Commitments!$I$6:$I$35,4)="","",INDEX(Commitments!$I$6:$I$35,4)/Divisor)) -> 1 | I43: =IF(INDEX(Commitments!$A$6:$A$35,4)="","",IF(INDEX(Commitments!$K$6:$K$35,4)="","",INDEX(Commitments!$K$6:$K$35,4)/Divisor)) -> 3.75 | K43: =IF(INDEX(Commitments!$A$6:$A$35,4)="","",IF(INDEX(Commitments!$L$6:$L$35,4)="","",INDEX(Commitments!$L$6:$L$35,4)/Divisor)) -> 0.25 | M43: =IF(INDEX(Commitments!$A$6:$A$35,4)="","",IF(INDEX(Commitments!$J$6:$J$35,4)="","",INDEX(Commitments!$J$6:$J$35,4)/Divisor)) -> 0 | O43: =IF(INDEX(Commitments!$A$6:$A$35,4)="","",IF(INDEX(Commitments!$N$6:$N$35,4)="","",INDEX(Commitments!$N$6:$N$35,4)/Divisor)) -> 1.0382 | P43: =IF(INDEX(Commitments!$A$6:$A$35,4)="","",IF(INDEX(Commitments!$O$6:$O$35,4)="","",INDEX(Commitments!$O$6:$O$35,4))) -> 1.0382 | R43: =IF(INDEX(Commitments!$A$6:$A$35,4)="","",IF(INDEX(Commitments!$P$6:$P$35,4)="","",INDEX(Commitments!$P$6:$P$35,4))) -> 0 | S43: =IF(INDEX(Commitments!$A$6:$A$35,4)="","",IF(INDEX(Commitments!$Q$6:$Q$35,4)="","",INDEX(Commitments!$Q$6:$Q$35,4))) -> 46315 | T43: =IF(INDEX(Commitments!$A$6:$A$35,4)="","",IF(INDEX(Commitments!$R$6:$R$35,4)="","",INDEX(Commitments!$R$6:$R$35,4)/Divisor)) -> 0.5
B44: =IF(INDEX(Commitments!$A$6:$A$35,5)="","",INDEX(Commitments!$E$6:$E$35,5)&"") | C44: =IF(INDEX(Commitments!$A$6:$A$35,5)="","",INDEX(Commitments!$D$6:$D$35,5)&"") | D44: =IF(INDEX(Commitments!$A$6:$A$35,5)="","",IF(INDEX(Commitments!$G$6:$G$35,5)="","",INDEX(Commitments!$G$6:$G$35,5)/Divisor)) | E44: =IF(INDEX(Commitments!$A$6:$A$35,5)="","",IF(INDEX(Commitments!$H$6:$H$35,5)="","",INDEX(Commitments!$H$6:$H$35,5)/Divisor)) | F44: =IF(INDEX(Commitments!$A$6:$A$35,5)="","",IF(INDEX(Commitments!$M$6:$M$35,5)="","",INDEX(Commitments!$M$6:$M$35,5))) | G44: =IF(INDEX(Commitments!$A$6:$A$35,5)="","",IF(INDEX(Commitments!$I$6:$I$35,5)="","",INDEX(Commitments!$I$6:$I$35,5)/Divisor)) | I44: =IF(INDEX(Commitments!$A$6:$A$35,5)="","",IF(INDEX(Commitments!$K$6:$K$35,5)="","",INDEX(Commitments!$K$6:$K$35,5)/Divisor)) | K44: =IF(INDEX(Commitments!$A$6:$A$35,5)="","",IF(INDEX(Commitments!$L$6:$L$35,5)="","",INDEX(Commitments!$L$6:$L$35,5)/Divisor)) | M44: =IF(INDEX(Commitments!$A$6:$A$35,5)="","",IF(INDEX(Commitments!$J$6:$J$35,5)="","",INDEX(Commitments!$J$6:$J$35,5)/Divisor)) | O44: =IF(INDEX(Commitments!$A$6:$A$35,5)="","",IF(INDEX(Commitments!$N$6:$N$35,5)="","",INDEX(Commitments!$N$6:$N$35,5)/Divisor)) | P44: =IF(INDEX(Commitments!$A$6:$A$35,5)="","",IF(INDEX(Commitments!$O$6:$O$35,5)="","",INDEX(Commitments!$O$6:$O$35,5))) | R44: =IF(INDEX(Commitments!$A$6:$A$35,5)="","",IF(INDEX(Commitments!$P$6:$P$35,5)="","",INDEX(Commitments!$P$6:$P$35,5))) | S44: =IF(INDEX(Commitments!$A$6:$A$35,5)="","",IF(INDEX(Commitments!$Q$6:$Q$35,5)="","",INDEX(Commitments!$Q$6:$Q$35,5))) | T44: =IF(INDEX(Commitments!$A$6:$A$35,5)="","",IF(INDEX(Commitments!$R$6:$R$35,5)="","",INDEX(Commitments!$R$6:$R$35,5)/Divisor))
B45: =IF(INDEX(Commitments!$A$6:$A$35,6)="","",INDEX(Commitments!$E$6:$E$35,6)&"") | C45: =IF(INDEX(Commitments!$A$6:$A$35,6)="","",INDEX(Commitments!$D$6:$D$35,6)&"") | D45: =IF(INDEX(Commitments!$A$6:$A$35,6)="","",IF(INDEX(Commitments!$G$6:$G$35,6)="","",INDEX(Commitments!$G$6:$G$35,6)/Divisor)) | E45: =IF(INDEX(Commitments!$A$6:$A$35,6)="","",IF(INDEX(Commitments!$H$6:$H$35,6)="","",INDEX(Commitments!$H$6:$H$35,6)/Divisor)) | F45: =IF(INDEX(Commitments!$A$6:$A$35,6)="","",IF(INDEX(Commitments!$M$6:$M$35,6)="","",INDEX(Commitments!$M$6:$M$35,6))) | G45: =IF(INDEX(Commitments!$A$6:$A$35,6)="","",IF(INDEX(Commitments!$I$6:$I$35,6)="","",INDEX(Commitments!$I$6:$I$35,6)/Divisor)) | I45: =IF(INDEX(Commitments!$A$6:$A$35,6)="","",IF(INDEX(Commitments!$K$6:$K$35,6)="","",INDEX(Commitments!$K$6:$K$35,6)/Divisor)) | K45: =IF(INDEX(Commitments!$A$6:$A$35,6)="","",IF(INDEX(Commitments!$L$6:$L$35,6)="","",INDEX(Commitments!$L$6:$L$35,6)/Divisor)) | M45: =IF(INDEX(Commitments!$A$6:$A$35,6)="","",IF(INDEX(Commitments!$J$6:$J$35,6)="","",INDEX(Commitments!$J$6:$J$35,6)/Divisor)) | O45: =IF(INDEX(Commitments!$A$6:$A$35,6)="","",IF(INDEX(Commitments!$N$6:$N$35,6)="","",INDEX(Commitments!$N$6:$N$35,6)/Divisor)) | P45: =IF(INDEX(Commitments!$A$6:$A$35,6)="","",IF(INDEX(Commitments!$O$6:$O$35,6)="","",INDEX(Commitments!$O$6:$O$35,6))) | R45: =IF(INDEX(Commitments!$A$6:$A$35,6)="","",IF(INDEX(Commitments!$P$6:$P$35,6)="","",INDEX(Commitments!$P$6:$P$35,6))) | S45: =IF(INDEX(Commitments!$A$6:$A$35,6)="","",IF(INDEX(Commitments!$Q$6:$Q$35,6)="","",INDEX(Commitments!$Q$6:$Q$35,6))) | T45: =IF(INDEX(Commitments!$A$6:$A$35,6)="","",IF(INDEX(Commitments!$R$6:$R$35,6)="","",INDEX(Commitments!$R$6:$R$35,6)/Divisor))
B46: =IF(INDEX(Commitments!$A$6:$A$35,7)="","",INDEX(Commitments!$E$6:$E$35,7)&"") | C46: =IF(INDEX(Commitments!$A$6:$A$35,7)="","",INDEX(Commitments!$D$6:$D$35,7)&"") | D46: =IF(INDEX(Commitments!$A$6:$A$35,7)="","",IF(INDEX(Commitments!$G$6:$G$35,7)="","",INDEX(Commitments!$G$6:$G$35,7)/Divisor)) | E46: =IF(INDEX(Commitments!$A$6:$A$35,7)="","",IF(INDEX(Commitments!$H$6:$H$35,7)="","",INDEX(Commitments!$H$6:$H$35,7)/Divisor)) | F46: =IF(INDEX(Commitments!$A$6:$A$35,7)="","",IF(INDEX(Commitments!$M$6:$M$35,7)="","",INDEX(Commitments!$M$6:$M$35,7))) | G46: =IF(INDEX(Commitments!$A$6:$A$35,7)="","",IF(INDEX(Commitments!$I$6:$I$35,7)="","",INDEX(Commitments!$I$6:$I$35,7)/Divisor)) | I46: =IF(INDEX(Commitments!$A$6:$A$35,7)="","",IF(INDEX(Commitments!$K$6:$K$35,7)="","",INDEX(Commitments!$K$6:$K$35,7)/Divisor)) | K46: =IF(INDEX(Commitments!$A$6:$A$35,7)="","",IF(INDEX(Commitments!$L$6:$L$35,7)="","",INDEX(Commitments!$L$6:$L$35,7)/Divisor)) | M46: =IF(INDEX(Commitments!$A$6:$A$35,7)="","",IF(INDEX(Commitments!$J$6:$J$35,7)="","",INDEX(Commitments!$J$6:$J$35,7)/Divisor)) | O46: =IF(INDEX(Commitments!$A$6:$A$35,7)="","",IF(INDEX(Commitments!$N$6:$N$35,7)="","",INDEX(Commitments!$N$6:$N$35,7)/Divisor)) | P46: =IF(INDEX(Commitments!$A$6:$A$35,7)="","",IF(INDEX(Commitments!$O$6:$O$35,7)="","",INDEX(Commitments!$O$6:$O$35,7))) | R46: =IF(INDEX(Commitments!$A$6:$A$35,7)="","",IF(INDEX(Commitments!$P$6:$P$35,7)="","",INDEX(Commitments!$P$6:$P$35,7))) | S46: =IF(INDEX(Commitments!$A$6:$A$35,7)="","",IF(INDEX(Commitments!$Q$6:$Q$35,7)="","",INDEX(Commitments!$Q$6:$Q$35,7))) | T46: =IF(INDEX(Commitments!$A$6:$A$35,7)="","",IF(INDEX(Commitments!$R$6:$R$35,7)="","",INDEX(Commitments!$R$6:$R$35,7)/Divisor))
B47: =IF(INDEX(Commitments!$A$6:$A$35,8)="","",INDEX(Commitments!$E$6:$E$35,8)&"") | C47: =IF(INDEX(Commitments!$A$6:$A$35,8)="","",INDEX(Commitments!$D$6:$D$35,8)&"") | D47: =IF(INDEX(Commitments!$A$6:$A$35,8)="","",IF(INDEX(Commitments!$G$6:$G$35,8)="","",INDEX(Commitments!$G$6:$G$35,8)/Divisor)) | E47: =IF(INDEX(Commitments!$A$6:$A$35,8)="","",IF(INDEX(Commitments!$H$6:$H$35,8)="","",INDEX(Commitments!$H$6:$H$35,8)/Divisor)) | F47: =IF(INDEX(Commitments!$A$6:$A$35,8)="","",IF(INDEX(Commitments!$M$6:$M$35,8)="","",INDEX(Commitments!$M$6:$M$35,8))) | G47: =IF(INDEX(Commitments!$A$6:$A$35,8)="","",IF(INDEX(Commitments!$I$6:$I$35,8)="","",INDEX(Commitments!$I$6:$I$35,8)/Divisor)) | I47: =IF(INDEX(Commitments!$A$6:$A$35,8)="","",IF(INDEX(Commitments!$K$6:$K$35,8)="","",INDEX(Commitments!$K$6:$K$35,8)/Divisor)) | K47: =IF(INDEX(Commitments!$A$6:$A$35,8)="","",IF(INDEX(Commitments!$L$6:$L$35,8)="","",INDEX(Commitments!$L$6:$L$35,8)/Divisor)) | M47: =IF(INDEX(Commitments!$A$6:$A$35,8)="","",IF(INDEX(Commitments!$J$6:$J$35,8)="","",INDEX(Commitments!$J$6:$J$35,8)/Divisor)) | O47: =IF(INDEX(Commitments!$A$6:$A$35,8)="","",IF(INDEX(Commitments!$N$6:$N$35,8)="","",INDEX(Commitments!$N$6:$N$35,8)/Divisor)) | P47: =IF(INDEX(Commitments!$A$6:$A$35,8)="","",IF(INDEX(Commitments!$O$6:$O$35,8)="","",INDEX(Commitments!$O$6:$O$35,8))) | R47: =IF(INDEX(Commitments!$A$6:$A$35,8)="","",IF(INDEX(Commitments!$P$6:$P$35,8)="","",INDEX(Commitments!$P$6:$P$35,8))) | S47: =IF(INDEX(Commitments!$A$6:$A$35,8)="","",IF(INDEX(Commitments!$Q$6:$Q$35,8)="","",INDEX(Commitments!$Q$6:$Q$35,8))) | T47: =IF(INDEX(Commitments!$A$6:$A$35,8)="","",IF(INDEX(Commitments!$R$6:$R$35,8)="","",INDEX(Commitments!$R$6:$R$35,8)/Divisor))
B48: =IF(INDEX(Commitments!$A$6:$A$35,9)="","",INDEX(Commitments!$E$6:$E$35,9)&"") | C48: =IF(INDEX(Commitments!$A$6:$A$35,9)="","",INDEX(Commitments!$D$6:$D$35,9)&"") | D48: =IF(INDEX(Commitments!$A$6:$A$35,9)="","",IF(INDEX(Commitments!$G$6:$G$35,9)="","",INDEX(Commitments!$G$6:$G$35,9)/Divisor)) | E48: =IF(INDEX(Commitments!$A$6:$A$35,9)="","",IF(INDEX(Commitments!$H$6:$H$35,9)="","",INDEX(Commitments!$H$6:$H$35,9)/Divisor)) | F48: =IF(INDEX(Commitments!$A$6:$A$35,9)="","",IF(INDEX(Commitments!$M$6:$M$35,9)="","",INDEX(Commitments!$M$6:$M$35,9))) | G48: =IF(INDEX(Commitments!$A$6:$A$35,9)="","",IF(INDEX(Commitments!$I$6:$I$35,9)="","",INDEX(Commitments!$I$6:$I$35,9)/Divisor)) | I48: =IF(INDEX(Commitments!$A$6:$A$35,9)="","",IF(INDEX(Commitments!$K$6:$K$35,9)="","",INDEX(Commitments!$K$6:$K$35,9)/Divisor)) | K48: =IF(INDEX(Commitments!$A$6:$A$35,9)="","",IF(INDEX(Commitments!$L$6:$L$35,9)="","",INDEX(Commitments!$L$6:$L$35,9)/Divisor)) | M48: =IF(INDEX(Commitments!$A$6:$A$35,9)="","",IF(INDEX(Commitments!$J$6:$J$35,9)="","",INDEX(Commitments!$J$6:$J$35,9)/Divisor)) | O48: =IF(INDEX(Commitments!$A$6:$A$35,9)="","",IF(INDEX(Commitments!$N$6:$N$35,9)="","",INDEX(Commitments!$N$6:$N$35,9)/Divisor)) | P48: =IF(INDEX(Commitments!$A$6:$A$35,9)="","",IF(INDEX(Commitments!$O$6:$O$35,9)="","",INDEX(Commitments!$O$6:$O$35,9))) | R48: =IF(INDEX(Commitments!$A$6:$A$35,9)="","",IF(INDEX(Commitments!$P$6:$P$35,9)="","",INDEX(Commitments!$P$6:$P$35,9))) | S48: =IF(INDEX(Commitments!$A$6:$A$35,9)="","",IF(INDEX(Commitments!$Q$6:$Q$35,9)="","",INDEX(Commitments!$Q$6:$Q$35,9))) | T48: =IF(INDEX(Commitments!$A$6:$A$35,9)="","",IF(INDEX(Commitments!$R$6:$R$35,9)="","",INDEX(Commitments!$R$6:$R$35,9)/Divisor))
B49: =IF(INDEX(Commitments!$A$6:$A$35,10)="","",INDEX(Commitments!$E$6:$E$35,10)&"") | C49: =IF(INDEX(Commitments!$A$6:$A$35,10)="","",INDEX(Commitments!$D$6:$D$35,10)&"") | D49: =IF(INDEX(Commitments!$A$6:$A$35,10)="","",IF(INDEX(Commitments!$G$6:$G$35,10)="","",INDEX(Commitments!$G$6:$G$35,10)/Divisor)) | E49: =IF(INDEX(Commitments!$A$6:$A$35,10)="","",IF(INDEX(Commitments!$H$6:$H$35,10)="","",INDEX(Commitments!$H$6:$H$35,10)/Divisor)) | F49: =IF(INDEX(Commitments!$A$6:$A$35,10)="","",IF(INDEX(Commitments!$M$6:$M$35,10)="","",INDEX(Commitments!$M$6:$M$35,10))) | G49: =IF(INDEX(Commitments!$A$6:$A$35,10)="","",IF(INDEX(Commitments!$I$6:$I$35,10)="","",INDEX(Commitments!$I$6:$I$35,10)/Divisor)) | I49: =IF(INDEX(Commitments!$A$6:$A$35,10)="","",IF(INDEX(Commitments!$K$6:$K$35,10)="","",INDEX(Commitments!$K$6:$K$35,10)/Divisor)) | K49: =IF(INDEX(Commitments!$A$6:$A$35,10)="","",IF(INDEX(Commitments!$L$6:$L$35,10)="","",INDEX(Commitments!$L$6:$L$35,10)/Divisor)) | M49: =IF(INDEX(Commitments!$A$6:$A$35,10)="","",IF(INDEX(Commitments!$J$6:$J$35,10)="","",INDEX(Commitments!$J$6:$J$35,10)/Divisor)) | O49: =IF(INDEX(Commitments!$A$6:$A$35,10)="","",IF(INDEX(Commitments!$N$6:$N$35,10)="","",INDEX(Commitments!$N$6:$N$35,10)/Divisor)) | P49: =IF(INDEX(Commitments!$A$6:$A$35,10)="","",IF(INDEX(Commitments!$O$6:$O$35,10)="","",INDEX(Commitments!$O$6:$O$35,10))) | R49: =IF(INDEX(Commitments!$A$6:$A$35,10)="","",IF(INDEX(Commitments!$P$6:$P$35,10)="","",INDEX(Commitments!$P$6:$P$35,10))) | S49: =IF(INDEX(Commitments!$A$6:$A$35,10)="","",IF(INDEX(Commitments!$Q$6:$Q$35,10)="","",INDEX(Commitments!$Q$6:$Q$35,10))) | T49: =IF(INDEX(Commitments!$A$6:$A$35,10)="","",IF(INDEX(Commitments!$R$6:$R$35,10)="","",INDEX(Commitments!$R$6:$R$35,10)/Divisor))
B50: Total — every commitment | D50: =SUM(Commitments!$G$6:$G$35)/Divisor -> 21.2 | E50: =SUM(Commitments!$H$6:$H$35)/Divisor -> 12.95 | F50: =IF(N(D50)=0,"",E50/D50) -> 0.61084906 | G50: =SUM(Commitments!$I$6:$I$35)/Divisor -> 12.7 | I50: =SUM(Commitments!$K$6:$K$35)/Divisor -> 8.25 | K50: =SUM(Commitments!$L$6:$L$35)/Divisor -> 0.25 | M50: =SUM(Commitments!$J$6:$J$35)/Divisor -> 0.85 | O50: =SUM(Commitments!$N$6:$N$35)/Divisor -> 14.327 | P50: =IF(N(G50)=0,"",(O50+M50)/G50) -> 1.1950394 | R50: =IF(N(G50)=0,"",M50/G50) -> 0.066929134 | S50: =IF(COUNT(Commitments!$Q$6:$Q$35)=0,"",MIN(Commitments!$Q$6:$Q$35)) -> 46280 | T50: =SUM(Commitments!$R$6:$R$35)/Divisor -> 2
B51: =IF(COUNTA(Commitments!$A$6:$A$35)>10,COUNTA(Commitments!$A$6:$A$35)-10&" more commitment(s): see the Commitments sheet. The total row includes them.","")
B52: TVPI = (current value + distributions) ÷ paid; DPI = distributions ÷ paid. The total's next call date is the earliest one. Current value is the Holdings row for the same account and security.

Sheet Basket Allocation
A1: ="Basket Allocation — "&ClientName -> Basket Allocation — Malhotra Family Office (DEMO) | R1: =HYPERLINK("#'Start Here'!A1","← Start Here") -> ← Start Here
A2: ="Figures in "&UnitLabel&" · market values as at "&TEXT(ValDate,"dd-mmm-yyyy")&" · each basket's value by asset class, against the family's target" -> Figures in ₹ Crore · market values as at 30-Jun-2026 · each basket's value by asset class, against the family's target
A3: DEMO DATA — illustrative only: a fictional family, fictional securities and figures.
B5: Basket | C5: Code | D5: Market value by asset class | H5: Basket total | J5: Actual allocation (%) | K5: Target allocation (%) | L5: Gap: actual − target (% points) | N5: Investment at cost | O5: Gain / (loss) on what is held | P5: Absolute return (%) | Q5: XIRR (%) | R5: Share of value with an XIRR
D6: =Lists!$A$6 -> Equity | E6: =Lists!$A$7 -> Debt | F6: =Lists!$A$8 -> Cash | G6: =Lists!$A$9 -> Alternate
B7: =Lists!$L$6 -> Stable Growth | C7: =Lists!$K$6 -> SG | D7: =SUMIFS(Holdings!$R$6:$R$205,Holdings!$I$6:$I$205,$C7,Holdings!$G$6:$G$205,D$6)/Divisor -> 57.876525 | E7: =SUMIFS(Holdings!$R$6:$R$205,Holdings!$I$6:$I$205,$C7,Holdings!$G$6:$G$205,E$6)/Divisor -> 13.595184 | F7: =SUMIFS(Holdings!$R$6:$R$205,Holdings!$I$6:$I$205,$C7,Holdings!$G$6:$G$205,F$6)/Divisor -> 0 | G7: =SUMIFS(Holdings!$R$6:$R$205,Holdings!$I$6:$I$205,$C7,Holdings!$G$6:$G$205,G$6)/Divisor -> 4.728 | H7: =SUMIFS(Holdings!$R$6:$R$205,Holdings!$I$6:$I$205,$C7)/Divisor -> 76.199709 | J7: =IF(N($H$11)=0,"",H7/$H$11) -> 0.5502796 | K7: 0.45 | L7: =IF(OR(J7="",K7=""),"",J7-K7) -> 0.1002796 | N7: =SUMIFS(Holdings!$M$6:$M$205,Holdings!$I$6:$I$205,$C7)/Divisor -> 58.4168 | O7: =SUMIFS(Holdings!$S$6:$S$205,Holdings!$I$6:$I$205,$C7)/Divisor -> 17.782909 | P7: =IF(N(N7)=0,"",O7/N7) -> 0.3044143 | Q7: =IF(SUMIFS(Holdings!$AN$6:$AN$205,Holdings!$I$6:$I$205,$C7)=0,"",SUMIFS(Holdings!$AM$6:$AM$205,Holdings!$I$6:$I$205,$C7)/SUMIFS(Holdings!$AN$6:$AN$205,Holdings!$I$6:$I$205,$C7)) -> 0.13130084 | R7: =IF(N(H7)=0,"",SUMIFS(Holdings!$AN$6:$AN$205,Holdings!$I$6:$I$205,$C7)/Divisor/H7) -> 0.98637528
B8: =Lists!$L$7 -> Entrepreneurial Growth | C8: =Lists!$K$7 -> EG | D8: =SUMIFS(Holdings!$R$6:$R$205,Holdings!$I$6:$I$205,$C8,Holdings!$G$6:$G$205,D$6)/Divisor -> 0 | E8: =SUMIFS(Holdings!$R$6:$R$205,Holdings!$I$6:$I$205,$C8,Holdings!$G$6:$G$205,E$6)/Divisor -> 0 | F8: =SUMIFS(Holdings!$R$6:$R$205,Holdings!$I$6:$I$205,$C8,Holdings!$G$6:$G$205,F$6)/Divisor -> 0 | G8: =SUMIFS(Holdings!$R$6:$R$205,Holdings!$I$6:$I$205,$C8,Holdings!$G$6:$G$205,G$6)/Divisor -> 13.2888 | H8: =SUMIFS(Holdings!$R$6:$R$205,Holdings!$I$6:$I$205,$C8)/Divisor -> 13.2888 | J8: =IF(N($H$11)=0,"",H8/$H$11) -> 0.095965662 | K8: 0.12 | L8: =IF(OR(J8="",K8=""),"",J8-K8) -> -0.024034338 | N8: =SUMIFS(Holdings!$M$6:$M$205,Holdings!$I$6:$I$205,$C8)/Divisor -> 11.7 | O8: =SUMIFS(Holdings!$S$6:$S$205,Holdings!$I$6:$I$205,$C8)/Divisor -> 1.5888 | P8: =IF(N(N8)=0,"",O8/N8) -> 0.13579487 | Q8: =IF(SUMIFS(Holdings!$AN$6:$AN$205,Holdings!$I$6:$I$205,$C8)=0,"",SUMIFS(Holdings!$AM$6:$AM$205,Holdings!$I$6:$I$205,$C8)/SUMIFS(Holdings!$AN$6:$AN$205,Holdings!$I$6:$I$205,$C8)) -> 0.151 | R8: =IF(N(H8)=0,"",SUMIFS(Holdings!$AN$6:$AN$205,Holdings!$I$6:$I$205,$C8)/Divisor/H8) -> 0.57106736
B9: =Lists!$L$8 -> Liquidity | C9: =Lists!$K$8 -> LQ | D9: =SUMIFS(Holdings!$R$6:$R$205,Holdings!$I$6:$I$205,$C9,Holdings!$G$6:$G$205,D$6)/Divisor -> 0 | E9: =SUMIFS(Holdings!$R$6:$R$205,Holdings!$I$6:$I$205,$C9,Holdings!$G$6:$G$205,E$6)/Divisor -> 0 | F9: =SUMIFS(Holdings!$R$6:$R$205,Holdings!$I$6:$I$205,$C9,Holdings!$G$6:$G$205,F$6)/Divisor -> 17.741647 | G9: =SUMIFS(Holdings!$R$6:$R$205,Holdings!$I$6:$I$205,$C9,Holdings!$G$6:$G$205,G$6)/Divisor -> 0 | H9: =SUMIFS(Holdings!$R$6:$R$205,Holdings!$I$6:$I$205,$C9)/Divisor -> 17.741647 | J9: =IF(N($H$11)=0,"",H9/$H$11) -> 0.12812209 | K9: 0.15 | L9: =IF(OR(J9="",K9=""),"",J9-K9) -> -0.021877905 | N9: =SUMIFS(Holdings!$M$6:$M$205,Holdings!$I$6:$I$205,$C9)/Divisor -> 17.4556 | O9: =SUMIFS(Holdings!$S$6:$S$205,Holdings!$I$6:$I$205,$C9)/Divisor -> 0.28604696 | P9: =IF(N(N9)=0,"",O9/N9) -> 0.016387117 | Q9: =IF(SUMIFS(Holdings!$AN$6:$AN$205,Holdings!$I$6:$I$205,$C9)=0,"",SUMIFS(Holdings!$AM$6:$AM$205,Holdings!$I$6:$I$205,$C9)/SUMIFS(Holdings!$AN$6:$AN$205,Holdings!$I$6:$I$205,$C9)) | R9: =IF(N(H9)=0,"",SUMIFS(Holdings!$AN$6:$AN$205,Holdings!$I$6:$I$205,$C9)/Divisor/H9) -> 0
B10: =Lists!$L$9 -> Thematic & Tactical | C10: =Lists!$K$9 -> TT | D10: =SUMIFS(Holdings!$R$6:$R$205,Holdings!$I$6:$I$205,$C10,Holdings!$G$6:$G$205,D$6)/Divisor -> 26.477615 | E10: =SUMIFS(Holdings!$R$6:$R$205,Holdings!$I$6:$I$205,$C10,Holdings!$G$6:$G$205,E$6)/Divisor -> 0 | F10: =SUMIFS(Holdings!$R$6:$R$205,Holdings!$I$6:$I$205,$C10,Holdings!$G$6:$G$205,F$6)/Divisor -> 0 | G10: =SUMIFS(Holdings!$R$6:$R$205,Holdings!$I$6:$I$205,$C10,Holdings!$G$6:$G$205,G$6)/Divisor -> 4.76676 | H10: =SUMIFS(Holdings!$R$6:$R$205,Holdings!$I$6:$I$205,$C10)/Divisor -> 31.244375 | J10: =IF(N($H$11)=0,"",H10/$H$11) -> 0.22563265 | K10: 0.28 | L10: =IF(OR(J10="",K10=""),"",J10-K10) -> -0.054367353 | N10: =SUMIFS(Holdings!$M$6:$M$205,Holdings!$I$6:$I$205,$C10)/Divisor -> 22.62113 | O10: =SUMIFS(Holdings!$S$6:$S$205,Holdings!$I$6:$I$205,$C10)/Divisor -> 8.6232449 | P10: =IF(N(N10)=0,"",O10/N10) -> 0.3812031 | Q10: =IF(SUMIFS(Holdings!$AN$6:$AN$205,Holdings!$I$6:$I$205,$C10)=0,"",SUMIFS(Holdings!$AM$6:$AM$205,Holdings!$I$6:$I$205,$C10)/SUMIFS(Holdings!$AN$6:$AN$205,Holdings!$I$6:$I$205,$C10)) -> 0.15063669 | R10: =IF(N(H10)=0,"",SUMIFS(Holdings!$AN$6:$AN$205,Holdings!$I$6:$I$205,$C10)/Divisor/H10) -> 0.75110016
B11: Total | D11: =SUMIFS(Holdings!$R$6:$R$205,Holdings!$G$6:$G$205,D$6)/Divisor -> 84.35414 | E11: =SUMIFS(Holdings!$R$6:$R$205,Holdings!$G$6:$G$205,E$6)/Divisor -> 13.595184 | F11: =SUMIFS(Holdings!$R$6:$R$205,Holdings!$G$6:$G$205,F$6)/Divisor -> 17.741647 | G11: =SUMIFS(Holdings!$R$6:$R$205,Holdings!$G$6:$G$205,G$6)/Divisor -> 22.78356 | H11: =SUM(Holdings!$R$6:$R$205)/Divisor -> 138.47453 | J11: =SUM(J7:J10) -> 1 | K11: =SUM(K7:K10) -> 1 | N11: =SUM(Holdings!$M$6:$M$205)/Divisor -> 110.19353 | O11: =SUM(Holdings!$S$6:$S$205)/Divisor -> 28.281001 | P11: =IF(N(N11)=0,"",O11/N11) -> 0.25664847 | Q11: =IF(SUM(Holdings!$AN$6:$AN$205)=0,"",SUM(Holdings!$AM$6:$AM$205)/SUM(Holdings!$AN$6:$AN$205)) -> 0.13698029 | R11: =IF(N(H11)=0,"",SUM(Holdings!$AN$6:$AN$205)/Divisor/H11) -> 0.76705776
B13: Rebalancing band (± % points) | C13: 0.05 | D13: A gap inside the band is green; outside it, red. Type the band the family accepts before it rebalances.
B15: WHAT EACH BASKET HOLDS — the family's own grouping (Lists sheet)
B16: =Lists!$L$6&" ("&Lists!$K$6&")" -> Stable Growth (SG) | C16: =Lists!$M$6 -> Core, long-horizon compounding: diversified funds, PMS, quality debt.
B17: =Lists!$L$7&" ("&Lists!$K$7&")" -> Entrepreneurial Growth (EG) | C17: =Lists!$M$7 -> Private equity, venture and pre-IPO: illiquid, high upside.
B18: =Lists!$L$8&" ("&Lists!$K$8&")" -> Liquidity (LQ) | C18: =Lists!$M$8 -> Cash, liquid and arbitrage funds: money needed within 12 months.
B19: =Lists!$L$9&" ("&Lists!$K$9&")" -> Thematic & Tactical (TT) | C19: =Lists!$M$9 -> Direct stocks, sector and mid/small-cap calls, gold and silver.
B21: A security takes its category's default basket (Lists sheet) unless its Securities row overrides it: a direct stock the family treats as core can sit in Stable Growth.
B22: XIRR is value-weighted over the holdings held a year or more that report one; the last column says how much of the basket's value that covers.
B23: Basket Detail lists every holding in each basket, largest first.

Sheet Basket Detail
A1: ="Basket Detail — "&ClientName -> Basket Detail — Malhotra Family Office (DEMO) | O1: =HYPERLINK("#'Start Here'!A1","← Start Here") -> ← Start Here
A2: ="Figures in "&UnitLabel&" · market values as at "&TEXT(ValDate,"dd-mmm-yyyy")&" · every holding in each basket, largest first (up to 15 per basket; each total covers every holding)" -> Figures in ₹ Crore · market values as at 30-Jun-2026 · every holding in each basket, largest first (up to 15 per basket; each total covers every holding)
A3: DEMO DATA — illustrative only: a fictional family, fictional securities and figures.
B5: =Lists!$L$6&" · "&Lists!$K$6 -> Stable Growth · SG | R5: =Lists!$K$6 -> SG
B6: Security / product | C6: Entity | D6: Advisor / manager | E6: Category | F6: First investment | G6: Investment at cost | H6: Market value | I6: % of basket | J6: Gain / (loss) on what is held | K6: Return shown | L6: Return (%) | M6: Benchmark return (%) | N6: Alpha (% points) | O6: Benchmark
B7: =IF($Q7="","",INDEX(Holdings!$F$6:$F$205,$Q7)&"") -> Cedar India Opportunities Fund – Class A | C7: =IF($Q7="","",INDEX(Holdings!$D$6:$D$205,$Q7)&"") -> Arjun Malhotra | D7: =IF($Q7="","",INDEX(Holdings!$E$6:$E$205,$Q7)&"") -> Cedar Asset Managers | E7: =IF($Q7="","",INDEX(Holdings!$H$6:$H$205,$Q7)&"") -> AIF Cat III – Listed Equity | F7: =IF($Q7="","",IF(INDEX(Holdings!$J$6:$J$205,$Q7)="","",INDEX(Holdings!$J$6:$J$205,$Q7))) -> 44946 | G7: =IF($Q7="","",IF(INDEX(Holdings!$M$6:$M$205,$Q7)="","",INDEX(Holdings!$M$6:$M$205,$Q7)/Divisor)) -> 14.6988 | H7: =IF($Q7="","",IF(INDEX(Holdings!$R$6:$R$205,$Q7)="","",INDEX(Holdings!$R$6:$R$205,$Q7)/Divisor)) -> 20.6422 | I7: =IF(OR($Q7="",N($H$22)=0),"",H7/$H$22) -> 0.27089605 | J7: =IF($Q7="","",IF(INDEX(Holdings!$S$6:$S$205,$Q7)="","",INDEX(Holdings!$S$6:$S$205,$Q7)/Divisor)) -> 5.9434 | K7: =IF($Q7="","",INDEX(Holdings!$AB$6:$AB$205,$Q7)&"") -> XIRR | L7: =IF($Q7="","",IF(K7="XIRR",INDEX(Holdings!$W$6:$W$205,$Q7),IF(K7="Absolute",IF(INDEX(Holdings!$T$6:$T$205,$Q7)="","",INDEX(Holdings!$T$6:$T$205,$Q7)),""))) -> 0.178 | M7: =IF($Q7="","",IF(K7="XIRR",IF(INDEX(Holdings!$Z$6:$Z$205,$Q7)="","",INDEX(Holdings!$Z$6:$Z$205,$Q7)),IF(K7="Absolute",IF(INDEX(Holdings!$Y$6:$Y$205,$Q7)="","",INDEX(Holdings!$Y$6:$Y$205,$Q7)),""))) -> 0.132 | N7: =IF(OR(L7="",M7=""),"",L7-M7) -> 0.046 | O7: =IF($Q7="","",INDEX(Holdings!$X$6:$X$205,$Q7)&"") -> Nifty 500 TRI | Q7: =IFERROR(MATCH($R$5&"|"&$S7,Holdings!$AL$6:$AL$205,0),"") -> 12 | S7: 1
B8: =IF($Q8="","",INDEX(Holdings!$F$6:$F$205,$Q8)&"") -> Banyan Focused Equity Portfolio | C8: =IF($Q8="","",INDEX(Holdings!$D$6:$D$205,$Q8)&"") -> Rajiv Malhotra | D8: =IF($Q8="","",INDEX(Holdings!$E$6:$E$205,$Q8)&"") -> Banyan Capital Managers | E8: =IF($Q8="","",INDEX(Holdings!$H$6:$H$205,$Q8)&"") -> PMS – Equity | F8: =IF($Q8="","",IF(INDEX(Holdings!$J$6:$J$205,$Q8)="","",INDEX(Holdings!$J$6:$J$205,$Q8))) -> 44652 | G8: =IF($Q8="","",IF(INDEX(Holdings!$M$6:$M$205,$Q8)="","",INDEX(Holdings!$M$6:$M$205,$Q8)/Divisor)) -> 15 | H8: =IF($Q8="","",IF(INDEX(Holdings!$R$6:$R$205,$Q8)="","",INDEX(Holdings!$R$6:$R$205,$Q8)/Divisor)) -> 18.124 | I8: =IF(OR($Q8="",N($H$22)=0),"",H8/$H$22) -> 0.23784868 | J8: =IF($Q8="","",IF(INDEX(Holdings!$S$6:$S$205,$Q8)="","",INDEX(Holdings!$S$6:$S$205,$Q8)/Divisor)) -> 3.124 | K8: =IF($Q8="","",INDEX(Holdings!$AB$6:$AB$205,$Q8)&"") -> XIRR | L8: =IF($Q8="","",IF(K8="XIRR",INDEX(Holdings!$W$6:$W$205,$Q8),IF(K8="Absolute",IF(INDEX(Holdings!$T$6:$T$205,$Q8)="","",INDEX(Holdings!$T$6:$T$205,$Q8)),""))) -> 0.142 | M8: =IF($Q8="","",IF(K8="XIRR",IF(INDEX(Holdings!$Z$6:$Z$205,$Q8)="","",INDEX(Holdings!$Z$6:$Z$205,$Q8)),IF(K8="Absolute",IF(INDEX(Holdings!$Y$6:$Y$205,$Q8)="","",INDEX(Holdings!$Y$6:$Y$205,$Q8)),""))) -> 0.121 | N8: =IF(OR(L8="",M8=""),"",L8-M8) -> 0.021 | O8: =IF($Q8="","",INDEX(Holdings!$X$6:$X$205,$Q8)&"") -> Nifty 500 TRI | Q8: =IFERROR(MATCH($R$5&"|"&$S8,Holdings!$AL$6:$AL$205,0),"") -> 4 | S8: 2
B9: =IF($Q9="","",INDEX(Holdings!$F$6:$F$205,$Q9)&"") -> Himalaya Flexi Cap Fund – Direct Growth | C9: =IF($Q9="","",INDEX(Holdings!$D$6:$D$205,$Q9)&"") -> Nisha Malhotra | D9: =IF($Q9="","",INDEX(Holdings!$E$6:$E$205,$Q9)&"") -> Orchid Wealth Advisors | E9: =IF($Q9="","",INDEX(Holdings!$H$6:$H$205,$Q9)&"") -> Equity MF – Large / Flexi / Multi Cap | F9: =IF($Q9="","",IF(INDEX(Holdings!$J$6:$J$205,$Q9)="","",INDEX(Holdings!$J$6:$J$205,$Q9))) -> 43108 | G9: =IF($Q9="","",IF(INDEX(Holdings!$M$6:$M$205,$Q9)="","",INDEX(Holdings!$M$6:$M$205,$Q9)/Divisor)) -> 3.84 | H9: =IF($Q9="","",IF(INDEX(Holdings!$R$6:$R$205,$Q9)="","",INDEX(Holdings!$R$6:$R$205,$Q9)/Divisor)) -> 9.64312 | I9: =IF(OR($Q9="",N($H$22)=0),"",H9/$H$22) -> 0.12655061 | J9: =IF($Q9="","",IF(INDEX(Holdings!$S$6:$S$205,$Q9)="","",INDEX(Holdings!$S$6:$S$205,$Q9)/Divisor)) -> 5.80312 | K9: =IF($Q9="","",INDEX(Holdings!$AB$6:$AB$205,$Q9)&"") -> XIRR | L9: =IF($Q9="","",IF(K9="XIRR",INDEX(Holdings!$W$6:$W$205,$Q9),IF(K9="Absolute",IF(INDEX(Holdings!$T$6:$T$205,$Q9)="","",INDEX(Holdings!$T$6:$T$205,$Q9)),""))) -> 0.112 | M9: =IF($Q9="","",IF(K9="XIRR",IF(INDEX(Holdings!$Z$6:$Z$205,$Q9)="","",INDEX(Holdings!$Z$6:$Z$205,$Q9)),IF(K9="Absolute",IF(INDEX(Holdings!$Y$6:$Y$205,$Q9)="","",INDEX(Holdings!$Y$6:$Y$205,$Q9)),""))) -> 0.126 | N9: =IF(OR(L9="",M9=""),"",L9-M9) -> -0.014 | O9: =IF($Q9="","",INDEX(Holdings!$X$6:$X$205,$Q9)&"") -> Nifty 500 TRI | Q9: =IFERROR(MATCH($R$5&"|"&$S9,Holdings!$AL$6:$AL$205,0),"") -> 6 | S9: 3
B10: =IF($Q10="","",INDEX(Holdings!$F$6:$F$205,$Q10)&"") -> Narmada Corporate Bond Fund – Direct Growth | C10: =IF($Q10="","",INDEX(Holdings!$D$6:$D$205,$Q10)&"") -> Malhotra Family Trust | D10: =IF($Q10="","",INDEX(Holdings!$E$6:$E$205,$Q10)&"") -> Granite Wealth | E10: =IF($Q10="","",INDEX(Holdings!$H$6:$H$205,$Q10)&"") -> Debt MF | F10: =IF($Q10="","",IF(INDEX(Holdings!$J$6:$J$205,$Q10)="","",INDEX(Holdings!$J$6:$J$205,$Q10))) -> 45494 | G10: =IF($Q10="","",IF(INDEX(Holdings!$M$6:$M$205,$Q10)="","",INDEX(Holdings!$M$6:$M$205,$Q10)/Divisor)) -> 7 | H10: =IF($Q10="","",IF(INDEX(Holdings!$R$6:$R$205,$Q10)="","",INDEX(Holdings!$R$6:$R$205,$Q10)/Divisor)) -> 7.494984 | I10: =IF(OR($Q10="",N($H$22)=0),"",H10/$H$22) -> 0.098359746 | J10: =IF($Q10="","",IF(INDEX(Holdings!$S$6:$S$205,$Q10)="","",INDEX(Holdings!$S$6:$S$205,$Q10)/Divisor)) -> 0.494984 | K10: =IF($Q10="","",INDEX(Holdings!$AB$6:$AB$205,$Q10)&"") -> XIRR | L10: =IF($Q10="","",IF(K10="XIRR",INDEX(Holdings!$W$6:$W$205,$Q10),IF(K10="Absolute",IF(INDEX(Holdings!$T$6:$T$205,$Q10)="","",INDEX(Holdings!$T$6:$T$205,$Q10)),""))) -> 0.079 | M10: =IF($Q10="","",IF(K10="XIRR",IF(INDEX(Holdings!$Z$6:$Z$205,$Q10)="","",INDEX(Holdings!$Z$6:$Z$205,$Q10)),IF(K10="Absolute",IF(INDEX(Holdings!$Y$6:$Y$205,$Q10)="","",INDEX(Holdings!$Y$6:$Y$205,$Q10)),""))) -> 0.074 | N10: =IF(OR(L10="",M10=""),"",L10-M10) -> 0.005 | O10: =IF($Q10="","",INDEX(Holdings!$X$6:$X$205,$Q10)&"") -> CRISIL Composite Bond Index | Q10: =IFERROR(MATCH($R$5&"|"&$S10,Holdings!$AL$6:$AL$205,0),"") -> 18 | S10: 4
B11: =IF($Q11="","",INDEX(Holdings!$F$6:$F$205,$Q11)&"") -> Coromandel Digital Services Ltd | C11: =IF($Q11="","",INDEX(Holdings!$D$6:$D$205,$Q11)&"") -> Rajiv Malhotra | D11: =IF($Q11="","",INDEX(Holdings!$E$6:$E$205,$Q11)&"") -> Self-directed | E11: =IF($Q11="","",INDEX(Holdings!$H$6:$H$205,$Q11)&"") -> Direct Equity | F11: =IF($Q11="","",IF(INDEX(Holdings!$J$6:$J$205,$Q11)="","",INDEX(Holdings!$J$6:$J$205,$Q11))) -> 44211 | G11: =IF($Q11="","",IF(INDEX(Holdings!$M$6:$M$205,$Q11)="","",INDEX(Holdings!$M$6:$M$205,$Q11)/Divisor)) -> 3.978 | H11: =IF($Q11="","",IF(INDEX(Holdings!$R$6:$R$205,$Q11)="","",INDEX(Holdings!$R$6:$R$205,$Q11)/Divisor)) -> 5.454 | I11: =IF(OR($Q11="",N($H$22)=0),"",H11/$H$22) -> 0.071575076 | J11: =IF($Q11="","",IF(INDEX(Holdings!$S$6:$S$205,$Q11)="","",INDEX(Holdings!$S$6:$S$205,$Q11)/Divisor)) -> 1.476 | K11: =IF($Q11="","",INDEX(Holdings!$AB$6:$AB$205,$Q11)&"") -> XIRR | L11: =IF($Q11="","",IF(K11="XIRR",INDEX(Holdings!$W$6:$W$205,$Q11),IF(K11="Absolute",IF(INDEX(Holdings!$T$6:$T$205,$Q11)="","",INDEX(Holdings!$T$6:$T$205,$Q11)),""))) -> 0.086 | M11: =IF($Q11="","",IF(K11="XIRR",IF(INDEX(Holdings!$Z$6:$Z$205,$Q11)="","",INDEX(Holdings!$Z$6:$Z$205,$Q11)),IF(K11="Absolute",IF(INDEX(Holdings!$Y$6:$Y$205,$Q11)="","",INDEX(Holdings!$Y$6:$Y$205,$Q11)),""))) -> 0.118 | N11: =IF(OR(L11="",M11=""),"",L11-M11) -> -0.032 | O11: =IF($Q11="","",INDEX(Holdings!$X$6:$X$205,$Q11)&"") -> Nifty 500 TRI | Q11: =IFERROR(MATCH($R$5&"|"&$S11,Holdings!$AL$6:$AL$205,0),"") -> 3 | S11: 5
B12: =IF($Q12="","",INDEX(Holdings!$F$6:$F$205,$Q12)&"") -> Orion Housing Finance 8.60% NCD 2029 | C12: =IF($Q12="","",INDEX(Holdings!$D$6:$D$205,$Q12)&"") -> Malhotra Family Trust | D12: =IF($Q12="","",INDEX(Holdings!$E$6:$E$205,$Q12)&"") -> Granite Wealth | E12: =IF($Q12="","",INDEX(Holdings!$H$6:$H$205,$Q12)&"") -> Bonds / NCDs | F12: =IF($Q12="","",IF(INDEX(Holdings!$J$6:$J$205,$Q12)="","",INDEX(Holdings!$J$6:$J$205,$Q12))) -> 45365 | G12: =IF($Q12="","",IF(INDEX(Holdings!$M$6:$M$205,$Q12)="","",INDEX(Holdings!$M$6:$M$205,$Q12)/Divisor)) -> 5 | H12: =IF($Q12="","",IF(INDEX(Holdings!$R$6:$R$205,$Q12)="","",INDEX(Holdings!$R$6:$R$205,$Q12)/Divisor)) -> 5.062 | I12: =IF(OR($Q12="",N($H$22)=0),"",H12/$H$22) -> 0.0664307 | J12: =IF($Q12="","",IF(INDEX(Holdings!$S$6:$S$205,$Q12)="","",INDEX(Holdings!$S$6:$S$205,$Q12)/Divisor)) -> 0.062 | K12: =IF($Q12="","",INDEX(Holdings!$AB$6:$AB$205,$Q12)&"") -> XIRR | L12: =IF($Q12="","",IF(K12="XIRR",INDEX(Holdings!$W$6:$W$205,$Q12),IF(K12="Absolute",IF(INDEX(Holdings!$T$6:$T$205,$Q12)="","",INDEX(Holdings!$T$6:$T$205,$Q12)),""))) -> 0.089 | M12: =IF($Q12="","",IF(K12="XIRR",IF(INDEX(Holdings!$Z$6:$Z$205,$Q12)="","",INDEX(Holdings!$Z$6:$Z$205,$Q12)),IF(K12="Absolute",IF(INDEX(Holdings!$Y$6:$Y$205,$Q12)="","",INDEX(Holdings!$Y$6:$Y$205,$Q12)),""))) -> 0.076 | N12: =IF(OR(L12="",M12=""),"",L12-M12) -> 0.013 | O12: =IF($Q12="","",INDEX(Holdings!$X$6:$X$205,$Q12)&"") -> CRISIL Composite Bond Index | Q12: =IFERROR(MATCH($R$5&"|"&$S12,Holdings!$AL$6:$AL$205,0),"") -> 16 | S12: 6
B13: =IF($Q13="","",INDEX(Holdings!$F$6:$F$205,$Q13)&"") -> Tapti Infrastructure InvIT | C13: =IF($Q13="","",INDEX(Holdings!$D$6:$D$205,$Q13)&"") -> Malhotra Family Trust | D13: =IF($Q13="","",INDEX(Holdings!$E$6:$E$205,$Q13)&"") -> Granite Wealth | E13: =IF($Q13="","",INDEX(Holdings!$H$6:$H$205,$Q13)&"") -> REIT / InvIT | F13: =IF($Q13="","",IF(INDEX(Holdings!$J$6:$J$205,$Q13)="","",INDEX(Holdings!$J$6:$J$205,$Q13))) -> 45595 | G13: =IF($Q13="","",IF(INDEX(Holdings!$M$6:$M$205,$Q13)="","",INDEX(Holdings!$M$6:$M$205,$Q13)/Divisor)) -> 4.4 | H13: =IF($Q13="","",IF(INDEX(Holdings!$R$6:$R$205,$Q13)="","",INDEX(Holdings!$R$6:$R$205,$Q13)/Divisor)) -> 4.728 | I13: =IF(OR($Q13="",N($H$22)=0),"",H13/$H$22) -> 0.062047481 | J13: =IF($Q13="","",IF(INDEX(Holdings!$S$6:$S$205,$Q13)="","",INDEX(Holdings!$S$6:$S$205,$Q13)/Divisor)) -> 0.328 | K13: =IF($Q13="","",INDEX(Holdings!$AB$6:$AB$205,$Q13)&"") -> XIRR | L13: =IF($Q13="","",IF(K13="XIRR",INDEX(Holdings!$W$6:$W$205,$Q13),IF(K13="Absolute",IF(INDEX(Holdings!$T$6:$T$205,$Q13)="","",INDEX(Holdings!$T$6:$T$205,$Q13)),""))) -> 0.126 | M13: =IF($Q13="","",IF(K13="XIRR",IF(INDEX(Holdings!$Z$6:$Z$205,$Q13)="","",INDEX(Holdings!$Z$6:$Z$205,$Q13)),IF(K13="Absolute",IF(INDEX(Holdings!$Y$6:$Y$205,$Q13)="","",INDEX(Holdings!$Y$6:$Y$205,$Q13)),""))) -> 0.091 | N13: =IF(OR(L13="",M13=""),"",L13-M13) -> 0.035 | O13: =IF($Q13="","",INDEX(Holdings!$X$6:$X$205,$Q13)&"") -> Nifty REITs & InvITs Index | Q13: =IFERROR(MATCH($R$5&"|"&$S13,Holdings!$AL$6:$AL$205,0),"") -> 19 | S13: 7
B14: =IF($Q14="","",INDEX(Holdings!$F$6:$F$205,$Q14)&"") -> Jaipur Balanced Advantage Fund – Direct Growth | C14: =IF($Q14="","",INDEX(Holdings!$D$6:$D$205,$Q14)&"") -> Nisha Malhotra | D14: =IF($Q14="","",INDEX(Holdings!$E$6:$E$205,$Q14)&"") -> Orchid Wealth Advisors | E14: =IF($Q14="","",INDEX(Holdings!$H$6:$H$205,$Q14)&"") -> Equity MF – Hybrid / BAF | F14: =IF($Q14="","",IF(INDEX(Holdings!$J$6:$J$205,$Q14)="","",INDEX(Holdings!$J$6:$J$205,$Q14))) -> 45202 | G14: =IF($Q14="","",IF(INDEX(Holdings!$M$6:$M$205,$Q14)="","",INDEX(Holdings!$M$6:$M$205,$Q14)/Divisor)) -> 3.5 | H14: =IF($Q14="","",IF(INDEX(Holdings!$R$6:$R$205,$Q14)="","",INDEX(Holdings!$R$6:$R$205,$Q14)/Divisor)) -> 4.013205 | I14: =IF(OR($Q14="",N($H$22)=0),"",H14/$H$22) -> 0.052666933 | J14: =IF($Q14="","",IF(INDEX(Holdings!$S$6:$S$205,$Q14)="","",INDEX(Holdings!$S$6:$S$205,$Q14)/Divisor)) -> 0.513205 | K14: =IF($Q14="","",INDEX(Holdings!$AB$6:$AB$205,$Q14)&"") -> XIRR | L14: =IF($Q14="","",IF(K14="XIRR",INDEX(Holdings!$W$6:$W$205,$Q14),IF(K14="Absolute",IF(INDEX(Holdings!$T$6:$T$205,$Q14)="","",INDEX(Holdings!$T$6:$T$205,$Q14)),""))) -> 0.108 | M14: =IF($Q14="","",IF(K14="XIRR",IF(INDEX(Holdings!$Z$6:$Z$205,$Q14)="","",INDEX(Holdings!$Z$6:$Z$205,$Q14)),IF(K14="Absolute",IF(INDEX(Holdings!$Y$6:$Y$205,$Q14)="","",INDEX(Holdings!$Y$6:$Y$205,$Q14)),""))) -> 0.115 | N14: =IF(OR(L14="",M14=""),"",L14-M14) -> -0.007 | O14: =IF($Q14="","",INDEX(Holdings!$X$6:$X$205,$Q14)&"") -> CRISIL Hybrid 50+50 Moderate Index | Q14: =IFERROR(MATCH($R$5&"|"&$S14,Holdings!$AL$6:$AL$205,0),"") -> 8 | S14: 8
B15: =IF($Q15="","",INDEX(Holdings!$F$6:$F$205,$Q15)&"") -> Sahyadri Private Credit Fund – Series I | C15: =IF($Q15="","",INDEX(Holdings!$D$6:$D$205,$Q15)&"") -> Malhotra Family Trust | D15: =IF($Q15="","",INDEX(Holdings!$E$6:$E$205,$Q15)&"") -> Sahyadri Investment Managers | E15: =IF($Q15="","",INDEX(Holdings!$H$6:$H$205,$Q15)&"") -> AIF Cat II – Private Credit | F15: =IF($Q15="","",IF(INDEX(Holdings!$J$6:$J$205,$Q15)="","",INDEX(Holdings!$J$6:$J$205,$Q15))) -> 46037 | G15: =IF($Q15="","",IF(INDEX(Holdings!$M$6:$M$205,$Q15)="","",INDEX(Holdings!$M$6:$M$205,$Q15)/Divisor)) -> 1 | H15: =IF($Q15="","",IF(INDEX(Holdings!$R$6:$R$205,$Q15)="","",INDEX(Holdings!$R$6:$R$205,$Q15)/Divisor)) -> 1.0382 | I15: =IF(OR($Q15="",N($H$22)=0),"",H15/$H$22) -> 0.013624724 | J15: =IF($Q15="","",IF(INDEX(Holdings!$S$6:$S$205,$Q15)="","",INDEX(Holdings!$S$6:$S$205,$Q15)/Divisor)) -> 0.0382 | K15: =IF($Q15="","",INDEX(Holdings!$AB$6:$AB$205,$Q15)&"") -> Absolute | L15: =IF($Q15="","",IF(K15="XIRR",INDEX(Holdings!$W$6:$W$205,$Q15),IF(K15="Absolute",IF(INDEX(Holdings!$T$6:$T$205,$Q15)="","",INDEX(Holdings!$T$6:$T$205,$Q15)),""))) -> 0.0382 | M15: =IF($Q15="","",IF(K15="XIRR",IF(INDEX(Holdings!$Z$6:$Z$205,$Q15)="","",INDEX(Holdings!$Z$6:$Z$205,$Q15)),IF(K15="Absolute",IF(INDEX(Holdings!$Y$6:$Y$205,$Q15)="","",INDEX(Holdings!$Y$6:$Y$205,$Q15)),""))) -> 0.031 | N15: =IF(OR(L15="",M15=""),"",L15-M15) -> 0.0072 | O15: =IF($Q15="","",INDEX(Holdings!$X$6:$X$205,$Q15)&"") -> CRISIL Composite Bond Index | Q15: =IFERROR(MATCH($R$5&"|"&$S15,Holdings!$AL$6:$AL$205,0),"") -> 23 | S15: 9
B16: =IF($Q16="","",INDEX(Holdings!$F$6:$F$205,$Q16)&"") | C16: =IF($Q16="","",INDEX(Holdings!$D$6:$D$205,$Q16)&"") | D16: =IF($Q16="","",INDEX(Holdings!$E$6:$E$205,$Q16)&"") | E16: =IF($Q16="","",INDEX(Holdings!$H$6:$H$205,$Q16)&"") | F16: =IF($Q16="","",IF(INDEX(Holdings!$J$6:$J$205,$Q16)="","",INDEX(Holdings!$J$6:$J$205,$Q16))) | G16: =IF($Q16="","",IF(INDEX(Holdings!$M$6:$M$205,$Q16)="","",INDEX(Holdings!$M$6:$M$205,$Q16)/Divisor)) | H16: =IF($Q16="","",IF(INDEX(Holdings!$R$6:$R$205,$Q16)="","",INDEX(Holdings!$R$6:$R$205,$Q16)/Divisor)) | I16: =IF(OR($Q16="",N($H$22)=0),"",H16/$H$22) | J16: =IF($Q16="","",IF(INDEX(Holdings!$S$6:$S$205,$Q16)="","",INDEX(Holdings!$S$6:$S$205,$Q16)/Divisor)) | K16: =IF($Q16="","",INDEX(Holdings!$AB$6:$AB$205,$Q16)&"") | L16: =IF($Q16="","",IF(K16="XIRR",INDEX(Holdings!$W$6:$W$205,$Q16),IF(K16="Absolute",IF(INDEX(Holdings!$T$6:$T$205,$Q16)="","",INDEX(Holdings!$T$6:$T$205,$Q16)),""))) | M16: =IF($Q16="","",IF(K16="XIRR",IF(INDEX(Holdings!$Z$6:$Z$205,$Q16)="","",INDEX(Holdings!$Z$6:$Z$205,$Q16)),IF(K16="Absolute",IF(INDEX(Holdings!$Y$6:$Y$205,$Q16)="","",INDEX(Holdings!$Y$6:$Y$205,$Q16)),""))) | N16: =IF(OR(L16="",M16=""),"",L16-M16) | O16: =IF($Q16="","",INDEX(Holdings!$X$6:$X$205,$Q16)&"") | Q16: =IFERROR(MATCH($R$5&"|"&$S16,Holdings!$AL$6:$AL$205,0),"") | S16: 10
B17: =IF($Q17="","",INDEX(Holdings!$F$6:$F$205,$Q17)&"") | C17: =IF($Q17="","",INDEX(Holdings!$D$6:$D$205,$Q17)&"") | D17: =IF($Q17="","",INDEX(Holdings!$E$6:$E$205,$Q17)&"") | E17: =IF($Q17="","",INDEX(Holdings!$H$6:$H$205,$Q17)&"") | F17: =IF($Q17="","",IF(INDEX(Holdings!$J$6:$J$205,$Q17)="","",INDEX(Holdings!$J$6:$J$205,$Q17))) | G17: =IF($Q17="","",IF(INDEX(Holdings!$M$6:$M$205,$Q17)="","",INDEX(Holdings!$M$6:$M$205,$Q17)/Divisor)) | H17: =IF($Q17="","",IF(INDEX(Holdings!$R$6:$R$205,$Q17)="","",INDEX(Holdings!$R$6:$R$205,$Q17)/Divisor)) | I17: =IF(OR($Q17="",N($H$22)=0),"",H17/$H$22) | J17: =IF($Q17="","",IF(INDEX(Holdings!$S$6:$S$205,$Q17)="","",INDEX(Holdings!$S$6:$S$205,$Q17)/Divisor)) | K17: =IF($Q17="","",INDEX(Holdings!$AB$6:$AB$205,$Q17)&"") | L17: =IF($Q17="","",IF(K17="XIRR",INDEX(Holdings!$W$6:$W$205,$Q17),IF(K17="Absolute",IF(INDEX(Holdings!$T$6:$T$205,$Q17)="","",INDEX(Holdings!$T$6:$T$205,$Q17)),""))) | M17: =IF($Q17="","",IF(K17="XIRR",IF(INDEX(Holdings!$Z$6:$Z$205,$Q17)="","",INDEX(Holdings!$Z$6:$Z$205,$Q17)),IF(K17="Absolute",IF(INDEX(Holdings!$Y$6:$Y$205,$Q17)="","",INDEX(Holdings!$Y$6:$Y$205,$Q17)),""))) | N17: =IF(OR(L17="",M17=""),"",L17-M17) | O17: =IF($Q17="","",INDEX(Holdings!$X$6:$X$205,$Q17)&"") | Q17: =IFERROR(MATCH($R$5&"|"&$S17,Holdings!$AL$6:$AL$205,0),"") | S17: 11
B18: =IF($Q18="","",INDEX(Holdings!$F$6:$F$205,$Q18)&"") | C18: =IF($Q18="","",INDEX(Holdings!$D$6:$D$205,$Q18)&"") | D18: =IF($Q18="","",INDEX(Holdings!$E$6:$E$205,$Q18)&"") | E18: =IF($Q18="","",INDEX(Holdings!$H$6:$H$205,$Q18)&"") | F18: =IF($Q18="","",IF(INDEX(Holdings!$J$6:$J$205,$Q18)="","",INDEX(Holdings!$J$6:$J$205,$Q18))) | G18: =IF($Q18="","",IF(INDEX(Holdings!$M$6:$M$205,$Q18)="","",INDEX(Holdings!$M$6:$M$205,$Q18)/Divisor)) | H18: =IF($Q18="","",IF(INDEX(Holdings!$R$6:$R$205,$Q18)="","",INDEX(Holdings!$R$6:$R$205,$Q18)/Divisor)) | I18: =IF(OR($Q18="",N($H$22)=0),"",H18/$H$22) | J18: =IF($Q18="","",IF(INDEX(Holdings!$S$6:$S$205,$Q18)="","",INDEX(Holdings!$S$6:$S$205,$Q18)/Divisor)) | K18: =IF($Q18="","",INDEX(Holdings!$AB$6:$AB$205,$Q18)&"") | L18: =IF($Q18="","",IF(K18="XIRR",INDEX(Holdings!$W$6:$W$205,$Q18),IF(K18="Absolute",IF(INDEX(Holdings!$T$6:$T$205,$Q18)="","",INDEX(Holdings!$T$6:$T$205,$Q18)),""))) | M18: =IF($Q18="","",IF(K18="XIRR",IF(INDEX(Holdings!$Z$6:$Z$205,$Q18)="","",INDEX(Holdings!$Z$6:$Z$205,$Q18)),IF(K18="Absolute",IF(INDEX(Holdings!$Y$6:$Y$205,$Q18)="","",INDEX(Holdings!$Y$6:$Y$205,$Q18)),""))) | N18: =IF(OR(L18="",M18=""),"",L18-M18) | O18: =IF($Q18="","",INDEX(Holdings!$X$6:$X$205,$Q18)&"") | Q18: =IFERROR(MATCH($R$5&"|"&$S18,Holdings!$AL$6:$AL$205,0),"") | S18: 12
... B21: =IF($Q21="","",INDEX(Holdings!$F$6:$F$205,$Q21)&"") | C21: =IF($Q21="","",INDEX(Holdings!$D$6:$D$205,$Q21)&"") | D21: =IF($Q21="","",INDEX(Holdings!$E$6:$E$205,$Q21)&"") | E21: =IF($Q21="","",INDEX(Holdings!$H$6:$H$205,$Q21)&"") | F21: =IF($Q21="","",IF(INDEX(Holdings!$J$6:$J$205,$Q21)="","",INDEX(Holdings!$J$6:$J$205,$Q21))) | G21: =IF($Q21="","",IF(INDEX(Holdings!$M$6:$M$205,$Q21)="","",INDEX(Holdings!$M$6:$M$205,$Q21)/Divisor)) | H21: =IF($Q21="","",IF(INDEX(Holdings!$R$6:$R$205,$Q21)="","",INDEX(Holdings!$R$6:$R$205,$Q21)/Divisor)) | I21: =IF(OR($Q21="",N($H$22)=0),"",H21/$H$22) | J21: =IF($Q21="","",IF(INDEX(Holdings!$S$6:$S$205,$Q21)="","",INDEX(Holdings!$S$6:$S$205,$Q21)/Divisor)) | K21: =IF($Q21="","",INDEX(Holdings!$AB$6:$AB$205,$Q21)&"") | L21: =IF($Q21="","",IF(K21="XIRR",INDEX(Holdings!$W$6:$W$205,$Q21),IF(K21="Absolute",IF(INDEX(Holdings!$T$6:$T$205,$Q21)="","",INDEX(Holdings!$T$6:$T$205,$Q21)),""))) | M21: =IF($Q21="","",IF(K21="XIRR",IF(INDEX(Holdings!$Z$6:$Z$205,$Q21)="","",INDEX(Holdings!$Z$6:$Z$205,$Q21)),IF(K21="Absolute",IF(INDEX(Holdings!$Y$6:$Y$205,$Q21)="","",INDEX(Holdings!$Y$6:$Y$205,$Q21)),""))) | N21: =IF(OR(L21="",M21=""),"",L21-M21) | O21: =IF($Q21="","",INDEX(Holdings!$X$6:$X$205,$Q21)&"") | Q21: =IFERROR(MATCH($R$5&"|"&$S21,Holdings!$AL$6:$AL$205,0),"") | S21: 15
B22: ="Total — "&Lists!$L$6 -> Total — Stable Growth | G22: =SUMIFS(Holdings!$M$6:$M$205,Holdings!$I$6:$I$205,$R$5)/Divisor -> 58.4168 | H22: =SUMIFS(Holdings!$R$6:$R$205,Holdings!$I$6:$I$205,$R$5)/Divisor -> 76.199709 | I22: =IF(N(H22)=0,"",SUM(I7:I21)) -> 1 | J22: =SUMIFS(Holdings!$S$6:$S$205,Holdings!$I$6:$I$205,$R$5)/Divisor -> 17.782909 | K22: =IF(SUMIFS(Holdings!$AN$6:$AN$205,Holdings!$I$6:$I$205,$R$5)>0,"XIRR",IF(N(G22)>0,"Absolute","")) -> XIRR | L22: =IF(K22="XIRR",IF(SUMIFS(Holdings!$AN$6:$AN$205,Holdings!$I$6:$I$205,$R$5)=0,"",SUMIFS(Holdings!$AM$6:$AM$205,Holdings!$I$6:$I$205,$R$5)/SUMIFS(Holdings!$AN$6:$AN$205,Holdings!$I$6:$I$205,$R$5)),IF(K22="Absolute",J22/G22,"")) -> 0.13130084 | M22: =IF(K22="XIRR",IF(SUMIFS(Holdings!$AN$6:$AN$205,Holdings!$I$6:$I$205,$R$5)=0,"",SUMIFS(Holdings!$AO$6:$AO$205,Holdings!$I$6:$I$205,$R$5)/SUMIFS(Holdings!$AN$6:$AN$205,Holdings!$I$6:$I$205,$R$5)),IF(K22="Absolute",IF(SUMIFS(Holdings!$AQ$6:$AQ$205,Holdings!$I$6:$I$205,$R$5)=0,"",SUMIFS(Holdings!$AP$6:$AP$205,Holdings!$I$6:$I$205,$R$5)/SUMIFS(Holdings!$AQ$6:$AQ$205,Holdings!$I$6:$I$205,$R$5)),"")) -> 0.11451988 | N22: =IF(OR(L22="",M22=""),"",L22-M22) -> 0.016780956
B23: =IF(SUMPRODUCT((Holdings!$I$6:$I$205=$R$5)*ISNUMBER(Holdings!$R$6:$R$205))>15,SUMPRODUCT((Holdings!$I$6:$I$205=$R$5)*ISNUMBER(Holdings!$R$6:$R$205))-15&" more holding(s) in this basket are not listed; the total includes them.",IF(SUMPRODUCT((Holdings!$I$6:$I$205=$R$5)*ISNUMBER(Holdings!$R$6:$R$205))=0,"Nothing is held in this basket.",""))
B26: =Lists!$L$7&" · "&Lists!$K$7 -> Entrepreneurial Growth · EG | R26: =Lists!$K$7 -> EG
B27: Security / product | C27: Entity | D27: Advisor / manager | E27: Category | F27: First investment | G27: Investment at cost | H27: Market value | I27: % of basket | J27: Gain / (loss) on what is held | K27: Return shown | L27: Return (%) | M27: Benchmark return (%) | N27: Alpha (% points) | O27: Benchmark
B28: =IF($Q28="","",INDEX(Holdings!$F$6:$F$205,$Q28)&"") -> Fernhill Ventures Fund II – Class A | C28: =IF($Q28="","",INDEX(Holdings!$D$6:$D$205,$Q28)&"") -> Malhotra Family Trust | D28: =IF($Q28="","",INDEX(Holdings!$E$6:$E$205,$Q28)&"") -> Fernhill Partners | E28: =IF($Q28="","",INDEX(Holdings!$H$6:$H$205,$Q28)&"") -> AIF Cat I / II – PE / VC Fund | F28: =IF($Q28="","",IF(INDEX(Holdings!$J$6:$J$205,$Q28)="","",INDEX(Holdings!$J$6:$J$205,$Q28))) -> 45184 | G28: =IF($Q28="","",IF(INDEX(Holdings!$M$6:$M$205,$Q28)="","",INDEX(Holdings!$M$6:$M$205,$Q28)/Divisor)) -> 6 | H28: =IF($Q28="","",IF(INDEX(Holdings!$R$6:$R$205,$Q28)="","",INDEX(Holdings!$R$6:$R$205,$Q28)/Divisor)) -> 7.5888 | I28: =IF(OR($Q28="",N($H$43)=0),"",H28/$H$43) -> 0.57106736 | J28: =IF($Q28="","",IF(INDEX(Holdings!$S$6:$S$205,$Q28)="","",INDEX(Holdings!$S$6:$S$205,$Q28)/Divisor)) -> 1.5888 | K28: =IF($Q28="","",INDEX(Holdings!$AB$6:$AB$205,$Q28)&"") -> XIRR | L28: =IF($Q28="","",IF(K28="XIRR",INDEX(Holdings!$W$6:$W$205,$Q28),IF(K28="Absolute",IF(INDEX(Holdings!$T$6:$T$205,$Q28)="","",INDEX(Holdings!$T$6:$T$205,$Q28)),""))) -> 0.151 | M28: =IF($Q28="","",IF(K28="XIRR",IF(INDEX(Holdings!$Z$6:$Z$205,$Q28)="","",INDEX(Holdings!$Z$6:$Z$205,$Q28)),IF(K28="Absolute",IF(INDEX(Holdings!$Y$6:$Y$205,$Q28)="","",INDEX(Holdings!$Y$6:$Y$205,$Q28)),""))) -> 0.128 | N28: =IF(OR(L28="",M28=""),"",L28-M28) -> 0.023 | O28: =IF($Q28="","",INDEX(Holdings!$X$6:$X$205,$Q28)&"") -> Nifty 500 TRI | Q28: =IFERROR(MATCH($R$26&"|"&$S28,Holdings!$AL$6:$AL$205,0),"") -> 15 | S28: 1
B29: =IF($Q29="","",INDEX(Holdings!$F$6:$F$205,$Q29)&"") -> Rangoli Foods Pvt Ltd – Equity | C29: =IF($Q29="","",INDEX(Holdings!$D$6:$D$205,$Q29)&"") -> Malhotra Holdings LLP | D29: =IF($Q29="","",INDEX(Holdings!$E$6:$E$205,$Q29)&"") -> Self-directed | E29: =IF($Q29="","",INDEX(Holdings!$H$6:$H$205,$Q29)&"") -> Pre-IPO | F29: =IF($Q29="","",IF(INDEX(Holdings!$J$6:$J$205,$Q29)="","",INDEX(Holdings!$J$6:$J$205,$Q29))) -> 45979 | G29: =IF($Q29="","",IF(INDEX(Holdings!$M$6:$M$205,$Q29)="","",INDEX(Holdings!$M$6:$M$205,$Q29)/Divisor)) -> 3.2 | H29: =IF($Q29="","",IF(INDEX(Holdings!$R$6:$R$205,$Q29)="","",INDEX(Holdings!$R$6:$R$205,$Q29)/Divisor)) -> 3.2 | I29: =IF(OR($Q29="",N($H$43)=0),"",H29/$H$43) -> 0.24080429 | J29: =IF($Q29="","",IF(INDEX(Holdings!$S$6:$S$205,$Q29)="","",INDEX(Holdings!$S$6:$S$205,$Q29)/Divisor)) -> 0 | K29: =IF($Q29="","",INDEX(Holdings!$AB$6:$AB$205,$Q29)&"") -> At cost | L29: =IF($Q29="","",IF(K29="XIRR",INDEX(Holdings!$W$6:$W$205,$Q29),IF(K29="Absolute",IF(INDEX(Holdings!$T$6:$T$205,$Q29)="","",INDEX(Holdings!$T$6:$T$205,$Q29)),""))) | M29: =IF($Q29="","",IF(K29="XIRR",IF(INDEX(Holdings!$Z$6:$Z$205,$Q29)="","",INDEX(Holdings!$Z$6:$Z$205,$Q29)),IF(K29="Absolute",IF(INDEX(Holdings!$Y$6:$Y$205,$Q29)="","",INDEX(Holdings!$Y$6:$Y$205,$Q29)),""))) | N29: =IF(OR(L29="",M29=""),"",L29-M29) | O29: =IF($Q29="","",INDEX(Holdings!$X$6:$X$205,$Q29)&"") | Q29: =IFERROR(MATCH($R$26&"|"&$S29,Holdings!$AL$6:$AL$205,0),"") -> 21 | S29: 2
B30: =IF($Q30="","",INDEX(Holdings!$F$6:$F$205,$Q30)&"") -> Quill Robotics Pvt Ltd – Series A CCPS | C30: =IF($Q30="","",INDEX(Holdings!$D$6:$D$205,$Q30)&"") -> Rajiv Malhotra | D30: =IF($Q30="","",INDEX(Holdings!$E$6:$E$205,$Q30)&"") -> Self-directed | E30: =IF($Q30="","",INDEX(Holdings!$H$6:$H$205,$Q30)&"") -> Private Equity – Unlisted Shares | F30: =IF($Q30="","",IF(INDEX(Holdings!$J$6:$J$205,$Q30)="","",INDEX(Holdings!$J$6:$J$205,$Q30))) -> 45514 | G30: =IF($Q30="","",IF(INDEX(Holdings!$M$6:$M$205,$Q30)="","",INDEX(Holdings!$M$6:$M$205,$Q30)/Divisor)) -> 2.5 | H30: =IF($Q30="","",IF(INDEX(Holdings!$R$6:$R$205,$Q30)="","",INDEX(Holdings!$R$6:$R$205,$Q30)/Divisor)) -> 2.5 | I30: =IF(OR($Q30="",N($H$43)=0),"",H30/$H$43) -> 0.18812835 | J30: =IF($Q30="","",IF(INDEX(Holdings!$S$6:$S$205,$Q30)="","",INDEX(Holdings!$S$6:$S$205,$Q30)/Divisor)) -> 0 | K30: =IF($Q30="","",INDEX(Holdings!$AB$6:$AB$205,$Q30)&"") -> At cost | L30: =IF($Q30="","",IF(K30="XIRR",INDEX(Holdings!$W$6:$W$205,$Q30),IF(K30="Absolute",IF(INDEX(Holdings!$T$6:$T$205,$Q30)="","",INDEX(Holdings!$T$6:$T$205,$Q30)),""))) | M30: =IF($Q30="","",IF(K30="XIRR",IF(INDEX(Holdings!$Z$6:$Z$205,$Q30)="","",INDEX(Holdings!$Z$6:$Z$205,$Q30)),IF(K30="Absolute",IF(INDEX(Holdings!$Y$6:$Y$205,$Q30)="","",INDEX(Holdings!$Y$6:$Y$205,$Q30)),""))) | N30: =IF(OR(L30="",M30=""),"",L30-M30) | O30: =IF($Q30="","",INDEX(Holdings!$X$6:$X$205,$Q30)&"") | Q30: =IFERROR(MATCH($R$26&"|"&$S30,Holdings!$AL$6:$AL$205,0),"") -> 5 | S30: 3
B31: =IF($Q31="","",INDEX(Holdings!$F$6:$F$205,$Q31)&"") | C31: =IF($Q31="","",INDEX(Holdings!$D$6:$D$205,$Q31)&"") | D31: =IF($Q31="","",INDEX(Holdings!$E$6:$E$205,$Q31)&"") | E31: =IF($Q31="","",INDEX(Holdings!$H$6:$H$205,$Q31)&"") | F31: =IF($Q31="","",IF(INDEX(Holdings!$J$6:$J$205,$Q31)="","",INDEX(Holdings!$J$6:$J$205,$Q31))) | G31: =IF($Q31="","",IF(INDEX(Holdings!$M$6:$M$205,$Q31)="","",INDEX(Holdings!$M$6:$M$205,$Q31)/Divisor)) | H31: =IF($Q31="","",IF(INDEX(Holdings!$R$6:$R$205,$Q31)="","",INDEX(Holdings!$R$6:$R$205,$Q31)/Divisor)) | I31: =IF(OR($Q31="",N($H$43)=0),"",H31/$H$43) | J31: =IF($Q31="","",IF(INDEX(Holdings!$S$6:$S$205,$Q31)="","",INDEX(Holdings!$S$6:$S$205,$Q31)/Divisor)) | K31: =IF($Q31="","",INDEX(Holdings!$AB$6:$AB$205,$Q31)&"") | L31: =IF($Q31="","",IF(K31="XIRR",INDEX(Holdings!$W$6:$W$205,$Q31),IF(K31="Absolute",IF(INDEX(Holdings!$T$6:$T$205,$Q31)="","",INDEX(Holdings!$T$6:$T$205,$Q31)),""))) | M31: =IF($Q31="","",IF(K31="XIRR",IF(INDEX(Holdings!$Z$6:$Z$205,$Q31)="","",INDEX(Holdings!$Z$6:$Z$205,$Q31)),IF(K31="Absolute",IF(INDEX(Holdings!$Y$6:$Y$205,$Q31)="","",INDEX(Holdings!$Y$6:$Y$205,$Q31)),""))) | N31: =IF(OR(L31="",M31=""),"",L31-M31) | O31: =IF($Q31="","",INDEX(Holdings!$X$6:$X$205,$Q31)&"") | Q31: =IFERROR(MATCH($R$26&"|"&$S31,Holdings!$AL$6:$AL$205,0),"") | S31: 4
B32: =IF($Q32="","",INDEX(Holdings!$F$6:$F$205,$Q32)&"") | C32: =IF($Q32="","",INDEX(Holdings!$D$6:$D$205,$Q32)&"") | D32: =IF($Q32="","",INDEX(Holdings!$E$6:$E$205,$Q32)&"") | E32: =IF($Q32="","",INDEX(Holdings!$H$6:$H$205,$Q32)&"") | F32: =IF($Q32="","",IF(INDEX(Holdings!$J$6:$J$205,$Q32)="","",INDEX(Holdings!$J$6:$J$205,$Q32))) | G32: =IF($Q32="","",IF(INDEX(Holdings!$M$6:$M$205,$Q32)="","",INDEX(Holdings!$M$6:$M$205,$Q32)/Divisor)) | H32: =IF($Q32="","",IF(INDEX(Holdings!$R$6:$R$205,$Q32)="","",INDEX(Holdings!$R$6:$R$205,$Q32)/Divisor)) | I32: =IF(OR($Q32="",N($H$43)=0),"",H32/$H$43) | J32: =IF($Q32="","",IF(INDEX(Holdings!$S$6:$S$205,$Q32)="","",INDEX(Holdings!$S$6:$S$205,$Q32)/Divisor)) | K32: =IF($Q32="","",INDEX(Holdings!$AB$6:$AB$205,$Q32)&"") | L32: =IF($Q32="","",IF(K32="XIRR",INDEX(Holdings!$W$6:$W$205,$Q32),IF(K32="Absolute",IF(INDEX(Holdings!$T$6:$T$205,$Q32)="","",INDEX(Holdings!$T$6:$T$205,$Q32)),""))) | M32: =IF($Q32="","",IF(K32="XIRR",IF(INDEX(Holdings!$Z$6:$Z$205,$Q32)="","",INDEX(Holdings!$Z$6:$Z$205,$Q32)),IF(K32="Absolute",IF(INDEX(Holdings!$Y$6:$Y$205,$Q32)="","",INDEX(Holdings!$Y$6:$Y$205,$Q32)),""))) | N32: =IF(OR(L32="",M32=""),"",L32-M32) | O32: =IF($Q32="","",INDEX(Holdings!$X$6:$X$205,$Q32)&"") | Q32: =IFERROR(MATCH($R$26&"|"&$S32,Holdings!$AL$6:$AL$205,0),"") | S32: 5
B33: =IF($Q33="","",INDEX(Holdings!$F$6:$F$205,$Q33)&"") | C33: =IF($Q33="","",INDEX(Holdings!$D$6:$D$205,$Q33)&"") | D33: =IF($Q33="","",INDEX(Holdings!$E$6:$E$205,$Q33)&"") | E33: =IF($Q33="","",INDEX(Holdings!$H$6:$H$205,$Q33)&"") | F33: =IF($Q33="","",IF(INDEX(Holdings!$J$6:$J$205,$Q33)="","",INDEX(Holdings!$J$6:$J$205,$Q33))) | G33: =IF($Q33="","",IF(INDEX(Holdings!$M$6:$M$205,$Q33)="","",INDEX(Holdings!$M$6:$M$205,$Q33)/Divisor)) | H33: =IF($Q33="","",IF(INDEX(Holdings!$R$6:$R$205,$Q33)="","",INDEX(Holdings!$R$6:$R$205,$Q33)/Divisor)) | I33: =IF(OR($Q33="",N($H$43)=0),"",H33/$H$43) | J33: =IF($Q33="","",IF(INDEX(Holdings!$S$6:$S$205,$Q33)="","",INDEX(Holdings!$S$6:$S$205,$Q33)/Divisor)) | K33: =IF($Q33="","",INDEX(Holdings!$AB$6:$AB$205,$Q33)&"") | L33: =IF($Q33="","",IF(K33="XIRR",INDEX(Holdings!$W$6:$W$205,$Q33),IF(K33="Absolute",IF(INDEX(Holdings!$T$6:$T$205,$Q33)="","",INDEX(Holdings!$T$6:$T$205,$Q33)),""))) | M33: =IF($Q33="","",IF(K33="XIRR",IF(INDEX(Holdings!$Z$6:$Z$205,$Q33)="","",INDEX(Holdings!$Z$6:$Z$205,$Q33)),IF(K33="Absolute",IF(INDEX(Holdings!$Y$6:$Y$205,$Q33)="","",INDEX(Holdings!$Y$6:$Y$205,$Q33)),""))) | N33: =IF(OR(L33="",M33=""),"",L33-M33) | O33: =IF($Q33="","",INDEX(Holdings!$X$6:$X$205,$Q33)&"") | Q33: =IFERROR(MATCH($R$26&"|"&$S33,Holdings!$AL$6:$AL$205,0),"") | S33: 6
B34: =IF($Q34="","",INDEX(Holdings!$F$6:$F$205,$Q34)&"") | C34: =IF($Q34="","",INDEX(Holdings!$D$6:$D$205,$Q34)&"") | D34: =IF($Q34="","",INDEX(Holdings!$E$6:$E$205,$Q34)&"") | E34: =IF($Q34="","",INDEX(Holdings!$H$6:$H$205,$Q34)&"") | F34: =IF($Q34="","",IF(INDEX(Holdings!$J$6:$J$205,$Q34)="","",INDEX(Holdings!$J$6:$J$205,$Q34))) | G34: =IF($Q34="","",IF(INDEX(Holdings!$M$6:$M$205,$Q34)="","",INDEX(Holdings!$M$6:$M$205,$Q34)/Divisor)) | H34: =IF($Q34="","",IF(INDEX(Holdings!$R$6:$R$205,$Q34)="","",INDEX(Holdings!$R$6:$R$205,$Q34)/Divisor)) | I34: =IF(OR($Q34="",N($H$43)=0),"",H34/$H$43) | J34: =IF($Q34="","",IF(INDEX(Holdings!$S$6:$S$205,$Q34)="","",INDEX(Holdings!$S$6:$S$205,$Q34)/Divisor)) | K34: =IF($Q34="","",INDEX(Holdings!$AB$6:$AB$205,$Q34)&"") | L34: =IF($Q34="","",IF(K34="XIRR",INDEX(Holdings!$W$6:$W$205,$Q34),IF(K34="Absolute",IF(INDEX(Holdings!$T$6:$T$205,$Q34)="","",INDEX(Holdings!$T$6:$T$205,$Q34)),""))) | M34: =IF($Q34="","",IF(K34="XIRR",IF(INDEX(Holdings!$Z$6:$Z$205,$Q34)="","",INDEX(Holdings!$Z$6:$Z$205,$Q34)),IF(K34="Absolute",IF(INDEX(Holdings!$Y$6:$Y$205,$Q34)="","",INDEX(Holdings!$Y$6:$Y$205,$Q34)),""))) | N34: =IF(OR(L34="",M34=""),"",L34-M34) | O34: =IF($Q34="","",INDEX(Holdings!$X$6:$X$205,$Q34)&"") | Q34: =IFERROR(MATCH($R$26&"|"&$S34,Holdings!$AL$6:$AL$205,0),"") | S34: 7
B35: =IF($Q35="","",INDEX(Holdings!$F$6:$F$205,$Q35)&"") | C35: =IF($Q35="","",INDEX(Holdings!$D$6:$D$205,$Q35)&"") | D35: =IF($Q35="","",INDEX(Holdings!$E$6:$E$205,$Q35)&"") | E35: =IF($Q35="","",INDEX(Holdings!$H$6:$H$205,$Q35)&"") | F35: =IF($Q35="","",IF(INDEX(Holdings!$J$6:$J$205,$Q35)="","",INDEX(Holdings!$J$6:$J$205,$Q35))) | G35: =IF($Q35="","",IF(INDEX(Holdings!$M$6:$M$205,$Q35)="","",INDEX(Holdings!$M$6:$M$205,$Q35)/Divisor)) | H35: =IF($Q35="","",IF(INDEX(Holdings!$R$6:$R$205,$Q35)="","",INDEX(Holdings!$R$6:$R$205,$Q35)/Divisor)) | I35: =IF(OR($Q35="",N($H$43)=0),"",H35/$H$43) | J35: =IF($Q35="","",IF(INDEX(Holdings!$S$6:$S$205,$Q35)="","",INDEX(Holdings!$S$6:$S$205,$Q35)/Divisor)) | K35: =IF($Q35="","",INDEX(Holdings!$AB$6:$AB$205,$Q35)&"") | L35: =IF($Q35="","",IF(K35="XIRR",INDEX(Holdings!$W$6:$W$205,$Q35),IF(K35="Absolute",IF(INDEX(Holdings!$T$6:$T$205,$Q35)="","",INDEX(Holdings!$T$6:$T$205,$Q35)),""))) | M35: =IF($Q35="","",IF(K35="XIRR",IF(INDEX(Holdings!$Z$6:$Z$205,$Q35)="","",INDEX(Holdings!$Z$6:$Z$205,$Q35)),IF(K35="Absolute",IF(INDEX(Holdings!$Y$6:$Y$205,$Q35)="","",INDEX(Holdings!$Y$6:$Y$205,$Q35)),""))) | N35: =IF(OR(L35="",M35=""),"",L35-M35) | O35: =IF($Q35="","",INDEX(Holdings!$X$6:$X$205,$Q35)&"") | Q35: =IFERROR(MATCH($R$26&"|"&$S35,Holdings!$AL$6:$AL$205,0),"") | S35: 8
B36: =IF($Q36="","",INDEX(Holdings!$F$6:$F$205,$Q36)&"") | C36: =IF($Q36="","",INDEX(Holdings!$D$6:$D$205,$Q36)&"") | D36: =IF($Q36="","",INDEX(Holdings!$E$6:$E$205,$Q36)&"") | E36: =IF($Q36="","",INDEX(Holdings!$H$6:$H$205,$Q36)&"") | F36: =IF($Q36="","",IF(INDEX(Holdings!$J$6:$J$205,$Q36)="","",INDEX(Holdings!$J$6:$J$205,$Q36))) | G36: =IF($Q36="","",IF(INDEX(Holdings!$M$6:$M$205,$Q36)="","",INDEX(Holdings!$M$6:$M$205,$Q36)/Divisor)) | H36: =IF($Q36="","",IF(INDEX(Holdings!$R$6:$R$205,$Q36)="","",INDEX(Holdings!$R$6:$R$205,$Q36)/Divisor)) | I36: =IF(OR($Q36="",N($H$43)=0),"",H36/$H$43) | J36: =IF($Q36="","",IF(INDEX(Holdings!$S$6:$S$205,$Q36)="","",INDEX(Holdings!$S$6:$S$205,$Q36)/Divisor)) | K36: =IF($Q36="","",INDEX(Holdings!$AB$6:$AB$205,$Q36)&"") | L36: =IF($Q36="","",IF(K36="XIRR",INDEX(Holdings!$W$6:$W$205,$Q36),IF(K36="Absolute",IF(INDEX(Holdings!$T$6:$T$205,$Q36)="","",INDEX(Holdings!$T$6:$T$205,$Q36)),""))) | M36: =IF($Q36="","",IF(K36="XIRR",IF(INDEX(Holdings!$Z$6:$Z$205,$Q36)="","",INDEX(Holdings!$Z$6:$Z$205,$Q36)),IF(K36="Absolute",IF(INDEX(Holdings!$Y$6:$Y$205,$Q36)="","",INDEX(Holdings!$Y$6:$Y$205,$Q36)),""))) | N36: =IF(OR(L36="",M36=""),"",L36-M36) | O36: =IF($Q36="","",INDEX(Holdings!$X$6:$X$205,$Q36)&"") | Q36: =IFERROR(MATCH($R$26&"|"&$S36,Holdings!$AL$6:$AL$205,0),"") | S36: 9
B37: =IF($Q37="","",INDEX(Holdings!$F$6:$F$205,$Q37)&"") | C37: =IF($Q37="","",INDEX(Holdings!$D$6:$D$205,$Q37)&"") | D37: =IF($Q37="","",INDEX(Holdings!$E$6:$E$205,$Q37)&"") | E37: =IF($Q37="","",INDEX(Holdings!$H$6:$H$205,$Q37)&"") | F37: =IF($Q37="","",IF(INDEX(Holdings!$J$6:$J$205,$Q37)="","",INDEX(Holdings!$J$6:$J$205,$Q37))) | G37: =IF($Q37="","",IF(INDEX(Holdings!$M$6:$M$205,$Q37)="","",INDEX(Holdings!$M$6:$M$205,$Q37)/Divisor)) | H37: =IF($Q37="","",IF(INDEX(Holdings!$R$6:$R$205,$Q37)="","",INDEX(Holdings!$R$6:$R$205,$Q37)/Divisor)) | I37: =IF(OR($Q37="",N($H$43)=0),"",H37/$H$43) | J37: =IF($Q37="","",IF(INDEX(Holdings!$S$6:$S$205,$Q37)="","",INDEX(Holdings!$S$6:$S$205,$Q37)/Divisor)) | K37: =IF($Q37="","",INDEX(Holdings!$AB$6:$AB$205,$Q37)&"") | L37: =IF($Q37="","",IF(K37="XIRR",INDEX(Holdings!$W$6:$W$205,$Q37),IF(K37="Absolute",IF(INDEX(Holdings!$T$6:$T$205,$Q37)="","",INDEX(Holdings!$T$6:$T$205,$Q37)),""))) | M37: =IF($Q37="","",IF(K37="XIRR",IF(INDEX(Holdings!$Z$6:$Z$205,$Q37)="","",INDEX(Holdings!$Z$6:$Z$205,$Q37)),IF(K37="Absolute",IF(INDEX(Holdings!$Y$6:$Y$205,$Q37)="","",INDEX(Holdings!$Y$6:$Y$205,$Q37)),""))) | N37: =IF(OR(L37="",M37=""),"",L37-M37) | O37: =IF($Q37="","",INDEX(Holdings!$X$6:$X$205,$Q37)&"") | Q37: =IFERROR(MATCH($R$26&"|"&$S37,Holdings!$AL$6:$AL$205,0),"") | S37: 10
B38: =IF($Q38="","",INDEX(Holdings!$F$6:$F$205,$Q38)&"") | C38: =IF($Q38="","",INDEX(Holdings!$D$6:$D$205,$Q38)&"") | D38: =IF($Q38="","",INDEX(Holdings!$E$6:$E$205,$Q38)&"") | E38: =IF($Q38="","",INDEX(Holdings!$H$6:$H$205,$Q38)&"") | F38: =IF($Q38="","",IF(INDEX(Holdings!$J$6:$J$205,$Q38)="","",INDEX(Holdings!$J$6:$J$205,$Q38))) | G38: =IF($Q38="","",IF(INDEX(Holdings!$M$6:$M$205,$Q38)="","",INDEX(Holdings!$M$6:$M$205,$Q38)/Divisor)) | H38: =IF($Q38="","",IF(INDEX(Holdings!$R$6:$R$205,$Q38)="","",INDEX(Holdings!$R$6:$R$205,$Q38)/Divisor)) | I38: =IF(OR($Q38="",N($H$43)=0),"",H38/$H$43) | J38: =IF($Q38="","",IF(INDEX(Holdings!$S$6:$S$205,$Q38)="","",INDEX(Holdings!$S$6:$S$205,$Q38)/Divisor)) | K38: =IF($Q38="","",INDEX(Holdings!$AB$6:$AB$205,$Q38)&"") | L38: =IF($Q38="","",IF(K38="XIRR",INDEX(Holdings!$W$6:$W$205,$Q38),IF(K38="Absolute",IF(INDEX(Holdings!$T$6:$T$205,$Q38)="","",INDEX(Holdings!$T$6:$T$205,$Q38)),""))) | M38: =IF($Q38="","",IF(K38="XIRR",IF(INDEX(Holdings!$Z$6:$Z$205,$Q38)="","",INDEX(Holdings!$Z$6:$Z$205,$Q38)),IF(K38="Absolute",IF(INDEX(Holdings!$Y$6:$Y$205,$Q38)="","",INDEX(Holdings!$Y$6:$Y$205,$Q38)),""))) | N38: =IF(OR(L38="",M38=""),"",L38-M38) | O38: =IF($Q38="","",INDEX(Holdings!$X$6:$X$205,$Q38)&"") | Q38: =IFERROR(MATCH($R$26&"|"&$S38,Holdings!$AL$6:$AL$205,0),"") | S38: 11
B39: =IF($Q39="","",INDEX(Holdings!$F$6:$F$205,$Q39)&"") | C39: =IF($Q39="","",INDEX(Holdings!$D$6:$D$205,$Q39)&"") | D39: =IF($Q39="","",INDEX(Holdings!$E$6:$E$205,$Q39)&"") | E39: =IF($Q39="","",INDEX(Holdings!$H$6:$H$205,$Q39)&"") | F39: =IF($Q39="","",IF(INDEX(Holdings!$J$6:$J$205,$Q39)="","",INDEX(Holdings!$J$6:$J$205,$Q39))) | G39: =IF($Q39="","",IF(INDEX(Holdings!$M$6:$M$205,$Q39)="","",INDEX(Holdings!$M$6:$M$205,$Q39)/Divisor)) | H39: =IF($Q39="","",IF(INDEX(Holdings!$R$6:$R$205,$Q39)="","",INDEX(Holdings!$R$6:$R$205,$Q39)/Divisor)) | I39: =IF(OR($Q39="",N($H$43)=0),"",H39/$H$43) | J39: =IF($Q39="","",IF(INDEX(Holdings!$S$6:$S$205,$Q39)="","",INDEX(Holdings!$S$6:$S$205,$Q39)/Divisor)) | K39: =IF($Q39="","",INDEX(Holdings!$AB$6:$AB$205,$Q39)&"") | L39: =IF($Q39="","",IF(K39="XIRR",INDEX(Holdings!$W$6:$W$205,$Q39),IF(K39="Absolute",IF(INDEX(Holdings!$T$6:$T$205,$Q39)="","",INDEX(Holdings!$T$6:$T$205,$Q39)),""))) | M39: =IF($Q39="","",IF(K39="XIRR",IF(INDEX(Holdings!$Z$6:$Z$205,$Q39)="","",INDEX(Holdings!$Z$6:$Z$205,$Q39)),IF(K39="Absolute",IF(INDEX(Holdings!$Y$6:$Y$205,$Q39)="","",INDEX(Holdings!$Y$6:$Y$205,$Q39)),""))) | N39: =IF(OR(L39="",M39=""),"",L39-M39) | O39: =IF($Q39="","",INDEX(Holdings!$X$6:$X$205,$Q39)&"") | Q39: =IFERROR(MATCH($R$26&"|"&$S39,Holdings!$AL$6:$AL$205,0),"") | S39: 12
... B42: =IF($Q42="","",INDEX(Holdings!$F$6:$F$205,$Q42)&"") | C42: =IF($Q42="","",INDEX(Holdings!$D$6:$D$205,$Q42)&"") | D42: =IF($Q42="","",INDEX(Holdings!$E$6:$E$205,$Q42)&"") | E42: =IF($Q42="","",INDEX(Holdings!$H$6:$H$205,$Q42)&"") | F42: =IF($Q42="","",IF(INDEX(Holdings!$J$6:$J$205,$Q42)="","",INDEX(Holdings!$J$6:$J$205,$Q42))) | G42: =IF($Q42="","",IF(INDEX(Holdings!$M$6:$M$205,$Q42)="","",INDEX(Holdings!$M$6:$M$205,$Q42)/Divisor)) | H42: =IF($Q42="","",IF(INDEX(Holdings!$R$6:$R$205,$Q42)="","",INDEX(Holdings!$R$6:$R$205,$Q42)/Divisor)) | I42: =IF(OR($Q42="",N($H$43)=0),"",H42/$H$43) | J42: =IF($Q42="","",IF(INDEX(Holdings!$S$6:$S$205,$Q42)="","",INDEX(Holdings!$S$6:$S$205,$Q42)/Divisor)) | K42: =IF($Q42="","",INDEX(Holdings!$AB$6:$AB$205,$Q42)&"") | L42: =IF($Q42="","",IF(K42="XIRR",INDEX(Holdings!$W$6:$W$205,$Q42),IF(K42="Absolute",IF(INDEX(Holdings!$T$6:$T$205,$Q42)="","",INDEX(Holdings!$T$6:$T$205,$Q42)),""))) | M42: =IF($Q42="","",IF(K42="XIRR",IF(INDEX(Holdings!$Z$6:$Z$205,$Q42)="","",INDEX(Holdings!$Z$6:$Z$205,$Q42)),IF(K42="Absolute",IF(INDEX(Holdings!$Y$6:$Y$205,$Q42)="","",INDEX(Holdings!$Y$6:$Y$205,$Q42)),""))) | N42: =IF(OR(L42="",M42=""),"",L42-M42) | O42: =IF($Q42="","",INDEX(Holdings!$X$6:$X$205,$Q42)&"") | Q42: =IFERROR(MATCH($R$26&"|"&$S42,Holdings!$AL$6:$AL$205,0),"") | S42: 15
B43: ="Total — "&Lists!$L$7 -> Total — Entrepreneurial Growth | G43: =SUMIFS(Holdings!$M$6:$M$205,Holdings!$I$6:$I$205,$R$26)/Divisor -> 11.7 | H43: =SUMIFS(Holdings!$R$6:$R$205,Holdings!$I$6:$I$205,$R$26)/Divisor -> 13.2888 | I43: =IF(N(H43)=0,"",SUM(I28:I42)) -> 1 | J43: =SUMIFS(Holdings!$S$6:$S$205,Holdings!$I$6:$I$205,$R$26)/Divisor -> 1.5888 | K43: =IF(SUMIFS(Holdings!$AN$6:$AN$205,Holdings!$I$6:$I$205,$R$26)>0,"XIRR",IF(N(G43)>0,"Absolute","")) -> XIRR | L43: =IF(K43="XIRR",IF(SUMIFS(Holdings!$AN$6:$AN$205,Holdings!$I$6:$I$205,$R$26)=0,"",SUMIFS(Holdings!$AM$6:$AM$205,Holdings!$I$6:$I$205,$R$26)/SUMIFS(Holdings!$AN$6:$AN$205,Holdings!$I$6:$I$205,$R$26)),IF(K43="Absolute",J43/G43,"")) -> 0.151 | M43: =IF(K43="XIRR",IF(SUMIFS(Holdings!$AN$6:$AN$205,Holdings!$I$6:$I$205,$R$26)=0,"",SUMIFS(Holdings!$AO$6:$AO$205,Holdings!$I$6:$I$205,$R$26)/SUMIFS(Holdings!$AN$6:$AN$205,Holdings!$I$6:$I$205,$R$26)),IF(K43="Absolute",IF(SUMIFS(Holdings!$AQ$6:$AQ$205,Holdings!$I$6:$I$205,$R$26)=0,"",SUMIFS(Holdings!$AP$6:$AP$205,Holdings!$I$6:$I$205,$R$26)/SUMIFS(Holdings!$AQ$6:$AQ$205,Holdings!$I$6:$I$205,$R$26)),"")) -> 0.128 | N43: =IF(OR(L43="",M43=""),"",L43-M43) -> 0.023
B44: =IF(SUMPRODUCT((Holdings!$I$6:$I$205=$R$26)*ISNUMBER(Holdings!$R$6:$R$205))>15,SUMPRODUCT((Holdings!$I$6:$I$205=$R$26)*ISNUMBER(Holdings!$R$6:$R$205))-15&" more holding(s) in this basket are not listed; the total includes them.",IF(SUMPRODUCT((Holdings!$I$6:$I$205=$R$26)*ISNUMBER(Holdings!$R$6:$R$205))=0,"Nothing is held in this basket.",""))
B47: =Lists!$L$8&" · "&Lists!$K$8 -> Liquidity · LQ | R47: =Lists!$K$8 -> LQ
B48: Security / product | C48: Entity | D48: Advisor / manager | E48: Category | F48: First investment | G48: Investment at cost | H48: Market value | I48: % of basket | J48: Gain / (loss) on what is held | K48: Return shown | L48: Return (%) | M48: Benchmark return (%) | N48: Alpha (% points) | O48: Benchmark
B49: =IF($Q49="","",INDEX(Holdings!$F$6:$F$205,$Q49)&"") -> Malabar Arbitrage Fund – Direct Growth | C49: =IF($Q49="","",INDEX(Holdings!$D$6:$D$205,$Q49)&"") -> Malhotra Family Trust | D49: =IF($Q49="","",INDEX(Holdings!$E$6:$E$205,$Q49)&"") -> Granite Wealth | E49: =IF($Q49="","",INDEX(Holdings!$H$6:$H$205,$Q49)&"") -> Arbitrage Fund | F49: =IF($Q49="","",IF(INDEX(Holdings!$J$6:$J$205,$Q49)="","",INDEX(Holdings!$J$6:$J$205,$Q49))) -> 45993 | G49: =IF($Q49="","",IF(INDEX(Holdings!$M$6:$M$205,$Q49)="","",INDEX(Holdings!$M$6:$M$205,$Q49)/Divisor)) -> 5.8156 | H49: =IF($Q49="","",IF(INDEX(Holdings!$R$6:$R$205,$Q49)="","",INDEX(Holdings!$R$6:$R$205,$Q49)/Divisor)) -> 5.997504 | I49: =IF(OR($Q49="",N($H$64)=0),"",H49/$H$64) -> 0.33804663 | J49: =IF($Q49="","",IF(INDEX(Holdings!$S$6:$S$205,$Q49)="","",INDEX(Holdings!$S$6:$S$205,$Q49)/Divisor)) -> 0.181904 | K49: =IF($Q49="","",INDEX(Holdings!$AB$6:$AB$205,$Q49)&"") -> Absolute | L49: =IF($Q49="","",IF(K49="XIRR",INDEX(Holdings!$W$6:$W$205,$Q49),IF(K49="Absolute",IF(INDEX(Holdings!$T$6:$T$205,$Q49)="","",INDEX(Holdings!$T$6:$T$205,$Q49)),""))) -> 0.03127863 | M49: =IF($Q49="","",IF(K49="XIRR",IF(INDEX(Holdings!$Z$6:$Z$205,$Q49)="","",INDEX(Holdings!$Z$6:$Z$205,$Q49)),IF(K49="Absolute",IF(INDEX(Holdings!$Y$6:$Y$205,$Q49)="","",INDEX(Holdings!$Y$6:$Y$205,$Q49)),""))) -> 0.033 | N49: =IF(OR(L49="",M49=""),"",L49-M49) -> -0.0017213701 | O49: =IF($Q49="","",INDEX(Holdings!$X$6:$X$205,$Q49)&"") -> Nifty 50 Arbitrage Index | Q49: =IFERROR(MATCH($R$47&"|"&$S49,Holdings!$AL$6:$AL$205,0),"") -> 17 | S49: 1
B50: =IF($Q50="","",INDEX(Holdings!$F$6:$F$205,$Q50)&"") -> Lotus Liquid Fund – Direct Growth | C50: =IF($Q50="","",INDEX(Holdings!$D$6:$D$205,$Q50)&"") -> Arjun Malhotra | D50: =IF($Q50="","",INDEX(Holdings!$E$6:$E$205,$Q50)&"") -> Self-directed | E50: =IF($Q50="","",INDEX(Holdings!$H$6:$H$205,$Q50)&"") -> Liquid / Overnight Fund | F50: =IF($Q50="","",IF(INDEX(Holdings!$J$6:$J$205,$Q50)="","",INDEX(Holdings!$J$6:$J$205,$Q50))) -> 46092 | G50: =IF($Q50="","",IF(INDEX(Holdings!$M$6:$M$205,$Q50)="","",INDEX(Holdings!$M$6:$M$205,$Q50)/Divisor)) -> 4.945 | H50: =IF($Q50="","",IF(INDEX(Holdings!$R$6:$R$205,$Q50)="","",INDEX(Holdings!$R$6:$R$205,$Q50)/Divisor)) -> 4.9994644 | I50: =IF(OR($Q50="",N($H$64)=0),"",H50/$H$64) -> 0.28179258 | J50: =IF($Q50="","",IF(INDEX(Holdings!$S$6:$S$205,$Q50)="","",INDEX(Holdings!$S$6:$S$205,$Q50)/Divisor)) -> 0.054464396 | K50: =IF($Q50="","",INDEX(Holdings!$AB$6:$AB$205,$Q50)&"") -> Absolute | L50: =IF($Q50="","",IF(K50="XIRR",INDEX(Holdings!$W$6:$W$205,$Q50),IF(K50="Absolute",IF(INDEX(Holdings!$T$6:$T$205,$Q50)="","",INDEX(Holdings!$T$6:$T$205,$Q50)),""))) -> 0.011014033 | M50: =IF($Q50="","",IF(K50="XIRR",IF(INDEX(Holdings!$Z$6:$Z$205,$Q50)="","",INDEX(Holdings!$Z$6:$Z$205,$Q50)),IF(K50="Absolute",IF(INDEX(Holdings!$Y$6:$Y$205,$Q50)="","",INDEX(Holdings!$Y$6:$Y$205,$Q50)),""))) -> 0.012 | N50: =IF(OR(L50="",M50=""),"",L50-M50) -> -0.0009859665 | O50: =IF($Q50="","",INDEX(Holdings!$X$6:$X$205,$Q50)&"") -> CRISIL Liquid Debt Index | Q50: =IFERROR(MATCH($R$47&"|"&$S50,Holdings!$AL$6:$AL$205,0),"") -> 13 | S50: 2
B51: =IF($Q51="","",INDEX(Holdings!$F$6:$F$205,$Q51)&"") -> Meridian Bank – Operating Current Account | C51: =IF($Q51="","",INDEX(Holdings!$D$6:$D$205,$Q51)&"") -> Malhotra Holdings LLP | D51: =IF($Q51="","",INDEX(Holdings!$E$6:$E$205,$Q51)&"") -> Self-directed | E51: =IF($Q51="","",INDEX(Holdings!$H$6:$H$205,$Q51)&"") -> Bank / Cash Balance | F51: =IF($Q51="","",IF(INDEX(Holdings!$J$6:$J$205,$Q51)="","",INDEX(Holdings!$J$6:$J$205,$Q51))) | G51: =IF($Q51="","",IF(INDEX(Holdings!$M$6:$M$205,$Q51)="","",INDEX(Holdings!$M$6:$M$205,$Q51)/Divisor)) -> 3.745 | H51: =IF($Q51="","",IF(INDEX(Holdings!$R$6:$R$205,$Q51)="","",INDEX(Holdings!$R$6:$R$205,$Q51)/Divisor)) -> 3.745 | I51: =IF(OR($Q51="",N($H$64)=0),"",H51/$H$64) -> 0.21108525 | J51: =IF($Q51="","",IF(INDEX(Holdings!$S$6:$S$205,$Q51)="","",INDEX(Holdings!$S$6:$S$205,$Q51)/Divisor)) -> 0 | K51: =IF($Q51="","",INDEX(Holdings!$AB$6:$AB$205,$Q51)&"") -> No date | L51: =IF($Q51="","",IF(K51="XIRR",INDEX(Holdings!$W$6:$W$205,$Q51),IF(K51="Absolute",IF(INDEX(Holdings!$T$6:$T$205,$Q51)="","",INDEX(Holdings!$T$6:$T$205,$Q51)),""))) | M51: =IF($Q51="","",IF(K51="XIRR",IF(INDEX(Holdings!$Z$6:$Z$205,$Q51)="","",INDEX(Holdings!$Z$6:$Z$205,$Q51)),IF(K51="Absolute",IF(INDEX(Holdings!$Y$6:$Y$205,$Q51)="","",INDEX(Holdings!$Y$6:$Y$205,$Q51)),""))) | N51: =IF(OR(L51="",M51=""),"",L51-M51) | O51: =IF($Q51="","",INDEX(Holdings!$X$6:$X$205,$Q51)&"") | Q51: =IFERROR(MATCH($R$47&"|"&$S51,Holdings!$AL$6:$AL$205,0),"") -> 20 | S51: 3
B52: =IF($Q52="","",INDEX(Holdings!$F$6:$F$205,$Q52)&"") -> Lotus Liquid Fund – Direct Growth | C52: =IF($Q52="","",INDEX(Holdings!$D$6:$D$205,$Q52)&"") -> Malhotra Holdings LLP | D52: =IF($Q52="","",INDEX(Holdings!$E$6:$E$205,$Q52)&"") -> Orchid Wealth Advisors | E52: =IF($Q52="","",INDEX(Holdings!$H$6:$H$205,$Q52)&"") -> Liquid / Overnight Fund | F52: =IF($Q52="","",IF(INDEX(Holdings!$J$6:$J$205,$Q52)="","",INDEX(Holdings!$J$6:$J$205,$Q52))) -> 46027 | G52: =IF($Q52="","",IF(INDEX(Holdings!$M$6:$M$205,$Q52)="","",INDEX(Holdings!$M$6:$M$205,$Q52)/Divisor)) -> 2.95 | H52: =IF($Q52="","",IF(INDEX(Holdings!$R$6:$R$205,$Q52)="","",INDEX(Holdings!$R$6:$R$205,$Q52)/Divisor)) -> 2.9996786 | I52: =IF(OR($Q52="",N($H$64)=0),"",H52/$H$64) -> 0.16907554 | J52: =IF($Q52="","",IF(INDEX(Holdings!$S$6:$S$205,$Q52)="","",INDEX(Holdings!$S$6:$S$205,$Q52)/Divisor)) -> 0.049678569 | K52: =IF($Q52="","",INDEX(Holdings!$AB$6:$AB$205,$Q52)&"") -> Absolute | L52: =IF($Q52="","",IF(K52="XIRR",INDEX(Holdings!$W$6:$W$205,$Q52),IF(K52="Absolute",IF(INDEX(Holdings!$T$6:$T$205,$Q52)="","",INDEX(Holdings!$T$6:$T$205,$Q52)),""))) -> 0.016840193 | M52: =IF($Q52="","",IF(K52="XIRR",IF(INDEX(Holdings!$Z$6:$Z$205,$Q52)="","",INDEX(Holdings!$Z$6:$Z$205,$Q52)),IF(K52="Absolute",IF(INDEX(Holdings!$Y$6:$Y$205,$Q52)="","",INDEX(Holdings!$Y$6:$Y$205,$Q52)),""))) -> 0.017 | N52: =IF(OR(L52="",M52=""),"",L52-M52) -> -0.00015980707 | O52: =IF($Q52="","",INDEX(Holdings!$X$6:$X$205,$Q52)&"") -> CRISIL Liquid Debt Index | Q52: =IFERROR(MATCH($R$47&"|"&$S52,Holdings!$AL$6:$AL$205,0),"") -> 22 | S52: 4
B53: =IF($Q53="","",INDEX(Holdings!$F$6:$F$205,$Q53)&"") | C53: =IF($Q53="","",INDEX(Holdings!$D$6:$D$205,$Q53)&"") | D53: =IF($Q53="","",INDEX(Holdings!$E$6:$E$205,$Q53)&"") | E53: =IF($Q53="","",INDEX(Holdings!$H$6:$H$205,$Q53)&"") | F53: =IF($Q53="","",IF(INDEX(Holdings!$J$6:$J$205,$Q53)="","",INDEX(Holdings!$J$6:$J$205,$Q53))) | G53: =IF($Q53="","",IF(INDEX(Holdings!$M$6:$M$205,$Q53)="","",INDEX(Holdings!$M$6:$M$205,$Q53)/Divisor)) | H53: =IF($Q53="","",IF(INDEX(Holdings!$R$6:$R$205,$Q53)="","",INDEX(Holdings!$R$6:$R$205,$Q53)/Divisor)) | I53: =IF(OR($Q53="",N($H$64)=0),"",H53/$H$64) | J53: =IF($Q53="","",IF(INDEX(Holdings!$S$6:$S$205,$Q53)="","",INDEX(Holdings!$S$6:$S$205,$Q53)/Divisor)) | K53: =IF($Q53="","",INDEX(Holdings!$AB$6:$AB$205,$Q53)&"") | L53: =IF($Q53="","",IF(K53="XIRR",INDEX(Holdings!$W$6:$W$205,$Q53),IF(K53="Absolute",IF(INDEX(Holdings!$T$6:$T$205,$Q53)="","",INDEX(Holdings!$T$6:$T$205,$Q53)),""))) | M53: =IF($Q53="","",IF(K53="XIRR",IF(INDEX(Holdings!$Z$6:$Z$205,$Q53)="","",INDEX(Holdings!$Z$6:$Z$205,$Q53)),IF(K53="Absolute",IF(INDEX(Holdings!$Y$6:$Y$205,$Q53)="","",INDEX(Holdings!$Y$6:$Y$205,$Q53)),""))) | N53: =IF(OR(L53="",M53=""),"",L53-M53) | O53: =IF($Q53="","",INDEX(Holdings!$X$6:$X$205,$Q53)&"") | Q53: =IFERROR(MATCH($R$47&"|"&$S53,Holdings!$AL$6:$AL$205,0),"") | S53: 5
B54: =IF($Q54="","",INDEX(Holdings!$F$6:$F$205,$Q54)&"") | C54: =IF($Q54="","",INDEX(Holdings!$D$6:$D$205,$Q54)&"") | D54: =IF($Q54="","",INDEX(Holdings!$E$6:$E$205,$Q54)&"") | E54: =IF($Q54="","",INDEX(Holdings!$H$6:$H$205,$Q54)&"") | F54: =IF($Q54="","",IF(INDEX(Holdings!$J$6:$J$205,$Q54)="","",INDEX(Holdings!$J$6:$J$205,$Q54))) | G54: =IF($Q54="","",IF(INDEX(Holdings!$M$6:$M$205,$Q54)="","",INDEX(Holdings!$M$6:$M$205,$Q54)/Divisor)) | H54: =IF($Q54="","",IF(INDEX(Holdings!$R$6:$R$205,$Q54)="","",INDEX(Holdings!$R$6:$R$205,$Q54)/Divisor)) | I54: =IF(OR($Q54="",N($H$64)=0),"",H54/$H$64) | J54: =IF($Q54="","",IF(INDEX(Holdings!$S$6:$S$205,$Q54)="","",INDEX(Holdings!$S$6:$S$205,$Q54)/Divisor)) | K54: =IF($Q54="","",INDEX(Holdings!$AB$6:$AB$205,$Q54)&"") | L54: =IF($Q54="","",IF(K54="XIRR",INDEX(Holdings!$W$6:$W$205,$Q54),IF(K54="Absolute",IF(INDEX(Holdings!$T$6:$T$205,$Q54)="","",INDEX(Holdings!$T$6:$T$205,$Q54)),""))) | M54: =IF($Q54="","",IF(K54="XIRR",IF(INDEX(Holdings!$Z$6:$Z$205,$Q54)="","",INDEX(Holdings!$Z$6:$Z$205,$Q54)),IF(K54="Absolute",IF(INDEX(Holdings!$Y$6:$Y$205,$Q54)="","",INDEX(Holdings!$Y$6:$Y$205,$Q54)),""))) | N54: =IF(OR(L54="",M54=""),"",L54-M54) | O54: =IF($Q54="","",INDEX(Holdings!$X$6:$X$205,$Q54)&"") | Q54: =IFERROR(MATCH($R$47&"|"&$S54,Holdings!$AL$6:$AL$205,0),"") | S54: 6
B55: =IF($Q55="","",INDEX(Holdings!$F$6:$F$205,$Q55)&"") | C55: =IF($Q55="","",INDEX(Holdings!$D$6:$D$205,$Q55)&"") | D55: =IF($Q55="","",INDEX(Holdings!$E$6:$E$205,$Q55)&"") | E55: =IF($Q55="","",INDEX(Holdings!$H$6:$H$205,$Q55)&"") | F55: =IF($Q55="","",IF(INDEX(Holdings!$J$6:$J$205,$Q55)="","",INDEX(Holdings!$J$6:$J$205,$Q55))) | G55: =IF($Q55="","",IF(INDEX(Holdings!$M$6:$M$205,$Q55)="","",INDEX(Holdings!$M$6:$M$205,$Q55)/Divisor)) | H55: =IF($Q55="","",IF(INDEX(Holdings!$R$6:$R$205,$Q55)="","",INDEX(Holdings!$R$6:$R$205,$Q55)/Divisor)) | I55: =IF(OR($Q55="",N($H$64)=0),"",H55/$H$64) | J55: =IF($Q55="","",IF(INDEX(Holdings!$S$6:$S$205,$Q55)="","",INDEX(Holdings!$S$6:$S$205,$Q55)/Divisor)) | K55: =IF($Q55="","",INDEX(Holdings!$AB$6:$AB$205,$Q55)&"") | L55: =IF($Q55="","",IF(K55="XIRR",INDEX(Holdings!$W$6:$W$205,$Q55),IF(K55="Absolute",IF(INDEX(Holdings!$T$6:$T$205,$Q55)="","",INDEX(Holdings!$T$6:$T$205,$Q55)),""))) | M55: =IF($Q55="","",IF(K55="XIRR",IF(INDEX(Holdings!$Z$6:$Z$205,$Q55)="","",INDEX(Holdings!$Z$6:$Z$205,$Q55)),IF(K55="Absolute",IF(INDEX(Holdings!$Y$6:$Y$205,$Q55)="","",INDEX(Holdings!$Y$6:$Y$205,$Q55)),""))) | N55: =IF(OR(L55="",M55=""),"",L55-M55) | O55: =IF($Q55="","",INDEX(Holdings!$X$6:$X$205,$Q55)&"") | Q55: =IFERROR(MATCH($R$47&"|"&$S55,Holdings!$AL$6:$AL$205,0),"") | S55: 7
B56: =IF($Q56="","",INDEX(Holdings!$F$6:$F$205,$Q56)&"") | C56: =IF($Q56="","",INDEX(Holdings!$D$6:$D$205,$Q56)&"") | D56: =IF($Q56="","",INDEX(Holdings!$E$6:$E$205,$Q56)&"") | E56: =IF($Q56="","",INDEX(Holdings!$H$6:$H$205,$Q56)&"") | F56: =IF($Q56="","",IF(INDEX(Holdings!$J$6:$J$205,$Q56)="","",INDEX(Holdings!$J$6:$J$205,$Q56))) | G56: =IF($Q56="","",IF(INDEX(Holdings!$M$6:$M$205,$Q56)="","",INDEX(Holdings!$M$6:$M$205,$Q56)/Divisor)) | H56: =IF($Q56="","",IF(INDEX(Holdings!$R$6:$R$205,$Q56)="","",INDEX(Holdings!$R$6:$R$205,$Q56)/Divisor)) | I56: =IF(OR($Q56="",N($H$64)=0),"",H56/$H$64) | J56: =IF($Q56="","",IF(INDEX(Holdings!$S$6:$S$205,$Q56)="","",INDEX(Holdings!$S$6:$S$205,$Q56)/Divisor)) | K56: =IF($Q56="","",INDEX(Holdings!$AB$6:$AB$205,$Q56)&"") | L56: =IF($Q56="","",IF(K56="XIRR",INDEX(Holdings!$W$6:$W$205,$Q56),IF(K56="Absolute",IF(INDEX(Holdings!$T$6:$T$205,$Q56)="","",INDEX(Holdings!$T$6:$T$205,$Q56)),""))) | M56: =IF($Q56="","",IF(K56="XIRR",IF(INDEX(Holdings!$Z$6:$Z$205,$Q56)="","",INDEX(Holdings!$Z$6:$Z$205,$Q56)),IF(K56="Absolute",IF(INDEX(Holdings!$Y$6:$Y$205,$Q56)="","",INDEX(Holdings!$Y$6:$Y$205,$Q56)),""))) | N56: =IF(OR(L56="",M56=""),"",L56-M56) | O56: =IF($Q56="","",INDEX(Holdings!$X$6:$X$205,$Q56)&"") | Q56: =IFERROR(MATCH($R$47&"|"&$S56,Holdings!$AL$6:$AL$205,0),"") | S56: 8
B57: =IF($Q57="","",INDEX(Holdings!$F$6:$F$205,$Q57)&"") | C57: =IF($Q57="","",INDEX(Holdings!$D$6:$D$205,$Q57)&"") | D57: =IF($Q57="","",INDEX(Holdings!$E$6:$E$205,$Q57)&"") | E57: =IF($Q57="","",INDEX(Holdings!$H$6:$H$205,$Q57)&"") | F57: =IF($Q57="","",IF(INDEX(Holdings!$J$6:$J$205,$Q57)="","",INDEX(Holdings!$J$6:$J$205,$Q57))) | G57: =IF($Q57="","",IF(INDEX(Holdings!$M$6:$M$205,$Q57)="","",INDEX(Holdings!$M$6:$M$205,$Q57)/Divisor)) | H57: =IF($Q57="","",IF(INDEX(Holdings!$R$6:$R$205,$Q57)="","",INDEX(Holdings!$R$6:$R$205,$Q57)/Divisor)) | I57: =IF(OR($Q57="",N($H$64)=0),"",H57/$H$64) | J57: =IF($Q57="","",IF(INDEX(Holdings!$S$6:$S$205,$Q57)="","",INDEX(Holdings!$S$6:$S$205,$Q57)/Divisor)) | K57: =IF($Q57="","",INDEX(Holdings!$AB$6:$AB$205,$Q57)&"") | L57: =IF($Q57="","",IF(K57="XIRR",INDEX(Holdings!$W$6:$W$205,$Q57),IF(K57="Absolute",IF(INDEX(Holdings!$T$6:$T$205,$Q57)="","",INDEX(Holdings!$T$6:$T$205,$Q57)),""))) | M57: =IF($Q57="","",IF(K57="XIRR",IF(INDEX(Holdings!$Z$6:$Z$205,$Q57)="","",INDEX(Holdings!$Z$6:$Z$205,$Q57)),IF(K57="Absolute",IF(INDEX(Holdings!$Y$6:$Y$205,$Q57)="","",INDEX(Holdings!$Y$6:$Y$205,$Q57)),""))) | N57: =IF(OR(L57="",M57=""),"",L57-M57) | O57: =IF($Q57="","",INDEX(Holdings!$X$6:$X$205,$Q57)&"") | Q57: =IFERROR(MATCH($R$47&"|"&$S57,Holdings!$AL$6:$AL$205,0),"") | S57: 9
B58: =IF($Q58="","",INDEX(Holdings!$F$6:$F$205,$Q58)&"") | C58: =IF($Q58="","",INDEX(Holdings!$D$6:$D$205,$Q58)&"") | D58: =IF($Q58="","",INDEX(Holdings!$E$6:$E$205,$Q58)&"") | E58: =IF($Q58="","",INDEX(Holdings!$H$6:$H$205,$Q58)&"") | F58: =IF($Q58="","",IF(INDEX(Holdings!$J$6:$J$205,$Q58)="","",INDEX(Holdings!$J$6:$J$205,$Q58))) | G58: =IF($Q58="","",IF(INDEX(Holdings!$M$6:$M$205,$Q58)="","",INDEX(Holdings!$M$6:$M$205,$Q58)/Divisor)) | H58: =IF($Q58="","",IF(INDEX(Holdings!$R$6:$R$205,$Q58)="","",INDEX(Holdings!$R$6:$R$205,$Q58)/Divisor)) | I58: =IF(OR($Q58="",N($H$64)=0),"",H58/$H$64) | J58: =IF($Q58="","",IF(INDEX(Holdings!$S$6:$S$205,$Q58)="","",INDEX(Holdings!$S$6:$S$205,$Q58)/Divisor)) | K58: =IF($Q58="","",INDEX(Holdings!$AB$6:$AB$205,$Q58)&"") | L58: =IF($Q58="","",IF(K58="XIRR",INDEX(Holdings!$W$6:$W$205,$Q58),IF(K58="Absolute",IF(INDEX(Holdings!$T$6:$T$205,$Q58)="","",INDEX(Holdings!$T$6:$T$205,$Q58)),""))) | M58: =IF($Q58="","",IF(K58="XIRR",IF(INDEX(Holdings!$Z$6:$Z$205,$Q58)="","",INDEX(Holdings!$Z$6:$Z$205,$Q58)),IF(K58="Absolute",IF(INDEX(Holdings!$Y$6:$Y$205,$Q58)="","",INDEX(Holdings!$Y$6:$Y$205,$Q58)),""))) | N58: =IF(OR(L58="",M58=""),"",L58-M58) | O58: =IF($Q58="","",INDEX(Holdings!$X$6:$X$205,$Q58)&"") | Q58: =IFERROR(MATCH($R$47&"|"&$S58,Holdings!$AL$6:$AL$205,0),"") | S58: 10
B59: =IF($Q59="","",INDEX(Holdings!$F$6:$F$205,$Q59)&"") | C59: =IF($Q59="","",INDEX(Holdings!$D$6:$D$205,$Q59)&"") | D59: =IF($Q59="","",INDEX(Holdings!$E$6:$E$205,$Q59)&"") | E59: =IF($Q59="","",INDEX(Holdings!$H$6:$H$205,$Q59)&"") | F59: =IF($Q59="","",IF(INDEX(Holdings!$J$6:$J$205,$Q59)="","",INDEX(Holdings!$J$6:$J$205,$Q59))) | G59: =IF($Q59="","",IF(INDEX(Holdings!$M$6:$M$205,$Q59)="","",INDEX(Holdings!$M$6:$M$205,$Q59)/Divisor)) | H59: =IF($Q59="","",IF(INDEX(Holdings!$R$6:$R$205,$Q59)="","",INDEX(Holdings!$R$6:$R$205,$Q59)/Divisor)) | I59: =IF(OR($Q59="",N($H$64)=0),"",H59/$H$64) | J59: =IF($Q59="","",IF(INDEX(Holdings!$S$6:$S$205,$Q59)="","",INDEX(Holdings!$S$6:$S$205,$Q59)/Divisor)) | K59: =IF($Q59="","",INDEX(Holdings!$AB$6:$AB$205,$Q59)&"") | L59: =IF($Q59="","",IF(K59="XIRR",INDEX(Holdings!$W$6:$W$205,$Q59),IF(K59="Absolute",IF(INDEX(Holdings!$T$6:$T$205,$Q59)="","",INDEX(Holdings!$T$6:$T$205,$Q59)),""))) | M59: =IF($Q59="","",IF(K59="XIRR",IF(INDEX(Holdings!$Z$6:$Z$205,$Q59)="","",INDEX(Holdings!$Z$6:$Z$205,$Q59)),IF(K59="Absolute",IF(INDEX(Holdings!$Y$6:$Y$205,$Q59)="","",INDEX(Holdings!$Y$6:$Y$205,$Q59)),""))) | N59: =IF(OR(L59="",M59=""),"",L59-M59) | O59: =IF($Q59="","",INDEX(Holdings!$X$6:$X$205,$Q59)&"") | Q59: =IFERROR(MATCH($R$47&"|"&$S59,Holdings!$AL$6:$AL$205,0),"") | S59: 11
B60: =IF($Q60="","",INDEX(Holdings!$F$6:$F$205,$Q60)&"") | C60: =IF($Q60="","",INDEX(Holdings!$D$6:$D$205,$Q60)&"") | D60: =IF($Q60="","",INDEX(Holdings!$E$6:$E$205,$Q60)&"") | E60: =IF($Q60="","",INDEX(Holdings!$H$6:$H$205,$Q60)&"") | F60: =IF($Q60="","",IF(INDEX(Holdings!$J$6:$J$205,$Q60)="","",INDEX(Holdings!$J$6:$J$205,$Q60))) | G60: =IF($Q60="","",IF(INDEX(Holdings!$M$6:$M$205,$Q60)="","",INDEX(Holdings!$M$6:$M$205,$Q60)/Divisor)) | H60: =IF($Q60="","",IF(INDEX(Holdings!$R$6:$R$205,$Q60)="","",INDEX(Holdings!$R$6:$R$205,$Q60)/Divisor)) | I60: =IF(OR($Q60="",N($H$64)=0),"",H60/$H$64) | J60: =IF($Q60="","",IF(INDEX(Holdings!$S$6:$S$205,$Q60)="","",INDEX(Holdings!$S$6:$S$205,$Q60)/Divisor)) | K60: =IF($Q60="","",INDEX(Holdings!$AB$6:$AB$205,$Q60)&"") | L60: =IF($Q60="","",IF(K60="XIRR",INDEX(Holdings!$W$6:$W$205,$Q60),IF(K60="Absolute",IF(INDEX(Holdings!$T$6:$T$205,$Q60)="","",INDEX(Holdings!$T$6:$T$205,$Q60)),""))) | M60: =IF($Q60="","",IF(K60="XIRR",IF(INDEX(Holdings!$Z$6:$Z$205,$Q60)="","",INDEX(Holdings!$Z$6:$Z$205,$Q60)),IF(K60="Absolute",IF(INDEX(Holdings!$Y$6:$Y$205,$Q60)="","",INDEX(Holdings!$Y$6:$Y$205,$Q60)),""))) | N60: =IF(OR(L60="",M60=""),"",L60-M60) | O60: =IF($Q60="","",INDEX(Holdings!$X$6:$X$205,$Q60)&"") | Q60: =IFERROR(MATCH($R$47&"|"&$S60,Holdings!$AL$6:$AL$205,0),"") | S60: 12
... B63: =IF($Q63="","",INDEX(Holdings!$F$6:$F$205,$Q63)&"") | C63: =IF($Q63="","",INDEX(Holdings!$D$6:$D$205,$Q63)&"") | D63: =IF($Q63="","",INDEX(Holdings!$E$6:$E$205,$Q63)&"") | E63: =IF($Q63="","",INDEX(Holdings!$H$6:$H$205,$Q63)&"") | F63: =IF($Q63="","",IF(INDEX(Holdings!$J$6:$J$205,$Q63)="","",INDEX(Holdings!$J$6:$J$205,$Q63))) | G63: =IF($Q63="","",IF(INDEX(Holdings!$M$6:$M$205,$Q63)="","",INDEX(Holdings!$M$6:$M$205,$Q63)/Divisor)) | H63: =IF($Q63="","",IF(INDEX(Holdings!$R$6:$R$205,$Q63)="","",INDEX(Holdings!$R$6:$R$205,$Q63)/Divisor)) | I63: =IF(OR($Q63="",N($H$64)=0),"",H63/$H$64) | J63: =IF($Q63="","",IF(INDEX(Holdings!$S$6:$S$205,$Q63)="","",INDEX(Holdings!$S$6:$S$205,$Q63)/Divisor)) | K63: =IF($Q63="","",INDEX(Holdings!$AB$6:$AB$205,$Q63)&"") | L63: =IF($Q63="","",IF(K63="XIRR",INDEX(Holdings!$W$6:$W$205,$Q63),IF(K63="Absolute",IF(INDEX(Holdings!$T$6:$T$205,$Q63)="","",INDEX(Holdings!$T$6:$T$205,$Q63)),""))) | M63: =IF($Q63="","",IF(K63="XIRR",IF(INDEX(Holdings!$Z$6:$Z$205,$Q63)="","",INDEX(Holdings!$Z$6:$Z$205,$Q63)),IF(K63="Absolute",IF(INDEX(Holdings!$Y$6:$Y$205,$Q63)="","",INDEX(Holdings!$Y$6:$Y$205,$Q63)),""))) | N63: =IF(OR(L63="",M63=""),"",L63-M63) | O63: =IF($Q63="","",INDEX(Holdings!$X$6:$X$205,$Q63)&"") | Q63: =IFERROR(MATCH($R$47&"|"&$S63,Holdings!$AL$6:$AL$205,0),"") | S63: 15
B64: ="Total — "&Lists!$L$8 -> Total — Liquidity | G64: =SUMIFS(Holdings!$M$6:$M$205,Holdings!$I$6:$I$205,$R$47)/Divisor -> 17.4556 | H64: =SUMIFS(Holdings!$R$6:$R$205,Holdings!$I$6:$I$205,$R$47)/Divisor -> 17.741647 | I64: =IF(N(H64)=0,"",SUM(I49:I63)) -> 1 | J64: =SUMIFS(Holdings!$S$6:$S$205,Holdings!$I$6:$I$205,$R$47)/Divisor -> 0.28604696 | K64: =IF(SUMIFS(Holdings!$AN$6:$AN$205,Holdings!$I$6:$I$205,$R$47)>0,"XIRR",IF(N(G64)>0,"Absolute","")) -> Absolute | L64: =IF(K64="XIRR",IF(SUMIFS(Holdings!$AN$6:$AN$205,Holdings!$I$6:$I$205,$R$47)=0,"",SUMIFS(Holdings!$AM$6:$AM$205,Holdings!$I$6:$I$205,$R$47)/SUMIFS(Holdings!$AN$6:$AN$205,Holdings!$I$6:$I$205,$R$47)),IF(K64="Absolute",J64/G64,"")) -> 0.016387117 | M64: =IF(K64="XIRR",IF(SUMIFS(Holdings!$AN$6:$AN$205,Holdings!$I$6:$I$205,$R$47)=0,"",SUMIFS(Holdings!$AO$6:$AO$205,Holdings!$I$6:$I$205,$R$47)/SUMIFS(Holdings!$AN$6:$AN$205,Holdings!$I$6:$I$205,$R$47)),IF(K64="Absolute",IF(SUMIFS(Holdings!$AQ$6:$AQ$205,Holdings!$I$6:$I$205,$R$47)=0,"",SUMIFS(Holdings!$AP$6:$AP$205,Holdings!$I$6:$I$205,$R$47)/SUMIFS(Holdings!$AQ$6:$AQ$205,Holdings!$I$6:$I$205,$R$47)),"")) -> 0.021983341 | N64: =IF(OR(L64="",M64=""),"",L64-M64) -> -0.0055962241
B65: =IF(SUMPRODUCT((Holdings!$I$6:$I$205=$R$47)*ISNUMBER(Holdings!$R$6:$R$205))>15,SUMPRODUCT((Holdings!$I$6:$I$205=$R$47)*ISNUMBER(Holdings!$R$6:$R$205))-15&" more holding(s) in this basket are not listed; the total includes them.",IF(SUMPRODUCT((Holdings!$I$6:$I$205=$R$47)*ISNUMBER(Holdings!$R$6:$R$205))=0,"Nothing is held in this basket.",""))
B68: =Lists!$L$9&" · "&Lists!$K$9 -> Thematic & Tactical · TT | R68: =Lists!$K$9 -> TT
B69: Security / product | C69: Entity | D69: Advisor / manager | E69: Category | F69: First investment | G69: Investment at cost | H69: Market value | I69: % of basket | J69: Gain / (loss) on what is held | K69: Return shown | L69: Return (%) | M69: Benchmark return (%) | N69: Alpha (% points) | O69: Benchmark
B70: =IF($Q70="","",INDEX(Holdings!$F$6:$F$205,$Q70)&"") -> Aravali Cements Ltd | C70: =IF($Q70="","",INDEX(Holdings!$D$6:$D$205,$Q70)&"") -> Rajiv Malhotra | D70: =IF($Q70="","",INDEX(Holdings!$E$6:$E$205,$Q70)&"") -> Self-directed | E70: =IF($Q70="","",INDEX(Holdings!$H$6:$H$205,$Q70)&"") -> Direct Equity | F70: =IF($Q70="","",IF(INDEX(Holdings!$J$6:$J$205,$Q70)="","",INDEX(Holdings!$J$6:$J$205,$Q70))) -> 42441 | G70: =IF($Q70="","",IF(INDEX(Holdings!$M$6:$M$205,$Q70)="","",INDEX(Holdings!$M$6:$M$205,$Q70)/Divisor)) -> 4.53888 | H70: =IF($Q70="","",IF(INDEX(Holdings!$R$6:$R$205,$Q70)="","",INDEX(Holdings!$R$6:$R$205,$Q70)/Divisor)) -> 8.107 | I70: =IF(OR($Q70="",N($H$85)=0),"",H70/$H$85) -> 0.25947071 | J70: =IF($Q70="","",IF(INDEX(Holdings!$S$6:$S$205,$Q70)="","",INDEX(Holdings!$S$6:$S$205,$Q70)/Divisor)) -> 3.56812 | K70: =IF($Q70="","",INDEX(Holdings!$AB$6:$AB$205,$Q70)&"") -> XIRR | L70: =IF($Q70="","",IF(K70="XIRR",INDEX(Holdings!$W$6:$W$205,$Q70),IF(K70="Absolute",IF(INDEX(Holdings!$T$6:$T$205,$Q70)="","",INDEX(Holdings!$T$6:$T$205,$Q70)),""))) -> 0.179 | M70: =IF($Q70="","",IF(K70="XIRR",IF(INDEX(Holdings!$Z$6:$Z$205,$Q70)="","",INDEX(Holdings!$Z$6:$Z$205,$Q70)),IF(K70="Absolute",IF(INDEX(Holdings!$Y$6:$Y$205,$Q70)="","",INDEX(Holdings!$Y$6:$Y$205,$Q70)),""))) -> 0.131 | N70: =IF(OR(L70="",M70=""),"",L70-M70) -> 0.048 | O70: =IF($Q70="","",INDEX(Holdings!$X$6:$X$205,$Q70)&"") -> Nifty 500 TRI | Q70: =IFERROR(MATCH($R$68&"|"&$S70,Holdings!$AL$6:$AL$205,0),"") -> 1 | S70: 1
B71: =IF($Q71="","",INDEX(Holdings!$F$6:$F$205,$Q71)&"") -> Deccan Financial Services Ltd | C71: =IF($Q71="","",INDEX(Holdings!$D$6:$D$205,$Q71)&"") -> Nisha Malhotra | D71: =IF($Q71="","",INDEX(Holdings!$E$6:$E$205,$Q71)&"") -> Self-directed | E71: =IF($Q71="","",INDEX(Holdings!$H$6:$H$205,$Q71)&"") -> Direct Equity | F71: =IF($Q71="","",IF(INDEX(Holdings!$J$6:$J$205,$Q71)="","",INDEX(Holdings!$J$6:$J$205,$Q71))) -> 45910 | G71: =IF($Q71="","",IF(INDEX(Holdings!$M$6:$M$205,$Q71)="","",INDEX(Holdings!$M$6:$M$205,$Q71)/Divisor)) -> 5.60025 | H71: =IF($Q71="","",IF(INDEX(Holdings!$R$6:$R$205,$Q71)="","",INDEX(Holdings!$R$6:$R$205,$Q71)/Divisor)) -> 6.04152 | I71: =IF(OR($Q71="",N($H$85)=0),"",H71/$H$85) -> 0.19336345 | J71: =IF($Q71="","",IF(INDEX(Holdings!$S$6:$S$205,$Q71)="","",INDEX(Holdings!$S$6:$S$205,$Q71)/Divisor)) -> 0.44127 | K71: =IF($Q71="","",INDEX(Holdings!$AB$6:$AB$205,$Q71)&"") -> Absolute | L71: =IF($Q71="","",IF(K71="XIRR",INDEX(Holdings!$W$6:$W$205,$Q71),IF(K71="Absolute",IF(INDEX(Holdings!$T$6:$T$205,$Q71)="","",INDEX(Holdings!$T$6:$T$205,$Q71)),""))) -> 0.078794697 | M71: =IF($Q71="","",IF(K71="XIRR",IF(INDEX(Holdings!$Z$6:$Z$205,$Q71)="","",INDEX(Holdings!$Z$6:$Z$205,$Q71)),IF(K71="Absolute",IF(INDEX(Holdings!$Y$6:$Y$205,$Q71)="","",INDEX(Holdings!$Y$6:$Y$205,$Q71)),""))) -> 0.062 | N71: =IF(OR(L71="",M71=""),"",L71-M71) -> 0.016794697 | O71: =IF($Q71="","",INDEX(Holdings!$X$6:$X$205,$Q71)&"") -> Nifty 500 TRI | Q71: =IFERROR(MATCH($R$68&"|"&$S71,Holdings!$AL$6:$AL$205,0),"") -> 9 | S71: 2
B72: =IF($Q72="","",INDEX(Holdings!$F$6:$F$205,$Q72)&"") -> Indus Midcap Opportunities Fund – Direct Growth | C72: =IF($Q72="","",INDEX(Holdings!$D$6:$D$205,$Q72)&"") -> Nisha Malhotra | D72: =IF($Q72="","",INDEX(Holdings!$E$6:$E$205,$Q72)&"") -> Orchid Wealth Advisors | E72: =IF($Q72="","",INDEX(Holdings!$H$6:$H$205,$Q72)&"") -> Equity MF – Mid & Small Cap | F72: =IF($Q72="","",IF(INDEX(Holdings!$J$6:$J$205,$Q72)="","",INDEX(Holdings!$J$6:$J$205,$Q72))) -> 45031 | G72: =IF($Q72="","",IF(INDEX(Holdings!$M$6:$M$205,$Q72)="","",INDEX(Holdings!$M$6:$M$205,$Q72)/Divisor)) -> 4.25 | H72: =IF($Q72="","",IF(INDEX(Holdings!$R$6:$R$205,$Q72)="","",INDEX(Holdings!$R$6:$R$205,$Q72)/Divisor)) -> 5.8950699 | I72: =IF(OR($Q72="",N($H$85)=0),"",H72/$H$85) -> 0.1886762 | J72: =IF($Q72="","",IF(INDEX(Holdings!$S$6:$S$205,$Q72)="","",INDEX(Holdings!$S$6:$S$205,$Q72)/Divisor)) -> 1.6450699 | K72: =IF($Q72="","",INDEX(Holdings!$AB$6:$AB$205,$Q72)&"") -> XIRR | L72: =IF($Q72="","",IF(K72="XIRR",INDEX(Holdings!$W$6:$W$205,$Q72),IF(K72="Absolute",IF(INDEX(Holdings!$T$6:$T$205,$Q72)="","",INDEX(Holdings!$T$6:$T$205,$Q72)),""))) -> 0.214 | M72: =IF($Q72="","",IF(K72="XIRR",IF(INDEX(Holdings!$Z$6:$Z$205,$Q72)="","",INDEX(Holdings!$Z$6:$Z$205,$Q72)),IF(K72="Absolute",IF(INDEX(Holdings!$Y$6:$Y$205,$Q72)="","",INDEX(Holdings!$Y$6:$Y$205,$Q72)),""))) -> 0.189 | N72: =IF(OR(L72="",M72=""),"",L72-M72) -> 0.025 | O72: =IF($Q72="","",INDEX(Holdings!$X$6:$X$205,$Q72)&"") -> Nifty Midsmallcap 400 TRI | Q72: =IFERROR(MATCH($R$68&"|"&$S72,Holdings!$AL$6:$AL$205,0),"") -> 7 | S72: 3
B73: =IF($Q73="","",INDEX(Holdings!$F$6:$F$205,$Q73)&"") -> Sahyadri Precision Engineering Ltd | C73: =IF($Q73="","",INDEX(Holdings!$D$6:$D$205,$Q73)&"") -> Rajiv Malhotra | D73: =IF($Q73="","",INDEX(Holdings!$E$6:$E$205,$Q73)&"") -> Self-directed | E73: =IF($Q73="","",INDEX(Holdings!$H$6:$H$205,$Q73)&"") -> Direct Equity | F73: =IF($Q73="","",IF(INDEX(Holdings!$J$6:$J$205,$Q73)="","",INDEX(Holdings!$J$6:$J$205,$Q73))) -> 42907 | G73: =IF($Q73="","",IF(INDEX(Holdings!$M$6:$M$205,$Q73)="","",INDEX(Holdings!$M$6:$M$205,$Q73)/Divisor)) -> 2.48 | H73: =IF($Q73="","",IF(INDEX(Holdings!$R$6:$R$205,$Q73)="","",INDEX(Holdings!$R$6:$R$205,$Q73)/Divisor)) -> 4.8984 | I73: =IF(OR($Q73="",N($H$85)=0),"",H73/$H$85) -> 0.15677702 | J73: =IF($Q73="","",IF(INDEX(Holdings!$S$6:$S$205,$Q73)="","",INDEX(Holdings!$S$6:$S$205,$Q73)/Divisor)) -> 2.4184 | K73: =IF($Q73="","",INDEX(Holdings!$AB$6:$AB$205,$Q73)&"") -> XIRR | L73: =IF($Q73="","",IF(K73="XIRR",INDEX(Holdings!$W$6:$W$205,$Q73),IF(K73="Absolute",IF(INDEX(Holdings!$T$6:$T$205,$Q73)="","",INDEX(Holdings!$T$6:$T$205,$Q73)),""))) -> 0.124 | M73: =IF($Q73="","",IF(K73="XIRR",IF(INDEX(Holdings!$Z$6:$Z$205,$Q73)="","",INDEX(Holdings!$Z$6:$Z$205,$Q73)),IF(K73="Absolute",IF(INDEX(Holdings!$Y$6:$Y$205,$Q73)="","",INDEX(Holdings!$Y$6:$Y$205,$Q73)),""))) -> 0.129 | N73: =IF(OR(L73="",M73=""),"",L73-M73) -> -0.005 | O73: =IF($Q73="","",INDEX(Holdings!$X$6:$X$205,$Q73)&"") -> Nifty 500 TRI | Q73: =IFERROR(MATCH($R$68&"|"&$S73,Holdings!$AL$6:$AL$205,0),"") -> 2 | S73: 4
B74: =IF($Q74="","",INDEX(Holdings!$F$6:$F$205,$Q74)&"") -> Kaveri Gold ETF | C74: =IF($Q74="","",INDEX(Holdings!$D$6:$D$205,$Q74)&"") -> Nisha Malhotra | D74: =IF($Q74="","",INDEX(Holdings!$E$6:$E$205,$Q74)&"") -> Self-directed | E74: =IF($Q74="","",INDEX(Holdings!$H$6:$H$205,$Q74)&"") -> Gold / Silver (ETF, SGB, FoF) | F74: =IF($Q74="","",IF(INDEX(Holdings!$J$6:$J$205,$Q74)="","",INDEX(Holdings!$J$6:$J$205,$Q74))) -> 45334 | G74: =IF($Q74="","",IF(INDEX(Holdings!$M$6:$M$205,$Q74)="","",INDEX(Holdings!$M$6:$M$205,$Q74)/Divisor)) -> 2.52 | H74: =IF($Q74="","",IF(INDEX(Holdings!$R$6:$R$205,$Q74)="","",INDEX(Holdings!$R$6:$R$205,$Q74)/Divisor)) -> 3.03156 | I74: =IF(OR($Q74="",N($H$85)=0),"",H74/$H$85) -> 0.097027385 | J74: =IF($Q74="","",IF(INDEX(Holdings!$S$6:$S$205,$Q74)="","",INDEX(Holdings!$S$6:$S$205,$Q74)/Divisor)) -> 0.51156 | K74: =IF($Q74="","",INDEX(Holdings!$AB$6:$AB$205,$Q74)&"") -> XIRR | L74: =IF($Q74="","",IF(K74="XIRR",INDEX(Holdings!$W$6:$W$205,$Q74),IF(K74="Absolute",IF(INDEX(Holdings!$T$6:$T$205,$Q74)="","",INDEX(Holdings!$T$6:$T$205,$Q74)),""))) -> 0.116 | M74: =IF($Q74="","",IF(K74="XIRR",IF(INDEX(Holdings!$Z$6:$Z$205,$Q74)="","",INDEX(Holdings!$Z$6:$Z$205,$Q74)),IF(K74="Absolute",IF(INDEX(Holdings!$Y$6:$Y$205,$Q74)="","",INDEX(Holdings!$Y$6:$Y$205,$Q74)),""))) -> 0.123 | N74: =IF(OR(L74="",M74=""),"",L74-M74) -> -0.007 | O74: =IF($Q74="","",INDEX(Holdings!$X$6:$X$205,$Q74)&"") -> Domestic gold price (MCX) | Q74: =IFERROR(MATCH($R$68&"|"&$S74,Holdings!$AL$6:$AL$205,0),"") -> 11 | S74: 5
B75: =IF($Q75="","",INDEX(Holdings!$F$6:$F$205,$Q75)&"") -> Kaveri Silver ETF | C75: =IF($Q75="","",INDEX(Holdings!$D$6:$D$205,$Q75)&"") -> Arjun Malhotra | D75: =IF($Q75="","",INDEX(Holdings!$E$6:$E$205,$Q75)&"") -> Self-directed | E75: =IF($Q75="","",INDEX(Holdings!$H$6:$H$205,$Q75)&"") -> Gold / Silver (ETF, SGB, FoF) | F75: =IF($Q75="","",IF(INDEX(Holdings!$J$6:$J$205,$Q75)="","",INDEX(Holdings!$J$6:$J$205,$Q75))) -> 45875 | G75: =IF($Q75="","",IF(INDEX(Holdings!$M$6:$M$205,$Q75)="","",INDEX(Holdings!$M$6:$M$205,$Q75)/Divisor)) -> 1.44 | H75: =IF($Q75="","",IF(INDEX(Holdings!$R$6:$R$205,$Q75)="","",INDEX(Holdings!$R$6:$R$205,$Q75)/Divisor)) -> 1.7352 | I75: =IF(OR($Q75="",N($H$85)=0),"",H75/$H$85) -> 0.055536397 | J75: =IF($Q75="","",IF(INDEX(Holdings!$S$6:$S$205,$Q75)="","",INDEX(Holdings!$S$6:$S$205,$Q75)/Divisor)) -> 0.2952 | K75: =IF($Q75="","",INDEX(Holdings!$AB$6:$AB$205,$Q75)&"") -> Absolute | L75: =IF($Q75="","",IF(K75="XIRR",INDEX(Holdings!$W$6:$W$205,$Q75),IF(K75="Absolute",IF(INDEX(Holdings!$T$6:$T$205,$Q75)="","",INDEX(Holdings!$T$6:$T$205,$Q75)),""))) -> 0.205 | M75: =IF($Q75="","",IF(K75="XIRR",IF(INDEX(Holdings!$Z$6:$Z$205,$Q75)="","",INDEX(Holdings!$Z$6:$Z$205,$Q75)),IF(K75="Absolute",IF(INDEX(Holdings!$Y$6:$Y$205,$Q75)="","",INDEX(Holdings!$Y$6:$Y$205,$Q75)),""))) -> 0.184 | N75: =IF(OR(L75="",M75=""),"",L75-M75) -> 0.021 | O75: =IF($Q75="","",INDEX(Holdings!$X$6:$X$205,$Q75)&"") -> Domestic silver price (MCX) | Q75: =IFERROR(MATCH($R$68&"|"&$S75,Holdings!$AL$6:$AL$205,0),"") -> 14 | S75: 6
B76: =IF($Q76="","",INDEX(Holdings!$F$6:$F$205,$Q76)&"") -> Eastern Speciality Chemicals Ltd | C76: =IF($Q76="","",INDEX(Holdings!$D$6:$D$205,$Q76)&"") -> Nisha Malhotra | D76: =IF($Q76="","",INDEX(Holdings!$E$6:$E$205,$Q76)&"") -> Self-directed | E76: =IF($Q76="","",INDEX(Holdings!$H$6:$H$205,$Q76)&"") -> Direct Equity | F76: =IF($Q76="","",IF(INDEX(Holdings!$J$6:$J$205,$Q76)="","",INDEX(Holdings!$J$6:$J$205,$Q76))) -> 45417 | G76: =IF($Q76="","",IF(INDEX(Holdings!$M$6:$M$205,$Q76)="","",INDEX(Holdings!$M$6:$M$205,$Q76)/Divisor)) -> 1.792 | H76: =IF($Q76="","",IF(INDEX(Holdings!$R$6:$R$205,$Q76)="","",INDEX(Holdings!$R$6:$R$205,$Q76)/Divisor)) -> 1.535625 | I76: =IF(OR($Q76="",N($H$85)=0),"",H76/$H$85) -> 0.049148847 | J76: =IF($Q76="","",IF(INDEX(Holdings!$S$6:$S$205,$Q76)="","",INDEX(Holdings!$S$6:$S$205,$Q76)/Divisor)) -> -0.256375 | K76: =IF($Q76="","",INDEX(Holdings!$AB$6:$AB$205,$Q76)&"") -> XIRR | L76: =IF($Q76="","",IF(K76="XIRR",INDEX(Holdings!$W$6:$W$205,$Q76),IF(K76="Absolute",IF(INDEX(Holdings!$T$6:$T$205,$Q76)="","",INDEX(Holdings!$T$6:$T$205,$Q76)),""))) -> -0.089 | M76: =IF($Q76="","",IF(K76="XIRR",IF(INDEX(Holdings!$Z$6:$Z$205,$Q76)="","",INDEX(Holdings!$Z$6:$Z$205,$Q76)),IF(K76="Absolute",IF(INDEX(Holdings!$Y$6:$Y$205,$Q76)="","",INDEX(Holdings!$Y$6:$Y$205,$Q76)),""))) -> 0.098 | N76: =IF(OR(L76="",M76=""),"",L76-M76) -> -0.187 | O76: =IF($Q76="","",INDEX(Holdings!$X$6:$X$205,$Q76)&"") -> Nifty 500 TRI | Q76: =IFERROR(MATCH($R$68&"|"&$S76,Holdings!$AL$6:$AL$205,0),"") -> 10 | S76: 7
B77: =IF($Q77="","",INDEX(Holdings!$F$6:$F$205,$Q77)&"") | C77: =IF($Q77="","",INDEX(Holdings!$D$6:$D$205,$Q77)&"") | D77: =IF($Q77="","",INDEX(Holdings!$E$6:$E$205,$Q77)&"") | E77: =IF($Q77="","",INDEX(Holdings!$H$6:$H$205,$Q77)&"") | F77: =IF($Q77="","",IF(INDEX(Holdings!$J$6:$J$205,$Q77)="","",INDEX(Holdings!$J$6:$J$205,$Q77))) | G77: =IF($Q77="","",IF(INDEX(Holdings!$M$6:$M$205,$Q77)="","",INDEX(Holdings!$M$6:$M$205,$Q77)/Divisor)) | H77: =IF($Q77="","",IF(INDEX(Holdings!$R$6:$R$205,$Q77)="","",INDEX(Holdings!$R$6:$R$205,$Q77)/Divisor)) | I77: =IF(OR($Q77="",N($H$85)=0),"",H77/$H$85) | J77: =IF($Q77="","",IF(INDEX(Holdings!$S$6:$S$205,$Q77)="","",INDEX(Holdings!$S$6:$S$205,$Q77)/Divisor)) | K77: =IF($Q77="","",INDEX(Holdings!$AB$6:$AB$205,$Q77)&"") | L77: =IF($Q77="","",IF(K77="XIRR",INDEX(Holdings!$W$6:$W$205,$Q77),IF(K77="Absolute",IF(INDEX(Holdings!$T$6:$T$205,$Q77)="","",INDEX(Holdings!$T$6:$T$205,$Q77)),""))) | M77: =IF($Q77="","",IF(K77="XIRR",IF(INDEX(Holdings!$Z$6:$Z$205,$Q77)="","",INDEX(Holdings!$Z$6:$Z$205,$Q77)),IF(K77="Absolute",IF(INDEX(Holdings!$Y$6:$Y$205,$Q77)="","",INDEX(Holdings!$Y$6:$Y$205,$Q77)),""))) | N77: =IF(OR(L77="",M77=""),"",L77-M77) | O77: =IF($Q77="","",INDEX(Holdings!$X$6:$X$205,$Q77)&"") | Q77: =IFERROR(MATCH($R$68&"|"&$S77,Holdings!$AL$6:$AL$205,0),"") | S77: 8
B78: =IF($Q78="","",INDEX(Holdings!$F$6:$F$205,$Q78)&"") | C78: =IF($Q78="","",INDEX(Holdings!$D$6:$D$205,$Q78)&"") | D78: =IF($Q78="","",INDEX(Holdings!$E$6:$E$205,$Q78)&"") | E78: =IF($Q78="","",INDEX(Holdings!$H$6:$H$205,$Q78)&"") | F78: =IF($Q78="","",IF(INDEX(Holdings!$J$6:$J$205,$Q78)="","",INDEX(Holdings!$J$6:$J$205,$Q78))) | G78: =IF($Q78="","",IF(INDEX(Holdings!$M$6:$M$205,$Q78)="","",INDEX(Holdings!$M$6:$M$205,$Q78)/Divisor)) | H78: =IF($Q78="","",IF(INDEX(Holdings!$R$6:$R$205,$Q78)="","",INDEX(Holdings!$R$6:$R$205,$Q78)/Divisor)) | I78: =IF(OR($Q78="",N($H$85)=0),"",H78/$H$85) | J78: =IF($Q78="","",IF(INDEX(Holdings!$S$6:$S$205,$Q78)="","",INDEX(Holdings!$S$6:$S$205,$Q78)/Divisor)) | K78: =IF($Q78="","",INDEX(Holdings!$AB$6:$AB$205,$Q78)&"") | L78: =IF($Q78="","",IF(K78="XIRR",INDEX(Holdings!$W$6:$W$205,$Q78),IF(K78="Absolute",IF(INDEX(Holdings!$T$6:$T$205,$Q78)="","",INDEX(Holdings!$T$6:$T$205,$Q78)),""))) | M78: =IF($Q78="","",IF(K78="XIRR",IF(INDEX(Holdings!$Z$6:$Z$205,$Q78)="","",INDEX(Holdings!$Z$6:$Z$205,$Q78)),IF(K78="Absolute",IF(INDEX(Holdings!$Y$6:$Y$205,$Q78)="","",INDEX(Holdings!$Y$6:$Y$205,$Q78)),""))) | N78: =IF(OR(L78="",M78=""),"",L78-M78) | O78: =IF($Q78="","",INDEX(Holdings!$X$6:$X$205,$Q78)&"") | Q78: =IFERROR(MATCH($R$68&"|"&$S78,Holdings!$AL$6:$AL$205,0),"") | S78: 9
B79: =IF($Q79="","",INDEX(Holdings!$F$6:$F$205,$Q79)&"") | C79: =IF($Q79="","",INDEX(Holdings!$D$6:$D$205,$Q79)&"") | D79: =IF($Q79="","",INDEX(Holdings!$E$6:$E$205,$Q79)&"") | E79: =IF($Q79="","",INDEX(Holdings!$H$6:$H$205,$Q79)&"") | F79: =IF($Q79="","",IF(INDEX(Holdings!$J$6:$J$205,$Q79)="","",INDEX(Holdings!$J$6:$J$205,$Q79))) | G79: =IF($Q79="","",IF(INDEX(Holdings!$M$6:$M$205,$Q79)="","",INDEX(Holdings!$M$6:$M$205,$Q79)/Divisor)) | H79: =IF($Q79="","",IF(INDEX(Holdings!$R$6:$R$205,$Q79)="","",INDEX(Holdings!$R$6:$R$205,$Q79)/Divisor)) | I79: =IF(OR($Q79="",N($H$85)=0),"",H79/$H$85) | J79: =IF($Q79="","",IF(INDEX(Holdings!$S$6:$S$205,$Q79)="","",INDEX(Holdings!$S$6:$S$205,$Q79)/Divisor)) | K79: =IF($Q79="","",INDEX(Holdings!$AB$6:$AB$205,$Q79)&"") | L79: =IF($Q79="","",IF(K79="XIRR",INDEX(Holdings!$W$6:$W$205,$Q79),IF(K79="Absolute",IF(INDEX(Holdings!$T$6:$T$205,$Q79)="","",INDEX(Holdings!$T$6:$T$205,$Q79)),""))) | M79: =IF($Q79="","",IF(K79="XIRR",IF(INDEX(Holdings!$Z$6:$Z$205,$Q79)="","",INDEX(Holdings!$Z$6:$Z$205,$Q79)),IF(K79="Absolute",IF(INDEX(Holdings!$Y$6:$Y$205,$Q79)="","",INDEX(Holdings!$Y$6:$Y$205,$Q79)),""))) | N79: =IF(OR(L79="",M79=""),"",L79-M79) | O79: =IF($Q79="","",INDEX(Holdings!$X$6:$X$205,$Q79)&"") | Q79: =IFERROR(MATCH($R$68&"|"&$S79,Holdings!$AL$6:$AL$205,0),"") | S79: 10
B80: =IF($Q80="","",INDEX(Holdings!$F$6:$F$205,$Q80)&"") | C80: =IF($Q80="","",INDEX(Holdings!$D$6:$D$205,$Q80)&"") | D80: =IF($Q80="","",INDEX(Holdings!$E$6:$E$205,$Q80)&"") | E80: =IF($Q80="","",INDEX(Holdings!$H$6:$H$205,$Q80)&"") | F80: =IF($Q80="","",IF(INDEX(Holdings!$J$6:$J$205,$Q80)="","",INDEX(Holdings!$J$6:$J$205,$Q80))) | G80: =IF($Q80="","",IF(INDEX(Holdings!$M$6:$M$205,$Q80)="","",INDEX(Holdings!$M$6:$M$205,$Q80)/Divisor)) | H80: =IF($Q80="","",IF(INDEX(Holdings!$R$6:$R$205,$Q80)="","",INDEX(Holdings!$R$6:$R$205,$Q80)/Divisor)) | I80: =IF(OR($Q80="",N($H$85)=0),"",H80/$H$85) | J80: =IF($Q80="","",IF(INDEX(Holdings!$S$6:$S$205,$Q80)="","",INDEX(Holdings!$S$6:$S$205,$Q80)/Divisor)) | K80: =IF($Q80="","",INDEX(Holdings!$AB$6:$AB$205,$Q80)&"") | L80: =IF($Q80="","",IF(K80="XIRR",INDEX(Holdings!$W$6:$W$205,$Q80),IF(K80="Absolute",IF(INDEX(Holdings!$T$6:$T$205,$Q80)="","",INDEX(Holdings!$T$6:$T$205,$Q80)),""))) | M80: =IF($Q80="","",IF(K80="XIRR",IF(INDEX(Holdings!$Z$6:$Z$205,$Q80)="","",INDEX(Holdings!$Z$6:$Z$205,$Q80)),IF(K80="Absolute",IF(INDEX(Holdings!$Y$6:$Y$205,$Q80)="","",INDEX(Holdings!$Y$6:$Y$205,$Q80)),""))) | N80: =IF(OR(L80="",M80=""),"",L80-M80) | O80: =IF($Q80="","",INDEX(Holdings!$X$6:$X$205,$Q80)&"") | Q80: =IFERROR(MATCH($R$68&"|"&$S80,Holdings!$AL$6:$AL$205,0),"") | S80: 11
B81: =IF($Q81="","",INDEX(Holdings!$F$6:$F$205,$Q81)&"") | C81: =IF($Q81="","",INDEX(Holdings!$D$6:$D$205,$Q81)&"") | D81: =IF($Q81="","",INDEX(Holdings!$E$6:$E$205,$Q81)&"") | E81: =IF($Q81="","",INDEX(Holdings!$H$6:$H$205,$Q81)&"") | F81: =IF($Q81="","",IF(INDEX(Holdings!$J$6:$J$205,$Q81)="","",INDEX(Holdings!$J$6:$J$205,$Q81))) | G81: =IF($Q81="","",IF(INDEX(Holdings!$M$6:$M$205,$Q81)="","",INDEX(Holdings!$M$6:$M$205,$Q81)/Divisor)) | H81: =IF($Q81="","",IF(INDEX(Holdings!$R$6:$R$205,$Q81)="","",INDEX(Holdings!$R$6:$R$205,$Q81)/Divisor)) | I81: =IF(OR($Q81="",N($H$85)=0),"",H81/$H$85) | J81: =IF($Q81="","",IF(INDEX(Holdings!$S$6:$S$205,$Q81)="","",INDEX(Holdings!$S$6:$S$205,$Q81)/Divisor)) | K81: =IF($Q81="","",INDEX(Holdings!$AB$6:$AB$205,$Q81)&"") | L81: =IF($Q81="","",IF(K81="XIRR",INDEX(Holdings!$W$6:$W$205,$Q81),IF(K81="Absolute",IF(INDEX(Holdings!$T$6:$T$205,$Q81)="","",INDEX(Holdings!$T$6:$T$205,$Q81)),""))) | M81: =IF($Q81="","",IF(K81="XIRR",IF(INDEX(Holdings!$Z$6:$Z$205,$Q81)="","",INDEX(Holdings!$Z$6:$Z$205,$Q81)),IF(K81="Absolute",IF(INDEX(Holdings!$Y$6:$Y$205,$Q81)="","",INDEX(Holdings!$Y$6:$Y$205,$Q81)),""))) | N81: =IF(OR(L81="",M81=""),"",L81-M81) | O81: =IF($Q81="","",INDEX(Holdings!$X$6:$X$205,$Q81)&"") | Q81: =IFERROR(MATCH($R$68&"|"&$S81,Holdings!$AL$6:$AL$205,0),"") | S81: 12
... B84: =IF($Q84="","",INDEX(Holdings!$F$6:$F$205,$Q84)&"") | C84: =IF($Q84="","",INDEX(Holdings!$D$6:$D$205,$Q84)&"") | D84: =IF($Q84="","",INDEX(Holdings!$E$6:$E$205,$Q84)&"") | E84: =IF($Q84="","",INDEX(Holdings!$H$6:$H$205,$Q84)&"") | F84: =IF($Q84="","",IF(INDEX(Holdings!$J$6:$J$205,$Q84)="","",INDEX(Holdings!$J$6:$J$205,$Q84))) | G84: =IF($Q84="","",IF(INDEX(Holdings!$M$6:$M$205,$Q84)="","",INDEX(Holdings!$M$6:$M$205,$Q84)/Divisor)) | H84: =IF($Q84="","",IF(INDEX(Holdings!$R$6:$R$205,$Q84)="","",INDEX(Holdings!$R$6:$R$205,$Q84)/Divisor)) | I84: =IF(OR($Q84="",N($H$85)=0),"",H84/$H$85) | J84: =IF($Q84="","",IF(INDEX(Holdings!$S$6:$S$205,$Q84)="","",INDEX(Holdings!$S$6:$S$205,$Q84)/Divisor)) | K84: =IF($Q84="","",INDEX(Holdings!$AB$6:$AB$205,$Q84)&"") | L84: =IF($Q84="","",IF(K84="XIRR",INDEX(Holdings!$W$6:$W$205,$Q84),IF(K84="Absolute",IF(INDEX(Holdings!$T$6:$T$205,$Q84)="","",INDEX(Holdings!$T$6:$T$205,$Q84)),""))) | M84: =IF($Q84="","",IF(K84="XIRR",IF(INDEX(Holdings!$Z$6:$Z$205,$Q84)="","",INDEX(Holdings!$Z$6:$Z$205,$Q84)),IF(K84="Absolute",IF(INDEX(Holdings!$Y$6:$Y$205,$Q84)="","",INDEX(Holdings!$Y$6:$Y$205,$Q84)),""))) | N84: =IF(OR(L84="",M84=""),"",L84-M84) | O84: =IF($Q84="","",INDEX(Holdings!$X$6:$X$205,$Q84)&"") | Q84: =IFERROR(MATCH($R$68&"|"&$S84,Holdings!$AL$6:$AL$205,0),"") | S84: 15
B85: ="Total — "&Lists!$L$9 -> Total — Thematic & Tactical | G85: =SUMIFS(Holdings!$M$6:$M$205,Holdings!$I$6:$I$205,$R$68)/Divisor -> 22.62113 | H85: =SUMIFS(Holdings!$R$6:$R$205,Holdings!$I$6:$I$205,$R$68)/Divisor -> 31.244375 | I85: =IF(N(H85)=0,"",SUM(I70:I84)) -> 1 | J85: =SUMIFS(Holdings!$S$6:$S$205,Holdings!$I$6:$I$205,$R$68)/Divisor -> 8.6232449 | K85: =IF(SUMIFS(Holdings!$AN$6:$AN$205,Holdings!$I$6:$I$205,$R$68)>0,"XIRR",IF(N(G85)>0,"Absolute","")) -> XIRR | L85: =IF(K85="XIRR",IF(SUMIFS(Holdings!$AN$6:$AN$205,Holdings!$I$6:$I$205,$R$68)=0,"",SUMIFS(Holdings!$AM$6:$AM$205,Holdings!$I$6:$I$205,$R$68)/SUMIFS(Holdings!$AN$6:$AN$205,Holdings!$I$6:$I$205,$R$68)),IF(K85="Absolute",J85/G85,"")) -> 0.15063669 | M85: =IF(K85="XIRR",IF(SUMIFS(Holdings!$AN$6:$AN$205,Holdings!$I$6:$I$205,$R$68)=0,"",SUMIFS(Holdings!$AO$6:$AO$205,Holdings!$I$6:$I$205,$R$68)/SUMIFS(Holdings!$AN$6:$AN$205,Holdings!$I$6:$I$205,$R$68)),IF(K85="Absolute",IF(SUMIFS(Holdings!$AQ$6:$AQ$205,Holdings!$I$6:$I$205,$R$68)=0,"",SUMIFS(Holdings!$AP$6:$AP$205,Holdings!$I$6:$I$205,$R$68)/SUMIFS(Holdings!$AQ$6:$AQ$205,Holdings!$I$6:$I$205,$R$68)),"")) -> 0.1419593 | N85: =IF(OR(L85="",M85=""),"",L85-M85) -> 0.0086773882
B86: =IF(SUMPRODUCT((Holdings!$I$6:$I$205=$R$68)*ISNUMBER(Holdings!$R$6:$R$205))>15,SUMPRODUCT((Holdings!$I$6:$I$205=$R$68)*ISNUMBER(Holdings!$R$6:$R$205))-15&" more holding(s) in this basket are not listed; the total includes them.",IF(SUMPRODUCT((Holdings!$I$6:$I$205=$R$68)*ISNUMBER(Holdings!$R$6:$R$205))=0,"Nothing is held in this basket.",""))
B88: Held under a year | C88: Shaded rows show the absolute return since the first investment; the others the XIRR the statement reports, against the benchmark's return over the same period.
C89: A total row shows the basket's XIRR, value-weighted over the holdings that report one; where none does, its absolute return on cost. 'At cost' holdings (private equity, pre-IPO) carry no return until a priced round or a listing, and a holding with no investment date (a bank balance) shows none.

Sheet Investor Summary
A1: ="Investor Summary — "&ClientName -> Investor Summary — Malhotra Family Office (DEMO) | U1: =HYPERLINK("#'Start Here'!A1","← Start Here") -> ← Start Here
A2: ="Figures in "&UnitLabel&" · market values as at "&TEXT(ValDate,"dd-mmm-yyyy")&" · each entity's column: its value by category and the share of its own portfolio" -> Figures in ₹ Crore · market values as at 30-Jun-2026 · each entity's column: its value by category and the share of its own portfolio
A3: DEMO DATA — illustrative only: a fictional family, fictional securities and figures.
C5: =IFERROR(INDEX(L_EntityID,1),"") -> E01 | E5: =IFERROR(INDEX(L_EntityID,2),"") -> E02 | G5: =IFERROR(INDEX(L_EntityID,3),"") -> E03 | I5: =IFERROR(INDEX(L_EntityID,4),"") -> E04 | K5: =IFERROR(INDEX(L_EntityID,5),"") -> E05 | M5: =IFERROR(INDEX(L_EntityID,6),"") | O5: =IFERROR(INDEX(L_EntityID,7),"") | Q5: =IFERROR(INDEX(L_EntityID,8),"")
B6: Category | C6: =IF(C$5="","",IFERROR(INDEX(Entities!$C$6:$C$25,MATCH(C$5,Entities!$A$6:$A$25,0))&"",C$5)) -> Rajiv | E6: =IF(E$5="","",IFERROR(INDEX(Entities!$C$6:$C$25,MATCH(E$5,Entities!$A$6:$A$25,0))&"",E$5)) -> Nisha | G6: =IF(G$5="","",IFERROR(INDEX(Entities!$C$6:$C$25,MATCH(G$5,Entities!$A$6:$A$25,0))&"",G$5)) -> Arjun | I6: =IF(I$5="","",IFERROR(INDEX(Entities!$C$6:$C$25,MATCH(I$5,Entities!$A$6:$A$25,0))&"",I$5)) -> Family Trust | K6: =IF(K$5="","",IFERROR(INDEX(Entities!$C$6:$C$25,MATCH(K$5,Entities!$A$6:$A$25,0))&"",K$5)) -> Holdings LLP | M6: =IF(M$5="","",IFERROR(INDEX(Entities!$C$6:$C$25,MATCH(M$5,Entities!$A$6:$A$25,0))&"",M$5)) | O6: =IF(O$5="","",IFERROR(INDEX(Entities!$C$6:$C$25,MATCH(O$5,Entities!$A$6:$A$25,0))&"",O$5)) | Q6: =IF(Q$5="","",IFERROR(INDEX(Entities!$C$6:$C$25,MATCH(Q$5,Entities!$A$6:$A$25,0))&"",Q$5)) | T6: Family
C7: Value | D7: % of theirs | E7: Value | F7: % of theirs | G7: Value | H7: % of theirs | I7: Value | J7: % of theirs | K7: Value | L7: % of theirs | M7: Value | N7: % of theirs | O7: Value | P7: % of theirs | Q7: Value | R7: % of theirs | T7: Value | U7: % of family
B8: =Lists!$A$6 -> Equity | C8: =IF(C$5="","",SUMIFS(Holdings!$R$6:$R$205,Holdings!$AK$6:$AK$205,C$5,Holdings!$G$6:$G$205,$B8)/Divisor) -> 36.5834 | D8: =IF(OR(C$5="",N(C$32)=0),"",C8/C$32) -> 0.93603422 | E8: =IF(E$5="","",SUMIFS(Holdings!$R$6:$R$205,Holdings!$AK$6:$AK$205,E$5,Holdings!$G$6:$G$205,$B8)/Divisor) -> 27.12854 | F8: =IF(OR(E$5="",N(E$32)=0),"",E8/E$32) -> 0.89948442 | G8: =IF(G$5="","",SUMIFS(Holdings!$R$6:$R$205,Holdings!$AK$6:$AK$205,G$5,Holdings!$G$6:$G$205,$B8)/Divisor) -> 20.6422 | H8: =IF(OR(G$5="",N(G$32)=0),"",G8/G$32) -> 0.75400162 | I8: =IF(I$5="","",SUMIFS(Holdings!$R$6:$R$205,Holdings!$AK$6:$AK$205,I$5,Holdings!$G$6:$G$205,$B8)/Divisor) -> 0 | J8: =IF(OR(I$5="",N(I$32)=0),"",I8/I$32) -> 0 | K8: =IF(K$5="","",SUMIFS(Holdings!$R$6:$R$205,Holdings!$AK$6:$AK$205,K$5,Holdings!$G$6:$G$205,$B8)/Divisor) -> 0 | L8: =IF(OR(K$5="",N(K$32)=0),"",K8/K$32) -> 0 | M8: =IF(M$5="","",SUMIFS(Holdings!$R$6:$R$205,Holdings!$AK$6:$AK$205,M$5,Holdings!$G$6:$G$205,$B8)/Divisor) | N8: =IF(OR(M$5="",N(M$32)=0),"",M8/M$32) | O8: =IF(O$5="","",SUMIFS(Holdings!$R$6:$R$205,Holdings!$AK$6:$AK$205,O$5,Holdings!$G$6:$G$205,$B8)/Divisor) | P8: =IF(OR(O$5="",N(O$32)=0),"",O8/O$32) | Q8: =IF(Q$5="","",SUMIFS(Holdings!$R$6:$R$205,Holdings!$AK$6:$AK$205,Q$5,Holdings!$G$6:$G$205,$B8)/Divisor) | R8: =IF(OR(Q$5="",N(Q$32)=0),"",Q8/Q$32) | T8: =SUMIFS(Holdings!$R$6:$R$205,Holdings!$G$6:$G$205,$B8)/Divisor -> 84.35414 | U8: =IF(N($T$32)=0,"",T8/$T$32) -> 0.60916718
B9: =Lists!$D$6 -> Direct Equity | C9: =IF(C$5="","",SUMIFS(Holdings!$R$6:$R$205,Holdings!$AK$6:$AK$205,C$5,Holdings!$H$6:$H$205,$B9)/Divisor) -> 18.4594 | D9: =IF(OR(C$5="",N(C$32)=0),"",C9/C$32) -> 0.47230794 | E9: =IF(E$5="","",SUMIFS(Holdings!$R$6:$R$205,Holdings!$AK$6:$AK$205,E$5,Holdings!$H$6:$H$205,$B9)/Divisor) -> 7.577145 | F9: =IF(OR(E$5="",N(E$32)=0),"",E9/E$32) -> 0.25123077 | G9: =IF(G$5="","",SUMIFS(Holdings!$R$6:$R$205,Holdings!$AK$6:$AK$205,G$5,Holdings!$H$6:$H$205,$B9)/Divisor) -> 0 | H9: =IF(OR(G$5="",N(G$32)=0),"",G9/G$32) -> 0 | I9: =IF(I$5="","",SUMIFS(Holdings!$R$6:$R$205,Holdings!$AK$6:$AK$205,I$5,Holdings!$H$6:$H$205,$B9)/Divisor) -> 0 | J9: =IF(OR(I$5="",N(I$32)=0),"",I9/I$32) -> 0 | K9: =IF(K$5="","",SUMIFS(Holdings!$R$6:$R$205,Holdings!$AK$6:$AK$205,K$5,Holdings!$H$6:$H$205,$B9)/Divisor) -> 0 | L9: =IF(OR(K$5="",N(K$32)=0),"",K9/K$32) -> 0 | M9: =IF(M$5="","",SUMIFS(Holdings!$R$6:$R$205,Holdings!$AK$6:$AK$205,M$5,Holdings!$H$6:$H$205,$B9)/Divisor) | N9: =IF(OR(M$5="",N(M$32)=0),"",M9/M$32) | O9: =IF(O$5="","",SUMIFS(Holdings!$R$6:$R$205,Holdings!$AK$6:$AK$205,O$5,Holdings!$H$6:$H$205,$B9)/Divisor) | P9: =IF(OR(O$5="",N(O$32)=0),"",O9/O$32) | Q9: =IF(Q$5="","",SUMIFS(Holdings!$R$6:$R$205,Holdings!$AK$6:$AK$205,Q$5,Holdings!$H$6:$H$205,$B9)/Divisor) | R9: =IF(OR(Q$5="",N(Q$32)=0),"",Q9/Q$32) | T9: =SUMIFS(Holdings!$R$6:$R$205,Holdings!$H$6:$H$205,$B9)/Divisor -> 26.036545 | U9: =IF(N($T$32)=0,"",T9/$T$32) -> 0.18802407
B10: =Lists!$D$7 -> Equity MF – Large / Flexi / Multi Cap | C10: =IF(C$5="","",SUMIFS(Holdings!$R$6:$R$205,Holdings!$AK$6:$AK$205,C$5,Holdings!$H$6:$H$205,$B10)/Divisor) -> 0 | D10: =IF(OR(C$5="",N(C$32)=0),"",C10/C$32) -> 0 | E10: =IF(E$5="","",SUMIFS(Holdings!$R$6:$R$205,Holdings!$AK$6:$AK$205,E$5,Holdings!$H$6:$H$205,$B10)/Divisor) -> 9.64312 | F10: =IF(OR(E$5="",N(E$32)=0),"",E10/E$32) -> 0.31973104 | G10: =IF(G$5="","",SUMIFS(Holdings!$R$6:$R$205,Holdings!$AK$6:$AK$205,G$5,Holdings!$H$6:$H$205,$B10)/Divisor) -> 0 | H10: =IF(OR(G$5="",N(G$32)=0),"",G10/G$32) -> 0 | I10: =IF(I$5="","",SUMIFS(Holdings!$R$6:$R$205,Holdings!$AK$6:$AK$205,I$5,Holdings!$H$6:$H$205,$B10)/Divisor) -> 0 | J10: =IF(OR(I$5="",N(I$32)=0),"",I10/I$32) -> 0 | K10: =IF(K$5="","",SUMIFS(Holdings!$R$6:$R$205,Holdings!$AK$6:$AK$205,K$5,Holdings!$H$6:$H$205,$B10)/Divisor) -> 0 | L10: =IF(OR(K$5="",N(K$32)=0),"",K10/K$32) -> 0 | M10: =IF(M$5="","",SUMIFS(Holdings!$R$6:$R$205,Holdings!$AK$6:$AK$205,M$5,Holdings!$H$6:$H$205,$B10)/Divisor) | N10: =IF(OR(M$5="",N(M$32)=0),"",M10/M$32) | O10: =IF(O$5="","",SUMIFS(Holdings!$R$6:$R$205,Holdings!$AK$6:$AK$205,O$5,Holdings!$H$6:$H$205,$B10)/Divisor) | P10: =IF(OR(O$5="",N(O$32)=0),"",O10/O$32) | Q10: =IF(Q$5="","",SUMIFS(Holdings!$R$6:$R$205,Holdings!$AK$6:$AK$205,Q$5,Holdings!$H$6:$H$205,$B10)/Divisor) | R10: =IF(OR(Q$5="",N(Q$32)=0),"",Q10/Q$32) | T10: =SUMIFS(Holdings!$R$6:$R$205,Holdings!$H$6:$H$205,$B10)/Divisor -> 9.64312 | U10: =IF(N($T$32)=0,"",T10/$T$32) -> 0.069638221
B11: =Lists!$D$8 -> Equity MF – Mid & Small Cap | C11: =IF(C$5="","",SUMIFS(Holdings!$R$6:$R$205,Holdings!$AK$6:$AK$205,C$5,Holdings!$H$6:$H$205,$B11)/Divisor) -> 0 | D11: =IF(OR(C$5="",N(C$32)=0),"",C11/C$32) -> 0 | E11: =IF(E$5="","",SUMIFS(Holdings!$R$6:$R$205,Holdings!$AK$6:$AK$205,E$5,Holdings!$H$6:$H$205,$B11)/Divisor) -> 5.8950699 | F11: =IF(OR(E$5="",N(E$32)=0),"",E11/E$32) -> 0.19545923 | G11: =IF(G$5="","",SUMIFS(Holdings!$R$6:$R$205,Holdings!$AK$6:$AK$205,G$5,Holdings!$H$6:$H$205,$B11)/Divisor) -> 0 | H11: =IF(OR(G$5="",N(G$32)=0),"",G11/G$32) -> 0 | I11: =IF(I$5="","",SUMIFS(Holdings!$R$6:$R$205,Holdings!$AK$6:$AK$205,I$5,Holdings!$H$6:$H$205,$B11)/Divisor) -> 0 | J11: =IF(OR(I$5="",N(I$32)=0),"",I11/I$32) -> 0 | K11: =IF(K$5="","",SUMIFS(Holdings!$R$6:$R$205,Holdings!$AK$6:$AK$205,K$5,Holdings!$H$6:$H$205,$B11)/Divisor) -> 0 | L11: =IF(OR(K$5="",N(K$32)=0),"",K11/K$32) -> 0 | M11: =IF(M$5="","",SUMIFS(Holdings!$R$6:$R$205,Holdings!$AK$6:$AK$205,M$5,Holdings!$H$6:$H$205,$B11)/Divisor) | N11: =IF(OR(M$5="",N(M$32)=0),"",M11/M$32) | O11: =IF(O$5="","",SUMIFS(Holdings!$R$6:$R$205,Holdings!$AK$6:$AK$205,O$5,Holdings!$H$6:$H$205,$B11)/Divisor) | P11: =IF(OR(O$5="",N(O$32)=0),"",O11/O$32) | Q11: =IF(Q$5="","",SUMIFS(Holdings!$R$6:$R$205,Holdings!$AK$6:$AK$205,Q$5,Holdings!$H$6:$H$205,$B11)/Divisor) | R11: =IF(OR(Q$5="",N(Q$32)=0),"",Q11/Q$32) | T11: =SUMIFS(Holdings!$R$6:$R$205,Holdings!$H$6:$H$205,$B11)/Divisor -> 5.8950699 | U11: =IF(N($T$32)=0,"",T11/$T$32) -> 0.04257151
B12: =Lists!$D$9 -> Equity MF – Hybrid / BAF | C12: =IF(C$5="","",SUMIFS(Holdings!$R$6:$R$205,Holdings!$AK$6:$AK$205,C$5,Holdings!$H$6:$H$205,$B12)/Divisor) -> 0 | D12: =IF(OR(C$5="",N(C$32)=0),"",C12/C$32) -> 0 | E12: =IF(E$5="","",SUMIFS(Holdings!$R$6:$R$205,Holdings!$AK$6:$AK$205,E$5,Holdings!$H$6:$H$205,$B12)/Divisor) -> 4.013205 | F12: =IF(OR(E$5="",N(E$32)=0),"",E12/E$32) -> 0.13306339 | G12: =IF(G$5="","",SUMIFS(Holdings!$R$6:$R$205,Holdings!$AK$6:$AK$205,G$5,Holdings!$H$6:$H$205,$B12)/Divisor) -> 0 | H12: =IF(OR(G$5="",N(G$32)=0),"",G12/G$32) -> 0 | I12: =IF(I$5="","",SUMIFS(Holdings!$R$6:$R$205,Holdings!$AK$6:$AK$205,I$5,Holdings!$H$6:$H$205,$B12)/Divisor) -> 0 | J12: =IF(OR(I$5="",N(I$32)=0),"",I12/I$32) -> 0 | K12: =IF(K$5="","",SUMIFS(Holdings!$R$6:$R$205,Holdings!$AK$6:$AK$205,K$5,Holdings!$H$6:$H$205,$B12)/Divisor) -> 0 | L12: =IF(OR(K$5="",N(K$32)=0),"",K12/K$32) -> 0 | M12: =IF(M$5="","",SUMIFS(Holdings!$R$6:$R$205,Holdings!$AK$6:$AK$205,M$5,Holdings!$H$6:$H$205,$B12)/Divisor) | N12: =IF(OR(M$5="",N(M$32)=0),"",M12/M$32) | O12: =IF(O$5="","",SUMIFS(Holdings!$R$6:$R$205,Holdings!$AK$6:$AK$205,O$5,Holdings!$H$6:$H$205,$B12)/Divisor) | P12: =IF(OR(O$5="",N(O$32)=0),"",O12/O$32) | Q12: =IF(Q$5="","",SUMIFS(Holdings!$R$6:$R$205,Holdings!$AK$6:$AK$205,Q$5,Holdings!$H$6:$H$205,$B12)/Divisor) | R12: =IF(OR(Q$5="",N(Q$32)=0),"",Q12/Q$32) | T12: =SUMIFS(Holdings!$R$6:$R$205,Holdings!$H$6:$H$205,$B12)/Divisor -> 4.013205 | U12: =IF(N($T$32)=0,"",T12/$T$32) -> 0.028981539
B13: =Lists!$D$10 -> Equity ETF / Index Fund | C13: =IF(C$5="","",SUMIFS(Holdings!$R$6:$R$205,Holdings!$AK$6:$AK$205,C$5,Holdings!$H$6:$H$205,$B13)/Divisor) -> 0 | D13: =IF(OR(C$5="",N(C$32)=0),"",C13/C$32) -> 0 | E13: =IF(E$5="","",SUMIFS(Holdings!$R$6:$R$205,Holdings!$AK$6:$AK$205,E$5,Holdings!$H$6:$H$205,$B13)/Divisor) -> 0 | F13: =IF(OR(E$5="",N(E$32)=0),"",E13/E$32) -> 0 | G13: =IF(G$5="","",SUMIFS(Holdings!$R$6:$R$205,Holdings!$AK$6:$AK$205,G$5,Holdings!$H$6:$H$205,$B13)/Divisor) -> 0 | H13: =IF(OR(G$5="",N(G$32)=0),"",G13/G$32) -> 0 | I13: =IF(I$5="","",SUMIFS(Holdings!$R$6:$R$205,Holdings!$AK$6:$AK$205,I$5,Holdings!$H$6:$H$205,$B13)/Divisor) -> 0 | J13: =IF(OR(I$5="",N(I$32)=0),"",I13/I$32) -> 0 | K13: =IF(K$5="","",SUMIFS(Holdings!$R$6:$R$205,Holdings!$AK$6:$AK$205,K$5,Holdings!$H$6:$H$205,$B13)/Divisor) -> 0 | L13: =IF(OR(K$5="",N(K$32)=0),"",K13/K$32) -> 0 | M13: =IF(M$5="","",SUMIFS(Holdings!$R$6:$R$205,Holdings!$AK$6:$AK$205,M$5,Holdings!$H$6:$H$205,$B13)/Divisor) | N13: =IF(OR(M$5="",N(M$32)=0),"",M13/M$32) | O13: =IF(O$5="","",SUMIFS(Holdings!$R$6:$R$205,Holdings!$AK$6:$AK$205,O$5,Holdings!$H$6:$H$205,$B13)/Divisor) | P13: =IF(OR(O$5="",N(O$32)=0),"",O13/O$32) | Q13: =IF(Q$5="","",SUMIFS(Holdings!$R$6:$R$205,Holdings!$AK$6:$AK$205,Q$5,Holdings!$H$6:$H$205,$B13)/Divisor) | R13: =IF(OR(Q$5="",N(Q$32)=0),"",Q13/Q$32) | T13: =SUMIFS(Holdings!$R$6:$R$205,Holdings!$H$6:$H$205,$B13)/Divisor -> 0 | U13: =IF(N($T$32)=0,"",T13/$T$32) -> 0
B14: =Lists!$D$11 -> PMS – Equity | C14: =IF(C$5="","",SUMIFS(Holdings!$R$6:$R$205,Holdings!$AK$6:$AK$205,C$5,Holdings!$H$6:$H$205,$B14)/Divisor) -> 18.124 | D14: =IF(OR(C$5="",N(C$32)=0),"",C14/C$32) -> 0.46372629 | E14: =IF(E$5="","",SUMIFS(Holdings!$R$6:$R$205,Holdings!$AK$6:$AK$205,E$5,Holdings!$H$6:$H$205,$B14)/Divisor) -> 0 | F14: =IF(OR(E$5="",N(E$32)=0),"",E14/E$32) -> 0 | G14: =IF(G$5="","",SUMIFS(Holdings!$R$6:$R$205,Holdings!$AK$6:$AK$205,G$5,Holdings!$H$6:$H$205,$B14)/Divisor) -> 0 | H14: =IF(OR(G$5="",N(G$32)=0),"",G14/G$32) -> 0 | I14: =IF(I$5="","",SUMIFS(Holdings!$R$6:$R$205,Holdings!$AK$6:$AK$205,I$5,Holdings!$H$6:$H$205,$B14)/Divisor) -> 0 | J14: =IF(OR(I$5="",N(I$32)=0),"",I14/I$32) -> 0 | K14: =IF(K$5="","",SUMIFS(Holdings!$R$6:$R$205,Holdings!$AK$6:$AK$205,K$5,Holdings!$H$6:$H$205,$B14)/Divisor) -> 0 | L14: =IF(OR(K$5="",N(K$32)=0),"",K14/K$32) -> 0 | M14: =IF(M$5="","",SUMIFS(Holdings!$R$6:$R$205,Holdings!$AK$6:$AK$205,M$5,Holdings!$H$6:$H$205,$B14)/Divisor) | N14: =IF(OR(M$5="",N(M$32)=0),"",M14/M$32) | O14: =IF(O$5="","",SUMIFS(Holdings!$R$6:$R$205,Holdings!$AK$6:$AK$205,O$5,Holdings!$H$6:$H$205,$B14)/Divisor) | P14: =IF(OR(O$5="",N(O$32)=0),"",O14/O$32) | Q14: =IF(Q$5="","",SUMIFS(Holdings!$R$6:$R$205,Holdings!$AK$6:$AK$205,Q$5,Holdings!$H$6:$H$205,$B14)/Divisor) | R14: =IF(OR(Q$5="",N(Q$32)=0),"",Q14/Q$32) | T14: =SUMIFS(Holdings!$R$6:$R$205,Holdings!$H$6:$H$205,$B14)/Divisor -> 18.124 | U14: =IF(N($T$32)=0,"",T14/$T$32) -> 0.13088327
B15: =Lists!$D$12 -> AIF Cat III – Listed Equity | C15: =IF(C$5="","",SUMIFS(Holdings!$R$6:$R$205,Holdings!$AK$6:$AK$205,C$5,Holdings!$H$6:$H$205,$B15)/Divisor) -> 0 | D15: =IF(OR(C$5="",N(C$32)=0),"",C15/C$32) -> 0 | E15: =IF(E$5="","",SUMIFS(Holdings!$R$6:$R$205,Holdings!$AK$6:$AK$205,E$5,Holdings!$H$6:$H$205,$B15)/Divisor) -> 0 | F15: =IF(OR(E$5="",N(E$32)=0),"",E15/E$32) -> 0 | G15: =IF(G$5="","",SUMIFS(Holdings!$R$6:$R$205,Holdings!$AK$6:$AK$205,G$5,Holdings!$H$6:$H$205,$B15)/Divisor) -> 20.6422 | H15: =IF(OR(G$5="",N(G$32)=0),"",G15/G$32) -> 0.75400162 | I15: =IF(I$5="","",SUMIFS(Holdings!$R$6:$R$205,Holdings!$AK$6:$AK$205,I$5,Holdings!$H$6:$H$205,$B15)/Divisor) -> 0 | J15: =IF(OR(I$5="",N(I$32)=0),"",I15/I$32) -> 0 | K15: =IF(K$5="","",SUMIFS(Holdings!$R$6:$R$205,Holdings!$AK$6:$AK$205,K$5,Holdings!$H$6:$H$205,$B15)/Divisor) -> 0 | L15: =IF(OR(K$5="",N(K$32)=0),"",K15/K$32) -> 0 | M15: =IF(M$5="","",SUMIFS(Holdings!$R$6:$R$205,Holdings!$AK$6:$AK$205,M$5,Holdings!$H$6:$H$205,$B15)/Divisor) | N15: =IF(OR(M$5="",N(M$32)=0),"",M15/M$32) | O15: =IF(O$5="","",SUMIFS(Holdings!$R$6:$R$205,Holdings!$AK$6:$AK$205,O$5,Holdings!$H$6:$H$205,$B15)/Divisor) | P15: =IF(OR(O$5="",N(O$32)=0),"",O15/O$32) | Q15: =IF(Q$5="","",SUMIFS(Holdings!$R$6:$R$205,Holdings!$AK$6:$AK$205,Q$5,Holdings!$H$6:$H$205,$B15)/Divisor) | R15: =IF(OR(Q$5="",N(Q$32)=0),"",Q15/Q$32) | T15: =SUMIFS(Holdings!$R$6:$R$205,Holdings!$H$6:$H$205,$B15)/Divisor -> 20.6422 | U15: =IF(N($T$32)=0,"",T15/$T$32) -> 0.14906857
B16: =Lists!$A$7 -> Debt | C16: =IF(C$5="","",SUMIFS(Holdings!$R$6:$R$205,Holdings!$AK$6:$AK$205,C$5,Holdings!$G$6:$G$205,$B16)/Divisor) -> 0 | D16: =IF(OR(C$5="",N(C$32)=0),"",C16/C$32) -> 0 | E16: =IF(E$5="","",SUMIFS(Holdings!$R$6:$R$205,Holdings!$AK$6:$AK$205,E$5,Holdings!$G$6:$G$205,$B16)/Divisor) -> 0 | F16: =IF(OR(E$5="",N(E$32)=0),"",E16/E$32) -> 0 | G16: =IF(G$5="","",SUMIFS(Holdings!$R$6:$R$205,Holdings!$AK$6:$AK$205,G$5,Holdings!$G$6:$G$205,$B16)/Divisor) -> 0 | H16: =IF(OR(G$5="",N(G$32)=0),"",G16/G$32) -> 0 | I16: =IF(I$5="","",SUMIFS(Holdings!$R$6:$R$205,Holdings!$AK$6:$AK$205,I$5,Holdings!$G$6:$G$205,$B16)/Divisor) -> 13.595184 | J16: =IF(OR(I$5="",N(I$32)=0),"",I16/I$32) -> 0.4260546 | K16: =IF(K$5="","",SUMIFS(Holdings!$R$6:$R$205,Holdings!$AK$6:$AK$205,K$5,Holdings!$G$6:$G$205,$B16)/Divisor) -> 0 | L16: =IF(OR(K$5="",N(K$32)=0),"",K16/K$32) -> 0 | M16: =IF(M$5="","",SUMIFS(Holdings!$R$6:$R$205,Holdings!$AK$6:$AK$205,M$5,Holdings!$G$6:$G$205,$B16)/Divisor) | N16: =IF(OR(M$5="",N(M$32)=0),"",M16/M$32) | O16: =IF(O$5="","",SUMIFS(Holdings!$R$6:$R$205,Holdings!$AK$6:$AK$205,O$5,Holdings!$G$6:$G$205,$B16)/Divisor) | P16: =IF(OR(O$5="",N(O$32)=0),"",O16/O$32) | Q16: =IF(Q$5="","",SUMIFS(Holdings!$R$6:$R$205,Holdings!$AK$6:$AK$205,Q$5,Holdings!$G$6:$G$205,$B16)/Divisor) | R16: =IF(OR(Q$5="",N(Q$32)=0),"",Q16/Q$32) | T16: =SUMIFS(Holdings!$R$6:$R$205,Holdings!$G$6:$G$205,$B16)/Divisor -> 13.595184 | U16: =IF(N($T$32)=0,"",T16/$T$32) -> 0.098178228
B17: =Lists!$D$13 -> Debt MF | C17: =IF(C$5="","",SUMIFS(Holdings!$R$6:$R$205,Holdings!$AK$6:$AK$205,C$5,Holdings!$H$6:$H$205,$B17)/Divisor) -> 0 | D17: =IF(OR(C$5="",N(C$32)=0),"",C17/C$32) -> 0 | E17: =IF(E$5="","",SUMIFS(Holdings!$R$6:$R$205,Holdings!$AK$6:$AK$205,E$5,Holdings!$H$6:$H$205,$B17)/Divisor) -> 0 | F17: =IF(OR(E$5="",N(E$32)=0),"",E17/E$32) -> 0 | G17: =IF(G$5="","",SUMIFS(Holdings!$R$6:$R$205,Holdings!$AK$6:$AK$205,G$5,Holdings!$H$6:$H$205,$B17)/Divisor) -> 0 | H17: =IF(OR(G$5="",N(G$32)=0),"",G17/G$32) -> 0 | I17: =IF(I$5="","",SUMIFS(Holdings!$R$6:$R$205,Holdings!$AK$6:$AK$205,I$5,Holdings!$H$6:$H$205,$B17)/Divisor) -> 7.494984 | J17: =IF(OR(I$5="",N(I$32)=0),"",I17/I$32) -> 0.23488262 | K17: =IF(K$5="","",SUMIFS(Holdings!$R$6:$R$205,Holdings!$AK$6:$AK$205,K$5,Holdings!$H$6:$H$205,$B17)/Divisor) -> 0 | L17: =IF(OR(K$5="",N(K$32)=0),"",K17/K$32) -> 0 | M17: =IF(M$5="","",SUMIFS(Holdings!$R$6:$R$205,Holdings!$AK$6:$AK$205,M$5,Holdings!$H$6:$H$205,$B17)/Divisor) | N17: =IF(OR(M$5="",N(M$32)=0),"",M17/M$32) | O17: =IF(O$5="","",SUMIFS(Holdings!$R$6:$R$205,Holdings!$AK$6:$AK$205,O$5,Holdings!$H$6:$H$205,$B17)/Divisor) | P17: =IF(OR(O$5="",N(O$32)=0),"",O17/O$32) | Q17: =IF(Q$5="","",SUMIFS(Holdings!$R$6:$R$205,Holdings!$AK$6:$AK$205,Q$5,Holdings!$H$6:$H$205,$B17)/Divisor) | R17: =IF(OR(Q$5="",N(Q$32)=0),"",Q17/Q$32) | T17: =SUMIFS(Holdings!$R$6:$R$205,Holdings!$H$6:$H$205,$B17)/Divisor -> 7.494984 | U17: =IF(N($T$32)=0,"",T17/$T$32) -> 0.054125361
B18: =Lists!$D$14 -> Bonds / NCDs | C18: =IF(C$5="","",SUMIFS(Holdings!$R$6:$R$205,Holdings!$AK$6:$AK$205,C$5,Holdings!$H$6:$H$205,$B18)/Divisor) -> 0 | D18: =IF(OR(C$5="",N(C$32)=0),"",C18/C$32) -> 0 | E18: =IF(E$5="","",SUMIFS(Holdings!$R$6:$R$205,Holdings!$AK$6:$AK$205,E$5,Holdings!$H$6:$H$205,$B18)/Divisor) -> 0 | F18: =IF(OR(E$5="",N(E$32)=0),"",E18/E$32) -> 0 | G18: =IF(G$5="","",SUMIFS(Holdings!$R$6:$R$205,Holdings!$AK$6:$AK$205,G$5,Holdings!$H$6:$H$205,$B18)/Divisor) -> 0 | H18: =IF(OR(G$5="",N(G$32)=0),"",G18/G$32) -> 0 | I18: =IF(I$5="","",SUMIFS(Holdings!$R$6:$R$205,Holdings!$AK$6:$AK$205,I$5,Holdings!$H$6:$H$205,$B18)/Divisor) -> 5.062 | J18: =IF(OR(I$5="",N(I$32)=0),"",I18/I$32) -> 0.1586362 | K18: =IF(K$5="","",SUMIFS(Holdings!$R$6:$R$205,Holdings!$AK$6:$AK$205,K$5,Holdings!$H$6:$H$205,$B18)/Divisor) -> 0 | L18: =IF(OR(K$5="",N(K$32)=0),"",K18/K$32) -> 0 | M18: =IF(M$5="","",SUMIFS(Holdings!$R$6:$R$205,Holdings!$AK$6:$AK$205,M$5,Holdings!$H$6:$H$205,$B18)/Divisor) | N18: =IF(OR(M$5="",N(M$32)=0),"",M18/M$32) | O18: =IF(O$5="","",SUMIFS(Holdings!$R$6:$R$205,Holdings!$AK$6:$AK$205,O$5,Holdings!$H$6:$H$205,$B18)/Divisor) | P18: =IF(OR(O$5="",N(O$32)=0),"",O18/O$32) | Q18: =IF(Q$5="","",SUMIFS(Holdings!$R$6:$R$205,Holdings!$AK$6:$AK$205,Q$5,Holdings!$H$6:$H$205,$B18)/Divisor) | R18: =IF(OR(Q$5="",N(Q$32)=0),"",Q18/Q$32) | T18: =SUMIFS(Holdings!$R$6:$R$205,Holdings!$H$6:$H$205,$B18)/Divisor -> 5.062 | U18: =IF(N($T$32)=0,"",T18/$T$32) -> 0.036555459
B19: =Lists!$D$15 -> AIF Cat II – Private Credit | C19: =IF(C$5="","",SUMIFS(Holdings!$R$6:$R$205,Holdings!$AK$6:$AK$205,C$5,Holdings!$H$6:$H$205,$B19)/Divisor) -> 0 | D19: =IF(OR(C$5="",N(C$32)=0),"",C19/C$32) -> 0 | E19: =IF(E$5="","",SUMIFS(Holdings!$R$6:$R$205,Holdings!$AK$6:$AK$205,E$5,Holdings!$H$6:$H$205,$B19)/Divisor) -> 0 | F19: =IF(OR(E$5="",N(E$32)=0),"",E19/E$32) -> 0 | G19: =IF(G$5="","",SUMIFS(Holdings!$R$6:$R$205,Holdings!$AK$6:$AK$205,G$5,Holdings!$H$6:$H$205,$B19)/Divisor) -> 0 | H19: =IF(OR(G$5="",N(G$32)=0),"",G19/G$32) -> 0 | I19: =IF(I$5="","",SUMIFS(Holdings!$R$6:$R$205,Holdings!$AK$6:$AK$205,I$5,Holdings!$H$6:$H$205,$B19)/Divisor) -> 1.0382 | J19: =IF(OR(I$5="",N(I$32)=0),"",I19/I$32) -> 0.032535777 | K19: =IF(K$5="","",SUMIFS(Holdings!$R$6:$R$205,Holdings!$AK$6:$AK$205,K$5,Holdings!$H$6:$H$205,$B19)/Divisor) -> 0 | L19: =IF(OR(K$5="",N(K$32)=0),"",K19/K$32) -> 0 | M19: =IF(M$5="","",SUMIFS(Holdings!$R$6:$R$205,Holdings!$AK$6:$AK$205,M$5,Holdings!$H$6:$H$205,$B19)/Divisor) | N19: =IF(OR(M$5="",N(M$32)=0),"",M19/M$32) | O19: =IF(O$5="","",SUMIFS(Holdings!$R$6:$R$205,Holdings!$AK$6:$AK$205,O$5,Holdings!$H$6:$H$205,$B19)/Divisor) | P19: =IF(OR(O$5="",N(O$32)=0),"",O19/O$32) | Q19: =IF(Q$5="","",SUMIFS(Holdings!$R$6:$R$205,Holdings!$AK$6:$AK$205,Q$5,Holdings!$H$6:$H$205,$B19)/Divisor) | R19: =IF(OR(Q$5="",N(Q$32)=0),"",Q19/Q$32) | T19: =SUMIFS(Holdings!$R$6:$R$205,Holdings!$H$6:$H$205,$B19)/Divisor -> 1.0382 | U19: =IF(N($T$32)=0,"",T19/$T$32) -> 0.0074974076
B20: =Lists!$D$16 -> Structured Product / MLD | C20: =IF(C$5="","",SUMIFS(Holdings!$R$6:$R$205,Holdings!$AK$6:$AK$205,C$5,Holdings!$H$6:$H$205,$B20)/Divisor) -> 0 | D20: =IF(OR(C$5="",N(C$32)=0),"",C20/C$32) -> 0 | E20: =IF(E$5="","",SUMIFS(Holdings!$R$6:$R$205,Holdings!$AK$6:$AK$205,E$5,Holdings!$H$6:$H$205,$B20)/Divisor) -> 0 | F20: =IF(OR(E$5="",N(E$32)=0),"",E20/E$32) -> 0 | G20: =IF(G$5="","",SUMIFS(Holdings!$R$6:$R$205,Holdings!$AK$6:$AK$205,G$5,Holdings!$H$6:$H$205,$B20)/Divisor) -> 0 | H20: =IF(OR(G$5="",N(G$32)=0),"",G20/G$32) -> 0 | I20: =IF(I$5="","",SUMIFS(Holdings!$R$6:$R$205,Holdings!$AK$6:$AK$205,I$5,Holdings!$H$6:$H$205,$B20)/Divisor) -> 0 | J20: =IF(OR(I$5="",N(I$32)=0),"",I20/I$32) -> 0 | K20: =IF(K$5="","",SUMIFS(Holdings!$R$6:$R$205,Holdings!$AK$6:$AK$205,K$5,Holdings!$H$6:$H$205,$B20)/Divisor) -> 0 | L20: =IF(OR(K$5="",N(K$32)=0),"",K20/K$32) -> 0 | M20: =IF(M$5="","",SUMIFS(Holdings!$R$6:$R$205,Holdings!$AK$6:$AK$205,M$5,Holdings!$H$6:$H$205,$B20)/Divisor) | N20: =IF(OR(M$5="",N(M$32)=0),"",M20/M$32) | O20: =IF(O$5="","",SUMIFS(Holdings!$R$6:$R$205,Holdings!$AK$6:$AK$205,O$5,Holdings!$H$6:$H$205,$B20)/Divisor) | P20: =IF(OR(O$5="",N(O$32)=0),"",O20/O$32) | Q20: =IF(Q$5="","",SUMIFS(Holdings!$R$6:$R$205,Holdings!$AK$6:$AK$205,Q$5,Holdings!$H$6:$H$205,$B20)/Divisor) | R20: =IF(OR(Q$5="",N(Q$32)=0),"",Q20/Q$32) | T20: =SUMIFS(Holdings!$R$6:$R$205,Holdings!$H$6:$H$205,$B20)/Divisor -> 0 | U20: =IF(N($T$32)=0,"",T20/$T$32) -> 0
B21: =Lists!$A$8 -> Cash | C21: =IF(C$5="","",SUMIFS(Holdings!$R$6:$R$205,Holdings!$AK$6:$AK$205,C$5,Holdings!$G$6:$G$205,$B21)/Divisor) -> 0 | D21: =IF(OR(C$5="",N(C$32)=0),"",C21/C$32) -> 0 | E21: =IF(E$5="","",SUMIFS(Holdings!$R$6:$R$205,Holdings!$AK$6:$AK$205,E$5,Holdings!$G$6:$G$205,$B21)/Divisor) -> 0 | F21: =IF(OR(E$5="",N(E$32)=0),"",E21/E$32) -> 0 | G21: =IF(G$5="","",SUMIFS(Holdings!$R$6:$R$205,Holdings!$AK$6:$AK$205,G$5,Holdings!$G$6:$G$205,$B21)/Divisor) -> 4.9994644 | H21: =IF(OR(G$5="",N(G$32)=0),"",G21/G$32) -> 0.1826164 | I21: =IF(I$5="","",SUMIFS(Holdings!$R$6:$R$205,Holdings!$AK$6:$AK$205,I$5,Holdings!$G$6:$G$205,$B21)/Divisor) -> 5.997504 | J21: =IF(OR(I$5="",N(I$32)=0),"",I21/I$32) -> 0.18795363 | K21: =IF(K$5="","",SUMIFS(Holdings!$R$6:$R$205,Holdings!$AK$6:$AK$205,K$5,Holdings!$G$6:$G$205,$B21)/Divisor) -> 6.7446786 | L21: =IF(OR(K$5="",N(K$32)=0),"",K21/K$32) -> 0.67821987 | M21: =IF(M$5="","",SUMIFS(Holdings!$R$6:$R$205,Holdings!$AK$6:$AK$205,M$5,Holdings!$G$6:$G$205,$B21)/Divisor) | N21: =IF(OR(M$5="",N(M$32)=0),"",M21/M$32) | O21: =IF(O$5="","",SUMIFS(Holdings!$R$6:$R$205,Holdings!$AK$6:$AK$205,O$5,Holdings!$G$6:$G$205,$B21)/Divisor) | P21: =IF(OR(O$5="",N(O$32)=0),"",O21/O$32) | Q21: =IF(Q$5="","",SUMIFS(Holdings!$R$6:$R$205,Holdings!$AK$6:$AK$205,Q$5,Holdings!$G$6:$G$205,$B21)/Divisor) | R21: =IF(OR(Q$5="",N(Q$32)=0),"",Q21/Q$32) | T21: =SUMIFS(Holdings!$R$6:$R$205,Holdings!$G$6:$G$205,$B21)/Divisor -> 17.741647 | U21: =IF(N($T$32)=0,"",T21/$T$32) -> 0.12812209
B22: =Lists!$D$17 -> Liquid / Overnight Fund | C22: =IF(C$5="","",SUMIFS(Holdings!$R$6:$R$205,Holdings!$AK$6:$AK$205,C$5,Holdings!$H$6:$H$205,$B22)/Divisor) -> 0 | D22: =IF(OR(C$5="",N(C$32)=0),"",C22/C$32) -> 0 | E22: =IF(E$5="","",SUMIFS(Holdings!$R$6:$R$205,Holdings!$AK$6:$AK$205,E$5,Holdings!$H$6:$H$205,$B22)/Divisor) -> 0 | F22: =IF(OR(E$5="",N(E$32)=0),"",E22/E$32) -> 0 | G22: =IF(G$5="","",SUMIFS(Holdings!$R$6:$R$205,Holdings!$AK$6:$AK$205,G$5,Holdings!$H$6:$H$205,$B22)/Divisor) -> 4.9994644 | H22: =IF(OR(G$5="",N(G$32)=0),"",G22/G$32) -> 0.1826164 | I22: =IF(I$5="","",SUMIFS(Holdings!$R$6:$R$205,Holdings!$AK$6:$AK$205,I$5,Holdings!$H$6:$H$205,$B22)/Divisor) -> 0 | J22: =IF(OR(I$5="",N(I$32)=0),"",I22/I$32) -> 0 | K22: =IF(K$5="","",SUMIFS(Holdings!$R$6:$R$205,Holdings!$AK$6:$AK$205,K$5,Holdings!$H$6:$H$205,$B22)/Divisor) -> 2.9996786 | L22: =IF(OR(K$5="",N(K$32)=0),"",K22/K$32) -> 0.30163655 | M22: =IF(M$5="","",SUMIFS(Holdings!$R$6:$R$205,Holdings!$AK$6:$AK$205,M$5,Holdings!$H$6:$H$205,$B22)/Divisor) | N22: =IF(OR(M$5="",N(M$32)=0),"",M22/M$32) | O22: =IF(O$5="","",SUMIFS(Holdings!$R$6:$R$205,Holdings!$AK$6:$AK$205,O$5,Holdings!$H$6:$H$205,$B22)/Divisor) | P22: =IF(OR(O$5="",N(O$32)=0),"",O22/O$32) | Q22: =IF(Q$5="","",SUMIFS(Holdings!$R$6:$R$205,Holdings!$AK$6:$AK$205,Q$5,Holdings!$H$6:$H$205,$B22)/Divisor) | R22: =IF(OR(Q$5="",N(Q$32)=0),"",Q22/Q$32) | T22: =SUMIFS(Holdings!$R$6:$R$205,Holdings!$H$6:$H$205,$B22)/Divisor -> 7.999143 | U22: =IF(N($T$32)=0,"",T22/$T$32) -> 0.057766168
B23: =Lists!$D$18 -> Arbitrage Fund | C23: =IF(C$5="","",SUMIFS(Holdings!$R$6:$R$205,Holdings!$AK$6:$AK$205,C$5,Holdings!$H$6:$H$205,$B23)/Divisor) -> 0 | D23: =IF(OR(C$5="",N(C$32)=0),"",C23/C$32) -> 0 | E23: =IF(E$5="","",SUMIFS(Holdings!$R$6:$R$205,Holdings!$AK$6:$AK$205,E$5,Holdings!$H$6:$H$205,$B23)/Divisor) -> 0 | F23: =IF(OR(E$5="",N(E$32)=0),"",E23/E$32) -> 0 | G23: =IF(G$5="","",SUMIFS(Holdings!$R$6:$R$205,Holdings!$AK$6:$AK$205,G$5,Holdings!$H$6:$H$205,$B23)/Divisor) -> 0 | H23: =IF(OR(G$5="",N(G$32)=0),"",G23/G$32) -> 0 | I23: =IF(I$5="","",SUMIFS(Holdings!$R$6:$R$205,Holdings!$AK$6:$AK$205,I$5,Holdings!$H$6:$H$205,$B23)/Divisor) -> 5.997504 | J23: =IF(OR(I$5="",N(I$32)=0),"",I23/I$32) -> 0.18795363 | K23: =IF(K$5="","",SUMIFS(Holdings!$R$6:$R$205,Holdings!$AK$6:$AK$205,K$5,Holdings!$H$6:$H$205,$B23)/Divisor) -> 0 | L23: =IF(OR(K$5="",N(K$32)=0),"",K23/K$32) -> 0 | M23: =IF(M$5="","",SUMIFS(Holdings!$R$6:$R$205,Holdings!$AK$6:$AK$205,M$5,Holdings!$H$6:$H$205,$B23)/Divisor) | N23: =IF(OR(M$5="",N(M$32)=0),"",M23/M$32) | O23: =IF(O$5="","",SUMIFS(Holdings!$R$6:$R$205,Holdings!$AK$6:$AK$205,O$5,Holdings!$H$6:$H$205,$B23)/Divisor) | P23: =IF(OR(O$5="",N(O$32)=0),"",O23/O$32) | Q23: =IF(Q$5="","",SUMIFS(Holdings!$R$6:$R$205,Holdings!$AK$6:$AK$205,Q$5,Holdings!$H$6:$H$205,$B23)/Divisor) | R23: =IF(OR(Q$5="",N(Q$32)=0),"",Q23/Q$32) | T23: =SUMIFS(Holdings!$R$6:$R$205,Holdings!$H$6:$H$205,$B23)/Divisor -> 5.997504 | U23: =IF(N($T$32)=0,"",T23/$T$32) -> 0.043311243
B24: =Lists!$D$19 -> Bank / Cash Balance | C24: =IF(C$5="","",SUMIFS(Holdings!$R$6:$R$205,Holdings!$AK$6:$AK$205,C$5,Holdings!$H$6:$H$205,$B24)/Divisor) -> 0 | D24: =IF(OR(C$5="",N(C$32)=0),"",C24/C$32) -> 0 | E24: =IF(E$5="","",SUMIFS(Holdings!$R$6:$R$205,Holdings!$AK$6:$AK$205,E$5,Holdings!$H$6:$H$205,$B24)/Divisor) -> 0 | F24: =IF(OR(E$5="",N(E$32)=0),"",E24/E$32) -> 0 | G24: =IF(G$5="","",SUMIFS(Holdings!$R$6:$R$205,Holdings!$AK$6:$AK$205,G$5,Holdings!$H$6:$H$205,$B24)/Divisor) -> 0 | H24: =IF(OR(G$5="",N(G$32)=0),"",G24/G$32) -> 0 | I24: =IF(I$5="","",SUMIFS(Holdings!$R$6:$R$205,Holdings!$AK$6:$AK$205,I$5,Holdings!$H$6:$H$205,$B24)/Divisor) -> 0 | J24: =IF(OR(I$5="",N(I$32)=0),"",I24/I$32) -> 0 | K24: =IF(K$5="","",SUMIFS(Holdings!$R$6:$R$205,Holdings!$AK$6:$AK$205,K$5,Holdings!$H$6:$H$205,$B24)/Divisor) -> 3.745 | L24: =IF(OR(K$5="",N(K$32)=0),"",K24/K$32) -> 0.37658331 | M24: =IF(M$5="","",SUMIFS(Holdings!$R$6:$R$205,Holdings!$AK$6:$AK$205,M$5,Holdings!$H$6:$H$205,$B24)/Divisor) | N24: =IF(OR(M$5="",N(M$32)=0),"",M24/M$32) | O24: =IF(O$5="","",SUMIFS(Holdings!$R$6:$R$205,Holdings!$AK$6:$AK$205,O$5,Holdings!$H$6:$H$205,$B24)/Divisor) | P24: =IF(OR(O$5="",N(O$32)=0),"",O24/O$32) | Q24: =IF(Q$5="","",SUMIFS(Holdings!$R$6:$R$205,Holdings!$AK$6:$AK$205,Q$5,Holdings!$H$6:$H$205,$B24)/Divisor) | R24: =IF(OR(Q$5="",N(Q$32)=0),"",Q24/Q$32) | T24: =SUMIFS(Holdings!$R$6:$R$205,Holdings!$H$6:$H$205,$B24)/Divisor -> 3.745 | U24: =IF(N($T$32)=0,"",T24/$T$32) -> 0.027044685
B25: =Lists!$A$9 -> Alternate | C25: =IF(C$5="","",SUMIFS(Holdings!$R$6:$R$205,Holdings!$AK$6:$AK$205,C$5,Holdings!$G$6:$G$205,$B25)/Divisor) -> 2.5 | D25: =IF(OR(C$5="",N(C$32)=0),"",C25/C$32) -> 0.063965776 | E25: =IF(E$5="","",SUMIFS(Holdings!$R$6:$R$205,Holdings!$AK$6:$AK$205,E$5,Holdings!$G$6:$G$205,$B25)/Divisor) -> 3.03156 | F25: =IF(OR(E$5="",N(E$32)=0),"",E25/E$32) -> 0.10051558 | G25: =IF(G$5="","",SUMIFS(Holdings!$R$6:$R$205,Holdings!$AK$6:$AK$205,G$5,Holdings!$G$6:$G$205,$B25)/Divisor) -> 1.7352 | H25: =IF(OR(G$5="",N(G$32)=0),"",G25/G$32) -> 0.063381985 | I25: =IF(I$5="","",SUMIFS(Holdings!$R$6:$R$205,Holdings!$AK$6:$AK$205,I$5,Holdings!$G$6:$G$205,$B25)/Divisor) -> 12.3168 | J25: =IF(OR(I$5="",N(I$32)=0),"",I25/I$32) -> 0.38599178 | K25: =IF(K$5="","",SUMIFS(Holdings!$R$6:$R$205,Holdings!$AK$6:$AK$205,K$5,Holdings!$G$6:$G$205,$B25)/Divisor) -> 3.2 | L25: =IF(OR(K$5="",N(K$32)=0),"",K25/K$32) -> 0.32178013 | M25: =IF(M$5="","",SUMIFS(Holdings!$R$6:$R$205,Holdings!$AK$6:$AK$205,M$5,Holdings!$G$6:$G$205,$B25)/Divisor) | N25: =IF(OR(M$5="",N(M$32)=0),"",M25/M$32) | O25: =IF(O$5="","",SUMIFS(Holdings!$R$6:$R$205,Holdings!$AK$6:$AK$205,O$5,Holdings!$G$6:$G$205,$B25)/Divisor) | P25: =IF(OR(O$5="",N(O$32)=0),"",O25/O$32) | Q25: =IF(Q$5="","",SUMIFS(Holdings!$R$6:$R$205,Holdings!$AK$6:$AK$205,Q$5,Holdings!$G$6:$G$205,$B25)/Divisor) | R25: =IF(OR(Q$5="",N(Q$32)=0),"",Q25/Q$32) | T25: =SUMIFS(Holdings!$R$6:$R$205,Holdings!$G$6:$G$205,$B25)/Divisor -> 22.78356 | U25: =IF(N($T$32)=0,"",T25/$T$32) -> 0.16453249
B26: =Lists!$D$20 -> Gold / Silver (ETF, SGB, FoF) | C26: =IF(C$5="","",SUMIFS(Holdings!$R$6:$R$205,Holdings!$AK$6:$AK$205,C$5,Holdings!$H$6:$H$205,$B26)/Divisor) -> 0 | D26: =IF(OR(C$5="",N(C$32)=0),"",C26/C$32) -> 0 | E26: =IF(E$5="","",SUMIFS(Holdings!$R$6:$R$205,Holdings!$AK$6:$AK$205,E$5,Holdings!$H$6:$H$205,$B26)/Divisor) -> 3.03156 | F26: =IF(OR(E$5="",N(E$32)=0),"",E26/E$32) -> 0.10051558 | G26: =IF(G$5="","",SUMIFS(Holdings!$R$6:$R$205,Holdings!$AK$6:$AK$205,G$5,Holdings!$H$6:$H$205,$B26)/Divisor) -> 1.7352 | H26: =IF(OR(G$5="",N(G$32)=0),"",G26/G$32) -> 0.063381985 | I26: =IF(I$5="","",SUMIFS(Holdings!$R$6:$R$205,Holdings!$AK$6:$AK$205,I$5,Holdings!$H$6:$H$205,$B26)/Divisor) -> 0 | J26: =IF(OR(I$5="",N(I$32)=0),"",I26/I$32) -> 0 | K26: =IF(K$5="","",SUMIFS(Holdings!$R$6:$R$205,Holdings!$AK$6:$AK$205,K$5,Holdings!$H$6:$H$205,$B26)/Divisor) -> 0 | L26: =IF(OR(K$5="",N(K$32)=0),"",K26/K$32) -> 0 | M26: =IF(M$5="","",SUMIFS(Holdings!$R$6:$R$205,Holdings!$AK$6:$AK$205,M$5,Holdings!$H$6:$H$205,$B26)/Divisor) | N26: =IF(OR(M$5="",N(M$32)=0),"",M26/M$32) | O26: =IF(O$5="","",SUMIFS(Holdings!$R$6:$R$205,Holdings!$AK$6:$AK$205,O$5,Holdings!$H$6:$H$205,$B26)/Divisor) | P26: =IF(OR(O$5="",N(O$32)=0),"",O26/O$32) | Q26: =IF(Q$5="","",SUMIFS(Holdings!$R$6:$R$205,Holdings!$AK$6:$AK$205,Q$5,Holdings!$H$6:$H$205,$B26)/Divisor) | R26: =IF(OR(Q$5="",N(Q$32)=0),"",Q26/Q$32) | T26: =SUMIFS(Holdings!$R$6:$R$205,Holdings!$H$6:$H$205,$B26)/Divisor -> 4.76676 | U26: =IF(N($T$32)=0,"",T26/$T$32) -> 0.03442337
B27: =Lists!$D$21 -> REIT / InvIT | C27: =IF(C$5="","",SUMIFS(Holdings!$R$6:$R$205,Holdings!$AK$6:$AK$205,C$5,Holdings!$H$6:$H$205,$B27)/Divisor) -> 0 | D27: =IF(OR(C$5="",N(C$32)=0),"",C27/C$32) -> 0 | E27: =IF(E$5="","",SUMIFS(Holdings!$R$6:$R$205,Holdings!$AK$6:$AK$205,E$5,Holdings!$H$6:$H$205,$B27)/Divisor) -> 0 | F27: =IF(OR(E$5="",N(E$32)=0),"",E27/E$32) -> 0 | G27: =IF(G$5="","",SUMIFS(Holdings!$R$6:$R$205,Holdings!$AK$6:$AK$205,G$5,Holdings!$H$6:$H$205,$B27)/Divisor) -> 0 | H27: =IF(OR(G$5="",N(G$32)=0),"",G27/G$32) -> 0 | I27: =IF(I$5="","",SUMIFS(Holdings!$R$6:$R$205,Holdings!$AK$6:$AK$205,I$5,Holdings!$H$6:$H$205,$B27)/Divisor) -> 4.728 | J27: =IF(OR(I$5="",N(I$32)=0),"",I27/I$32) -> 0.1481691 | K27: =IF(K$5="","",SUMIFS(Holdings!$R$6:$R$205,Holdings!$AK$6:$AK$205,K$5,Holdings!$H$6:$H$205,$B27)/Divisor) -> 0 | L27: =IF(OR(K$5="",N(K$32)=0),"",K27/K$32) -> 0 | M27: =IF(M$5="","",SUMIFS(Holdings!$R$6:$R$205,Holdings!$AK$6:$AK$205,M$5,Holdings!$H$6:$H$205,$B27)/Divisor) | N27: =IF(OR(M$5="",N(M$32)=0),"",M27/M$32) | O27: =IF(O$5="","",SUMIFS(Holdings!$R$6:$R$205,Holdings!$AK$6:$AK$205,O$5,Holdings!$H$6:$H$205,$B27)/Divisor) | P27: =IF(OR(O$5="",N(O$32)=0),"",O27/O$32) | Q27: =IF(Q$5="","",SUMIFS(Holdings!$R$6:$R$205,Holdings!$AK$6:$AK$205,Q$5,Holdings!$H$6:$H$205,$B27)/Divisor) | R27: =IF(OR(Q$5="",N(Q$32)=0),"",Q27/Q$32) | T27: =SUMIFS(Holdings!$R$6:$R$205,Holdings!$H$6:$H$205,$B27)/Divisor -> 4.728 | U27: =IF(N($T$32)=0,"",T27/$T$32) -> 0.034143463
B28: =Lists!$D$22 -> AIF Cat I / II – PE / VC Fund | C28: =IF(C$5="","",SUMIFS(Holdings!$R$6:$R$205,Holdings!$AK$6:$AK$205,C$5,Holdings!$H$6:$H$205,$B28)/Divisor) -> 0 | D28: =IF(OR(C$5="",N(C$32)=0),"",C28/C$32) -> 0 | E28: =IF(E$5="","",SUMIFS(Holdings!$R$6:$R$205,Holdings!$AK$6:$AK$205,E$5,Holdings!$H$6:$H$205,$B28)/Divisor) -> 0 | F28: =IF(OR(E$5="",N(E$32)=0),"",E28/E$32) -> 0 | G28: =IF(G$5="","",SUMIFS(Holdings!$R$6:$R$205,Holdings!$AK$6:$AK$205,G$5,Holdings!$H$6:$H$205,$B28)/Divisor) -> 0 | H28: =IF(OR(G$5="",N(G$32)=0),"",G28/G$32) -> 0 | I28: =IF(I$5="","",SUMIFS(Holdings!$R$6:$R$205,Holdings!$AK$6:$AK$205,I$5,Holdings!$H$6:$H$205,$B28)/Divisor) -> 7.5888 | J28: =IF(OR(I$5="",N(I$32)=0),"",I28/I$32) -> 0.23782268 | K28: =IF(K$5="","",SUMIFS(Holdings!$R$6:$R$205,Holdings!$AK$6:$AK$205,K$5,Holdings!$H$6:$H$205,$B28)/Divisor) -> 0 | L28: =IF(OR(K$5="",N(K$32)=0),"",K28/K$32) -> 0 | M28: =IF(M$5="","",SUMIFS(Holdings!$R$6:$R$205,Holdings!$AK$6:$AK$205,M$5,Holdings!$H$6:$H$205,$B28)/Divisor) | N28: =IF(OR(M$5="",N(M$32)=0),"",M28/M$32) | O28: =IF(O$5="","",SUMIFS(Holdings!$R$6:$R$205,Holdings!$AK$6:$AK$205,O$5,Holdings!$H$6:$H$205,$B28)/Divisor) | P28: =IF(OR(O$5="",N(O$32)=0),"",O28/O$32) | Q28: =IF(Q$5="","",SUMIFS(Holdings!$R$6:$R$205,Holdings!$AK$6:$AK$205,Q$5,Holdings!$H$6:$H$205,$B28)/Divisor) | R28: =IF(OR(Q$5="",N(Q$32)=0),"",Q28/Q$32) | T28: =SUMIFS(Holdings!$R$6:$R$205,Holdings!$H$6:$H$205,$B28)/Divisor -> 7.5888 | U28: =IF(N($T$32)=0,"",T28/$T$32) -> 0.054802858
B29: =Lists!$D$23 -> Private Equity – Unlisted Shares | C29: =IF(C$5="","",SUMIFS(Holdings!$R$6:$R$205,Holdings!$AK$6:$AK$205,C$5,Holdings!$H$6:$H$205,$B29)/Divisor) -> 2.5 | D29: =IF(OR(C$5="",N(C$32)=0),"",C29/C$32) -> 0.063965776 | E29: =IF(E$5="","",SUMIFS(Holdings!$R$6:$R$205,Holdings!$AK$6:$AK$205,E$5,Holdings!$H$6:$H$205,$B29)/Divisor) -> 0 | F29: =IF(OR(E$5="",N(E$32)=0),"",E29/E$32) -> 0 | G29: =IF(G$5="","",SUMIFS(Holdings!$R$6:$R$205,Holdings!$AK$6:$AK$205,G$5,Holdings!$H$6:$H$205,$B29)/Divisor) -> 0 | H29: =IF(OR(G$5="",N(G$32)=0),"",G29/G$32) -> 0 | I29: =IF(I$5="","",SUMIFS(Holdings!$R$6:$R$205,Holdings!$AK$6:$AK$205,I$5,Holdings!$H$6:$H$205,$B29)/Divisor) -> 0 | J29: =IF(OR(I$5="",N(I$32)=0),"",I29/I$32) -> 0 | K29: =IF(K$5="","",SUMIFS(Holdings!$R$6:$R$205,Holdings!$AK$6:$AK$205,K$5,Holdings!$H$6:$H$205,$B29)/Divisor) -> 0 | L29: =IF(OR(K$5="",N(K$32)=0),"",K29/K$32) -> 0 | M29: =IF(M$5="","",SUMIFS(Holdings!$R$6:$R$205,Holdings!$AK$6:$AK$205,M$5,Holdings!$H$6:$H$205,$B29)/Divisor) | N29: =IF(OR(M$5="",N(M$32)=0),"",M29/M$32) | O29: =IF(O$5="","",SUMIFS(Holdings!$R$6:$R$205,Holdings!$AK$6:$AK$205,O$5,Holdings!$H$6:$H$205,$B29)/Divisor) | P29: =IF(OR(O$5="",N(O$32)=0),"",O29/O$32) | Q29: =IF(Q$5="","",SUMIFS(Holdings!$R$6:$R$205,Holdings!$AK$6:$AK$205,Q$5,Holdings!$H$6:$H$205,$B29)/Divisor) | R29: =IF(OR(Q$5="",N(Q$32)=0),"",Q29/Q$32) | T29: =SUMIFS(Holdings!$R$6:$R$205,Holdings!$H$6:$H$205,$B29)/Divisor -> 2.5 | U29: =IF(N($T$32)=0,"",T29/$T$32) -> 0.018053861
B30: =Lists!$D$24 -> Pre-IPO | C30: =IF(C$5="","",SUMIFS(Holdings!$R$6:$R$205,Holdings!$AK$6:$AK$205,C$5,Holdings!$H$6:$H$205,$B30)/Divisor) -> 0 | D30: =IF(OR(C$5="",N(C$32)=0),"",C30/C$32) -> 0 | E30: =IF(E$5="","",SUMIFS(Holdings!$R$6:$R$205,Holdings!$AK$6:$AK$205,E$5,Holdings!$H$6:$H$205,$B30)/Divisor) -> 0 | F30: =IF(OR(E$5="",N(E$32)=0),"",E30/E$32) -> 0 | G30: =IF(G$5="","",SUMIFS(Holdings!$R$6:$R$205,Holdings!$AK$6:$AK$205,G$5,Holdings!$H$6:$H$205,$B30)/Divisor) -> 0 | H30: =IF(OR(G$5="",N(G$32)=0),"",G30/G$32) -> 0 | I30: =IF(I$5="","",SUMIFS(Holdings!$R$6:$R$205,Holdings!$AK$6:$AK$205,I$5,Holdings!$H$6:$H$205,$B30)/Divisor) -> 0 | J30: =IF(OR(I$5="",N(I$32)=0),"",I30/I$32) -> 0 | K30: =IF(K$5="","",SUMIFS(Holdings!$R$6:$R$205,Holdings!$AK$6:$AK$205,K$5,Holdings!$H$6:$H$205,$B30)/Divisor) -> 3.2 | L30: =IF(OR(K$5="",N(K$32)=0),"",K30/K$32) -> 0.32178013 | M30: =IF(M$5="","",SUMIFS(Holdings!$R$6:$R$205,Holdings!$AK$6:$AK$205,M$5,Holdings!$H$6:$H$205,$B30)/Divisor) | N30: =IF(OR(M$5="",N(M$32)=0),"",M30/M$32) | O30: =IF(O$5="","",SUMIFS(Holdings!$R$6:$R$205,Holdings!$AK$6:$AK$205,O$5,Holdings!$H$6:$H$205,$B30)/Divisor) | P30: =IF(OR(O$5="",N(O$32)=0),"",O30/O$32) | Q30: =IF(Q$5="","",SUMIFS(Holdings!$R$6:$R$205,Holdings!$AK$6:$AK$205,Q$5,Holdings!$H$6:$H$205,$B30)/Divisor) | R30: =IF(OR(Q$5="",N(Q$32)=0),"",Q30/Q$32) | T30: =SUMIFS(Holdings!$R$6:$R$205,Holdings!$H$6:$H$205,$B30)/Divisor -> 3.2 | U30: =IF(N($T$32)=0,"",T30/$T$32) -> 0.023108943
B32: Total | C32: =IF(C$5="","",SUMIFS(Holdings!$R$6:$R$205,Holdings!$AK$6:$AK$205,C$5)/Divisor) -> 39.0834 | D32: =IF(OR(C$5="",N($T$32)=0),"",C32/$T$32) -> 0.28224252 | E32: =IF(E$5="","",SUMIFS(Holdings!$R$6:$R$205,Holdings!$AK$6:$AK$205,E$5)/Divisor) -> 30.1601 | F32: =IF(OR(E$5="",N($T$32)=0),"",E32/$T$32) -> 0.21780251 | G32: =IF(G$5="","",SUMIFS(Holdings!$R$6:$R$205,Holdings!$AK$6:$AK$205,G$5)/Divisor) -> 27.376864 | H32: =IF(OR(G$5="",N($T$32)=0),"",G32/$T$32) -> 0.19770325 | I32: =IF(I$5="","",SUMIFS(Holdings!$R$6:$R$205,Holdings!$AK$6:$AK$205,I$5)/Divisor) -> 31.909488 | J32: =IF(OR(I$5="",N($T$32)=0),"",I32/$T$32) -> 0.23043579 | K32: =IF(K$5="","",SUMIFS(Holdings!$R$6:$R$205,Holdings!$AK$6:$AK$205,K$5)/Divisor) -> 9.9446786 | L32: =IF(OR(K$5="",N($T$32)=0),"",K32/$T$32) -> 0.07181594 | M32: =IF(M$5="","",SUMIFS(Holdings!$R$6:$R$205,Holdings!$AK$6:$AK$205,M$5)/Divisor) | N32: =IF(OR(M$5="",N($T$32)=0),"",M32/$T$32) | O32: =IF(O$5="","",SUMIFS(Holdings!$R$6:$R$205,Holdings!$AK$6:$AK$205,O$5)/Divisor) | P32: =IF(OR(O$5="",N($T$32)=0),"",O32/$T$32) | Q32: =IF(Q$5="","",SUMIFS(Holdings!$R$6:$R$205,Holdings!$AK$6:$AK$205,Q$5)/Divisor) | R32: =IF(OR(Q$5="",N($T$32)=0),"",Q32/$T$32) | T32: =SUM(Holdings!$R$6:$R$205)/Divisor -> 138.47453 | U32: =IF(N(T32)=0,"",T32/T32) -> 1
B34: '% of theirs' is the category's share of that entity's own portfolio; on the Total row it is the entity's share of the family. Entities appear in the order of the Entities sheet.
B35: =IF(COUNTA(Entities!$A$6:$A$25)>8,COUNTA(Entities!$A$6:$A$25)-8&" more entit(ies) are not shown here but are in the Family column: see Checks.","")

Sheet Period Change
A1: ="Period Change — "&ClientName -> Period Change — Malhotra Family Office (DEMO) | O1: =HYPERLINK("#'Start Here'!A1","← Start Here") -> ← Start Here
A2: ="Figures in "&UnitLabel&" · from "&TEXT(PrevDate,"dd-mmm-yyyy")&" to "&TEXT(ValDate,"dd-mmm-yyyy")&" ("&(ValDate-PrevDate)&" days)" -> Figures in ₹ Crore · from 31-Mar-2026 to 30-Jun-2026 (91 days)
A3: DEMO DATA — illustrative only: a fictional family, fictional securities and figures.
B5: Category | C5: ="Value on "&TEXT(PrevDate,"dd-mmm-yyyy") -> Value on 31-Mar-2026 | D5: Money in and out | F5: Gain in value (market) | G5: ="Value on "&TEXT(ValDate,"dd-mmm-yyyy") -> Value on 30-Jun-2026 | I5: Outside the holding value | L5: Net gain | M5: Return for the period (%) | O5: Transactions in the period
D6: Invested | E6: Redeemed / distributed | I6: Dividend / interest received (gross) | J6: Fees paid from outside
B7: =Lists!$A$6 -> Equity | C7: =SUMIFS(Holdings!$AD$6:$AD$205,Holdings!$G$6:$G$205,$B7)/Divisor -> 79.360497 | D7: =-SUMIFS(Transactions!$N$6:$N$305,Transactions!$H$6:$H$305,$B7,Transactions!$O$6:$O$305,"Investment",Transactions!$B$6:$B$305,">"&PrevDate,Transactions!$B$6:$B$305,"<="&ValDate)/Divisor -> 1.0338 | E7: =SUMIFS(Transactions!$N$6:$N$305,Transactions!$H$6:$H$305,$B7,Transactions!$O$6:$O$305,"Divestment",Transactions!$B$6:$B$305,">"&PrevDate,Transactions!$B$6:$B$305,"<="&ValDate)/Divisor -> 0 | F7: =G7-C7-D7+E7 -> 3.9598428 | G7: =SUMIFS(Holdings!$R$6:$R$205,Holdings!$G$6:$G$205,$B7)/Divisor -> 84.35414 | I7: =SUMIFS(Transactions!$L$6:$L$305,Transactions!$H$6:$H$305,$B7,Transactions!$O$6:$O$305,"Income",Transactions!$B$6:$B$305,">"&PrevDate,Transactions!$B$6:$B$305,"<="&ValDate)/Divisor -> 0.0648 | J7: =-SUMIFS(Transactions!$N$6:$N$305,Transactions!$H$6:$H$305,$B7,Transactions!$O$6:$O$305,"Charges",Transactions!$B$6:$B$305,">"&PrevDate,Transactions!$B$6:$B$305,"<="&ValDate)/Divisor -> 0.05625 | L7: =F7+I7-J7 -> 3.9683928 | M7: =IF((C7+0.5*(D7-E7-I7))<=0,"",L7/(C7+0.5*(D7-E7-I7))) -> 0.049701208 | O7: =COUNTIFS(Transactions!$H$6:$H$305,$B7,Transactions!$B$6:$B$305,">"&PrevDate,Transactions!$B$6:$B$305,"<="&ValDate) -> 6
B8: =Lists!$D$6 -> Direct Equity | C8: =SUMIFS(Holdings!$AD$6:$AD$205,Holdings!$H$6:$H$205,$B8)/Divisor -> 24.851266 | D8: =-SUMIFS(Transactions!$N$6:$N$305,Transactions!$G$6:$G$305,$B8,Transactions!$O$6:$O$305,"Investment",Transactions!$B$6:$B$305,">"&PrevDate,Transactions!$B$6:$B$305,"<="&ValDate)/Divisor -> 0 | E8: =SUMIFS(Transactions!$N$6:$N$305,Transactions!$G$6:$G$305,$B8,Transactions!$O$6:$O$305,"Divestment",Transactions!$B$6:$B$305,">"&PrevDate,Transactions!$B$6:$B$305,"<="&ValDate)/Divisor -> 0 | F8: =G8-C8-D8+E8 -> 1.1852795 | G8: =SUMIFS(Holdings!$R$6:$R$205,Holdings!$H$6:$H$205,$B8)/Divisor -> 26.036545 | I8: =SUMIFS(Transactions!$L$6:$L$305,Transactions!$G$6:$G$305,$B8,Transactions!$O$6:$O$305,"Income",Transactions!$B$6:$B$305,">"&PrevDate,Transactions!$B$6:$B$305,"<="&ValDate)/Divisor -> 0.0648 | J8: =-SUMIFS(Transactions!$N$6:$N$305,Transactions!$G$6:$G$305,$B8,Transactions!$O$6:$O$305,"Charges",Transactions!$B$6:$B$305,">"&PrevDate,Transactions!$B$6:$B$305,"<="&ValDate)/Divisor -> 0 | L8: =F8+I8-J8 -> 1.2500795 | M8: =IF((C8+0.5*(D8-E8-I8))<=0,"",L8/(C8+0.5*(D8-E8-I8))) -> 0.050368116 | O8: =COUNTIFS(Transactions!$G$6:$G$305,$B8,Transactions!$B$6:$B$305,">"&PrevDate,Transactions!$B$6:$B$305,"<="&ValDate) -> 1
B9: =Lists!$D$7 -> Equity MF – Large / Flexi / Multi Cap | C9: =SUMIFS(Holdings!$AD$6:$AD$205,Holdings!$H$6:$H$205,$B9)/Divisor -> 9.2633237 | D9: =-SUMIFS(Transactions!$N$6:$N$305,Transactions!$G$6:$G$305,$B9,Transactions!$O$6:$O$305,"Investment",Transactions!$B$6:$B$305,">"&PrevDate,Transactions!$B$6:$B$305,"<="&ValDate)/Divisor -> 0 | E9: =SUMIFS(Transactions!$N$6:$N$305,Transactions!$G$6:$G$305,$B9,Transactions!$O$6:$O$305,"Divestment",Transactions!$B$6:$B$305,">"&PrevDate,Transactions!$B$6:$B$305,"<="&ValDate)/Divisor -> 0 | F9: =G9-C9-D9+E9 -> 0.3797963 | G9: =SUMIFS(Holdings!$R$6:$R$205,Holdings!$H$6:$H$205,$B9)/Divisor -> 9.64312 | I9: =SUMIFS(Transactions!$L$6:$L$305,Transactions!$G$6:$G$305,$B9,Transactions!$O$6:$O$305,"Income",Transactions!$B$6:$B$305,">"&PrevDate,Transactions!$B$6:$B$305,"<="&ValDate)/Divisor -> 0 | J9: =-SUMIFS(Transactions!$N$6:$N$305,Transactions!$G$6:$G$305,$B9,Transactions!$O$6:$O$305,"Charges",Transactions!$B$6:$B$305,">"&PrevDate,Transactions!$B$6:$B$305,"<="&ValDate)/Divisor -> 0 | L9: =F9+I9-J9 -> 0.3797963 | M9: =IF((C9+0.5*(D9-E9-I9))<=0,"",L9/(C9+0.5*(D9-E9-I9))) -> 0.041000003 | O9: =COUNTIFS(Transactions!$G$6:$G$305,$B9,Transactions!$B$6:$B$305,">"&PrevDate,Transactions!$B$6:$B$305,"<="&ValDate) -> 0
B10: =Lists!$D$8 -> Equity MF – Mid & Small Cap | C10: =SUMIFS(Holdings!$AD$6:$AD$205,Holdings!$H$6:$H$205,$B10)/Divisor -> 5.3731995 | D10: =-SUMIFS(Transactions!$N$6:$N$305,Transactions!$G$6:$G$305,$B10,Transactions!$O$6:$O$305,"Investment",Transactions!$B$6:$B$305,">"&PrevDate,Transactions!$B$6:$B$305,"<="&ValDate)/Divisor -> 0.135 | E10: =SUMIFS(Transactions!$N$6:$N$305,Transactions!$G$6:$G$305,$B10,Transactions!$O$6:$O$305,"Divestment",Transactions!$B$6:$B$305,">"&PrevDate,Transactions!$B$6:$B$305,"<="&ValDate)/Divisor -> 0 | F10: =G10-C10-D10+E10 -> 0.38687037 | G10: =SUMIFS(Holdings!$R$6:$R$205,Holdings!$H$6:$H$205,$B10)/Divisor -> 5.8950699 | I10: =SUMIFS(Transactions!$L$6:$L$305,Transactions!$G$6:$G$305,$B10,Transactions!$O$6:$O$305,"Income",Transactions!$B$6:$B$305,">"&PrevDate,Transactions!$B$6:$B$305,"<="&ValDate)/Divisor -> 0 | J10: =-SUMIFS(Transactions!$N$6:$N$305,Transactions!$G$6:$G$305,$B10,Transactions!$O$6:$O$305,"Charges",Transactions!$B$6:$B$305,">"&PrevDate,Transactions!$B$6:$B$305,"<="&ValDate)/Divisor -> 0 | L10: =F10+I10-J10 -> 0.38687037 | M10: =IF((C10+0.5*(D10-E10-I10))<=0,"",L10/(C10+0.5*(D10-E10-I10))) -> 0.071106734 | O10: =COUNTIFS(Transactions!$G$6:$G$305,$B10,Transactions!$B$6:$B$305,">"&PrevDate,Transactions!$B$6:$B$305,"<="&ValDate) -> 3
